Workbook

Sheet Units
A1: Notes
A2: Global LNG liquefaction capacity - 'Global supply' section of the master future-capacity table
A4: Purpose
A5: Nameplate liquefaction capacity by plant / train (existing), and every project under construction, at FID or planned, with the expected start, plus closures. It feeds the Europe LNG-need forecast: the supply side the balancing item draws on.
A7: Units
A8: capacity_value is in mtpa as published (million tonnes of LNG per year). capacity_bcfd is DERIVED: 1 mtpa = 1.36 bcm/y of gas (DISR REQ note c) = 1.36 x 35.3147 / 365.25 = 0.1315 Bcf/d. The US figures are EIA baseload nameplate (peak in the notes); other countries are nominal capacity as published.
A9: Nameplate is not output: US plants run above baseload nameplate, Qatar and the UAE export through the Strait of Hormuz (disrupted in 2026), Russian volumes are sanctioned, Nigerian and Trinidad plants are feedgas-limited.
A11: Sheets
A12: Projects: the shared row schema (one row per plant / train / project; status OPERATING is an extension of the schema's status list for existing capacity; all other statuses are the schema's).
A13: History: every change of status / expected_online / capacity_value of a row between runs (old -> new, date seen).
A14: Capacity by month: Jan 2021 - Dec 2030 nameplate by status, no ramp-up. Yellow cell = ramp months (ASSUMPTION), used only in the 'with ramp' columns.
A15: By country: nameplate now and in Dec 2030 by status, per host country. Additions by year: per chart group, additions and closures. Placement: how each project's start month was fixed.
... A23: Charts: native Excel stacked charts on 'Chart - Nameplate' and 'Chart - Additions' (redrawn every run, no borders, mmm/yy), PNGs in output/PNG Charts.

Sheet Chart - Nameplate
A1: Month | B1: United States - operating | C1: Qatar - operating | D1: Australia - operating | E1: Canada - operating | F1: Mexico - operating | G1: Russia - operating | H1: Africa - operating | I1: Other - operating | J1: United States - UC + FID | K1: Qatar - UC + FID | L1: Australia - UC + FID | M1: Canada - UC + FID | N1: Mexico - UC + FID | O1: Russia - UC + FID | P1: Africa - UC + FID | Q1: Other - UC + FID | R1: United States - planned (dated) | S1: Qatar - planned (dated) | T1: Australia - planned (dated) | U1: Canada - planned (dated) | V1: Mexico - planned (dated) | W1: Russia - planned (dated) | X1: Africa - planned (dated) | Y1: Other - planned (dated) | Z1: Offline (damaged / shut-in)
A2: 44197 | B2: 72.31 | C2: 77 | D2: 87.8 | E2: 0.3 | F2: 0 | G2: 29.1 | H2: 70.8 | I2: 110.1 | J2: 0 | K2: 0 | L2: 0 | M2: 0 | N2: 0 | O2: 0 | P2: 0 | Q2: 0 | R2: 0 | S2: 0 | T2: 0 | U2: 0 | V2: 0 | W2: 0 | X2: 0 | Y2: 0 | Z2: 10.2
A3: 44228 | B3: 72.31 | C3: 77 | D3: 87.8 | E3: 0.3 | F3: 0 | G3: 29.1 | H3: 70.8 | I3: 110.1 | J3: 0 | K3: 0 | L3: 0 | M3: 0 | N3: 0 | O3: 0 | P3: 0 | Q3: 0 | R3: 0 | S3: 0 | T3: 0 | U3: 0 | V3: 0 | W3: 0 | X3: 0 | Y3: 0 | Z3: 10.2
A4: 44256 | B4: 72.31 | C4: 77 | D4: 87.8 | E4: 0.3 | F4: 0 | G4: 29.1 | H4: 70.8 | I4: 110.1 | J4: 0 | K4: 0 | L4: 0 | M4: 0 | N4: 0 | O4: 0 | P4: 0 | Q4: 0 | R4: 0 | S4: 0 | T4: 0 | U4: 0 | V4: 0 | W4: 0 | X4: 0 | Y4: 0 | Z4: 10.2
A5: 44287 | B5: 72.31 | C5: 77 | D5: 87.8 | E5: 0.3 | F5: 0 | G5: 29.1 | H5: 70.8 | I5: 110.1 | J5: 0 | K5: 0 | L5: 0 | M5: 0 | N5: 0 | O5: 0 | P5: 0 | Q5: 0 | R5: 0 | S5: 0 | T5: 0 | U5: 0 | V5: 0 | W5: 0 | X5: 0 | Y5: 0 | Z5: 10.2
A6: 44317 | B6: 72.31 | C6: 77 | D6: 87.8 | E6: 0.3 | F6: 0 | G6: 29.1 | H6: 70.8 | I6: 110.1 | J6: 0 | K6: 0 | L6: 0 | M6: 0 | N6: 0 | O6: 0 | P6: 0 | Q6: 0 | R6: 0 | S6: 0 | T6: 0 | U6: 0 | V6: 0 | W6: 0 | X6: 0 | Y6: 0 | Z6: 10.2
A7: 44348 | B7: 72.31 | C7: 77 | D7: 87.8 | E7: 0.3 | F7: 0 | G7: 29.1 | H7: 70.8 | I7: 110.1 | J7: 0 | K7: 0 | L7: 0 | M7: 0 | N7: 0 | O7: 0 | P7: 0 | Q7: 0 | R7: 0 | S7: 0 | T7: 0 | U7: 0 | V7: 0 | W7: 0 | X7: 0 | Y7: 0 | Z7: 10.2
A8: 44378 | B8: 72.31 | C8: 77 | D8: 87.8 | E8: 0.3 | F8: 0 | G8: 29.1 | H8: 70.8 | I8: 110.1 | J8: 0 | K8: 0 | L8: 0 | M8: 0 | N8: 0 | O8: 0 | P8: 0 | Q8: 0 | R8: 0 | S8: 0 | T8: 0 | U8: 0 | V8: 0 | W8: 0 | X8: 0 | Y8: 0 | Z8: 10.2
A9: 44409 | B9: 72.31 | C9: 77 | D9: 87.8 | E9: 0.3 | F9: 0 | G9: 29.1 | H9: 70.8 | I9: 110.1 | J9: 0 | K9: 0 | L9: 0 | M9: 0 | N9: 0 | O9: 0 | P9: 0 | Q9: 0 | R9: 0 | S9: 0 | T9: 0 | U9: 0 | V9: 0 | W9: 0 | X9: 0 | Y9: 0 | Z9: 10.2
A10: 44440 | B10: 72.31 | C10: 77 | D10: 87.8 | E10: 0.3 | F10: 0 | G10: 29.1 | H10: 70.8 | I10: 110.1 | J10: 0 | K10: 0 | L10: 0 | M10: 0 | N10: 0 | O10: 0 | P10: 0 | Q10: 0 | R10: 0 | S10: 0 | T10: 0 | U10: 0 | V10: 0 | W10: 0 | X10: 0 | Y10: 0 | Z10: 10.2
A11: 44470 | B11: 72.31 | C11: 77 | D11: 87.8 | E11: 0.3 | F11: 0 | G11: 29.1 | H11: 70.8 | I11: 110.1 | J11: 0 | K11: 0 | L11: 0 | M11: 0 | N11: 0 | O11: 0 | P11: 0 | Q11: 0 | R11: 0 | S11: 0 | T11: 0 | U11: 0 | V11: 0 | W11: 0 | X11: 0 | Y11: 0 | Z11: 10.2
A12: 44501 | B12: 72.31 | C12: 77 | D12: 87.8 | E12: 0.3 | F12: 0 | G12: 29.1 | H12: 70.8 | I12: 110.1 | J12: 0 | K12: 0 | L12: 0 | M12: 0 | N12: 0 | O12: 0 | P12: 0 | Q12: 0 | R12: 0 | S12: 0 | T12: 0 | U12: 0 | V12: 0 | W12: 0 | X12: 0 | Y12: 0 | Z12: 10.2
A13: 44531 | B13: 76.81 | C13: 77 | D13: 87.8 | E13: 0.3 | F13: 0 | G13: 29.1 | H13: 70.8 | I13: 110.1 | J13: 0 | K13: 0 | L13: 0 | M13: 0 | N13: 0 | O13: 0 | P13: 0 | Q13: 0 | R13: 0 | S13: 0 | T13: 0 | U13: 0 | V13: 0 | W13: 0 | X13: 0 | Y13: 0 | Z13: 10.2
... A121: 47818 | B121: 120.384 | C121: 64.2 | D121: 85.2 | E121: 14.3 | F121: 4.65 | G121: 43.8 | H121: 77.1 | I121: 110.1 | J121: 97.369 | K121: 8 | L121: 0 | M121: 2.1 | N121: 0 | O121: 0 | P121: 16.72 | Q121: 20.05 | R121: 0 | S121: 0 | T121: 0 | U121: 0 | V121: 0 | W121: 0 | X121: 0 | Y121: 0 | Z121: 23

Sheet Chart - Additions
A1: Year | B1: United States | C1: Qatar | D1: Australia | E1: Canada | F1: Mexico | G1: Russia | H1: Africa | I1: Other
A2: 2021 | B2: 4.5 | C2: 0 | D2: 0 | E2: 0 | F2: 0 | G2: 0 | H2: 0 | I2: 0
A3: 2022 | B3: 10 | C3: 0 | D3: 0 | E3: 0 | F3: 0 | G3: 1.5 | H3: 3.4 | I3: 0
A4: 2023 | B4: 0 | C4: 0 | D4: 0 | E4: 0 | F4: 0 | G4: 0 | H4: 0 | I4: 0
A5: 2024 | B5: 9.9 | C5: 0 | D5: 0 | E5: 0 | F5: 1.4 | G5: 6.6 | H5: 0.6 | I5: 0
A6: 2025 | B6: 15.616 | C6: 0 | D6: 0 | E6: 14 | F6: 0 | G6: 6.6 | H6: 2.3 | I6: 0
A7: 2026 | B7: 14.687 | C7: 0 | D7: 0 | E7: 0 | F7: 3.25 | G7: 0 | H7: 2.4 | I7: 0
A8: 2027 | B8: 42.4 | C8: 8 | D8: 0 | E8: 2.1 | F8: 0 | G8: 0 | H8: 0 | I8: 2.45
A9: 2028 | B9: 8.38 | C9: 0 | D9: 0 | E9: 0 | F9: 0 | G9: 0 | H9: 3.6 | I9: 14.1
A10: 2029 | B10: 22.16 | C10: 0 | D10: 0 | E10: 0 | F10: 0 | G10: 0 | H10: 13.12 | I10: 3.5
A11: 2030 | B11: 17.8 | C11: 0 | D11: 0 | E11: 0 | F11: 0 | G11: 0 | H11: 0 | I11: 0

Sheet Projects
A1: region | B1: country | C1: asset_type | D1: project | E1: operator | F1: fuel_or_type | G1: capacity_value | H1: capacity_unit | I1: capacity_mw | J1: capacity_bcfd | K1: status | L1: expected_online | M1: online_date_basis | N1: first_seen | O1: last_seen | P1: source_publisher | Q1: source_document | R1: source_url | S1: as_of_date | T1: evidence | U1: notes
A2: Global supply | B2: United States | C2: liquefaction_train | D2: Sabine Pass Train 1 | E2: Cheniere Energy | F2: liquefaction | G2: 4.5 | H2: mtpa | J2: 0.5917 | K2: OPERATING | L2: 2016-02 | M2: SOURCED_MONTH | N2: 2026-10-12 | O2: 2026-10-12 | P2: U.S. Energy Information Administration | Q2: U.S. Liquefaction Capacity workbook (U.S.liquefactioncapacity_2026_Q3.xlsx; release 2026-10-01) | R2: https://www.eia.gov/naturalgas/importsexports/liquefactioncapacity/U.S.liquefactioncapacity_2026_Q3.xlsx | S2: 2026-10-01 | T2: SOURCED | U2: EIA status 'Commercial operation'; in-service '2016-02-01'. Baseload nameplate 4.50 mtpa; EIA peak nameplate 5.76 mtpa (EIA's own Mtpa where marked ^ else its Bcf/d conversion). [capacity_bcfd DERIVED: mtpa x 1.36 bcm/y x 35.3147 / 365.25 = 0.1315 Bcf/d per mtpa]
A3: Global supply | B3: United States | C3: liquefaction_train | D3: Sabine Pass Train 2 | E3: Cheniere Energy | F3: liquefaction | G3: 4.5 | H3: mtpa | J3: 0.5917 | K3: OPERATING | L3: 2016-08 | M3: SOURCED_MONTH | N3: 2026-10-12 | O3: 2026-10-12 | P3: U.S. Energy Information Administration | Q3: U.S. Liquefaction Capacity workbook (U.S.liquefactioncapacity_2026_Q3.xlsx; release 2026-10-01) | R3: https://www.eia.gov/naturalgas/importsexports/liquefactioncapacity/U.S.liquefactioncapacity_2026_Q3.xlsx | S3: 2026-10-01 | T3: SOURCED | U3: EIA status 'Commercial operation'; in-service '2016-08-01'. Baseload nameplate 4.50 mtpa; EIA peak nameplate 5.76 mtpa (EIA's own Mtpa where marked ^ else its Bcf/d conversion). [capacity_bcfd DERIVED: mtpa x 1.36 bcm/y x 35.3147 / 365.25 = 0.1315 Bcf/d per mtpa]
A4: Global supply | B4: United States | C4: liquefaction_train | D4: Sabine Pass Train 3 | E4: Cheniere Energy | F4: liquefaction | G4: 4.5 | H4: mtpa | J4: 0.5917 | K4: OPERATING | L4: 2017-01 | M4: SOURCED_MONTH | N4: 2026-10-12 | O4: 2026-10-12 | P4: U.S. Energy Information Administration | Q4: U.S. Liquefaction Capacity workbook (U.S.liquefactioncapacity_2026_Q3.xlsx; release 2026-10-01) | R4: https://www.eia.gov/naturalgas/importsexports/liquefactioncapacity/U.S.liquefactioncapacity_2026_Q3.xlsx | S4: 2026-10-01 | T4: SOURCED | U4: EIA status 'Commercial operation'; in-service '2017-01-01'. Baseload nameplate 4.50 mtpa; EIA peak nameplate 5.76 mtpa (EIA's own Mtpa where marked ^ else its Bcf/d conversion). [capacity_bcfd DERIVED: mtpa x 1.36 bcm/y x 35.3147 / 365.25 = 0.1315 Bcf/d per mtpa]
A5: Global supply | B5: United States | C5: liquefaction_train | D5: Sabine Pass Train 4 | E5: Cheniere Energy | F5: liquefaction | G5: 4.5 | H5: mtpa | J5: 0.5917 | K5: OPERATING | L5: 2017-08 | M5: SOURCED_MONTH | N5: 2026-10-12 | O5: 2026-10-12 | P5: U.S. Energy Information Administration | Q5: U.S. Liquefaction Capacity workbook (U.S.liquefactioncapacity_2026_Q3.xlsx; release 2026-10-01) | R5: https://www.eia.gov/naturalgas/importsexports/liquefactioncapacity/U.S.liquefactioncapacity_2026_Q3.xlsx | S5: 2026-10-01 | T5: SOURCED | U5: EIA status 'Commercial operation'; in-service '2017-08-01'. Baseload nameplate 4.50 mtpa; EIA peak nameplate 5.76 mtpa (EIA's own Mtpa where marked ^ else its Bcf/d conversion). [capacity_bcfd DERIVED: mtpa x 1.36 bcm/y x 35.3147 / 365.25 = 0.1315 Bcf/d per mtpa]
A6: Global supply | B6: United States | C6: liquefaction_train | D6: Sabine Pass Train 5 | E6: Cheniere Energy | F6: liquefaction | G6: 4.5 | H6: mtpa | J6: 0.5917 | K6: OPERATING | L6: 2018-11 | M6: SOURCED_MONTH | N6: 2026-10-12 | O6: 2026-10-12 | P6: U.S. Energy Information Administration | Q6: U.S. Liquefaction Capacity workbook (U.S.liquefactioncapacity_2026_Q3.xlsx; release 2026-10-01) | R6: https://www.eia.gov/naturalgas/importsexports/liquefactioncapacity/U.S.liquefactioncapacity_2026_Q3.xlsx | S6: 2026-10-01 | T6: SOURCED | U6: EIA status 'Commercial operation'; in-service '2018-11-01'. Baseload nameplate 4.50 mtpa; EIA peak nameplate 5.76 mtpa (EIA's own Mtpa where marked ^ else its Bcf/d conversion). [capacity_bcfd DERIVED: mtpa x 1.36 bcm/y x 35.3147 / 365.25 = 0.1315 Bcf/d per mtpa]
A7: Global supply | B7: United States | C7: liquefaction_train | D7: Sabine Pass Train 6 | E7: Cheniere Energy | F7: liquefaction | G7: 4.5 | H7: mtpa | J7: 0.5917 | K7: OPERATING | L7: 2021-12 | M7: SOURCED_MONTH | N7: 2026-10-12 | O7: 2026-10-12 | P7: U.S. Energy Information Administration | Q7: U.S. Liquefaction Capacity workbook (U.S.liquefactioncapacity_2026_Q3.xlsx; release 2026-10-01) | R7: https://www.eia.gov/naturalgas/importsexports/liquefactioncapacity/U.S.liquefactioncapacity_2026_Q3.xlsx | S7: 2026-10-01 | T7: SOURCED | U7: EIA status 'Commercial operation'; in-service '2021-12-01'. Baseload nameplate 4.50 mtpa; EIA peak nameplate 5.76 mtpa (EIA's own Mtpa where marked ^ else its Bcf/d conversion). [capacity_bcfd DERIVED: mtpa x 1.36 bcm/y x 35.3147 / 365.25 = 0.1315 Bcf/d per mtpa]
A8: Global supply | B8: United States | C8: liquefaction_train | D8: Cove Point Train 1 | E8: Berkshire Hathaway BHE GT&S | F8: liquefaction | G8: 5.25 | H8: mtpa | J8: 0.6904 | K8: OPERATING | L8: 2018-03 | M8: SOURCED_MONTH | N8: 2026-10-12 | O8: 2026-10-12 | P8: U.S. Energy Information Administration | Q8: U.S. Liquefaction Capacity workbook (U.S.liquefactioncapacity_2026_Q3.xlsx; release 2026-10-01) | R8: https://www.eia.gov/naturalgas/importsexports/liquefactioncapacity/U.S.liquefactioncapacity_2026_Q3.xlsx | S8: 2026-10-01 | T8: SOURCED | U8: EIA status 'Commercial operation'; in-service '2018-03-01'. Baseload nameplate 5.25 mtpa; EIA peak nameplate 5.75 mtpa (EIA's own Mtpa where marked ^ else its Bcf/d conversion). [capacity_bcfd DERIVED: mtpa x 1.36 bcm/y x 35.3147 / 365.25 = 0.1315 Bcf/d per mtpa]
A9: Global supply | B9: United States | C9: liquefaction_train | D9: Elba Island Trains 1-5A | E9: Kinder Morgan | F9: liquefaction | G9: 1.25 | H9: mtpa | J9: 0.1644 | K9: OPERATING | L9: 2019-09 | M9: SOURCED_MONTH | N9: 2026-10-12 | O9: 2026-10-12 | P9: U.S. Energy Information Administration | Q9: U.S. Liquefaction Capacity workbook (U.S.liquefactioncapacity_2026_Q3.xlsx; release 2026-10-01) | R9: https://www.eia.gov/naturalgas/importsexports/liquefactioncapacity/U.S.liquefactioncapacity_2026_Q3.xlsx | S9: 2026-10-01 | T9: SOURCED | U9: EIA status 'Commercial operation'; in-service '2019-09-01'. Baseload nameplate 1.25 mtpa; EIA peak nameplate 1.45 mtpa (EIA's own Mtpa where marked ^ else its Bcf/d conversion). [capacity_bcfd DERIVED: mtpa x 1.36 bcm/y x 35.3147 / 365.25 = 0.1315 Bcf/d per mtpa]
A10: Global supply | B10: United States | C10: liquefaction_train | D10: Elba Island Trains 6-10A | E10: Kinder Morgan | F10: liquefaction | G10: 1.25 | H10: mtpa | J10: 0.1644 | K10: OPERATING | L10: 2020-05 | M10: SOURCED_MONTH | N10: 2026-10-12 | O10: 2026-10-12 | P10: U.S. Energy Information Administration | Q10: U.S. Liquefaction Capacity workbook (U.S.liquefactioncapacity_2026_Q3.xlsx; release 2026-10-01) | R10: https://www.eia.gov/naturalgas/importsexports/liquefactioncapacity/U.S.liquefactioncapacity_2026_Q3.xlsx | S10: 2026-10-01 | T10: SOURCED | U10: EIA status 'Commercial operation'; in-service '2020-05-01'. Baseload nameplate 1.25 mtpa; EIA peak nameplate 1.45 mtpa (EIA's own Mtpa where marked ^ else its Bcf/d conversion). [capacity_bcfd DERIVED: mtpa x 1.36 bcm/y x 35.3147 / 365.25 = 0.1315 Bcf/d per mtpa]
A11: Global supply | B11: United States | C11: liquefaction_train | D11: Corpus Christi Train 1 | E11: Cheniere Energy | F11: liquefaction | G11: 4.52 | H11: mtpa | J11: 0.5944 | K11: OPERATING | L11: 2018-12 | M11: SOURCED_MONTH | N11: 2026-10-12 | O11: 2026-10-12 | P11: U.S. Energy Information Administration | Q11: U.S. Liquefaction Capacity workbook (U.S.liquefactioncapacity_2026_Q3.xlsx; release 2026-10-01) | R11: https://www.eia.gov/naturalgas/importsexports/liquefactioncapacity/U.S.liquefactioncapacity_2026_Q3.xlsx | S11: 2026-10-01 | T11: SOURCED | U11: EIA status 'Commercial operation'; in-service '2018-12-01'. Baseload nameplate 4.52 mtpa; EIA peak nameplate 6.07 mtpa (EIA's own Mtpa where marked ^ else its Bcf/d conversion). [capacity_bcfd DERIVED: mtpa x 1.36 bcm/y x 35.3147 / 365.25 = 0.1315 Bcf/d per mtpa]
A12: Global supply | B12: United States | C12: liquefaction_train | D12: Corpus Christi Train 2 | E12: Cheniere Energy | F12: liquefaction | G12: 4.52 | H12: mtpa | J12: 0.5944 | K12: OPERATING | L12: 2019-07 | M12: SOURCED_MONTH | N12: 2026-10-12 | O12: 2026-10-12 | P12: U.S. Energy Information Administration | Q12: U.S. Liquefaction Capacity workbook (U.S.liquefactioncapacity_2026_Q3.xlsx; release 2026-10-01) | R12: https://www.eia.gov/naturalgas/importsexports/liquefactioncapacity/U.S.liquefactioncapacity_2026_Q3.xlsx | S12: 2026-10-01 | T12: SOURCED | U12: EIA status 'Commercial operation'; in-service '2019-07-01'. Baseload nameplate 4.52 mtpa; EIA peak nameplate 6.07 mtpa (EIA's own Mtpa where marked ^ else its Bcf/d conversion). [capacity_bcfd DERIVED: mtpa x 1.36 bcm/y x 35.3147 / 365.25 = 0.1315 Bcf/d per mtpa]
A13: Global supply | B13: United States | C13: liquefaction_train | D13: Corpus Christi Train 3 | E13: Cheniere Energy | F13: liquefaction | G13: 4.52 | H13: mtpa | J13: 0.5944 | K13: OPERATING | L13: 2020-12 | M13: SOURCED_MONTH | N13: 2026-10-12 | O13: 2026-10-12 | P13: U.S. Energy Information Administration | Q13: U.S. Liquefaction Capacity workbook (U.S.liquefactioncapacity_2026_Q3.xlsx; release 2026-10-01) | R13: https://www.eia.gov/naturalgas/importsexports/liquefactioncapacity/U.S.liquefactioncapacity_2026_Q3.xlsx | S13: 2026-10-01 | T13: SOURCED | U13: EIA status 'Commercial operation'; in-service '2020-12-01'. Baseload nameplate 4.52 mtpa; EIA peak nameplate 6.07 mtpa (EIA's own Mtpa where marked ^ else its Bcf/d conversion). [capacity_bcfd DERIVED: mtpa x 1.36 bcm/y x 35.3147 / 365.25 = 0.1315 Bcf/d per mtpa]
... A46: Global supply | B46: United States | C46: liquefaction_train | D46: Delfin FLNG Train 1 | E46: Fairwood Group | F46: liquefaction | G46: 4 | H46: mtpa | J46: 0.526 | K46: UNDER_CONSTRUCTION | L46: 2030 | M46: SOURCED_YEAR | N46: 2026-10-12 | O46: 2026-10-12 | P46: U.S. Energy Information Administration | Q46: U.S. Liquefaction Capacity workbook (U.S.liquefactioncapacity_2026_Q3.xlsx; release 2026-10-01) | R46: https://www.eia.gov/naturalgas/importsexports/liquefactioncapacity/U.S.liquefactioncapacity_2026_Q3.xlsx | S46: 2026-10-01 | T46: SOURCED | U46: EIA status 'Under construction'; in-service '2030'. Baseload nameplate 4.00 mtpa; EIA peak nameplate 4.40 mtpa (EIA's own Mtpa where marked ^ else its Bcf/d conversion). [capacity_bcfd DERIVED: mtpa x 1.36 bcm/y x 35.3147 / 365.25 = 0.1315 Bcf/d per mtpa]
A47: Global supply | B47: United States | C47: liquefaction_train | D47: Cameron LNG Train 4A | E47: Cameron LNG, LLC | F47: liquefaction | G47: 6.75 | H47: mtpa | J47: 0.8876 | K47: PERMITTED | M47: NOT_STATED | N47: 2026-10-12 | O47: 2026-10-12 | P47: U.S. Energy Information Administration | Q47: U.S. Liquefaction Capacity workbook (U.S.liquefactioncapacity_2026_Q3.xlsx; release 2026-10-01) | R47: https://www.eia.gov/naturalgas/importsexports/liquefactioncapacity/U.S.liquefactioncapacity_2026_Q3.xlsx | S47: 2026-10-01 | T47: SOURCED | U47: EIA 'Approved' tab (DOE and FERC/MARAD approved, no FID): Completed FEED on a new design of one larger-size train, rather than 2 trains as was initially proposed. Awarded EPC contract to Bechtel. FID TBA. Design capacity 6.75 mtpa (1 train(s)). [capacity_bcfd DERIVED: mtpa x 1.36 bcm/y x 35.3147 / 365.25 = 0.1315 Bcf/d per mtpa]
A48: Global supply | B48: United States | C48: liquefaction_train | D48: Lake Charles LNG | E48: Energy Transfer, LP | F48: liquefaction | G48: 16.5 | H48: mtpa | J48: 2.1698 | K48: SUSPENDED | M48: NOT_STATED | N48: 2026-10-12 | O48: 2026-10-12 | P48: U.S. Energy Information Administration | Q48: U.S. Liquefaction Capacity workbook (U.S.liquefactioncapacity_2026_Q3.xlsx; release 2026-10-01) | R48: https://www.eia.gov/naturalgas/importsexports/liquefactioncapacity/U.S.liquefactioncapacity_2026_Q3.xlsx | S48: 2026-10-01 | T48: SOURCED | U48: EIA 'Approved' tab (DOE and FERC/MARAD approved, no FID): Completed FEED, reviewed EPC tenders, signed a preliminary EPC contract with a consortium led by Technip Energies and KBR. FID TBAD. Design capacity 16.50 mtpa (3 train(s)). Energy Transfer suspended development on 18 Dec 2025 (EIA note D). [capacity_bcfd DERIVED: mtpa x 1.36 bcm/y x 35.3147 / 365.25 = 0.1315 Bcf/d per mtpa]
A49: Global supply | B49: United States | C49: liquefaction_train | D49: Woodside Louisiana LNG (formerly Driftwood LNG) Phase 2 | E49: Woodside Energy | F49: liquefaction | G49: 11.04 | H49: mtpa | J49: 1.4518 | K49: PERMITTED | M49: NOT_STATED | N49: 2026-10-12 | O49: 2026-10-12 | P49: U.S. Energy Information Administration | Q49: U.S. Liquefaction Capacity workbook (U.S.liquefactioncapacity_2026_Q3.xlsx; release 2026-10-01) | R49: https://www.eia.gov/naturalgas/importsexports/liquefactioncapacity/U.S.liquefactioncapacity_2026_Q3.xlsx | S49: 2026-10-01 | T49: SOURCED | U49: EIA 'Approved' tab (DOE and FERC/MARAD approved, no FID): Completed FEED, awarded EPC contract to Bechtel Energy, issued limited notice to proceed to commence construction, FID TBA. Design capacity 11.04 mtpa (2 train(s)). [capacity_bcfd DERIVED: mtpa x 1.36 bcm/y x 35.3147 / 365.25 = 0.1315 Bcf/d per mtpa]
A50: Global supply | B50: United States | C50: liquefaction_train | D50: Freeport LNG Train 4C | E50: Freeport LNG | F50: liquefaction | G50: 5.1 | H50: mtpa | J50: 0.6706 | K50: PERMITTED | M50: NOT_STATED | N50: 2026-10-12 | O50: 2026-10-12 | P50: U.S. Energy Information Administration | Q50: U.S. Liquefaction Capacity workbook (U.S.liquefactioncapacity_2026_Q3.xlsx; release 2026-10-01) | R50: https://www.eia.gov/naturalgas/importsexports/liquefactioncapacity/U.S.liquefactioncapacity_2026_Q3.xlsx | S50: 2026-10-01 | T50: SOURCED | U50: EIA 'Approved' tab (DOE and FERC/MARAD approved, no FID): Completed FEED, awarded EPC contract to Kiewit Energy. FID TBA. Design capacity 5.10 mtpa (1 train(s)). [capacity_bcfd DERIVED: mtpa x 1.36 bcm/y x 35.3147 / 365.25 = 0.1315 Bcf/d per mtpa]
A51: Global supply | B51: United States | C51: liquefaction_train | D51: Texas LNG | E51: Glenfarne Energy Transition, LLC | F51: liquefaction | G51: 4 | H51: mtpa | J51: 0.526 | K51: PERMITTED | M51: NOT_STATED | N51: 2026-10-12 | O51: 2026-10-12 | P51: U.S. Energy Information Administration | Q51: U.S. Liquefaction Capacity workbook (U.S.liquefactioncapacity_2026_Q3.xlsx; release 2026-10-01) | R51: https://www.eia.gov/naturalgas/importsexports/liquefactioncapacity/U.S.liquefactioncapacity_2026_Q3.xlsx | S51: 2026-10-01 | T51: SOURCED | U51: EIA 'Approved' tab (DOE and FERC/MARAD approved, no FID): Completed FEED, selected engineering, procurement, and construction (EPC) contractor. FID targeted for 2026.. Design capacity 4.00 mtpa (2 train(s)). [capacity_bcfd DERIVED: mtpa x 1.36 bcm/y x 35.3147 / 365.25 = 0.1315 Bcf/d per mtpa]
A52: Global supply | B52: United States | C52: liquefaction_train | D52: Gulf LNGE | E52: Gulf LNG Liquefaction Company, LLC | F52: liquefaction | G52: 10.85 | H52: mtpa | J52: 1.4268 | K52: PERMITTED | M52: NOT_STATED | N52: 2026-10-12 | O52: 2026-10-12 | P52: U.S. Energy Information Administration | Q52: U.S. Liquefaction Capacity workbook (U.S.liquefactioncapacity_2026_Q3.xlsx; release 2026-10-01) | R52: https://www.eia.gov/naturalgas/importsexports/liquefactioncapacity/U.S.liquefactioncapacity_2026_Q3.xlsx | S52: 2026-10-01 | T52: SOURCED | U52: EIA 'Approved' tab (DOE and FERC/MARAD approved, no FID): Undergoing FEED. Design capacity 10.85 mtpa (2 train(s)). [capacity_bcfd DERIVED: mtpa x 1.36 bcm/y x 35.3147 / 365.25 = 0.1315 Bcf/d per mtpa]
A53: Global supply | B53: United States | C53: liquefaction_train | D53: Delfin FLNG additional vessels (beyond Train 1) | E53: Fairwood Group | F53: liquefaction | G53: 4.4 | H53: mtpa | J53: 0.5786 | K53: PERMITTED | M53: NOT_STATED | N53: 2026-10-12 | O53: 2026-10-12 | P53: U.S. Energy Information Administration | Q53: U.S. Liquefaction Capacity workbook (U.S.liquefactioncapacity_2026_Q3.xlsx; release 2026-10-01) | R53: https://www.eia.gov/naturalgas/importsexports/liquefactioncapacity/U.S.liquefactioncapacity_2026_Q3.xlsx | S53: 2026-10-01 | T53: DERIVED | U53: EIA 'Approved' tab (DOE and FERC/MARAD approved, no FID): Completed FEED, awarded EPC contract to Samsung Heavy Industries and Black & Veatch. Project was granted DOE authorization for a 5-year extension to 2029 to commence operations. . Design capacity 8.80 mtpa (2 train(s)). Total approved 8.8 mtpa less the first vessel (4.4 mtpa, under construction in the other tab): remainder DERIVED. [capacity_bcfd DERIVED: mtpa x 1.36 bcm/y x 35.3147 / 365.25 = 0.1315 Bcf/d per mtpa]
A54: Global supply | B54: United States | C54: liquefaction_train | D54: Alaska LNG | E54: Alaska Gasline Development Corporation (AGDC) | F54: liquefaction | G54: 20 | H54: mtpa | J54: 2.63 | K54: PLANNED | M54: NOT_STATED | N54: 2026-10-12 | O54: 2026-10-12 | P54: U.S. Energy Information Administration | Q54: U.S. Liquefaction Capacity workbook (U.S.liquefactioncapacity_2026_Q3.xlsx; release 2026-10-01) | R54: https://www.eia.gov/naturalgas/importsexports/liquefactioncapacity/U.S.liquefactioncapacity_2026_Q3.xlsx | S54: 2026-10-01 | T54: SOURCED | U54: EIA 'Approved' tab (DOE and FERC/MARAD approved, no FID): Proposed. Design capacity 20.00 mtpa (3 train(s)). [capacity_bcfd DERIVED: mtpa x 1.36 bcm/y x 35.3147 / 365.25 = 0.1315 Bcf/d per mtpa]
A55: Global supply | B55: Qatar | C55: liquefaction_train | D55: Existing LNG trains at Ras Laffan (14 trains) excl. the two damaged trains | E55: QatarEnergy LNG | F55: liquefaction | G55: 64.2 | H55: mtpa | J55: 8.4423 | K55: OPERATING | L55: 1996 | M55: SOURCED_YEAR | N55: 2026-10-12 | O55: 2026-10-12 | P55: QatarEnergy | Q55: Update to Investors, November 2025 (North Field expansion programme, p.9) | R55: https://www.qatarenergy.qa/en/MediaCenter/Publications/QatarEnergy_Investors_Presentation_November_2025.pdf | S55: 2025-11-01 | T55: DERIVED | U55: 77 mtpa current (QatarEnergy Nov 2025 deck: 14 trains) less 12.8 mtpa damaged (next row, GIIGNL figure). DISR REQ Sep 2026: capacity 'largely intact', ~80% of capacity within a month of the Strait reopening. Export routes depend on the Strait of Hormuz, which was disrupted in 2026 (DISR REQ Sep 2026): nameplate unchanged, exports constrained. [capacity_bcfd DERIVED: mtpa x 1.36 bcm/y x 35.3147 / 365.25 = 0.1315 Bcf/d per mtpa]
A56: Global supply | B56: Qatar | C56: liquefaction_train | D56: Ras Laffan LNG Trains 4 and 6 (damaged by missile strikes 18 Mar 2026) | E56: QatarEnergy LNG | F56: liquefaction | G56: 12.8 | H56: mtpa | J56: 1.6832 | K56: SUSPENDED | L56: 1996 | M56: SOURCED_YEAR | N56: 2026-10-12 | O56: 2026-10-12 | P56: GIIGNL (used only where no official figure was opened; named as publisher) | Q56: GIIGNL Annual Report 2026 edition (2025 data): liquefaction plants table and 'Liquefaction' regional sections | R56: https://giignl-documents.s3.fr-par.scw.cloud/public/giignl-2026-annual-report.pdf | S56: 2026-05-20 | T56: SOURCED | U56: NUMBER FROM GIIGNL (publisher; no QatarEnergy document with it was reachable): strikes damaged LNG Trains 4 and 6, removing 12.8 mtpa, repairs three to five years per QatarEnergy's March 2026 statement as quoted by GIIGNL; Reuters 7 Oct 2026: repairs could take three years. DISR REQ Sep 2026 confirms missile damage mid-March 2026 (no mtpa). No return date is stated. [capacity_bcfd DERIVED: mtpa x 1.36 bcm/y x 35.3147 / 365.25 = 0.1315 Bcf/d per mtpa]
A57: Global supply | B57: Qatar | C57: liquefaction_train | D57: North Field East expansion, Train 1 of 4 (8 mtpa) | E57: QatarEnergy LNG | F57: liquefaction | G57: 8 | H57: mtpa | J57: 1.052 | K57: UNDER_CONSTRUCTION | L57: 2027 | M57: SOURCED_YEAR | N57: 2026-10-12 | O57: 2026-10-12 | P57: Reuters (copy on BOE Report) | Q57: QatarEnergy's LNG expansion project poised to start operations in November, sources say (7 Oct 2026) | R57: https://boereport.com/2026/10/07/qatarenergys-lng-expansion-project-poised-to-start-operations-in-november-sources-say/amp/ | S57: 2026-10-07 | T57: SOURCED | U57: Date: QatarEnergy CEO, production expected in H1 2027 (Reuters copy, 7 Oct 2026; same report: train ready to start in November 2026, LNG from it in Q1 2027, per two unnamed sources). Capacity: NFE = 32 mtpa in 4 trains of 8 (QatarEnergy deck Nov 2025). GIIGNL 2026: first two NFE trains had been expected late 2026, now likely postponed. Export routes depend on the Strait of Hormuz, which was disrupted in 2026 (DISR REQ Sep 2026): nameplate unchanged, exports constrained. [capacity_bcfd DERIVED: mtpa x 1.36 bcm/y x 35.3147 / 365.25 = 0.1315 Bcf/d per mtpa]
A58: Global supply | B58: Qatar | C58: liquefaction_train | D58: North Field East expansion, Trains 2-4 (3 x 8 mtpa) | E58: QatarEnergy LNG | F58: liquefaction | G58: 24 | H58: mtpa | J58: 3.156 | K58: UNDER_CONSTRUCTION | M58: NOT_STATED | N58: 2026-10-12 | O58: 2026-10-12 | P58: QatarEnergy | Q58: Update to Investors, November 2025 (North Field expansion programme, p.9) | R58: https://www.qatarenergy.qa/en/MediaCenter/Publications/QatarEnergy_Investors_Presentation_November_2025.pdf | S58: 2025-11-01 | T58: SOURCED | U58: 4 trains x 8 mtpa = 32 mtpa (deck p.9); no per-train date in an opened QatarEnergy document. Programme target 142 mtpa by 2030 (deck). DISR REQ Sep 2026 (NexantECA): Qatari capacity expected to stay below 90 Mt until 2029 and reach 133 Mt by 2031 (was 142 Mt by 2031). [capacity_bcfd DERIVED: mtpa x 1.36 bcm/y x 35.3147 / 365.25 = 0.1315 Bcf/d per mtpa]
A59: Global supply | B59: Qatar | C59: liquefaction_train | D59: North Field South expansion (2 trains x 8 mtpa) | E59: QatarEnergy LNG | F59: liquefaction | G59: 16 | H59: mtpa | J59: 2.104 | K59: UNDER_CONSTRUCTION | M59: NOT_STATED | N59: 2026-10-12 | O59: 2026-10-12 | P59: QatarEnergy | Q59: Update to Investors, November 2025 (North Field expansion programme, p.9) | R59: https://www.qatarenergy.qa/en/MediaCenter/Publications/QatarEnergy_Investors_Presentation_November_2025.pdf | S59: 2025-11-01 | T59: SOURCED | U59: 16 mtpa, 2 trains of 8 mtpa (deck p.9). No start date in an opened QatarEnergy document; part of the 142 mtpa-by-2030 programme. [capacity_bcfd DERIVED: mtpa x 1.36 bcm/y x 35.3147 / 365.25 = 0.1315 Bcf/d per mtpa]
A60: Global supply | B60: Qatar | C60: liquefaction_train | D60: North Field West expansion (2 trains x 8 mtpa) | E60: QatarEnergy LNG | F60: liquefaction | G60: 16 | H60: mtpa | J60: 2.104 | K60: PLANNED | M60: NOT_STATED | N60: 2026-10-12 | O60: 2026-10-12 | P60: QatarEnergy | Q60: Update to Investors, November 2025 (North Field expansion programme, p.9) | R60: https://www.qatarenergy.qa/en/MediaCenter/Publications/QatarEnergy_Investors_Presentation_November_2025.pdf | S60: 2025-11-01 | T60: SOURCED | U60: 16 mtpa, 2 trains (deck p.9; announced Feb 2024). Programme target 142 mtpa by 2030. No FID or per-train date in an opened document. [capacity_bcfd DERIVED: mtpa x 1.36 bcm/y x 35.3147 / 365.25 = 0.1315 Bcf/d per mtpa]
A61: Global supply | B61: Canada | C61: liquefaction_train | D61: LNG Canada Phase 1 (2 trains) | E61: LNG Canada (Shell 40%) | F61: liquefaction | G61: 14 | H61: mtpa | J61: 1.841 | K61: COMMISSIONED_RECENT | L61: 2025 | M61: SOURCED_YEAR | N61: 2026-10-12 | O61: 2026-10-12 | P61: Shell Canada Energy / Shell plc (release text as republished by Hellenic Shipping News) | Q61: Shell takes final investment decision to double LNG Canada capacity (29 Sep 2026) | R61: https://www.hellenicshippingnews.com/shell-takes-final-investment-decision-to-double-lng-canada-capacity | S61: 2026-09-29 | T61: SOURCED | U61: Capacity: Shell release 29 Sep 2026 (Phase 2 raises capacity 'from 14 mtpa to 28 mtpa'). Start year 2025 from GIIGNL 2026 (Trains 1 and 2, 7.0 each, online in 2025; month not stated). [capacity_bcfd DERIVED: mtpa x 1.36 bcm/y x 35.3147 / 365.25 = 0.1315 Bcf/d per mtpa]
A62: Global supply | B62: Canada | C62: liquefaction_train | D62: Tilbury LNG | E62: FortisBC | F62: liquefaction | G62: 0.3 | H62: mtpa | J62: 0.0394 | K62: OPERATING | L62: 1971 | M62: SOURCED_YEAR | N62: 2026-10-12 | O62: 2026-10-12 | P62: GIIGNL (used only where no official figure was opened; named as publisher) | Q62: GIIGNL Annual Report 2026 edition (2025 data): liquefaction plants table and 'Liquefaction' regional sections | R62: https://giignl-documents.s3.fr-par.scw.cloud/public/giignl-2026-annual-report.pdf | S62: 2026-05-20 | T62: SOURCED | U62: Small-scale plant, Delta BC (GIIGNL number). [capacity_bcfd DERIVED: mtpa x 1.36 bcm/y x 35.3147 / 365.25 = 0.1315 Bcf/d per mtpa]
A63: Global supply | B63: Canada | C63: liquefaction_train | D63: LNG Canada Phase 2 (2 trains, +14 mtpa) | E63: LNG Canada (Shell 40%) | F63: liquefaction | G63: 14 | H63: mtpa | J63: 1.841 | K63: FID | M63: NOT_STATED | N63: 2026-10-12 | O63: 2026-10-12 | P63: Shell Canada Energy / Shell plc (release text as republished by Hellenic Shipping News) | Q63: Shell takes final investment decision to double LNG Canada capacity (29 Sep 2026) | R63: https://www.hellenicshippingnews.com/shell-takes-final-investment-decision-to-double-lng-canada-capacity | S63: 2026-09-29 | T63: SOURCED | U63: FID 29 Sep 2026: doubles capacity from 14 to 28 mtpa; 'commercial operations expected to begin in the early 2030s' (no month; not in the dated series). [capacity_bcfd DERIVED: mtpa x 1.36 bcm/y x 35.3147 / 365.25 = 0.1315 Bcf/d per mtpa]
A64: Global supply | B64: Canada | C64: liquefaction_train | D64: Woodfibre LNG | E64: Woodfibre LNG | F64: liquefaction | G64: 2.1 | H64: mtpa | J64: 0.2762 | K64: UNDER_CONSTRUCTION | L64: 2027 | M64: SOURCED_YEAR | N64: 2026-10-12 | O64: 2026-10-12 | P64: Woodfibre LNG | Q64: Construction page (2.1 million tonnes of LNG per year; substantial completion expected by 2027) | R64: https://woodfibrelng.ca/construction/ | S64: 2026-10-12 | T64: SOURCED | U64: Company: designed to produce 2.1 million tonnes of LNG per year; substantial completion expected by 2027 (GIIGNL: 65% complete March 2026). [capacity_bcfd DERIVED: mtpa x 1.36 bcm/y x 35.3147 / 365.25 = 0.1315 Bcf/d per mtpa]
A65: Global supply | B65: Canada | C65: liquefaction_train | D65: Cedar LNG (floating, Kitimat) | E65: Cedar LNG (Haisla Nation / Pembina) | F65: liquefaction | H65: mtpa | K65: UNDER_CONSTRUCTION | L65: 2028 | M65: SOURCED_QUARTER | N65: 2026-10-12 | O65: 2026-10-12 | P65: Pembina Pipeline Corporation | Q65: Q2 2026 results news release (Cedar LNG first exports late 2028) | R65: https://www.pembina.com/media-centre/news/details/fa13b9e4-bbc0-44d0-9ab6-88c72cbd54e5 | S65: 2026-07-30 | T65: SOURCED | U65: Pembina Q2 2026: first exports expected late 2028; vessel more than 70% complete. NO capacity figure in any opened document (Pembina, Cedar site, GIIGNL): left blank, not in the totals ('Tried'). [capacity_bcfd DERIVED: mtpa x 1.36 bcm/y x 35.3147 / 365.25 = 0.1315 Bcf/d per mtpa]
A66: Global supply | B66: Canada | C66: liquefaction_train | D66: Ksi Lisims LNG (floating, 12 mtpa) | E66: Ksi Lisims LNG (Nisga'a Nation / Rockies LNG / Western LNG) | F66: liquefaction | G66: 12 | H66: mtpa | J66: 1.578 | K66: PERMITTED | M66: NOT_STATED | N66: 2026-10-12 | O66: 2026-10-12 | P66: GIIGNL (used only where no official figure was opened; named as publisher) | Q66: GIIGNL Annual Report 2026 edition (2025 data): liquefaction plants table and 'Liquefaction' regional sections | R66: https://giignl-documents.s3.fr-par.scw.cloud/public/giignl-2026-annual-report.pdf | S66: 2026-05-20 | T66: SOURCED | U66: NUMBER FROM GIIGNL (no official figure opened): 12 MTPA FLNG, federal approvals, fast-tracked; no FID reported there. [capacity_bcfd DERIVED: mtpa x 1.36 bcm/y x 35.3147 / 365.25 = 0.1315 Bcf/d per mtpa]
A67: Global supply | B67: Mexico | C67: liquefaction_train | D67: Energia Costa Azul LNG Phase 1 (1 train, 3.25 mtpa) | E67: Sempra Infrastructure | F67: liquefaction | G67: 3.25 | H67: mtpa | J67: 0.4274 | K67: COMMISSIONED_RECENT | L67: 2026-07 | M67: SOURCED_MONTH | N67: 2026-10-12 | O67: 2026-10-12 | P67: GIIGNL (used only where no official figure was opened; named as publisher) | Q67: GIIGNL Annual Report 2026 edition (2025 data): liquefaction plants table and 'Liquefaction' regional sections | R67: https://giignl-documents.s3.fr-par.scw.cloud/public/giignl-2026-annual-report.pdf | S67: 2026-05-20 | T67: SOURCED | U67: Capacity 3.25 mtpa from GIIGNL 2026 (no official figure opened). Start: TotalEnergies 2Q26 release says ECA LNG 'started-up early July' 2026. [capacity_bcfd DERIVED: mtpa x 1.36 bcm/y x 35.3147 / 365.25 = 0.1315 Bcf/d per mtpa]
A68: Global supply | B68: Mexico | C68: liquefaction_train | D68: Altamira FLNG 1 (floating) | E68: New Fortress Energy | F68: liquefaction | G68: 1.4 | H68: mtpa | J68: 0.1841 | K68: OPERATING | L68: 2024 | M68: SOURCED_YEAR | N68: 2026-10-12 | O68: 2026-10-12 | P68: GIIGNL (used only where no official figure was opened; named as publisher) | Q68: GIIGNL Annual Report 2026 edition (2025 data): liquefaction plants table and 'Liquefaction' regional sections | R68: https://giignl-documents.s3.fr-par.scw.cloud/public/giignl-2026-annual-report.pdf | S68: 2026-05-20 | T68: SOURCED | U68: GIIGNL plants table: operating since 2024. [capacity_bcfd DERIVED: mtpa x 1.36 bcm/y x 35.3147 / 365.25 = 0.1315 Bcf/d per mtpa]
A69: Global supply | B69: Australia | C69: liquefaction_train | D69: Gorgon LNG | E69: Chevron | F69: liquefaction | G69: 15.6 | H69: mtpa | J69: 2.0514 | K69: OPERATING | L69: 2016 | M69: SOURCED_YEAR | N69: 2026-10-12 | O69: 2026-10-12 | P69: Department of Industry, Science and Resources (Australia) | Q69: Resources and Energy Quarterly, September 2026 (section 6 LNG; map 'Nameplate capacity, million tonnes per annum') | R69: https://www.industry.gov.au/sites/default/files/2026-10/resources-and-energy-quarterly-september-2026.pdf | S69: 2026-10-02 | T69: SOURCED | U69: DISR REQ Sep 2026 nameplate map (labels read from the PDF text; plant-to-label match checked against the 88 Mtpa total). [capacity_bcfd DERIVED: mtpa x 1.36 bcm/y x 35.3147 / 365.25 = 0.1315 Bcf/d per mtpa]
A70: Global supply | B70: Australia | C70: liquefaction_train | D70: Wheatstone LNG | E70: Chevron | F70: liquefaction | G70: 8.9 | H70: mtpa | J70: 1.1704 | K70: OPERATING | L70: 2017 | M70: SOURCED_YEAR | N70: 2026-10-12 | O70: 2026-10-12 | P70: Department of Industry, Science and Resources (Australia) | Q70: Resources and Energy Quarterly, September 2026 (section 6 LNG; map 'Nameplate capacity, million tonnes per annum') | R70: https://www.industry.gov.au/sites/default/files/2026-10/resources-and-energy-quarterly-september-2026.pdf | S70: 2026-10-02 | T70: SOURCED | U70: DISR REQ Sep 2026 nameplate map. [capacity_bcfd DERIVED: mtpa x 1.36 bcm/y x 35.3147 / 365.25 = 0.1315 Bcf/d per mtpa]
A71: Global supply | B71: Australia | C71: liquefaction_train | D71: Ichthys LNG | E71: INPEX | F71: liquefaction | G71: 8.9 | H71: mtpa | J71: 1.1704 | K71: OPERATING | L71: 2018 | M71: SOURCED_YEAR | N71: 2026-10-12 | O71: 2026-10-12 | P71: Department of Industry, Science and Resources (Australia) | Q71: Resources and Energy Quarterly, September 2026 (section 6 LNG; map 'Nameplate capacity, million tonnes per annum') | R71: https://www.industry.gov.au/sites/default/files/2026-10/resources-and-energy-quarterly-september-2026.pdf | S71: 2026-10-02 | T71: SOURCED | U71: DISR REQ Sep 2026 nameplate map. [capacity_bcfd DERIVED: mtpa x 1.36 bcm/y x 35.3147 / 365.25 = 0.1315 Bcf/d per mtpa]
A72: Global supply | B72: Australia | C72: liquefaction_train | D72: Pluto LNG Train 1 | E72: Woodside | F72: liquefaction | G72: 4.7 | H72: mtpa | J72: 0.6181 | K72: OPERATING | L72: 2012 | M72: SOURCED_YEAR | N72: 2026-10-12 | O72: 2026-10-12 | P72: Department of Industry, Science and Resources (Australia) | Q72: Resources and Energy Quarterly, September 2026 (section 6 LNG; map 'Nameplate capacity, million tonnes per annum') | R72: https://www.industry.gov.au/sites/default/files/2026-10/resources-and-energy-quarterly-september-2026.pdf | S72: 2026-10-02 | T72: SOURCED | U72: DISR REQ Sep 2026 nameplate map (GIIGNL: 4.9). [capacity_bcfd DERIVED: mtpa x 1.36 bcm/y x 35.3147 / 365.25 = 0.1315 Bcf/d per mtpa]
A73: Global supply | B73: Australia | C73: liquefaction_train | D73: Prelude FLNG | E73: Shell | F73: liquefaction | G73: 3.6 | H73: mtpa | J73: 0.4734 | K73: OPERATING | L73: 2019 | M73: SOURCED_YEAR | N73: 2026-10-12 | O73: 2026-10-12 | P73: Department of Industry, Science and Resources (Australia) | Q73: Resources and Energy Quarterly, September 2026 (section 6 LNG; map 'Nameplate capacity, million tonnes per annum') | R73: https://www.industry.gov.au/sites/default/files/2026-10/resources-and-energy-quarterly-september-2026.pdf | S73: 2026-10-02 | T73: SOURCED | U73: DISR REQ Sep 2026 nameplate map. [capacity_bcfd DERIVED: mtpa x 1.36 bcm/y x 35.3147 / 365.25 = 0.1315 Bcf/d per mtpa]
A74: Global supply | B74: Australia | C74: liquefaction_train | D74: Darwin LNG | E74: Santos | F74: liquefaction | G74: 3.7 | H74: mtpa | J74: 0.4866 | K74: OPERATING | L74: 2006 | M74: SOURCED_YEAR | N74: 2026-10-12 | O74: 2026-10-12 | P74: Department of Industry, Science and Resources (Australia) | Q74: Resources and Energy Quarterly, September 2026 (section 6 LNG; map 'Nameplate capacity, million tonnes per annum') | R74: https://www.industry.gov.au/sites/default/files/2026-10/resources-and-energy-quarterly-september-2026.pdf | S74: 2026-10-02 | T74: SOURCED | U74: DISR REQ Sep 2026 nameplate map. Barossa gas replaced Bayu-Undan; first Barossa cargo Jan 2026 (GIIGNL). [capacity_bcfd DERIVED: mtpa x 1.36 bcm/y x 35.3147 / 365.25 = 0.1315 Bcf/d per mtpa]
A75: Global supply | B75: Australia | C75: liquefaction_train | D75: Australia Pacific LNG (APLNG) | E75: Origin / ConocoPhillips | F75: liquefaction | G75: 9 | H75: mtpa | J75: 1.1835 | K75: OPERATING | L75: 2016 | M75: SOURCED_YEAR | N75: 2026-10-12 | O75: 2026-10-12 | P75: Department of Industry, Science and Resources (Australia) | Q75: Resources and Energy Quarterly, September 2026 (section 6 LNG; map 'Nameplate capacity, million tonnes per annum') | R75: https://www.industry.gov.au/sites/default/files/2026-10/resources-and-energy-quarterly-september-2026.pdf | S75: 2026-10-02 | T75: SOURCED | U75: DISR REQ Sep 2026 nameplate map. [capacity_bcfd DERIVED: mtpa x 1.36 bcm/y x 35.3147 / 365.25 = 0.1315 Bcf/d per mtpa]
A76: Global supply | B76: Australia | C76: liquefaction_train | D76: Gladstone LNG (GLNG) | E76: Santos | F76: liquefaction | G76: 7.8 | H76: mtpa | J76: 1.0257 | K76: OPERATING | L76: 2015 | M76: SOURCED_YEAR | N76: 2026-10-12 | O76: 2026-10-12 | P76: Department of Industry, Science and Resources (Australia) | Q76: Resources and Energy Quarterly, September 2026 (section 6 LNG; map 'Nameplate capacity, million tonnes per annum') | R76: https://www.industry.gov.au/sites/default/files/2026-10/resources-and-energy-quarterly-september-2026.pdf | S76: 2026-10-02 | T76: SOURCED | U76: DISR REQ Sep 2026 nameplate map. [capacity_bcfd DERIVED: mtpa x 1.36 bcm/y x 35.3147 / 365.25 = 0.1315 Bcf/d per mtpa]
A77: Global supply | B77: Australia | C77: liquefaction_train | D77: Queensland Curtis LNG (QCLNG) | E77: Shell | F77: liquefaction | G77: 8.5 | H77: mtpa | J77: 1.1178 | K77: OPERATING | L77: 2015 | M77: SOURCED_YEAR | N77: 2026-10-12 | O77: 2026-10-12 | P77: Department of Industry, Science and Resources (Australia) | Q77: Resources and Energy Quarterly, September 2026 (section 6 LNG; map 'Nameplate capacity, million tonnes per annum') | R77: https://www.industry.gov.au/sites/default/files/2026-10/resources-and-energy-quarterly-september-2026.pdf | S77: 2026-10-02 | T77: SOURCED | U77: DISR REQ Sep 2026 nameplate map. [capacity_bcfd DERIVED: mtpa x 1.36 bcm/y x 35.3147 / 365.25 = 0.1315 Bcf/d per mtpa]
A78: Global supply | B78: Australia | C78: liquefaction_train | D78: North West Shelf LNG, four remaining trains | E78: Woodside | F78: liquefaction | G78: 14.5 | H78: mtpa | J78: 1.9068 | K78: OPERATING | L78: 1989 | M78: SOURCED_YEAR | N78: 2026-10-12 | O78: 2026-10-12 | P78: GIIGNL (used only where no official figure was opened; named as publisher) | Q78: GIIGNL Annual Report 2026 edition (2025 data): liquefaction plants table and 'Liquefaction' regional sections | R78: https://giignl-documents.s3.fr-par.scw.cloud/public/giignl-2026-annual-report.pdf | S78: 2026-05-20 | T78: SOURCED | U78: DISR REQ lists NWS at 16.9 Mtpa (all five trains). Woodside H1 2026: Karratha Gas Plant has four onshore LNG trains; GIIGNL 2026 (number used): Train 2 permanently ceased, total 17 -> 14.5 mtpa. [capacity_bcfd DERIVED: mtpa x 1.36 bcm/y x 35.3147 / 365.25 = 0.1315 Bcf/d per mtpa]
A79: Global supply | B79: Australia | C79: liquefaction_train | D79: North West Shelf LNG Train 2 (permanently ceased) | E79: Woodside | F79: liquefaction | G79: 2.6 | H79: mtpa | J79: 0.3419 | K79: CLOSED | L79: 1989 | M79: SOURCED_YEAR | N79: 2026-10-12 | O79: 2026-10-12 | P79: GIIGNL (used only where no official figure was opened; named as publisher) | Q79: GIIGNL Annual Report 2026 edition (2025 data): liquefaction plants table and 'Liquefaction' regional sections | R79: https://giignl-documents.s3.fr-par.scw.cloud/public/giignl-2026-annual-report.pdf | S79: 2026-05-20 | T79: SOURCED | U79: GIIGNL 2026: Woodside definitively ceased operations at Train 2 (2.6 mtpa) as feedgas declined; month not stated (placed mid-2025). [capacity_bcfd DERIVED: mtpa x 1.36 bcm/y x 35.3147 / 365.25 = 0.1315 Bcf/d per mtpa]
A80: Global supply | B80: Australia | C80: liquefaction_train | D80: Pluto Train 2 (Scarborough Energy Project) | E80: Woodside | F80: liquefaction | H80: mtpa | K80: UNDER_CONSTRUCTION | L80: 2026 | M80: SOURCED_QUARTER | N80: 2026-10-12 | O80: 2026-10-12 | P80: Woodside Energy | Q80: Half-Year Report 2026 (period ended 30 June 2026) | R80: https://www.woodside.com/docs/default-source/investor-documents/quarterly-and-half-yearly-pdfs-and-data-tables/2026/half-year-2026-report.pdf?sfvrsn=df6d6ddc_6 | S80: 2026-08-26 | T80: SOURCED | U80: Woodside H1 2026: 98% complete, first LNG cargo on track for Q4 2026. NO nameplate capacity in any opened document (Woodside, DISR REQ, GIIGNL): left blank, not in the totals ('Tried'). [capacity_bcfd DERIVED: mtpa x 1.36 bcm/y x 35.3147 / 365.25 = 0.1315 Bcf/d per mtpa]
A81: Global supply | B81: Russia | C81: liquefaction_train | D81: Yamal LNG, Trains 1-4 | E81: Novatek (Yamal LNG) | F81: liquefaction | G81: 17.4 | H81: mtpa | J81: 2.2881 | K81: OPERATING | L81: 2017 | M81: SOURCED_YEAR | N81: 2026-10-12 | O81: 2026-10-12 | P81: GIIGNL (used only where no official figure was opened; named as publisher) | Q81: GIIGNL Annual Report 2026 edition (2025 data): liquefaction plants table and 'Liquefaction' regional sections | R81: https://giignl-documents.s3.fr-par.scw.cloud/public/giignl-2026-annual-report.pdf | S81: 2026-05-20 | T81: SOURCED | U81: T1-T3 5.5 each + T4 0.9 (GIIGNL plants table). [capacity_bcfd DERIVED: mtpa x 1.36 bcm/y x 35.3147 / 365.25 = 0.1315 Bcf/d per mtpa]
A82: Global supply | B82: Russia | C82: liquefaction_train | D82: Sakhalin-2 (2 trains) | E82: Sakhalin Energy | F82: liquefaction | G82: 10.8 | H82: mtpa | J82: 1.4202 | K82: OPERATING | L82: 2009 | M82: SOURCED_YEAR | N82: 2026-10-12 | O82: 2026-10-12 | P82: GIIGNL (used only where no official figure was opened; named as publisher) | Q82: GIIGNL Annual Report 2026 edition (2025 data): liquefaction plants table and 'Liquefaction' regional sections | R82: https://giignl-documents.s3.fr-par.scw.cloud/public/giignl-2026-annual-report.pdf | S82: 2026-05-20 | T82: SOURCED | U82: 2 x 5.4 (GIIGNL). [capacity_bcfd DERIVED: mtpa x 1.36 bcm/y x 35.3147 / 365.25 = 0.1315 Bcf/d per mtpa]
A83: Global supply | B83: Russia | C83: liquefaction_train | D83: Portovaya LNG | E83: Gazprom / Portovaya | F83: liquefaction | G83: 1.5 | H83: mtpa | J83: 0.1973 | K83: OPERATING | L83: 2022 | M83: SOURCED_YEAR | N83: 2026-10-12 | O83: 2026-10-12 | P83: GIIGNL (used only where no official figure was opened; named as publisher) | Q83: GIIGNL Annual Report 2026 edition (2025 data): liquefaction plants table and 'Liquefaction' regional sections | R83: https://giignl-documents.s3.fr-par.scw.cloud/public/giignl-2026-annual-report.pdf | S83: 2026-05-20 | T83: SOURCED | U83: US sanctions Jan 2025; GIIGNL: exports from both Baltic terminals ceased after the 27 Feb 2025 grace period; DISR REQ Sep 2026: Portovaya and Arctic LNG 2 resumed regular loadings in mid-2026, to China. Sanctioned by European buyers. [capacity_bcfd DERIVED: mtpa x 1.36 bcm/y x 35.3147 / 365.25 = 0.1315 Bcf/d per mtpa]
A84: Global supply | B84: Russia | C84: liquefaction_train | D84: Vysotsk LNG | E84: Novatek | F84: liquefaction | G84: 0.9 | H84: mtpa | J84: 0.1184 | K84: OPERATING | L84: 2019 | M84: SOURCED_YEAR | N84: 2026-10-12 | O84: 2026-10-12 | P84: GIIGNL (used only where no official figure was opened; named as publisher) | Q84: GIIGNL Annual Report 2026 edition (2025 data): liquefaction plants table and 'Liquefaction' regional sections | R84: https://giignl-documents.s3.fr-par.scw.cloud/public/giignl-2026-annual-report.pdf | S84: 2026-05-20 | T84: SOURCED | U84: US-sanctioned Jan 2025; exports ceased after Feb 2025 (GIIGNL). [capacity_bcfd DERIVED: mtpa x 1.36 bcm/y x 35.3147 / 365.25 = 0.1315 Bcf/d per mtpa]
A85: Global supply | B85: Russia | C85: liquefaction_train | D85: Arctic LNG 2, Train 1 | E85: Novatek | F85: liquefaction | G85: 6.6 | H85: mtpa | J85: 0.8679 | K85: OPERATING | L85: 2024 | M85: SOURCED_YEAR | N85: 2026-10-12 | O85: 2026-10-12 | P85: Novatek | Q85: FID release, Arctic LNG 2 (2019: three trains of 6.6 mtpa; schedule since changed) | R85: https://www.novatek.ru/common/upload/press/FID_Arctic_LNG_2_Eng.pdf | S85: 2019-09-01 | T85: SOURCED | U85: 6.6 mtpa per train (Novatek FID release); start 2024 from GIIGNL. Under US, EU and UK sanctions (2024); DISR REQ Sep 2026: regular cargo loadings to China since mid-2026. [capacity_bcfd DERIVED: mtpa x 1.36 bcm/y x 35.3147 / 365.25 = 0.1315 Bcf/d per mtpa]
A86: Global supply | B86: Russia | C86: liquefaction_train | D86: Arctic LNG 2, Train 2 | E86: Novatek | F86: liquefaction | G86: 6.6 | H86: mtpa | J86: 0.8679 | K86: COMMISSIONED_RECENT | L86: 2025 | M86: SOURCED_YEAR | N86: 2026-10-12 | O86: 2026-10-12 | P86: Novatek | Q86: FID release, Arctic LNG 2 (2019: three trains of 6.6 mtpa; schedule since changed) | R86: https://www.novatek.ru/common/upload/press/FID_Arctic_LNG_2_Eng.pdf | S86: 2019-09-01 | T86: SOURCED | U86: 6.6 mtpa per train (Novatek FID release); GIIGNL 2026: Train 2 started production in May 2025, exports limited by sanctions and ice-class carriers. Sanctioned. [capacity_bcfd DERIVED: mtpa x 1.36 bcm/y x 35.3147 / 365.25 = 0.1315 Bcf/d per mtpa]
A87: Global supply | B87: Russia | C87: liquefaction_train | D87: Arctic LNG 2, Train 3 | E87: Novatek | F87: liquefaction | G87: 6.6 | H87: mtpa | J87: 0.8679 | K87: PLANNED | M87: NOT_STATED | N87: 2026-10-12 | O87: 2026-10-12 | P87: Novatek | Q87: FID release, Arctic LNG 2 (2019: three trains of 6.6 mtpa; schedule since changed) | R87: https://www.novatek.ru/common/upload/press/FID_Arctic_LNG_2_Eng.pdf | S87: 2019-09-01 | T87: SOURCED | U87: Original schedule (Novatek 2019 FID release) was 2026; GIIGNL 2026: Novatek's other planned projects remain delayed. No current Train 3 date in an opened document. Sanctioned. [capacity_bcfd DERIVED: mtpa x 1.36 bcm/y x 35.3147 / 365.25 = 0.1315 Bcf/d per mtpa]
A88: Global supply | B88: Nigeria | C88: liquefaction_train | D88: Nigeria LNG, Trains 1-6 | E88: NLNG (NNPC 49%, Shell, TotalEnergies, Eni) | F88: liquefaction | G88: 22 | H88: mtpa | J88: 2.893 | K88: OPERATING | L88: 1999 | M88: SOURCED_YEAR | N88: 2026-10-12 | O88: 2026-10-12 | P88: Nigeria LNG Limited | Q88: Facts and Figures 2024 (six trains 22 MTPA; Train 7 lifts capacity to 30 MTPA; FID Dec 2019) | R88: https://www.nlng.com/documents/2024_NLNG_FACTS_FIGURESB_compressed.pdf | S88: 2025-01-01 | T88: SOURCED | U88: Operator: six trains, 22 MTPA. DISR REQ Sep 2026: output recovering from the 2022 force majeure. [capacity_bcfd DERIVED: mtpa x 1.36 bcm/y x 35.3147 / 365.25 = 0.1315 Bcf/d per mtpa]
A89: Global supply | B89: Nigeria | C89: liquefaction_train | D89: Nigeria LNG Train 7 | E89: NLNG | F89: liquefaction | G89: 8 | H89: mtpa | J89: 1.052 | K89: UNDER_CONSTRUCTION | M89: NOT_STATED | N89: 2026-10-12 | O89: 2026-10-12 | P89: Nigeria LNG Limited | Q89: Facts and Figures 2024 (six trains 22 MTPA; Train 7 lifts capacity to 30 MTPA; FID Dec 2019) | R89: https://www.nlng.com/documents/2024_NLNG_FACTS_FIGURESB_compressed.pdf | S89: 2025-01-01 | T89: DERIVED | U89: Operator: Train 7 lifts capacity from 22 to 30 mtpa (+8 DERIVED); FID Dec 2019. GIIGNL 2026: over 80% complete. No start date in an opened document. [capacity_bcfd DERIVED: mtpa x 1.36 bcm/y x 35.3147 / 365.25 = 0.1315 Bcf/d per mtpa]
A90: Global supply | B90: Algeria | C90: liquefaction_train | D90: Arzew GL1Z, GL2Z, GL3Z and Skikda GL1K | E90: Sonatrach | F90: liquefaction | G90: 25.3 | H90: mtpa | J90: 3.327 | K90: OPERATING | L90: 1978 | M90: SOURCED_YEAR | N90: 2026-10-12 | O90: 2026-10-12 | P90: GIIGNL (used only where no official figure was opened; named as publisher) | Q90: GIIGNL Annual Report 2026 edition (2025 data): liquefaction plants table and 'Liquefaction' regional sections | R90: https://giignl-documents.s3.fr-par.scw.cloud/public/giignl-2026-annual-report.pdf | S90: 2026-05-20 | T90: SOURCED | U90: 4.7 + 7.9 + 8.2 + 4.5 (GIIGNL plants table; GIIGNL Algeria total 25.3). [capacity_bcfd DERIVED: mtpa x 1.36 bcm/y x 35.3147 / 365.25 = 0.1315 Bcf/d per mtpa]
A91: Global supply | B91: Egypt | C91: liquefaction_train | D91: Damietta LNG and Idku (Egyptian LNG) T1-T2 | E91: SEGAS (Eni/EGAS) and ELNG (Shell/Petronas) | F91: liquefaction | G91: 12.2 | H91: mtpa | J91: 1.6043 | K91: OPERATING | L91: 2005 | M91: SOURCED_YEAR | N91: 2026-10-12 | O91: 2026-10-12 | P91: GIIGNL (used only where no official figure was opened; named as publisher) | Q91: GIIGNL Annual Report 2026 edition (2025 data): liquefaction plants table and 'Liquefaction' regional sections | R91: https://giignl-documents.s3.fr-par.scw.cloud/public/giignl-2026-annual-report.pdf | S91: 2026-05-20 | T91: SOURCED | U91: 5.0 + 3.6 + 3.6 (GIIGNL). [capacity_bcfd DERIVED: mtpa x 1.36 bcm/y x 35.3147 / 365.25 = 0.1315 Bcf/d per mtpa]
A92: Global supply | B92: Angola | C92: liquefaction_train | D92: Angola LNG | E92: Angola LNG (Chevron, Sonangol, bp, Eni, TotalEnergies) | F92: liquefaction | G92: 5.2 | H92: mtpa | J92: 0.6838 | K92: OPERATING | L92: 2013 | M92: SOURCED_YEAR | N92: 2026-10-12 | O92: 2026-10-12 | P92: GIIGNL (used only where no official figure was opened; named as publisher) | Q92: GIIGNL Annual Report 2026 edition (2025 data): liquefaction plants table and 'Liquefaction' regional sections | R92: https://giignl-documents.s3.fr-par.scw.cloud/public/giignl-2026-annual-report.pdf | S92: 2026-05-20 | T92: SOURCED | U92: GIIGNL plants table. [capacity_bcfd DERIVED: mtpa x 1.36 bcm/y x 35.3147 / 365.25 = 0.1315 Bcf/d per mtpa]
A93: Global supply | B93: Equatorial Guinea | C93: liquefaction_train | D93: EG LNG | E93: EG LNG (Marathon / Sonagas) | F93: liquefaction | G93: 3.7 | H93: mtpa | J93: 0.4866 | K93: OPERATING | L93: 2007 | M93: SOURCED_YEAR | N93: 2026-10-12 | O93: 2026-10-12 | P93: GIIGNL (used only where no official figure was opened; named as publisher) | Q93: GIIGNL Annual Report 2026 edition (2025 data): liquefaction plants table and 'Liquefaction' regional sections | R93: https://giignl-documents.s3.fr-par.scw.cloud/public/giignl-2026-annual-report.pdf | S93: 2026-05-20 | T93: SOURCED | U93: GIIGNL plants table. [capacity_bcfd DERIVED: mtpa x 1.36 bcm/y x 35.3147 / 365.25 = 0.1315 Bcf/d per mtpa]
A94: Global supply | B94: Mozambique | C94: liquefaction_train | D94: Coral South FLNG | E94: Eni (Area 4) | F94: liquefaction | G94: 3.4 | H94: mtpa | J94: 0.4471 | K94: OPERATING | L94: 2022 | M94: SOURCED_YEAR | N94: 2026-10-12 | O94: 2026-10-12 | P94: GIIGNL (used only where no official figure was opened; named as publisher) | Q94: GIIGNL Annual Report 2026 edition (2025 data): liquefaction plants table and 'Liquefaction' regional sections | R94: https://giignl-documents.s3.fr-par.scw.cloud/public/giignl-2026-annual-report.pdf | S94: 2026-05-20 | T94: SOURCED | U94: GIIGNL plants table; operating since 2022. [capacity_bcfd DERIVED: mtpa x 1.36 bcm/y x 35.3147 / 365.25 = 0.1315 Bcf/d per mtpa]
A95: Global supply | B95: Cameroon | C95: liquefaction_train | D95: Kribi FLNG Hilli Episeyo (contract ended, relocating to Argentina) | E95: Golar LNG | F95: liquefaction | G95: 2.4 | H95: mtpa | J95: 0.3156 | K95: CLOSED | L95: 2018 | M95: SOURCED_YEAR | N95: 2026-10-12 | O95: 2026-10-12 | P95: Golar LNG | Q95: Interim results for the period ended June 30, 2026 | R95: https://mfn.se/one/a/golar-lng/golar-lng-limited-interim-results-for-the-period-ended-june-30-2026-b168e773 | S95: 2026-08-13 | T95: SOURCED | U95: Golar Q2 2026: Hilli ended its eight-year Cameroon contract (156 cargoes), repositioning to Singapore for modifications before a 20-year contract in Argentina. Capacity 2.4 from GIIGNL. Closure month not stated (placed mid-2026). [capacity_bcfd DERIVED: mtpa x 1.36 bcm/y x 35.3147 / 365.25 = 0.1315 Bcf/d per mtpa]
A96: Global supply | B96: Congo | C96: liquefaction_train | D96: Tango FLNG | E96: Eni (Congo LNG) | F96: liquefaction | G96: 0.6 | H96: mtpa | J96: 0.0789 | K96: OPERATING | L96: 2024 | M96: SOURCED_YEAR | N96: 2026-10-12 | O96: 2026-10-12 | P96: GIIGNL (used only where no official figure was opened; named as publisher) | Q96: GIIGNL Annual Report 2026 edition (2025 data): liquefaction plants table and 'Liquefaction' regional sections | R96: https://giignl-documents.s3.fr-par.scw.cloud/public/giignl-2026-annual-report.pdf | S96: 2026-05-20 | T96: SOURCED | U96: GIIGNL: Phase 1 FLNG. [capacity_bcfd DERIVED: mtpa x 1.36 bcm/y x 35.3147 / 365.25 = 0.1315 Bcf/d per mtpa]
A97: Global supply | B97: Congo | C97: liquefaction_train | D97: Nguya FLNG (Congo LNG Phase 2) | E97: Eni | F97: liquefaction | G97: 2.4 | H97: mtpa | J97: 0.3156 | K97: COMMISSIONED_RECENT | L97: 2026-02 | M97: SOURCED_MONTH | N97: 2026-10-12 | O97: 2026-10-12 | P97: Department of Industry, Science and Resources (Australia) | Q97: Resources and Energy Quarterly, September 2026 (section 6 LNG; map 'Nameplate capacity, million tonnes per annum') | R97: https://www.industry.gov.au/sites/default/files/2026-10/resources-and-energy-quarterly-september-2026.pdf | S97: 2026-10-02 | T97: SOURCED | U97: Capacity: DISR REQ Sep 2026 (phase two, +2.4 Mtpa, 'nearing production'). Start Feb 2026 from GIIGNL 2026 (first cargo shipped); the two sources differ. [capacity_bcfd DERIVED: mtpa x 1.36 bcm/y x 35.3147 / 365.25 = 0.1315 Bcf/d per mtpa]
A98: Global supply | B98: Mauritania/Senegal | C98: liquefaction_train | D98: Greater Tortue Ahmeyim (GTA) Phase 1, FLNG Gimi | E98: bp (Kosmos, PETROSEN, SMH) | F98: liquefaction | G98: 2.3 | H98: mtpa | J98: 0.3024 | K98: COMMISSIONED_RECENT | L98: 2025 | M98: SOURCED_YEAR | N98: 2026-10-12 | O98: 2026-10-12 | P98: Department of Industry, Science and Resources (Australia) | Q98: Resources and Energy Quarterly, September 2026 (section 6 LNG; map 'Nameplate capacity, million tonnes per annum') | R98: https://www.industry.gov.au/sites/default/files/2026-10/resources-and-energy-quarterly-september-2026.pdf | S98: 2026-10-02 | T98: SOURCED | U98: DISR REQ Sep 2026: 2.3 Mtpa capacity, ramping up by H2 2026. Start year 2025 from GIIGNL 2026 (GIIGNL plants table: 2.4). [capacity_bcfd DERIVED: mtpa x 1.36 bcm/y x 35.3147 / 365.25 = 0.1315 Bcf/d per mtpa]
A99: Global supply | B99: Mozambique | C99: liquefaction_train | D99: Mozambique LNG (Afungi, 2 units) | E99: TotalEnergies | F99: liquefaction | G99: 13.12 | H99: mtpa | J99: 1.7253 | K99: UNDER_CONSTRUCTION | L99: 2029 | M99: SOURCED_YEAR | N99: 2026-10-12 | O99: 2026-10-12 | P99: Mozambique LNG (TotalEnergies-operated project site) | Q99: Project page: development (two liquefaction units, 13.12 MTPA) | R99: https://mozambiquelng.co.mz/about-the-mozambique-liquefied-natural-gas-project/development/ | S99: 2026-10-12 | T99: SOURCED | U99: Project site: two liquefaction units, 13.12 MTPA. DISR REQ Sep 2026: '13.2 Mtpa from 2029' (year used). GIIGNL quotes 12.8. [capacity_bcfd DERIVED: mtpa x 1.36 bcm/y x 35.3147 / 365.25 = 0.1315 Bcf/d per mtpa]
A100: Global supply | B100: Mozambique | C100: liquefaction_train | D100: Coral North FLNG (Eni, Area 4) | E100: Eni | F100: liquefaction | G100: 3.6 | H100: mtpa | J100: 0.4734 | K100: FID | L100: 2028 | M100: SOURCED_YEAR | N100: 2026-10-12 | O100: 2026-10-12 | P100: Eni | Q100: Eni announces Final Investment Decision for Mozambique's Coral North project (2 Oct 2025) | R100: https://www.eni.com/en-IT/media/press-release/2025/10/pr-eni-announces-final-investment-decision-mozambique-coral-north-project.html | S100: 2025-10-02 | T100: SOURCED | U100: Eni FID release 2 Oct 2025: production liquefaction capacity 3.6 MTPA, aiming to deliver within schedule in 2028. [capacity_bcfd DERIVED: mtpa x 1.36 bcm/y x 35.3147 / 365.25 = 0.1315 Bcf/d per mtpa]
A101: Global supply | B101: Norway | C101: liquefaction_train | D101: Hammerfest LNG (Snohvit) | E101: Equinor | F101: liquefaction | G101: 4.2 | H101: mtpa | J101: 0.5523 | K101: OPERATING | L101: 2007 | M101: SOURCED_YEAR | N101: 2026-10-12 | O101: 2026-10-12 | P101: GIIGNL (used only where no official figure was opened; named as publisher) | Q101: GIIGNL Annual Report 2026 edition (2025 data): liquefaction plants table and 'Liquefaction' regional sections | R101: https://giignl-documents.s3.fr-par.scw.cloud/public/giignl-2026-annual-report.pdf | S101: 2026-05-20 | T101: SOURCED | U101: GIIGNL plants table. [capacity_bcfd DERIVED: mtpa x 1.36 bcm/y x 35.3147 / 365.25 = 0.1315 Bcf/d per mtpa]
... A114: Global supply | B114: Indonesia | C114: liquefaction_train | D114: Bontang LNG (Train E on standby, F-H operating) | E114: Pertamina | F114: liquefaction | G114: 11.5 | H114: mtpa | J114: 1.5123 | K114: OPERATING | L114: 1977 | M114: SOURCED_YEAR | N114: 2026-10-12 | O114: 2026-10-12 | P114: GIIGNL (used only where no official figure was opened; named as publisher) | Q114: GIIGNL Annual Report 2026 edition (2025 data): liquefaction plants table and 'Liquefaction' regional sections | R114: https://giignl-documents.s3.fr-par.scw.cloud/public/giignl-2026-annual-report.pdf | S114: 2026-05-20 | T114: DERIVED | U114: DERIVED: GIIGNL Indonesia total 24.9 less Tangguh 11.4 less Donggi-Senoro 2.0. Only Trains G and H operating on limited feedgas (GIIGNL). [capacity_bcfd DERIVED: mtpa x 1.36 bcm/y x 35.3147 / 365.25 = 0.1315 Bcf/d per mtpa]
A115: Global supply | B115: Indonesia | C115: liquefaction_train | D115: Abadi LNG (Masela) | E115: INPEX / Pertamina / PETRONAS | F115: liquefaction | G115: 9.5 | H115: mtpa | J115: 1.2492 | K115: PLANNED | M115: NOT_STATED | N115: 2026-10-12 | O115: 2026-10-12 | P115: GIIGNL (used only where no official figure was opened; named as publisher) | Q115: GIIGNL Annual Report 2026 edition (2025 data): liquefaction plants table and 'Liquefaction' regional sections | R115: https://giignl-documents.s3.fr-par.scw.cloud/public/giignl-2026-annual-report.pdf | S115: 2026-05-20 | T115: SOURCED | U115: GIIGNL 2026: environmental approval granted, FEED completion expected end-2026; 9.5 MTPA design. No FID or start date. [capacity_bcfd DERIVED: mtpa x 1.36 bcm/y x 35.3147 / 365.25 = 0.1315 Bcf/d per mtpa]
A116: Global supply | B116: Papua New Guinea | C116: liquefaction_train | D116: PNG LNG (2 trains) | E116: ExxonMobil / Santos | F116: liquefaction | G116: 8.3 | H116: mtpa | J116: 1.0915 | K116: OPERATING | L116: 2014 | M116: SOURCED_YEAR | N116: 2026-10-12 | O116: 2026-10-12 | P116: GIIGNL (used only where no official figure was opened; named as publisher) | Q116: GIIGNL Annual Report 2026 edition (2025 data): liquefaction plants table and 'Liquefaction' regional sections | R116: https://giignl-documents.s3.fr-par.scw.cloud/public/giignl-2026-annual-report.pdf | S116: 2026-05-20 | T116: SOURCED | U116: GIIGNL total 8.3 (trains 4.1 + 4.1 in its table). [capacity_bcfd DERIVED: mtpa x 1.36 bcm/y x 35.3147 / 365.25 = 0.1315 Bcf/d per mtpa]
A117: Global supply | B117: Argentina | C117: liquefaction_train | D117: Southern Energy (SESA) FLNG Hilli Episeyo (relocated from Cameroon) | E117: Southern Energy (PAE, YPF, Pampa, Harbour, Golar) | F117: liquefaction | G117: 2.45 | H117: mtpa | J117: 0.3222 | K117: FID | L117: 2027 | M117: SOURCED_YEAR | N117: 2026-10-12 | O117: 2026-10-12 | P117: Golar LNG | Q117: Interim results for the period ended June 30, 2026 | R117: https://mfn.se/one/a/golar-lng/golar-lng-limited-interim-results-for-the-period-ended-june-30-2026-b168e773 | S117: 2026-08-13 | T117: SOURCED | U117: Golar Q2 2026: 20-year contract commencing H2 2027; capacity 2.45 mtpa from GIIGNL 2026. [capacity_bcfd DERIVED: mtpa x 1.36 bcm/y x 35.3147 / 365.25 = 0.1315 Bcf/d per mtpa]
A118: Global supply | B118: Argentina | C118: liquefaction_train | D118: Southern Energy (SESA) FLNG Esperanza (MKII) | E118: Southern Energy | F118: liquefaction | G118: 3.5 | H118: mtpa | J118: 0.4603 | K118: UNDER_CONSTRUCTION | L118: 2028 | M118: SOURCED_YEAR | N118: 2026-10-12 | O118: 2026-10-12 | P118: Golar LNG | Q118: Interim results for the period ended June 30, 2026 | R118: https://mfn.se/one/a/golar-lng/golar-lng-limited-interim-results-for-the-period-ended-june-30-2026-b168e773 | S118: 2026-08-13 | T118: SOURCED | U118: Golar Q2 2026: 3.5 MTPA MKII unit, conversion completes Q4 2027, contract start-up scheduled H2 2028. [capacity_bcfd DERIVED: mtpa x 1.36 bcm/y x 35.3147 / 365.25 = 0.1315 Bcf/d per mtpa]
A119: Global supply | B119: Unallocated (FLNG) | C119: liquefaction_train | D119: Golar FLNG Four (MKII, no charter yet) | E119: Golar LNG | F119: liquefaction | G119: 3.5 | H119: mtpa | J119: 0.4603 | K119: FID | L119: 2029 | M119: SOURCED_YEAR | N119: 2026-10-12 | O119: 2026-10-12 | P119: Golar LNG | Q119: Interim results for the period ended June 30, 2026 | R119: https://mfn.se/one/a/golar-lng/golar-lng-limited-interim-results-for-the-period-ended-june-30-2026-b168e773 | S119: 2026-08-13 | T119: SOURCED | U119: Golar Q2 2026: EPC signed 12 Aug 2026 with CIMC Raffles, 3.5 MTPA, delivery expected by year-end 2029; no charter or site yet. [capacity_bcfd DERIVED: mtpa x 1.36 bcm/y x 35.3147 / 365.25 = 0.1315 Bcf/d per mtpa]
A120: Global supply | B120: United States | C120: liquefaction_train | D120: Sabine Pass Stage 5 expansion (Train 7 + BOG re-liquefaction) | E120: Cheniere | F120: liquefaction | G120: 6 | H120: mtpa | J120: 0.789 | K120: PLANNED | M120: NOT_STATED | N120: 2026-10-12 | O120: 2026-10-12 | P120: Cheniere Energy | Q120: Cheniere Reports Second Quarter 2026 Results (Sabine Pass Stage 5 expansion) | R120: https://lngir.cheniere.com/_assets/_75dc2c9a1fb706f14e67cee93b0e9e5a/cheniere/news/2026-08-06_Cheniere_Reports_Second_Quarter_2026_Results_and_343.pdf | S120: 2026-08-06 | T120: SOURCED | U120: Cheniere Q2 2026: expected total production capacity of 'over 6 mtpa' (6.0 = the stated floor); FERC permit expected late 2026, FID early 2027; limited notice to proceed to Bechtel. [capacity_bcfd DERIVED: mtpa x 1.36 bcm/y x 35.3147 / 365.25 = 0.1315 Bcf/d per mtpa]

Sheet History
A1: key | B1: field | C1: old | D1: new | E1: date_seen

Sheet Capacity by month
A1: Month | B1: Operating (mtpa) | C1: Offline: damaged / shut-in (mtpa) | D1: Under construction, by expected month (cum.) | E1: FID, by expected month (cum.) | F1: Total sourced nameplate = operating + UC + FID | G1: Planned / permitted with a date (cum.) | H1: Total incl. dated planned | I1: Undated under construction (memo, constant) | J1: Undated FID (memo, constant) | K1: Undated planned / permitted (memo, constant) | L1: Total sourced nameplate (Bcf/d, DERIVED) | M1: Operating + UC + FID, with ramp (mtpa, ASSUMPTION) | N1: Incl. dated planned, with ramp (mtpa, ASSUMPTION) | O1: Ramp months (ASSUMPTION, editable)
A2: 44197 | B2: 447.41 | C2: 10.2 | D2: 0 | E2: 0 | F2: 447.41 | G2: 0 | H2: 447.41 | I2: 48 | J2: 14 | K2: 112.24 | L2: 58.834415 | M2: =B2+'Ramp calc'!AA4 | N2: =B2+'Ramp calc'!AA4+'Ramp calc'!AB4 | O2: 12
A3: 44228 | B3: 447.41 | C3: 10.2 | D3: 0 | E3: 0 | F3: 447.41 | G3: 0 | H3: 447.41 | I3: 48 | J3: 14 | K3: 112.24 | L3: 58.834415 | M3: =B3+'Ramp calc'!AA5 | N3: =B3+'Ramp calc'!AA5+'Ramp calc'!AB5 | O3: Used only in the 'with ramp' columns: each addition after the run month rises linearly from 0 to nameplate over this many months, starting in its start month.
A4: 44256 | B4: 447.41 | C4: 10.2 | D4: 0 | E4: 0 | F4: 447.41 | G4: 0 | H4: 447.41 | I4: 48 | J4: 14 | K4: 112.24 | L4: 58.834415 | M4: =B4+'Ramp calc'!AA6 | N4: =B4+'Ramp calc'!AA6+'Ramp calc'!AB6
A5: 44287 | B5: 447.41 | C5: 10.2 | D5: 0 | E5: 0 | F5: 447.41 | G5: 0 | H5: 447.41 | I5: 48 | J5: 14 | K5: 112.24 | L5: 58.834415 | M5: =B5+'Ramp calc'!AA7 | N5: =B5+'Ramp calc'!AA7+'Ramp calc'!AB7
A6: 44317 | B6: 447.41 | C6: 10.2 | D6: 0 | E6: 0 | F6: 447.41 | G6: 0 | H6: 447.41 | I6: 48 | J6: 14 | K6: 112.24 | L6: 58.834415 | M6: =B6+'Ramp calc'!AA8 | N6: =B6+'Ramp calc'!AA8+'Ramp calc'!AB8
A7: 44348 | B7: 447.41 | C7: 10.2 | D7: 0 | E7: 0 | F7: 447.41 | G7: 0 | H7: 447.41 | I7: 48 | J7: 14 | K7: 112.24 | L7: 58.834415 | M7: =B7+'Ramp calc'!AA9 | N7: =B7+'Ramp calc'!AA9+'Ramp calc'!AB9
A8: 44378 | B8: 447.41 | C8: 10.2 | D8: 0 | E8: 0 | F8: 447.41 | G8: 0 | H8: 447.41 | I8: 48 | J8: 14 | K8: 112.24 | L8: 58.834415 | M8: =B8+'Ramp calc'!AA10 | N8: =B8+'Ramp calc'!AA10+'Ramp calc'!AB10
A9: 44409 | B9: 447.41 | C9: 10.2 | D9: 0 | E9: 0 | F9: 447.41 | G9: 0 | H9: 447.41 | I9: 48 | J9: 14 | K9: 112.24 | L9: 58.834415 | M9: =B9+'Ramp calc'!AA11 | N9: =B9+'Ramp calc'!AA11+'Ramp calc'!AB11
A10: 44440 | B10: 447.41 | C10: 10.2 | D10: 0 | E10: 0 | F10: 447.41 | G10: 0 | H10: 447.41 | I10: 48 | J10: 14 | K10: 112.24 | L10: 58.834415 | M10: =B10+'Ramp calc'!AA12 | N10: =B10+'Ramp calc'!AA12+'Ramp calc'!AB12
A11: 44470 | B11: 447.41 | C11: 10.2 | D11: 0 | E11: 0 | F11: 447.41 | G11: 0 | H11: 447.41 | I11: 48 | J11: 14 | K11: 112.24 | L11: 58.834415 | M11: =B11+'Ramp calc'!AA13 | N11: =B11+'Ramp calc'!AA13+'Ramp calc'!AB13
A12: 44501 | B12: 447.41 | C12: 10.2 | D12: 0 | E12: 0 | F12: 447.41 | G12: 0 | H12: 447.41 | I12: 48 | J12: 14 | K12: 112.24 | L12: 58.834415 | M12: =B12+'Ramp calc'!AA14 | N12: =B12+'Ramp calc'!AA14+'Ramp calc'!AB14
A13: 44531 | B13: 451.91 | C13: 10.2 | D13: 0 | E13: 0 | F13: 451.91 | G13: 0 | H13: 451.91 | I13: 48 | J13: 14 | K13: 112.24 | L13: 59.426165 | M13: =B13+'Ramp calc'!AA15 | N13: =B13+'Ramp calc'!AA15+'Ramp calc'!AB15
A14: 44562 | B14: 451.91 | C14: 10.2 | D14: 0 | E14: 0 | F14: 451.91 | G14: 0 | H14: 451.91 | I14: 48 | J14: 14 | K14: 112.24 | L14: 59.426165 | M14: =B14+'Ramp calc'!AA16 | N14: =B14+'Ramp calc'!AA16+'Ramp calc'!AB16
A15: 44593 | B15: 451.91 | C15: 10.2 | D15: 0 | E15: 0 | F15: 451.91 | G15: 0 | H15: 451.91 | I15: 48 | J15: 14 | K15: 112.24 | L15: 59.426165 | M15: =B15+'Ramp calc'!AA17 | N15: =B15+'Ramp calc'!AA17+'Ramp calc'!AB17
... A121: 47818 | B121: 519.734 | C121: 23 | D121: 134.689 | E121: 9.55 | F121: 663.973 | G121: 0 | H121: 663.973 | I121: 48 | J121: 14 | K121: 112.24 | L121: 87.312449 | M121: =B121+'Ramp calc'!AA123 | N121: =B121+'Ramp calc'!AA123+'Ramp calc'!AB123

Sheet By country
A1: country | B1: Chart group | C1: Operating now (mtpa) | D1: Offline: damaged / shut-in (mtpa) | E1: Under construction: dated, online by Dec 2030 (mtpa) | F1: Under construction: undated (mtpa) | G1: FID: dated, online by Dec 2030 (mtpa) | H1: FID: undated (mtpa) | I1: Planned / permitted: dated (mtpa) | J1: Planned / permitted: undated (mtpa) | K1: Suspended / cancelled projects (memo, mtpa) | L1: Nameplate Dec 2030, sourced = operating + dated UC + FID (mtpa) | M1: Nameplate Dec 2030 incl. dated planned (mtpa) | N1: Pipeline incl. undated UC + FID (mtpa) | O1: Operating now (Bcf/d, DERIVED) | P1: Nameplate Dec 2030, sourced (Bcf/d, DERIVED)
A2: United States | B2: United States | C2: 120.384 | D2: 0 | E2: 97.369 | F2: 0 | G2: 0 | H2: 0 | I2: 0 | J2: 68.14 | K2: 16.5 | L2: 217.753 | M2: 217.753 | N2: 217.753 | O2: 15.83 | P2: 28.635
A3: Australia | B3: Australia | C3: 85.2 | D3: 0 | E3: 0 | F3: 0 | G3: 0 | H3: 0 | I3: 0 | J3: 0 | K3: 0 | L3: 85.2 | M3: 85.2 | N3: 85.2 | O3: 11.204 | P3: 11.204
A4: Qatar | B4: Qatar | C4: 64.2 | D4: 12.8 | E4: 8 | F4: 40 | G4: 0 | H4: 0 | I4: 0 | J4: 16 | K4: 0 | L4: 72.2 | M4: 72.2 | N4: 112.2 | O4: 8.442 | P4: 9.494
A5: Russia | B5: Russia | C5: 43.8 | D5: 0 | E5: 0 | F5: 0 | G5: 0 | H5: 0 | I5: 0 | J5: 6.6 | K5: 0 | L5: 43.8 | M5: 43.8 | N5: 43.8 | O5: 5.76 | P5: 5.76
A6: Malaysia | B6: Other | C6: 32.1 | D6: 0 | E6: 0 | F6: 0 | G6: 0 | H6: 0 | I6: 0 | J6: 0 | K6: 0 | L6: 32.1 | M6: 32.1 | N6: 32.1 | O6: 4.221 | P6: 4.221
A7: Algeria | B7: Africa | C7: 25.3 | D7: 0 | E7: 0 | F7: 0 | G7: 0 | H7: 0 | I7: 0 | J7: 0 | K7: 0 | L7: 25.3 | M7: 25.3 | N7: 25.3 | O7: 3.327 | P7: 3.327
A8: Indonesia | B8: Other | C8: 24.9 | D8: 0 | E8: 0 | F8: 0 | G8: 0 | H8: 0 | I8: 0 | J8: 9.5 | K8: 0 | L8: 24.9 | M8: 24.9 | N8: 24.9 | O8: 3.274 | P8: 3.274
A9: Nigeria | B9: Africa | C9: 22 | D9: 0 | E9: 0 | F9: 8 | G9: 0 | H9: 0 | I9: 0 | J9: 0 | K9: 0 | L9: 22 | M9: 22 | N9: 30 | O9: 2.893 | P9: 2.893
A10: Canada | B10: Canada | C10: 14.3 | D10: 0 | E10: 2.1 | F10: 0 | G10: 0 | H10: 14 | I10: 0 | J10: 12 | K10: 0 | L10: 16.4 | M10: 16.4 | N10: 30.4 | O10: 1.88 | P10: 2.157
A11: Egypt | B11: Africa | C11: 12.2 | D11: 0 | E11: 0 | F11: 0 | G11: 0 | H11: 0 | I11: 0 | J11: 0 | K11: 0 | L11: 12.2 | M11: 12.2 | N11: 12.2 | O11: 1.604 | P11: 1.604
A12: Trinidad and Tobago | B12: Other | C12: 11.8 | D12: 3 | E12: 0 | F12: 0 | G12: 0 | H12: 0 | I12: 0 | J12: 0 | K12: 0 | L12: 11.8 | M12: 11.8 | N12: 11.8 | O12: 1.552 | P12: 1.552
A13: Oman | B13: Other | C13: 11.5 | D13: 0 | E13: 1 | F13: 0 | G13: 0 | H13: 0 | I13: 0 | J13: 0 | K13: 0 | L13: 12.5 | M13: 12.5 | N13: 12.5 | O13: 1.512 | P13: 1.644
... A28: Yemen | B28: Other | C28: 0 | D28: 7.2 | E28: 0 | F28: 0 | G28: 0 | H28: 0 | I28: 0 | J28: 0 | K28: 0 | L28: 0 | M28: 0 | N28: 0 | O28: 0 | P28: 0
A29: WORLD TOTAL | C29: 519.734 | D29: 23 | E29: 134.689 | F29: 48 | G29: 9.55 | H29: 14 | I29: 0 | J29: 112.24 | K29: 16.5 | L29: 663.973 | M29: 663.973 | N29: 725.973 | O29: 68.345 | P29: 87.312

Sheet Additions by year
A1: year | B1: United States (additions) | C1: Qatar (additions) | D1: Australia (additions) | E1: Canada (additions) | F1: Mexico (additions) | G1: Russia (additions) | H1: Africa (additions) | I1: Other (additions) | J1: United States (offline/closed) | K1: Qatar (offline/closed) | L1: Australia (offline/closed) | M1: Canada (offline/closed) | N1: Mexico (offline/closed) | O1: Russia (offline/closed) | P1: Africa (offline/closed) | Q1: Other (offline/closed)
A2: 2021 | B2: 4.5 | C2: 0 | D2: 0 | E2: 0 | F2: 0 | G2: 0 | H2: 0 | I2: 0 | J2: 0 | K2: 0 | L2: 0 | M2: 0 | N2: 0 | O2: 0 | P2: 0 | Q2: 0
A3: 2022 | B3: 10 | C3: 0 | D3: 0 | E3: 0 | F3: 0 | G3: 1.5 | H3: 3.4 | I3: 0 | J3: 0 | K3: 0 | L3: 0 | M3: 0 | N3: 0 | O3: 0 | P3: 0 | Q3: 0
A4: 2023 | B4: 0 | C4: 0 | D4: 0 | E4: 0 | F4: 0 | G4: 0 | H4: 0 | I4: 0 | J4: 0 | K4: 0 | L4: 0 | M4: 0 | N4: 0 | O4: 0 | P4: 0 | Q4: 0
A5: 2024 | B5: 9.9 | C5: 0 | D5: 0 | E5: 0 | F5: 1.4 | G5: 6.6 | H5: 0.6 | I5: 0 | J5: 0 | K5: 0 | L5: 0 | M5: 0 | N5: 0 | O5: 0 | P5: 0 | Q5: 0
A6: 2025 | B6: 15.616 | C6: 0 | D6: 0 | E6: 14 | F6: 0 | G6: 6.6 | H6: 2.3 | I6: 0 | J6: 0 | K6: 0 | L6: 2.6 | M6: 0 | N6: 0 | O6: 0 | P6: 0 | Q6: 0
A7: 2026 | B7: 14.687 | C7: 0 | D7: 0 | E7: 0 | F7: 3.25 | G7: 0 | H7: 2.4 | I7: 0 | J7: 0 | K7: 12.8 | L7: 0 | M7: 0 | N7: 0 | O7: 0 | P7: 2.4 | Q7: 0
A8: 2027 | B8: 42.4 | C8: 8 | D8: 0 | E8: 2.1 | F8: 0 | G8: 0 | H8: 0 | I8: 2.45 | J8: 0 | K8: 0 | L8: 0 | M8: 0 | N8: 0 | O8: 0 | P8: 0 | Q8: 0
A9: 2028 | B9: 8.38 | C9: 0 | D9: 0 | E9: 0 | F9: 0 | G9: 0 | H9: 3.6 | I9: 14.1 | J9: 0 | K9: 0 | L9: 0 | M9: 0 | N9: 0 | O9: 0 | P9: 0 | Q9: 0
A10: 2029 | B10: 22.16 | C10: 0 | D10: 0 | E10: 0 | F10: 0 | G10: 0 | H10: 13.12 | I10: 3.5 | J10: 0 | K10: 0 | L10: 0 | M10: 0 | N10: 0 | O10: 0 | P10: 0 | Q10: 0
A11: 2030 | B11: 17.8 | C11: 0 | D11: 0 | E11: 0 | F11: 0 | G11: 0 | H11: 0 | I11: 0 | J11: 0 | K11: 0 | L11: 0 | M11: 0 | N11: 0 | O11: 0 | P11: 0 | Q11: 0

Sheet Placement
A1: project | B1: country | C1: layer | D1: source_date_text | E1: rule | F1: placed_month | G1: start_not_in_raw_source | H1: source_date_already_past | I1: end_month | J1: offline_from | K1: chart_group
A2: Sabine Pass Train 1 | B2: United States | C2: OP | D2: 2016-02 | E2: month as published | F2: 2016-02 | K2: United States
A3: Sabine Pass Train 2 | B3: United States | C3: OP | D3: 2016-08 | E3: month as published | F3: 2016-08 | K3: United States
A4: Sabine Pass Train 3 | B4: United States | C4: OP | D4: 2017-01 | E4: month as published | F4: 2017-01 | K4: United States
A5: Sabine Pass Train 4 | B5: United States | C5: OP | D5: 2017-08 | E5: month as published | F5: 2017-08 | K5: United States
A6: Sabine Pass Train 5 | B6: United States | C6: OP | D6: 2018-11 | E6: month as published | F6: 2018-11 | K6: United States
A7: Sabine Pass Train 6 | B7: United States | C7: OP | D7: 2021-12 | E7: month as published | F7: 2021-12 | K7: United States
A8: Cove Point Train 1 | B8: United States | C8: OP | D8: 2018-03 | E8: month as published | F8: 2018-03 | K8: United States
A9: Elba Island Trains 1-5A | B9: United States | C9: OP | D9: 2019-09 | E9: month as published | F9: 2019-09 | K9: United States
A10: Elba Island Trains 6-10A | B10: United States | C10: OP | D10: 2020-05 | E10: month as published | F10: 2020-05 | K10: United States
A11: Corpus Christi Train 1 | B11: United States | C11: OP | D11: 2018-12 | E11: month as published | F11: 2018-12 | K11: United States
A12: Corpus Christi Train 2 | B12: United States | C12: OP | D12: 2019-07 | E12: month as published | F12: 2019-07 | K12: United States
A13: Corpus Christi Train 3 | B13: United States | C13: OP | D13: 2020-12 | E13: month as published | F13: 2020-12 | K13: United States
... A46: Delfin FLNG Train 1 | B46: United States | C46: UC | D46: 2030 | E46: July (middle of the year) | F46: 2030-07 | K46: United States
A47: Cameron LNG Train 4A | B47: United States | C47: PL | E47: no date in an opened source - not in the dated series | K47: United States
A48: Lake Charles LNG | B48: United States | C48: MEMO | E48: no date in an opened source - not in the dated series | K48: United States
A49: Woodside Louisiana LNG (formerly Driftwood LNG) Phase 2 | B49: United States | C49: PL | E49: no date in an opened source - not in the dated series | K49: United States
A50: Freeport LNG Train 4C | B50: United States | C50: PL | E50: no date in an opened source - not in the dated series | K50: United States
A51: Texas LNG | B51: United States | C51: PL | E51: no date in an opened source - not in the dated series | K51: United States
A52: Gulf LNGE | B52: United States | C52: PL | E52: no date in an opened source - not in the dated series | K52: United States
A53: Delfin FLNG additional vessels (beyond Train 1) | B53: United States | C53: PL | E53: no date in an opened source - not in the dated series | K53: United States
A54: Alaska LNG | B54: United States | C54: PL | E54: no date in an opened source - not in the dated series | K54: United States
A55: Existing LNG trains at Ras Laffan (14 trains) excl. the two damaged trains | B55: Qatar | C55: OP | D55: 1996 | E55: July (middle of the year) | F55: 1996-07 | K55: Qatar
A56: Ras Laffan LNG Trains 4 and 6 (damaged by missile strikes 18 Mar 2026) | B56: Qatar | C56: OFF | D56: 1996 | E56: July (middle of the year) | F56: 1996-07 | J56: 2026-03 | K56: Qatar
A57: North Field East expansion, Train 1 of 4 (8 mtpa) | B57: Qatar | C57: UC | D57: 2027-H1 | E57: April (middle of H1) | F57: 2027-04 | K57: Qatar
A58: North Field East expansion, Trains 2-4 (3 x 8 mtpa) | B58: Qatar | C58: UC | E58: no date in an opened source - not in the dated series | K58: Qatar
A59: North Field South expansion (2 trains x 8 mtpa) | B59: Qatar | C59: UC | E59: no date in an opened source - not in the dated series | K59: Qatar
A60: North Field West expansion (2 trains x 8 mtpa) | B60: Qatar | C60: PL | E60: no date in an opened source - not in the dated series | K60: Qatar
A61: LNG Canada Phase 1 (2 trains) | B61: Canada | C61: OP | D61: 2025 | E61: July (middle of the year) | F61: 2025-07 | K61: Canada
A62: Tilbury LNG | B62: Canada | C62: OP | D62: 1971 | E62: July (middle of the year) | F62: 1971-07 | K62: Canada
A63: LNG Canada Phase 2 (2 trains, +14 mtpa) | B63: Canada | C63: FID | E63: no date in an opened source - not in the dated series | K63: Canada
A64: Woodfibre LNG | B64: Canada | C64: UC | D64: 2027 | E64: July (middle of the year) | F64: 2027-07 | K64: Canada
A65: Cedar LNG (floating, Kitimat) | B65: Canada | C65: UC | D65: 2028-Q4 | E65: middle month of the quarter | F65: 2028-11 | K65: Canada
A66: Ksi Lisims LNG (floating, 12 mtpa) | B66: Canada | C66: PL | E66: no date in an opened source - not in the dated series | K66: Canada
A67: Energia Costa Azul LNG Phase 1 (1 train, 3.25 mtpa) | B67: Mexico | C67: OP | D67: 2026-07 | E67: month as published | F67: 2026-10 | H67: yes - shown from run month | K67: Mexico
A68: Altamira FLNG 1 (floating) | B68: Mexico | C68: OP | D68: 2024 | E68: July (middle of the year) | F68: 2024-07 | K68: Mexico
A69: Gorgon LNG | B69: Australia | C69: OP | D69: 2016 | E69: July (middle of the year) | F69: 2016-07 | K69: Australia
A70: Wheatstone LNG | B70: Australia | C70: OP | D70: 2017 | E70: July (middle of the year) | F70: 2017-07 | K70: Australia
A71: Ichthys LNG | B71: Australia | C71: OP | D71: 2018 | E71: July (middle of the year) | F71: 2018-07 | K71: Australia
A72: Pluto LNG Train 1 | B72: Australia | C72: OP | D72: 2012 | E72: July (middle of the year) | F72: 2012-07 | K72: Australia
A73: Prelude FLNG | B73: Australia | C73: OP | D73: 2019 | E73: July (middle of the year) | F73: 2019-07 | K73: Australia
A74: Darwin LNG | B74: Australia | C74: OP | D74: 2006 | E74: July (middle of the year) | F74: 2006-07 | K74: Australia
A75: Australia Pacific LNG (APLNG) | B75: Australia | C75: OP | D75: 2016 | E75: July (middle of the year) | F75: 2016-07 | K75: Australia
A76: Gladstone LNG (GLNG) | B76: Australia | C76: OP | D76: 2015 | E76: July (middle of the year) | F76: 2015-07 | K76: Australia
A77: Queensland Curtis LNG (QCLNG) | B77: Australia | C77: OP | D77: 2015 | E77: July (middle of the year) | F77: 2015-07 | K77: Australia
A78: North West Shelf LNG, four remaining trains | B78: Australia | C78: OP | D78: 1989 | E78: July (middle of the year) | F78: 1989-07 | K78: Australia
A79: North West Shelf LNG Train 2 (permanently ceased) | B79: Australia | C79: OP | D79: 1989 | E79: July (middle of the year) | F79: 1989-07 | I79: 2025-07 | K79: Australia
A80: Pluto Train 2 (Scarborough Energy Project) | B80: Australia | C80: UC | D80: 2026-Q4 | E80: middle month of the quarter | F80: 2026-11 | K80: Australia
A81: Yamal LNG, Trains 1-4 | B81: Russia | C81: OP | D81: 2017 | E81: July (middle of the year) | F81: 2017-07 | K81: Russia
A82: Sakhalin-2 (2 trains) | B82: Russia | C82: OP | D82: 2009 | E82: July (middle of the year) | F82: 2009-07 | K82: Russia
A83: Portovaya LNG | B83: Russia | C83: OP | D83: 2022 | E83: July (middle of the year) | F83: 2022-07 | K83: Russia
A84: Vysotsk LNG | B84: Russia | C84: OP | D84: 2019 | E84: July (middle of the year) | F84: 2019-07 | K84: Russia
A85: Arctic LNG 2, Train 1 | B85: Russia | C85: OP | D85: 2024 | E85: July (middle of the year) | F85: 2024-07 | K85: Russia
A86: Arctic LNG 2, Train 2 | B86: Russia | C86: OP | D86: 2025 | E86: July (middle of the year) | F86: 2025-07 | K86: Russia
A87: Arctic LNG 2, Train 3 | B87: Russia | C87: PL | E87: no date in an opened source - not in the dated series | K87: Russia
A88: Nigeria LNG, Trains 1-6 | B88: Nigeria | C88: OP | D88: 1999 | E88: July (middle of the year) | F88: 1999-07 | K88: Africa
A89: Nigeria LNG Train 7 | B89: Nigeria | C89: UC | E89: no date in an opened source - not in the dated series | K89: Africa
A90: Arzew GL1Z, GL2Z, GL3Z and Skikda GL1K | B90: Algeria | C90: OP | D90: 1978 | E90: July (middle of the year) | F90: 1978-07 | K90: Africa
A91: Damietta LNG and Idku (Egyptian LNG) T1-T2 | B91: Egypt | C91: OP | D91: 2005 | E91: July (middle of the year) | F91: 2005-07 | K91: Africa
A92: Angola LNG | B92: Angola | C92: OP | D92: 2013 | E92: July (middle of the year) | F92: 2013-07 | K92: Africa
A93: EG LNG | B93: Equatorial Guinea | C93: OP | D93: 2007 | E93: July (middle of the year) | F93: 2007-07 | K93: Africa
A94: Coral South FLNG | B94: Mozambique | C94: OP | D94: 2022 | E94: July (middle of the year) | F94: 2022-07 | K94: Africa
A95: Kribi FLNG Hilli Episeyo (contract ended, relocating to Argentina) | B95: Cameroon | C95: OP | D95: 2018 | E95: July (middle of the year) | F95: 2018-07 | I95: 2026-07 | K95: Africa
A96: Tango FLNG | B96: Congo | C96: OP | D96: 2024 | E96: July (middle of the year) | F96: 2024-07 | K96: Africa
A97: Nguya FLNG (Congo LNG Phase 2) | B97: Congo | C97: OP | D97: 2026-02 | E97: month as published | F97: 2026-02 | K97: Africa
A98: Greater Tortue Ahmeyim (GTA) Phase 1, FLNG Gimi | B98: Mauritania/Senegal | C98: OP | D98: 2025 | E98: July (middle of the year) | F98: 2025-07 | K98: Africa
A99: Mozambique LNG (Afungi, 2 units) | B99: Mozambique | C99: UC | D99: 2029 | E99: July (middle of the year) | F99: 2029-07 | K99: Africa
A100: Coral North FLNG (Eni, Area 4) | B100: Mozambique | C100: FID | D100: 2028 | E100: July (middle of the year) | F100: 2028-07 | K100: Africa
A101: Hammerfest LNG (Snohvit) | B101: Norway | C101: OP | D101: 2007 | E101: July (middle of the year) | F101: 2007-07 | K101: Other
A102: Peru LNG | B102: Peru | C102: OP | D102: 2010 | E102: July (middle of the year) | F102: 2010-07 | K102: Other
A103: Atlantic LNG Trains 2-4 | B103: Trinidad and Tobago | C103: OP | D103: 2002 | E103: July (middle of the year) | F103: 2002-07 | K103: Other
A104: Atlantic LNG Train 1 (mothballed) | B104: Trinidad and Tobago | C104: OFF | D104: 1999 | E104: July (middle of the year) | F104: 1999-07 | J104: 2000-01 | K104: Other
A105: Balhaf LNG (2 trains) | B105: Yemen | C105: OFF | D105: 2009 | E105: July (middle of the year) | F105: 2009-07 | J105: 2015-01 | K105: Other
A106: Oman LNG (Qalhat), Trains 1-2 and Qalhat LNG | B106: Oman | C106: OP | D106: 2000 | E106: July (middle of the year) | F106: 2000-07 | K106: Other
A107: Marsa LNG (1 mtpa) | B107: Oman | C107: UC | D107: 2028 | E107: July (middle of the year) | F107: 2028-07 | K107: Other
A108: Das Island LNG (3 trains) | B108: United Arab Emirates | C108: OP | D108: 1977 | E108: July (middle of the year) | F108: 1977-07 | K108: Other
A109: Ruwais LNG (2 trains) | B109: United Arab Emirates | C109: UC | D109: 2028 | E109: July (middle of the year) | F109: 2028-07 | K109: Other
A110: PETRONAS LNG complex (Bintulu, MLNG T1-T9) and PFLNG Satu / Dua | B110: Malaysia | C110: OP | D110: 1983 | E110: July (middle of the year) | F110: 1983-07 | K110: Other
A111: Brunei LNG (5 trains) | B111: Brunei | C111: OP | D111: 1973 | E111: July (middle of the year) | F111: 1973-07 | K111: Other
A112: Tangguh LNG, Trains 1-3 | B112: Indonesia | C112: OP | D112: 2009 | E112: July (middle of the year) | F112: 2009-07 | K112: Other
A113: Donggi-Senoro LNG | B113: Indonesia | C113: OP | D113: 2015 | E113: July (middle of the year) | F113: 2015-07 | K113: Other
A114: Bontang LNG (Train E on standby, F-H operating) | B114: Indonesia | C114: OP | D114: 1977 | E114: July (middle of the year) | F114: 1977-07 | K114: Other
A115: Abadi LNG (Masela) | B115: Indonesia | C115: PL | E115: no date in an opened source - not in the dated series | K115: Other
A116: PNG LNG (2 trains) | B116: Papua New Guinea | C116: OP | D116: 2014 | E116: July (middle of the year) | F116: 2014-07 | K116: Other
A117: Southern Energy (SESA) FLNG Hilli Episeyo (relocated from Cameroon) | B117: Argentina | C117: FID | D117: 2027-H2 | E117: October (middle of H2) | F117: 2027-10 | K117: Other
A118: Southern Energy (SESA) FLNG Esperanza (MKII) | B118: Argentina | C118: UC | D118: 2028-H2 | E118: October (middle of H2) | F118: 2028-10 | K118: Other
A119: Golar FLNG Four (MKII, no charter yet) | B119: Unallocated (FLNG) | C119: FID | D119: 2029 | E119: July (middle of the year) | F119: 2029-07 | K119: Other
A120: Sabine Pass Stage 5 expansion (Train 7 + BOG re-liquefaction) | B120: United States | C120: PL | E120: no date in an opened source - not in the dated series | K120: United States

Sheet Sources
A1: publisher | B1: role | C1: document | D1: url | E1: as_of_date | F1: used_for
A2: Department of Industry, Science and Resources (Australia) | B2: Official / operator source of Projects numbers | C2: Resources and Energy Quarterly, September 2026 (section 6 LNG; map 'Nameplate capacity, million tonnes per annum') | D2: https://www.industry.gov.au/sites/default/files/2026-10/resources-and-energy-quarterly-september-2026.pdf | E2: 2026-10-02 | F2: Australian plant nameplates (map, 88 Mtpa total); GTA 2.3 Mtpa; Congo Nguya 2.4 Mtpa; Mozambique LNG 13.2 Mtpa from 2029; Qatar 77 -> 133 Mt by 2031 trajectory; Ras Laffan / Hormuz context.
A3: QatarEnergy | B3: Official / operator source of Projects numbers | C3: Update to Investors, November 2025 (North Field expansion programme, p.9) | D3: https://www.qatarenergy.qa/en/MediaCenter/Publications/QatarEnergy_Investors_Presentation_November_2025.pdf | E3: 2025-11-01 | F3: Qatar 77 mtpa (14 trains) now; NFE 32 (4 x 8), NFS 16 (2 x 8), NFW 16 (2 x 8); 142 mtpa by 2030.
A4: QatarEnergy | B4: Official / operator source of Projects numbers | C4: Annual Review 2024 | D4: https://www.qatarenergy.qa/en/MediaCenter/Publications/%E2%80%8BQatarEnergy%20Annual%20Review%202024.pdf | E4: 2025-06-01 | F4: Qatar programme background (no per-train dates).
A5: Cheniere Energy | B5: Official / operator source of Projects numbers | C5: Cheniere Reports Second Quarter 2026 Results (6 Aug 2026) | D5: https://lngir.cheniere.com/_assets/_75dc2c9a1fb706f14e67cee93b0e9e5a/cheniere/news/2026-08-06_Cheniere_Reports_Second_Quarter_2026_Results_and_343.pdf | E5: 2026-08-06 | F5: Corpus Christi Stage 3 train dates; Sabine Pass + Corpus Christi operating capacity (~55 mtpa).
A6: Golar LNG | B6: Official / operator source of Projects numbers | C6: Interim results for the period ended June 30, 2026 | D6: https://mfn.se/one/a/golar-lng/golar-lng-limited-interim-results-for-the-period-ended-june-30-2026-b168e773 | E6: 2026-08-13 | F6: Esperanza 3.5 MTPA (H2 2028); fourth FLNG 3.5 MTPA (end-2029).
A7: Eni | B7: Official / operator source of Projects numbers | C7: Eni announces Final Investment Decision for Mozambique's Coral North project (2 Oct 2025) | D7: https://www.eni.com/en-IT/media/press-release/2025/10/pr-eni-announces-final-investment-decision-mozambique-coral-north-project.html | E7: 2025-10-02 | F7: Coral North 3.6 MTPA, 2028.
A8: Nigeria LNG Limited | B8: Official / operator source of Projects numbers | C8: Facts and Figures 2024 (six trains 22 MTPA; Train 7 lifts capacity to 30 MTPA; FID Dec 2019) | D8: https://www.nlng.com/documents/2024_NLNG_FACTS_FIGURESB_compressed.pdf | E8: 2025-01-01 | F8: Nigeria 22 MTPA, Train 7 to 30 MTPA.
A9: Novatek | B9: Official / operator source of Projects numbers | C9: FID release, Arctic LNG 2 (2019: three trains of 6.6 mtpa; schedule since changed) | D9: https://www.novatek.ru/common/upload/press/FID_Arctic_LNG_2_Eng.pdf | E9: 2019-09-01 | F9: Arctic LNG 2 6.6 mtpa per train (design).
A10: Shell Canada Energy / Shell plc (release text as republished by Hellenic Shipping News) | B10: Official / operator source of Projects numbers | C10: Shell takes final investment decision to double LNG Canada capacity (29 Sep 2026) | D10: https://www.hellenicshippingnews.com/shell-takes-final-investment-decision-to-double-lng-canada-capacity | E10: 2026-09-29 | F10: LNG Canada Phase 1 = 14 mtpa; Phase 2 FID, +14 mtpa, early 2030s.
A11: Mozambique LNG (TotalEnergies-operated project site) | B11: Official / operator source of Projects numbers | C11: Project page: development (two liquefaction units, 13.12 MTPA) | D11: https://mozambiquelng.co.mz/about-the-mozambique-liquefied-natural-gas-project/development/ | E11: 2026-10-12 | F11: Mozambique LNG 13.12 MTPA.
A12: Woodfibre LNG | B12: Official / operator source of Projects numbers | C12: Construction page (2.1 million tonnes of LNG per year; substantial completion expected by 2027) | D12: https://woodfibrelng.ca/construction/ | E12: 2026-10-12 | F12: Woodfibre 2.1 mtpa, completion by 2027.
... A20: Reuters (copy on BOE Report) | B20: GIIGNL: number used only where no official figure was opened (labelled); otherwise cross-check. Others: dates / background | C20: QatarEnergy's LNG expansion project poised to start operations in November, sources say (7 Oct 2026) | D20: https://boereport.com/2026/10/07/qatarenergys-lng-expansion-project-poised-to-start-operations-in-november-sources-say/amp/ | E20: 2026-10-07 | F20: Press copy: NFE first train timing, Ras Laffan damage - 'Cross-check' only.

Sheet Cross-check
A1: country | B1: item | C1: publisher | D1: cross_check_value_mtpa | E1: raw_operating_in_Projects_mtpa | F1: difference_mtpa | G1: text
A2: WORLD | B2: Global liquefaction nominal capacity end-2025 | C2: GIIGNL Annual Report 2026 | D2: 524 | E2: 519.734 | F2: -4.266 | G2: 524 MTPA incl. 16.5 MTPA FLNG (executive summary)
A3: United States | B3: US liquefaction capacity 2025 | C3: GIIGNL Annual Report 2026 | D3: 110 | E3: 120.384 | F3: 10.384 | G3: 'nearly 110 MTPA' (nominal basis; EIA baseload sum is on a different basis and includes units commissioned in 2026)
A4: Qatar | B4: Existing trains | C4: GIIGNL Annual Report 2026 | D4: 77 | E4: 64.2 | F4: -12.8 | G4: Plants table / narrative: 77 MTPA
A5: Qatar | B5: Ras Laffan Trains 4 and 6 damaged 18 Mar 2026 | C5: GIIGNL Annual Report 2026 | D5: 12.8 | G5: Per QatarEnergy's March 2026 statement as quoted by GIIGNL: repairs 3-5 years; possible force majeure up to five years. Reuters (7 Oct 2026, via BOE Report): two trains damaged, repairs ~3 years, 17% of capacity.
A6: Qatar | B6: North Field East first train | C6: Reuters via BOE Report (press copy) | G6: CEO: production expected H1 2027; first train ready to start in Nov 2026, LNG from it in Q1 2027 (two unnamed sources). GIIGNL: first two NFE trains had been expected late 2026, likely postponed.
A7: Australia | B7: Plants table total | C7: GIIGNL Annual Report 2026 | D7: 85.8 | E7: 85.2 | F7: -0.6 | G7: GIIGNL Australia total (DISR REQ nameplate map sums to 88)
A8: Australia | B8: North West Shelf after Train 2 closure | C8: GIIGNL Annual Report 2026 | D8: 14.5 | G8: Train 2 (2.6 MTPA) permanently ceased; total from 17 to 14.5 MTPA
A9: Australia | B9: Pluto Train 2 (Scarborough) | C9: Woodside (dates) / none (capacity) | G9: First LNG cargo Q4 2026 (Woodside H1 2026); no Mtpa figure in an opened raw source
A10: Canada | B10: LNG Canada Trains 1-2 + Tilbury | C10: GIIGNL Annual Report 2026 | D10: 14.3 | E10: 14.3 | F10: 0 | G10: 7.0 + 7.0 online in 2025, Tilbury 0.3
A11: Canada | B11: Cedar LNG (floating) | C11: GIIGNL Annual Report 2026 | G11: Start-up targeted 2028 (Pembina: late 2028); no mtpa in the opened documents
A12: Canada | B12: Ksi Lisims LNG (floating) | C12: GIIGNL Annual Report 2026 | D12: 12 | G12: 12 MTPA FLNG, federal approvals, fast-tracked; no FID
A13: Mexico | B13: Energia Costa Azul Phase 1 + Altamira FLNG 1 | C13: GIIGNL Annual Report 2026 | D13: 4.65 | G13: 3.25 + 1.4. TotalEnergies 2Q26 release: ECA started up early July 2026 (no capacity)
A14: Russia | B14: Russia plants (Yamal 17.4, Sakhalin-2 10.8, Portovaya 1.5, Vysotsk 0.9, Arctic LNG 2 T1 6.6) | C14: GIIGNL Annual Report 2026 | D14: 37.2 | E14: 43.8 | F14: 6.6 | G14: GIIGNL Russia total 26.4 excl. Sakhalin-2; Arctic LNG 2 Train 2 started May 2025
A15: Nigeria | B15: NLNG six trains | C15: GIIGNL Annual Report 2026 | D15: 22.2 | E15: 22 | F15: -0.2 | G15: 3.3x3 + 4.1x3 (operator says 22)
A16: Algeria | B16: Arzew GL1Z/GL2Z/GL3Z, Skikda | C16: GIIGNL Annual Report 2026 | D16: 25.3 | G16: Plants table
A17: Egypt | B17: Damietta + Idku | C17: GIIGNL Annual Report 2026 | D17: 12.2 | G17: 5.0 + 3.6 + 3.6
A18: Angola | B18: Angola LNG | C18: GIIGNL Annual Report 2026 | D18: 5.2
A19: Equatorial Guinea | B19: EG LNG | C19: GIIGNL Annual Report 2026 | D19: 3.7
A20: Mozambique | B20: Coral South FLNG | C20: GIIGNL Annual Report 2026 | D20: 3.4 | G20: Operating since 2022
A21: Mozambique | B21: Mozambique LNG | C21: GIIGNL Annual Report 2026 | D21: 12.8 | G21: Narrative figure; operator site says 13.12
A22: Cameroon | B22: Hilli Episeyo FLNG (Kribi) | C22: GIIGNL Annual Report 2026 | D22: 2.4 | G22: Golar Q2 2026: contract ended, relocating to Argentina (Hilli + Gimi together 5.1 MTPA)
A23: Argentina | B23: Hilli Episeyo (SESA) | C23: GIIGNL Annual Report 2026 | D23: 2.45 | G23: Golar Q2 2026: 20-year contract commencing H2 2027
A24: Congo | B24: Tango FLNG 0.6 + Nguya 2.4 | C24: GIIGNL Annual Report 2026 | D24: 3 | G24: Nguya first cargo Feb 2026 per GIIGNL
A25: Mauritania/Senegal | B25: GTA Phase 1 (Gimi) | C25: GIIGNL Annual Report 2026 | D25: 2.4 | E25: 2.3 | F25: -0.1 | G25: plants table; narrative 'around 2.3'
A26: Norway | B26: Hammerfest LNG | C26: GIIGNL Annual Report 2026 | D26: 4.2
A27: Peru | B27: Peru LNG | C27: GIIGNL Annual Report 2026 | D27: 4.5
A28: Trinidad and Tobago | B28: Atlantic LNG T1-T4 (T1 mothballed) | C28: GIIGNL Annual Report 2026 | D28: 14.8
A29: Yemen | B29: Balhaf LNG (shut since 2015) | C29: GIIGNL Annual Report 2026 | D29: 7.2 | G29: table 2 x 3.6; narrative 6.7
A30: Oman | B30: Oman LNG + Qalhat | C30: GIIGNL Annual Report 2026 | D30: 11.5
A31: Oman | B31: Marsa LNG | C31: GIIGNL Annual Report 2026 | D31: 1 | G31: FID Apr 2024, 2028
A32: United Arab Emirates | B32: Das Island | C32: GIIGNL Annual Report 2026 | D32: 5.8
A33: United Arab Emirates | B33: Ruwais LNG | C33: GIIGNL Annual Report 2026 | D33: 9.6 | G33: FID June 2024, start-up 2028
A34: Malaysia | B34: PETRONAS LNG complex + PFLNG | C34: GIIGNL Annual Report 2026 | D34: 32.1
A35: Brunei | B35: Brunei LNG | C35: GIIGNL Annual Report 2026 | D35: 7
A36: Indonesia | B36: Bontang, Tangguh, Donggi-Senoro | C36: GIIGNL Annual Report 2026 | D36: 24.9 | G36: Abadi LNG 9.5 MTPA planned (FEED end-2026)
A37: Papua New Guinea | B37: PNG LNG | C37: GIIGNL Annual Report 2026 | D37: 8.3

Sheet Tried
A1: what | B1: url | C1: result
A2: SOURCE: FERC 'North American LNG Export Terminals - Existing, Approved not yet built, Proposed' | B2: https://www.ferc.gov/media/north-american-lng-export-terminals-existing-approved-not-yet-built-and-proposed | C2: Page reachable (12 Oct 2026) but the list is a linked document the HTML does not expose; FERC's earlier LNG pages list no start dates (TEXAS_STEO_FERC_PROBE). EIA's liquefaction workbook (cites the FERC and DOE dockets) is the US source.
A3: SOURCE: Canada Energy Regulator LNG export licences | B3: https://www.cer-rec.gc.ca/en/data-analysis/energy-commodities/natural-gas/report/lng-export-licences/index.html | C3: 404 after the CER site relaunch; replacement page not found. Licence volumes are not plant capacity in any case; operator releases are used for Canada.
A4: SOURCE: LNG Canada site (Phase 1 / Phase 2 pages) | B4: https://www.lngcanada.ca/ | C4: HTTP 202 (no content) from Actions on every inner page; Shell's release text (as republished) used.
A5: SOURCE: Shell release on shell.com | B5: https://www.shell.com/news-and-insights/newsroom/news-and-media-releases/2026/shell-takes-final-investment-decision-to-double-lng-canada-capacity.html | C5: Script-rendered page; the 14 -> 28 mtpa text is not in the HTML. The same release text was read on Hellenic Shipping News and is labelled so.
A6: SOURCE: DISR REQ Excel data (forecast / historical) | B6: https://www.industry.gov.au/sites/default/files/2026-10/resources-and-energy-quarterly-september-2026-forecast-data.xlsx | C6: Opened: Australian export volumes and prices only, no project capacity table. The PDF nameplate map is used.
A7: SOURCE: QatarEnergy statements on the Ras Laffan strikes (March 2026) and on per-train start dates | B7: https://www.qatarenergy.qa/en/MediaCenter/Pages/News.aspx | C7: News list is script-rendered (link templates only); the March statement, a damaged-train figure and a dated NFE/NFS/NFW schedule are NOT in any QatarEnergy document opened (deck Nov 2025, Annual Review 2024). The 12.8 mtpa / three-to-five-year figures are GIIGNL / Reuters: 'Cross-check' only.
A8: SOURCE: IGU World LNG Report 2026 | B8: https://www.igu.org/resources/world-lng-report-2025/ | C8: 404 on the guessed address; no direct PDF link found.
A9: SOURCE: TotalEnergies / Mozambique LNG restart release (businesswire) | B9: https://www.businesswire.com/news/home/20260129402488/en/ | C9: 403 from Actions; project site and DISR REQ used.
A10: SOURCE: Sempra Q2 2026 release; Kosmos GTA release; SEC exhibits | B10: https://www.sempra.com/newsroom/press-releases/sempra-reports-strong-second-quarter-2026-results | C10: 403 from Actions.
A11: SOURCE: GIIGNL Excel tables / LNG Trade Matrix / World LNG Map | B11: https://giignl.org/resources/ | C11: Members only; the free annual report PDF is used on 'Cross-check' only.
A12: NOT SOURCED: Qatar damaged-train size and return date from QatarEnergy itself | B12: https://www.qatarenergy.qa/en/MediaCenter/Pages/News.aspx | C12: March 2026 statement not reachable; 12.8 mtpa / 3-5 years are GIIGNL (labelled in Projects).
... A19: NOT SOURCED: Nigeria LNG Train 7 start date | B19: https://www.nlng.com/operations/train-7 | C19: Official page text empty (script-rendered); Facts and Figures 2024 gives capacity only.

Sheet Releases
A1: document | B1: url | C1: etag | D1: last_modified | E1: size | F1: sha256 | G1: checked | H1: result | I1: release_date
A2: EIA U.S. liquefaction capacity workbook | B2: https://www.eia.gov/naturalgas/importsexports/liquefactioncapacity/U.S.liquefactioncapacity_2026_Q3.xlsx | C2: "0d74ba3e551dd1:0" | D2: Thu, 01 Oct 2026 20:44:22 GMT | E2: 43840 | F2: c9acf6dc640b7428eb4370c9b44149df73bab5dec3b9b5f88b93c0b815142677 | G2: 2026-10-12 | H2: NEW/CHANGED - parsed | I2: 2026-10-01
A3: Department of Industry, Science and Resources (Australia): Resources and Energy Quarterly, September 2026 (section 6 LNG; map 'Nameplate capacity, million tonnes per annum') | B3: https://www.industry.gov.au/sites/default/files/2026-10/resources-and-energy-quarterly-september-2026.pdf | G3: 2026-10-12 | H3: UNREACHABLE (ReadTimeout)
A4: QatarEnergy: Update to Investors, November 2025 (North Field expansion programme, p.9) | B4: https://www.qatarenergy.qa/en/MediaCenter/Publications/QatarEnergy_Investors_Presentation_November_2025.pdf | C4: "{8B5669FD-1086-42E6-AAB0-9B4ABA1C4BCD},2" | D4: Sun, 30 Nov 2025 07:14:24 GMT | E4: 5032257 | G4: 2026-10-12 | H4: FIRST SEEN
A5: QatarEnergy: Annual Review 2024 | B5: https://www.qatarenergy.qa/en/MediaCenter/Publications/%E2%80%8BQatarEnergy%20Annual%20Review%202024.pdf | C5: "{B58CFE52-159E-4EB4-92CC-B561A7C304ED},1" | D5: Sun, 21 Sep 2025 05:38:28 GMT | E5: 13226936 | G5: 2026-10-12 | H5: FIRST SEEN
A6: Cheniere Energy: Cheniere Reports Second Quarter 2026 Results (6 Aug 2026) | B6: https://lngir.cheniere.com/_assets/_75dc2c9a1fb706f14e67cee93b0e9e5a/cheniere/news/2026-08-06_Cheniere_Reports_Second_Quarter_2026_Results_and_343.pdf | C6: "ca6fd7d90151f7cd4bb3262a53ef161e" | D6: Thu, 06 Aug 2026 11:36:42 GMT | E6: 123866 | G6: 2026-10-12 | H6: FIRST SEEN
A7: Golar LNG: Interim results for the period ended June 30, 2026 | B7: https://mfn.se/one/a/golar-lng/golar-lng-limited-interim-results-for-the-period-ended-june-30-2026-b168e773 | E7: 78242 | F7: ee363ea67ce7eb565ae64d8f614e5398bc6496572abeb90bef162874096e1129 | G7: 2026-10-12 | H7: FIRST SEEN
A8: Eni: Eni announces Final Investment Decision for Mozambique's Coral North project (2 Oct 2025) | B8: https://www.eni.com/en-IT/media/press-release/2025/10/pr-eni-announces-final-investment-decision-mozambique-coral-north-project.html | C8: "6203d-65da2d598c64a-gzip" | D8: Mon, 12 Oct 2026 11:16:49 GMT | E8: 36781 | G8: 2026-10-12 | H8: FIRST SEEN
A9: Nigeria LNG Limited: Facts and Figures 2024 (six trains 22 MTPA; Train 7 lifts capacity to 30 MTPA; FID Dec 2019) | B9: https://www.nlng.com/documents/2024_NLNG_FACTS_FIGURESB_compressed.pdf | C9: "8b769b-gjNnKhPc9L1uQPS6FP/AZDKctG0" | D9: Wed, 10 Jun 2026 08:53:56 GMT | E9: 9139867 | G9: 2026-10-12 | H9: FIRST SEEN
A10: Novatek: FID release, Arctic LNG 2 (2019: three trains of 6.6 mtpa; schedule since changed) | B10: https://www.novatek.ru/common/upload/press/FID_Arctic_LNG_2_Eng.pdf | C10: "5d70a544-2d879" | D10: Thu, 05 Sep 2019 06:03:48 GMT | E10: 186489 | G10: 2026-10-12 | H10: FIRST SEEN
A11: Shell Canada Energy / Shell plc (release text as republished by Hellenic Shipping News): Shell takes final investment decision to double LNG Canada capacity (29 Sep 2026) | B11: https://www.hellenicshippingnews.com/shell-takes-final-investment-decision-to-double-lng-canada-capacity | E11: 119417 | F11: 7c0b68510b8462f12ddf4eb4f46638ab41f7abc57e8652e8d2b70fa347fbf4c0 | G11: 2026-10-12 | H11: FIRST SEEN
A12: Mozambique LNG (TotalEnergies-operated project site): Project page: development (two liquefaction units, 13.12 MTPA) | B12: https://mozambiquelng.co.mz/about-the-mozambique-liquefied-natural-gas-project/development/ | D12: Mon, 12 Oct 2026 00:05:19 GMT | G12: 2026-10-12 | H12: FIRST SEEN
A13: Woodfibre LNG: Construction page (2.1 million tonnes of LNG per year; substantial completion expected by 2027) | B13: https://woodfibrelng.ca/construction/ | E13: 300145 | F13: fd6c274108f3abcb0eda2f9054c84702684daaa03cacecd6c33274eedd490298 | G13: 2026-10-12 | H13: FIRST SEEN
A14: GIIGNL (used only where no official figure was opened; named as publisher): GIIGNL Annual Report 2026 edition (2025 data): liquefaction plants table and 'Liquefaction' regional sections | B14: https://giignl-documents.s3.fr-par.scw.cloud/public/giignl-2026-annual-report.pdf | C14: "13af79b9282b79dd60720d67ca8a2b74" | D14: Tue, 06 Oct 2026 13:10:27 GMT | E14: 8355455 | G14: 2026-10-12 | H14: FIRST SEEN
A15: Woodside Energy: Second Quarter Report 2026 (period ended 30 June 2026) | B15: https://www.woodside.com/docs/default-source/investor-documents/quarterly-and-half-yearly-pdfs-and-data-tables/2026/second-quarter-2026-report.pdf | D15: Tue, 28 Jul 2026 23:07:17 GMT | E15: 261755 | G15: 2026-10-12 | H15: FIRST SEEN
A16: Woodside Energy: Half-Year Report 2026 (period ended 30 June 2026) | B16: https://www.woodside.com/docs/default-source/investor-documents/quarterly-and-half-yearly-pdfs-and-data-tables/2026/half-year-2026-report.pdf?sfvrsn=df6d6ddc_6 | D16: Mon, 24 Aug 2026 22:35:45 GMT | E16: 897154 | G16: 2026-10-12 | H16: FIRST SEEN
A17: TotalEnergies: 2Q26 results press release (ECA LNG start-up early July 2026) | B17: https://totalenergies.com/system/files/documents/totalenergies_pr-results-2q26_2026_en.pdf | D17: Mon, 27 Jul 2026 12:01:55 GMT | E17: 989621 | G17: 2026-10-12 | H17: FIRST SEEN
A18: Pembina Pipeline Corporation: Q2 2026 results news release (Cedar LNG first exports late 2028) | B18: https://www.pembina.com/media-centre/news/details/fa13b9e4-bbc0-44d0-9ab6-88c72cbd54e5 | E18: 319744 | F18: 68061fb2da55d5d73fb292f68f0449ef109866098c5bf68b2d13a700fb45d224 | G18: 2026-10-12 | H18: FIRST SEEN
A19: Reuters (copy on BOE Report): QatarEnergy's LNG expansion project poised to start operations in November, sources say (7 Oct 2026) | B19: https://boereport.com/2026/10/07/qatarenergys-lng-expansion-project-poised-to-start-operations-in-november-sources-say/amp/ | D19: Mon, 12 Oct 2026 11:50:15 GMT | G19: 2026-10-12 | H19: FIRST SEEN
A20: DISR REQ listing | B20: https://www.industry.gov.au/publications/resources-and-energy-quarterly | G20: 2026-10-12 | H20: UNREACHABLE (ReadTimeout)

Sheet EIA rows
A1: sheet | B1: project | C1: train | D1: base_bcfd | E1: base_mtpa | F1: peak_bcfd | G1: peak_mtpa | H1: status_raw | I1: in_service_raw | J1: operator | K1: detail | L1: release_date | M1: file
A2: UC | B2: Sabine Pass | C2: Train 1 | D2: 0.59 | E2: 4.5 | F2: 0.76 | G2: 5.76 | H2: Commercial operation | I2: 2016-02-01 | J2: Cheniere Energy | L2: 2026-10-01 | M2: U.S.liquefactioncapacity_2026_Q3.xlsx
A3: UC | B3: Sabine Pass | C3: Train 2 | D3: 0.59 | E3: 4.5 | F3: 0.76 | G3: 5.76 | H3: Commercial operation | I3: 2016-08-01 | J3: Cheniere Energy | L3: 2026-10-01 | M3: U.S.liquefactioncapacity_2026_Q3.xlsx
A4: UC | B4: Sabine Pass | C4: Train 3 | D4: 0.59 | E4: 4.5 | F4: 0.76 | G4: 5.76 | H4: Commercial operation | I4: 2017-01-01 | J4: Cheniere Energy | L4: 2026-10-01 | M4: U.S.liquefactioncapacity_2026_Q3.xlsx
A5: UC | B5: Sabine Pass | C5: Train 4 | D5: 0.59 | E5: 4.5 | F5: 0.76 | G5: 5.76 | H5: Commercial operation | I5: 2017-08-01 | J5: Cheniere Energy | L5: 2026-10-01 | M5: U.S.liquefactioncapacity_2026_Q3.xlsx
A6: UC | B6: Sabine Pass | C6: Train 5 | D6: 0.59 | E6: 4.5 | F6: 0.76 | G6: 5.76 | H6: Commercial operation | I6: 2018-11-01 | J6: Cheniere Energy | L6: 2026-10-01 | M6: U.S.liquefactioncapacity_2026_Q3.xlsx
A7: UC | B7: Sabine Pass | C7: Train 6 | D7: 0.59 | E7: 4.5 | F7: 0.76 | G7: 5.76 | H7: Commercial operation | I7: 2021-12-01 | J7: Cheniere Energy | L7: 2026-10-01 | M7: U.S.liquefactioncapacity_2026_Q3.xlsx
A8: UC | B8: Cove Point | C8: Train 1 | D8: 0.69 | E8: 5.25 | F8: 0.76 | G8: 5.75 | H8: Commercial operation | I8: 2018-03-01 | J8: Berkshire Hathaway BHE GT&S | L8: 2026-10-01 | M8: U.S.liquefactioncapacity_2026_Q3.xlsx
A9: UC | B9: Elba Island | C9: Trains 1-5A | D9: 0.16 | E9: 1.25 | F9: 0.22 | G9: 1.45 | H9: Commercial operation | I9: 2019-09-01 | J9: Kinder Morgan | L9: 2026-10-01 | M9: U.S.liquefactioncapacity_2026_Q3.xlsx
A10: UC | B10: Elba Island | C10: Trains 6-10A | D10: 0.16 | E10: 1.25 | F10: 0.22 | G10: 1.45 | H10: Commercial operation | I10: 2020-05-01 | J10: Kinder Morgan | L10: 2026-10-01 | M10: U.S.liquefactioncapacity_2026_Q3.xlsx
A11: UC | B11: Corpus Christi | C11: Train 1 | D11: 0.6 | E11: 4.52 | F11: 0.8 | G11: 6.07 | H11: Commercial operation | I11: 2018-12-01 | J11: Cheniere Energy | L11: 2026-10-01 | M11: U.S.liquefactioncapacity_2026_Q3.xlsx
A12: UC | B12: Corpus Christi | C12: Train 2 | D12: 0.6 | E12: 4.52 | F12: 0.8 | G12: 6.07 | H12: Commercial operation | I12: 2019-07-01 | J12: Cheniere Energy | L12: 2026-10-01 | M12: U.S.liquefactioncapacity_2026_Q3.xlsx
A13: UC | B13: Corpus Christi | C13: Train 3 | D13: 0.6 | E13: 4.52 | F13: 0.8 | G13: 6.07 | H13: Commercial operation | I13: 2020-12-01 | J13: Cheniere Energy | L13: 2026-10-01 | M13: U.S.liquefactioncapacity_2026_Q3.xlsx
... A40: UC | B40: Delfin FLNG | C40: Train 1 | D40: 0.53 | E40: 4 | F40: 0.58 | G40: 4.4 | H40: Under construction | I40: 2030 | J40: Fairwood Group | L40: 2026-10-01 | M40: U.S.liquefactioncapacity_2026_Q3.xlsx
A41: APPROVED | B41: Cameron LNG Train 4A | C41: 1 | D41: 0.96 | E41: 6.75 | F41: 0.96 | G41: 6.75 | H41: Approved | J41: Cameron LNG, LLC | K41: Completed FEED on a new design of one larger-size train, rather than 2 trains as was initially proposed. Awarded EPC contract to Bechtel. FID TBA | L41: 2026-10-01 | M41: U.S.liquefactioncapacity_2026_Q3.xlsx
A42: APPROVED | B42: Lake Charles LNG | C42: 3 | D42: 0.72 | E42: 5.5 | F42: 2.17 | G42: 16.5 | H42: Approved | J42: Energy Transfer, LP | K42: Completed FEED, reviewed EPC tenders, signed a preliminary EPC contract with a consortium led by Technip Energies and KBR. FID TBAD | L42: 2026-10-01 | M42: U.S.liquefactioncapacity_2026_Q3.xlsx
A43: APPROVED | B43: Lake Charles LNG (additional DOE application) | C43: n/a | H43: Approved | J43: Energy Transfer, LP | K43: Completed FEED, reviewed EPC tenders, signed a preliminary EPC contract with a consortium led by Technip Energies and KBR, FID TBAD | L43: 2026-10-01 | M43: U.S.liquefactioncapacity_2026_Q3.xlsx
A44: APPROVED | B44: Woodside Louisiana LNG (formerly Driftwood LNG) Phase 2 | C44: 2 | D44: 0.73 | E44: 5.52 | F44: 1.45 | G44: 11.04 | H44: Approved | J44: Woodside Energy | K44: Completed FEED, awarded EPC contract to Bechtel Energy, issued limited notice to proceed to commence construction, FID TBA | L44: 2026-10-01 | M44: U.S.liquefactioncapacity_2026_Q3.xlsx
A45: APPROVED | B45: Freeport LNG Train 4C | C45: 1 | D45: 0.74 | E45: 5.1 | F45: 0.74 | G45: 5.1 | H45: Approved | J45: Freeport LNG | K45: Completed FEED, awarded EPC contract to Kiewit Energy. FID TBA | L45: 2026-10-01 | M45: U.S.liquefactioncapacity_2026_Q3.xlsx
A46: APPROVED | B46: Texas LNG | C46: 2 | D46: 0.28 | E46: 2 | F46: 0.56 | G46: 4 | H46: Approved | J46: Glenfarne Energy Transition, LLC | K46: Completed FEED, selected engineering, procurement, and construction (EPC) contractor. FID targeted for 2026. | L46: 2026-10-01 | M46: U.S.liquefactioncapacity_2026_Q3.xlsx
A47: APPROVED | B47: Gulf LNGE | C47: 2 | D47: 0.71 | E47: 5.43 | F47: 1.43 | G47: 10.85 | H47: Approved | J47: Gulf LNG Liquefaction Company, LLC | K47: Undergoing FEED | L47: 2026-10-01 | M47: U.S.liquefactioncapacity_2026_Q3.xlsx
A48: APPROVED | B48: Delfin FLNG | C48: 2 | D48: 0.53 | E48: 4.4 | F48: 1.05 | G48: 8.8 | H48: Approved | J48: Fairwood Group | K48: Completed FEED, awarded EPC contract to Samsung Heavy Industries and Black & Veatch. Project was granted DOE authorization for a 5-year extension to 2029 to commence operations. | L48: 2026-10-01 | M48: U.S.liquefactioncapacity_2026_Q3.xlsx
A49: APPROVED | B49: Alaska LNG | C49: 3 | D49: 0.85 | E49: 6.67 | F49: 2.55 | G49: 20 | H49: Approved | J49: Alaska Gasline Development Corporation (AGDC) | K49: Proposed | L49: 2026-10-01 | M49: U.S.liquefactioncapacity_2026_Q3.xlsx

Sheet Ramp calc
A1: Month | B1: Corpus Christi Stage 3 Midscale Train 7 | C1: Corpus Christi Liquefaction Midscale Trains 8-9G | D1: Golden Pass Train 2D | E1: Golden Pass Train 3D | F1: Port Arthur LNG Phase 1 Trains 1-2 | G1: Port Arthur LNG Phase 2 Trains 3-4 | H1: Rio Grande LNG Phase 1 Train 1I | I1: Rio Grande LNG Phase 1 Train 2I | J1: Rio Grande LNG Phase 1 Train 3I | K1: Rio Grande LNG Phase 2 Train 4I | L1: Rio Grande LNG Phase 2 Train 5I | M1: Woodside Louisiana LNG Phase 1 Trains 1-3 | N1: Venture Global CP2 Phase 1 Trains 1-26 | O1: Venture Global CP2 Phase 2 Trains 27-36 | P1: Commonwealth LNG Trains 1-6 | Q1: Delfin FLNG Train 1 | R1: North Field East expansion, Train 1 of 4 (8 mtpa) | S1: Woodfibre LNG | T1: Mozambique LNG (Afungi, 2 units) | U1: Coral North FLNG (Eni, Area 4) | V1: Marsa LNG (1 mtpa) | W1: Ruwais LNG (2 trains) | X1: Southern Energy (SESA) FLNG Hilli Episeyo (relocated from Ca | Y1: Southern Energy (SESA) FLNG Esperanza (MKII) | Z1: Golar FLNG Four (MKII, no charter yet) | AA1: Operating UC + FID, ramped (sum) | AB1: Planned dated, ramped (sum)
A2: capacity (mtpa) | B2: 1.429 | C2: 2.98 | D2: 5.2 | E2: 5.2 | F2: 12 | G2: 12 | H2: 5.4 | I2: 5.4 | J2: 5.4 | K2: 5.4 | L2: 5.4 | M2: 16.56 | N2: 14.4 | O2: 5.6 | P2: 8.4 | Q2: 4 | R2: 8 | S2: 2.1 | T2: 13.12 | U2: 3.6 | V2: 1 | W2: 9.6 | X2: 2.45 | Y2: 3.5 | Z2: 3.5
A3: start month | B3: 46327 | C3: 46935 | D3: 46296 | E3: 46478 | F3: 46569 | G3: 48030 | H3: 46569 | I3: 46569 | J3: 46935 | K3: 47665 | L3: 48030 | M3: 47300 | N3: 46661 | O3: 47209 | P3: 47665 | Q3: 47665 | R3: 46478 | S3: 46569 | T3: 47300 | U3: 46935 | V3: 46935 | W3: 46935 | X3: 46661 | Y3: 47027 | Z3: 47300
A4: 44197 | B4: =IF(ISNUMBER(B$3),B$2*MAX(0,MIN(1,((YEAR($A4)-YEAR(B$3))*12+MONTH($A4)-MONTH(B$3)+1)/'Capacity by month'!$O$2)),0) | C4: =IF(ISNUMBER(C$3),C$2*MAX(0,MIN(1,((YEAR($A4)-YEAR(C$3))*12+MONTH($A4)-MONTH(C$3)+1)/'Capacity by month'!$O$2)),0) | D4: =IF(ISNUMBER(D$3),D$2*MAX(0,MIN(1,((YEAR($A4)-YEAR(D$3))*12+MONTH($A4)-MONTH(D$3)+1)/'Capacity by month'!$O$2)),0) | E4: =IF(ISNUMBER(E$3),E$2*MAX(0,MIN(1,((YEAR($A4)-YEAR(E$3))*12+MONTH($A4)-MONTH(E$3)+1)/'Capacity by month'!$O$2)),0) | F4: =IF(ISNUMBER(F$3),F$2*MAX(0,MIN(1,((YEAR($A4)-YEAR(F$3))*12+MONTH($A4)-MONTH(F$3)+1)/'Capacity by month'!$O$2)),0) | G4: =IF(ISNUMBER(G$3),G$2*MAX(0,MIN(1,((YEAR($A4)-YEAR(G$3))*12+MONTH($A4)-MONTH(G$3)+1)/'Capacity by month'!$O$2)),0) | H4: =IF(ISNUMBER(H$3),H$2*MAX(0,MIN(1,((YEAR($A4)-YEAR(H$3))*12+MONTH($A4)-MONTH(H$3)+1)/'Capacity by month'!$O$2)),0) | I4: =IF(ISNUMBER(I$3),I$2*MAX(0,MIN(1,((YEAR($A4)-YEAR(I$3))*12+MONTH($A4)-MONTH(I$3)+1)/'Capacity by month'!$O$2)),0) | ... Z4: =IF(ISNUMBER(Z$3),Z$2*MAX(0,MIN(1,((YEAR($A4)-YEAR(Z$3))*12+MONTH($A4)-MONTH(Z$3)+1)/'Capacity by month'!$O$2)),0) | AA4: =SUM(B4:Z4) | AB4: 0
A5: 44228 | B5: =IF(ISNUMBER(B$3),B$2*MAX(0,MIN(1,((YEAR($A5)-YEAR(B$3))*12+MONTH($A5)-MONTH(B$3)+1)/'Capacity by month'!$O$2)),0) | C5: =IF(ISNUMBER(C$3),C$2*MAX(0,MIN(1,((YEAR($A5)-YEAR(C$3))*12+MONTH($A5)-MONTH(C$3)+1)/'Capacity by month'!$O$2)),0) | D5: =IF(ISNUMBER(D$3),D$2*MAX(0,MIN(1,((YEAR($A5)-YEAR(D$3))*12+MONTH($A5)-MONTH(D$3)+1)/'Capacity by month'!$O$2)),0) | E5: =IF(ISNUMBER(E$3),E$2*MAX(0,MIN(1,((YEAR($A5)-YEAR(E$3))*12+MONTH($A5)-MONTH(E$3)+1)/'Capacity by month'!$O$2)),0) | F5: =IF(ISNUMBER(F$3),F$2*MAX(0,MIN(1,((YEAR($A5)-YEAR(F$3))*12+MONTH($A5)-MONTH(F$3)+1)/'Capacity by month'!$O$2)),0) | G5: =IF(ISNUMBER(G$3),G$2*MAX(0,MIN(1,((YEAR($A5)-YEAR(G$3))*12+MONTH($A5)-MONTH(G$3)+1)/'Capacity by month'!$O$2)),0) | H5: =IF(ISNUMBER(H$3),H$2*MAX(0,MIN(1,((YEAR($A5)-YEAR(H$3))*12+MONTH($A5)-MONTH(H$3)+1)/'Capacity by month'!$O$2)),0) | I5: =IF(ISNUMBER(I$3),I$2*MAX(0,MIN(1,((YEAR($A5)-YEAR(I$3))*12+MONTH($A5)-MONTH(I$3)+1)/'Capacity by month'!$O$2)),0) | ... Z5: =IF(ISNUMBER(Z$3),Z$2*MAX(0,MIN(1,((YEAR($A5)-YEAR(Z$3))*12+MONTH($A5)-MONTH(Z$3)+1)/'Capacity by month'!$O$2)),0) | AA5: =SUM(B5:Z5) | AB5: 0
A6: 44256 | B6: =IF(ISNUMBER(B$3),B$2*MAX(0,MIN(1,((YEAR($A6)-YEAR(B$3))*12+MONTH($A6)-MONTH(B$3)+1)/'Capacity by month'!$O$2)),0) | C6: =IF(ISNUMBER(C$3),C$2*MAX(0,MIN(1,((YEAR($A6)-YEAR(C$3))*12+MONTH($A6)-MONTH(C$3)+1)/'Capacity by month'!$O$2)),0) | D6: =IF(ISNUMBER(D$3),D$2*MAX(0,MIN(1,((YEAR($A6)-YEAR(D$3))*12+MONTH($A6)-MONTH(D$3)+1)/'Capacity by month'!$O$2)),0) | E6: =IF(ISNUMBER(E$3),E$2*MAX(0,MIN(1,((YEAR($A6)-YEAR(E$3))*12+MONTH($A6)-MONTH(E$3)+1)/'Capacity by month'!$O$2)),0) | F6: =IF(ISNUMBER(F$3),F$2*MAX(0,MIN(1,((YEAR($A6)-YEAR(F$3))*12+MONTH($A6)-MONTH(F$3)+1)/'Capacity by month'!$O$2)),0) | G6: =IF(ISNUMBER(G$3),G$2*MAX(0,MIN(1,((YEAR($A6)-YEAR(G$3))*12+MONTH($A6)-MONTH(G$3)+1)/'Capacity by month'!$O$2)),0) | H6: =IF(ISNUMBER(H$3),H$2*MAX(0,MIN(1,((YEAR($A6)-YEAR(H$3))*12+MONTH($A6)-MONTH(H$3)+1)/'Capacity by month'!$O$2)),0) | I6: =IF(ISNUMBER(I$3),I$2*MAX(0,MIN(1,((YEAR($A6)-YEAR(I$3))*12+MONTH($A6)-MONTH(I$3)+1)/'Capacity by month'!$O$2)),0) | ... Z6: =IF(ISNUMBER(Z$3),Z$2*MAX(0,MIN(1,((YEAR($A6)-YEAR(Z$3))*12+MONTH($A6)-MONTH(Z$3)+1)/'Capacity by month'!$O$2)),0) | AA6: =SUM(B6:Z6) | AB6: 0
A7: 44287 | B7: =IF(ISNUMBER(B$3),B$2*MAX(0,MIN(1,((YEAR($A7)-YEAR(B$3))*12+MONTH($A7)-MONTH(B$3)+1)/'Capacity by month'!$O$2)),0) | C7: =IF(ISNUMBER(C$3),C$2*MAX(0,MIN(1,((YEAR($A7)-YEAR(C$3))*12+MONTH($A7)-MONTH(C$3)+1)/'Capacity by month'!$O$2)),0) | D7: =IF(ISNUMBER(D$3),D$2*MAX(0,MIN(1,((YEAR($A7)-YEAR(D$3))*12+MONTH($A7)-MONTH(D$3)+1)/'Capacity by month'!$O$2)),0) | E7: =IF(ISNUMBER(E$3),E$2*MAX(0,MIN(1,((YEAR($A7)-YEAR(E$3))*12+MONTH($A7)-MONTH(E$3)+1)/'Capacity by month'!$O$2)),0) | F7: =IF(ISNUMBER(F$3),F$2*MAX(0,MIN(1,((YEAR($A7)-YEAR(F$3))*12+MONTH($A7)-MONTH(F$3)+1)/'Capacity by month'!$O$2)),0) | G7: =IF(ISNUMBER(G$3),G$2*MAX(0,MIN(1,((YEAR($A7)-YEAR(G$3))*12+MONTH($A7)-MONTH(G$3)+1)/'Capacity by month'!$O$2)),0) | H7: =IF(ISNUMBER(H$3),H$2*MAX(0,MIN(1,((YEAR($A7)-YEAR(H$3))*12+MONTH($A7)-MONTH(H$3)+1)/'Capacity by month'!$O$2)),0) | I7: =IF(ISNUMBER(I$3),I$2*MAX(0,MIN(1,((YEAR($A7)-YEAR(I$3))*12+MONTH($A7)-MONTH(I$3)+1)/'Capacity by month'!$O$2)),0) | ... Z7: =IF(ISNUMBER(Z$3),Z$2*MAX(0,MIN(1,((YEAR($A7)-YEAR(Z$3))*12+MONTH($A7)-MONTH(Z$3)+1)/'Capacity by month'!$O$2)),0) | AA7: =SUM(B7:Z7) | AB7: 0
A8: 44317 | B8: =IF(ISNUMBER(B$3),B$2*MAX(0,MIN(1,((YEAR($A8)-YEAR(B$3))*12+MONTH($A8)-MONTH(B$3)+1)/'Capacity by month'!$O$2)),0) | C8: =IF(ISNUMBER(C$3),C$2*MAX(0,MIN(1,((YEAR($A8)-YEAR(C$3))*12+MONTH($A8)-MONTH(C$3)+1)/'Capacity by month'!$O$2)),0) | D8: =IF(ISNUMBER(D$3),D$2*MAX(0,MIN(1,((YEAR($A8)-YEAR(D$3))*12+MONTH($A8)-MONTH(D$3)+1)/'Capacity by month'!$O$2)),0) | E8: =IF(ISNUMBER(E$3),E$2*MAX(0,MIN(1,((YEAR($A8)-YEAR(E$3))*12+MONTH($A8)-MONTH(E$3)+1)/'Capacity by month'!$O$2)),0) | F8: =IF(ISNUMBER(F$3),F$2*MAX(0,MIN(1,((YEAR($A8)-YEAR(F$3))*12+MONTH($A8)-MONTH(F$3)+1)/'Capacity by month'!$O$2)),0) | G8: =IF(ISNUMBER(G$3),G$2*MAX(0,MIN(1,((YEAR($A8)-YEAR(G$3))*12+MONTH($A8)-MONTH(G$3)+1)/'Capacity by month'!$O$2)),0) | H8: =IF(ISNUMBER(H$3),H$2*MAX(0,MIN(1,((YEAR($A8)-YEAR(H$3))*12+MONTH($A8)-MONTH(H$3)+1)/'Capacity by month'!$O$2)),0) | I8: =IF(ISNUMBER(I$3),I$2*MAX(0,MIN(1,((YEAR($A8)-YEAR(I$3))*12+MONTH($A8)-MONTH(I$3)+1)/'Capacity by month'!$O$2)),0) | ... Z8: =IF(ISNUMBER(Z$3),Z$2*MAX(0,MIN(1,((YEAR($A8)-YEAR(Z$3))*12+MONTH($A8)-MONTH(Z$3)+1)/'Capacity by month'!$O$2)),0) | AA8: =SUM(B8:Z8) | AB8: 0
A9: 44348 | B9: =IF(ISNUMBER(B$3),B$2*MAX(0,MIN(1,((YEAR($A9)-YEAR(B$3))*12+MONTH($A9)-MONTH(B$3)+1)/'Capacity by month'!$O$2)),0) | C9: =IF(ISNUMBER(C$3),C$2*MAX(0,MIN(1,((YEAR($A9)-YEAR(C$3))*12+MONTH($A9)-MONTH(C$3)+1)/'Capacity by month'!$O$2)),0) | D9: =IF(ISNUMBER(D$3),D$2*MAX(0,MIN(1,((YEAR($A9)-YEAR(D$3))*12+MONTH($A9)-MONTH(D$3)+1)/'Capacity by month'!$O$2)),0) | E9: =IF(ISNUMBER(E$3),E$2*MAX(0,MIN(1,((YEAR($A9)-YEAR(E$3))*12+MONTH($A9)-MONTH(E$3)+1)/'Capacity by month'!$O$2)),0) | F9: =IF(ISNUMBER(F$3),F$2*MAX(0,MIN(1,((YEAR($A9)-YEAR(F$3))*12+MONTH($A9)-MONTH(F$3)+1)/'Capacity by month'!$O$2)),0) | G9: =IF(ISNUMBER(G$3),G$2*MAX(0,MIN(1,((YEAR($A9)-YEAR(G$3))*12+MONTH($A9)-MONTH(G$3)+1)/'Capacity by month'!$O$2)),0) | H9: =IF(ISNUMBER(H$3),H$2*MAX(0,MIN(1,((YEAR($A9)-YEAR(H$3))*12+MONTH($A9)-MONTH(H$3)+1)/'Capacity by month'!$O$2)),0) | I9: =IF(ISNUMBER(I$3),I$2*MAX(0,MIN(1,((YEAR($A9)-YEAR(I$3))*12+MONTH($A9)-MONTH(I$3)+1)/'Capacity by month'!$O$2)),0) | ... Z9: =IF(ISNUMBER(Z$3),Z$2*MAX(0,MIN(1,((YEAR($A9)-YEAR(Z$3))*12+MONTH($A9)-MONTH(Z$3)+1)/'Capacity by month'!$O$2)),0) | AA9: =SUM(B9:Z9) | AB9: 0
A10: 44378 | B10: =IF(ISNUMBER(B$3),B$2*MAX(0,MIN(1,((YEAR($A10)-YEAR(B$3))*12+MONTH($A10)-MONTH(B$3)+1)/'Capacity by month'!$O$2)),0) | C10: =IF(ISNUMBER(C$3),C$2*MAX(0,MIN(1,((YEAR($A10)-YEAR(C$3))*12+MONTH($A10)-MONTH(C$3)+1)/'Capacity by month'!$O$2)),0) | D10: =IF(ISNUMBER(D$3),D$2*MAX(0,MIN(1,((YEAR($A10)-YEAR(D$3))*12+MONTH($A10)-MONTH(D$3)+1)/'Capacity by month'!$O$2)),0) | E10: =IF(ISNUMBER(E$3),E$2*MAX(0,MIN(1,((YEAR($A10)-YEAR(E$3))*12+MONTH($A10)-MONTH(E$3)+1)/'Capacity by month'!$O$2)),0) | F10: =IF(ISNUMBER(F$3),F$2*MAX(0,MIN(1,((YEAR($A10)-YEAR(F$3))*12+MONTH($A10)-MONTH(F$3)+1)/'Capacity by month'!$O$2)),0) | G10: =IF(ISNUMBER(G$3),G$2*MAX(0,MIN(1,((YEAR($A10)-YEAR(G$3))*12+MONTH($A10)-MONTH(G$3)+1)/'Capacity by month'!$O$2)),0) | H10: =IF(ISNUMBER(H$3),H$2*MAX(0,MIN(1,((YEAR($A10)-YEAR(H$3))*12+MONTH($A10)-MONTH(H$3)+1)/'Capacity by month'!$O$2)),0) | I10: =IF(ISNUMBER(I$3),I$2*MAX(0,MIN(1,((YEAR($A10)-YEAR(I$3))*12+MONTH($A10)-MONTH(I$3)+1)/'Capacity by month'!$O$2)),0) | ... Z10: =IF(ISNUMBER(Z$3),Z$2*MAX(0,MIN(1,((YEAR($A10)-YEAR(Z$3))*12+MONTH($A10)-MONTH(Z$3)+1)/'Capacity by month'!$O$2)),0) | AA10: =SUM(B10:Z10) | AB10: 0
A11: 44409 | B11: =IF(ISNUMBER(B$3),B$2*MAX(0,MIN(1,((YEAR($A11)-YEAR(B$3))*12+MONTH($A11)-MONTH(B$3)+1)/'Capacity by month'!$O$2)),0) | C11: =IF(ISNUMBER(C$3),C$2*MAX(0,MIN(1,((YEAR($A11)-YEAR(C$3))*12+MONTH($A11)-MONTH(C$3)+1)/'Capacity by month'!$O$2)),0) | D11: =IF(ISNUMBER(D$3),D$2*MAX(0,MIN(1,((YEAR($A11)-YEAR(D$3))*12+MONTH($A11)-MONTH(D$3)+1)/'Capacity by month'!$O$2)),0) | E11: =IF(ISNUMBER(E$3),E$2*MAX(0,MIN(1,((YEAR($A11)-YEAR(E$3))*12+MONTH($A11)-MONTH(E$3)+1)/'Capacity by month'!$O$2)),0) | F11: =IF(ISNUMBER(F$3),F$2*MAX(0,MIN(1,((YEAR($A11)-YEAR(F$3))*12+MONTH($A11)-MONTH(F$3)+1)/'Capacity by month'!$O$2)),0) | G11: =IF(ISNUMBER(G$3),G$2*MAX(0,MIN(1,((YEAR($A11)-YEAR(G$3))*12+MONTH($A11)-MONTH(G$3)+1)/'Capacity by month'!$O$2)),0) | H11: =IF(ISNUMBER(H$3),H$2*MAX(0,MIN(1,((YEAR($A11)-YEAR(H$3))*12+MONTH($A11)-MONTH(H$3)+1)/'Capacity by month'!$O$2)),0) | I11: =IF(ISNUMBER(I$3),I$2*MAX(0,MIN(1,((YEAR($A11)-YEAR(I$3))*12+MONTH($A11)-MONTH(I$3)+1)/'Capacity by month'!$O$2)),0) | ... Z11: =IF(ISNUMBER(Z$3),Z$2*MAX(0,MIN(1,((YEAR($A11)-YEAR(Z$3))*12+MONTH($A11)-MONTH(Z$3)+1)/'Capacity by month'!$O$2)),0) | AA11: =SUM(B11:Z11) | AB11: 0
A12: 44440 | B12: =IF(ISNUMBER(B$3),B$2*MAX(0,MIN(1,((YEAR($A12)-YEAR(B$3))*12+MONTH($A12)-MONTH(B$3)+1)/'Capacity by month'!$O$2)),0) | C12: =IF(ISNUMBER(C$3),C$2*MAX(0,MIN(1,((YEAR($A12)-YEAR(C$3))*12+MONTH($A12)-MONTH(C$3)+1)/'Capacity by month'!$O$2)),0) | D12: =IF(ISNUMBER(D$3),D$2*MAX(0,MIN(1,((YEAR($A12)-YEAR(D$3))*12+MONTH($A12)-MONTH(D$3)+1)/'Capacity by month'!$O$2)),0) | E12: =IF(ISNUMBER(E$3),E$2*MAX(0,MIN(1,((YEAR($A12)-YEAR(E$3))*12+MONTH($A12)-MONTH(E$3)+1)/'Capacity by month'!$O$2)),0) | F12: =IF(ISNUMBER(F$3),F$2*MAX(0,MIN(1,((YEAR($A12)-YEAR(F$3))*12+MONTH($A12)-MONTH(F$3)+1)/'Capacity by month'!$O$2)),0) | G12: =IF(ISNUMBER(G$3),G$2*MAX(0,MIN(1,((YEAR($A12)-YEAR(G$3))*12+MONTH($A12)-MONTH(G$3)+1)/'Capacity by month'!$O$2)),0) | H12: =IF(ISNUMBER(H$3),H$2*MAX(0,MIN(1,((YEAR($A12)-YEAR(H$3))*12+MONTH($A12)-MONTH(H$3)+1)/'Capacity by month'!$O$2)),0) | I12: =IF(ISNUMBER(I$3),I$2*MAX(0,MIN(1,((YEAR($A12)-YEAR(I$3))*12+MONTH($A12)-MONTH(I$3)+1)/'Capacity by month'!$O$2)),0) | ... Z12: =IF(ISNUMBER(Z$3),Z$2*MAX(0,MIN(1,((YEAR($A12)-YEAR(Z$3))*12+MONTH($A12)-MONTH(Z$3)+1)/'Capacity by month'!$O$2)),0) | AA12: =SUM(B12:Z12) | AB12: 0
A13: 44470 | B13: =IF(ISNUMBER(B$3),B$2*MAX(0,MIN(1,((YEAR($A13)-YEAR(B$3))*12+MONTH($A13)-MONTH(B$3)+1)/'Capacity by month'!$O$2)),0) | C13: =IF(ISNUMBER(C$3),C$2*MAX(0,MIN(1,((YEAR($A13)-YEAR(C$3))*12+MONTH($A13)-MONTH(C$3)+1)/'Capacity by month'!$O$2)),0) | D13: =IF(ISNUMBER(D$3),D$2*MAX(0,MIN(1,((YEAR($A13)-YEAR(D$3))*12+MONTH($A13)-MONTH(D$3)+1)/'Capacity by month'!$O$2)),0) | E13: =IF(ISNUMBER(E$3),E$2*MAX(0,MIN(1,((YEAR($A13)-YEAR(E$3))*12+MONTH($A13)-MONTH(E$3)+1)/'Capacity by month'!$O$2)),0) | F13: =IF(ISNUMBER(F$3),F$2*MAX(0,MIN(1,((YEAR($A13)-YEAR(F$3))*12+MONTH($A13)-MONTH(F$3)+1)/'Capacity by month'!$O$2)),0) | G13: =IF(ISNUMBER(G$3),G$2*MAX(0,MIN(1,((YEAR($A13)-YEAR(G$3))*12+MONTH($A13)-MONTH(G$3)+1)/'Capacity by month'!$O$2)),0) | H13: =IF(ISNUMBER(H$3),H$2*MAX(0,MIN(1,((YEAR($A13)-YEAR(H$3))*12+MONTH($A13)-MONTH(H$3)+1)/'Capacity by month'!$O$2)),0) | I13: =IF(ISNUMBER(I$3),I$2*MAX(0,MIN(1,((YEAR($A13)-YEAR(I$3))*12+MONTH($A13)-MONTH(I$3)+1)/'Capacity by month'!$O$2)),0) | ... Z13: =IF(ISNUMBER(Z$3),Z$2*MAX(0,MIN(1,((YEAR($A13)-YEAR(Z$3))*12+MONTH($A13)-MONTH(Z$3)+1)/'Capacity by month'!$O$2)),0) | AA13: =SUM(B13:Z13) | AB13: 0
A14: 44501 | B14: =IF(ISNUMBER(B$3),B$2*MAX(0,MIN(1,((YEAR($A14)-YEAR(B$3))*12+MONTH($A14)-MONTH(B$3)+1)/'Capacity by month'!$O$2)),0) | C14: =IF(ISNUMBER(C$3),C$2*MAX(0,MIN(1,((YEAR($A14)-YEAR(C$3))*12+MONTH($A14)-MONTH(C$3)+1)/'Capacity by month'!$O$2)),0) | D14: =IF(ISNUMBER(D$3),D$2*MAX(0,MIN(1,((YEAR($A14)-YEAR(D$3))*12+MONTH($A14)-MONTH(D$3)+1)/'Capacity by month'!$O$2)),0) | E14: =IF(ISNUMBER(E$3),E$2*MAX(0,MIN(1,((YEAR($A14)-YEAR(E$3))*12+MONTH($A14)-MONTH(E$3)+1)/'Capacity by month'!$O$2)),0) | F14: =IF(ISNUMBER(F$3),F$2*MAX(0,MIN(1,((YEAR($A14)-YEAR(F$3))*12+MONTH($A14)-MONTH(F$3)+1)/'Capacity by month'!$O$2)),0) | G14: =IF(ISNUMBER(G$3),G$2*MAX(0,MIN(1,((YEAR($A14)-YEAR(G$3))*12+MONTH($A14)-MONTH(G$3)+1)/'Capacity by month'!$O$2)),0) | H14: =IF(ISNUMBER(H$3),H$2*MAX(0,MIN(1,((YEAR($A14)-YEAR(H$3))*12+MONTH($A14)-MONTH(H$3)+1)/'Capacity by month'!$O$2)),0) | I14: =IF(ISNUMBER(I$3),I$2*MAX(0,MIN(1,((YEAR($A14)-YEAR(I$3))*12+MONTH($A14)-MONTH(I$3)+1)/'Capacity by month'!$O$2)),0) | ... Z14: =IF(ISNUMBER(Z$3),Z$2*MAX(0,MIN(1,((YEAR($A14)-YEAR(Z$3))*12+MONTH($A14)-MONTH(Z$3)+1)/'Capacity by month'!$O$2)),0) | AA14: =SUM(B14:Z14) | AB14: 0
A15: 44531 | B15: =IF(ISNUMBER(B$3),B$2*MAX(0,MIN(1,((YEAR($A15)-YEAR(B$3))*12+MONTH($A15)-MONTH(B$3)+1)/'Capacity by month'!$O$2)),0) | C15: =IF(ISNUMBER(C$3),C$2*MAX(0,MIN(1,((YEAR($A15)-YEAR(C$3))*12+MONTH($A15)-MONTH(C$3)+1)/'Capacity by month'!$O$2)),0) | D15: =IF(ISNUMBER(D$3),D$2*MAX(0,MIN(1,((YEAR($A15)-YEAR(D$3))*12+MONTH($A15)-MONTH(D$3)+1)/'Capacity by month'!$O$2)),0) | E15: =IF(ISNUMBER(E$3),E$2*MAX(0,MIN(1,((YEAR($A15)-YEAR(E$3))*12+MONTH($A15)-MONTH(E$3)+1)/'Capacity by month'!$O$2)),0) | F15: =IF(ISNUMBER(F$3),F$2*MAX(0,MIN(1,((YEAR($A15)-YEAR(F$3))*12+MONTH($A15)-MONTH(F$3)+1)/'Capacity by month'!$O$2)),0) | G15: =IF(ISNUMBER(G$3),G$2*MAX(0,MIN(1,((YEAR($A15)-YEAR(G$3))*12+MONTH($A15)-MONTH(G$3)+1)/'Capacity by month'!$O$2)),0) | H15: =IF(ISNUMBER(H$3),H$2*MAX(0,MIN(1,((YEAR($A15)-YEAR(H$3))*12+MONTH($A15)-MONTH(H$3)+1)/'Capacity by month'!$O$2)),0) | I15: =IF(ISNUMBER(I$3),I$2*MAX(0,MIN(1,((YEAR($A15)-YEAR(I$3))*12+MONTH($A15)-MONTH(I$3)+1)/'Capacity by month'!$O$2)),0) | ... Z15: =IF(ISNUMBER(Z$3),Z$2*MAX(0,MIN(1,((YEAR($A15)-YEAR(Z$3))*12+MONTH($A15)-MONTH(Z$3)+1)/'Capacity by month'!$O$2)),0) | AA15: =SUM(B15:Z15) | AB15: 0
... A123: 47818 | B123: =IF(ISNUMBER(B$3),B$2*MAX(0,MIN(1,((YEAR($A123)-YEAR(B$3))*12+MONTH($A123)-MONTH(B$3)+1)/'Capacity by month'!$O$2)),0) | C123: =IF(ISNUMBER(C$3),C$2*MAX(0,MIN(1,((YEAR($A123)-YEAR(C$3))*12+MONTH($A123)-MONTH(C$3)+1)/'Capacity by month'!$O$2)),0) | D123: =IF(ISNUMBER(D$3),D$2*MAX(0,MIN(1,((YEAR($A123)-YEAR(D$3))*12+MONTH($A123)-MONTH(D$3)+1)/'Capacity by month'!$O$2)),0) | E123: =IF(ISNUMBER(E$3),E$2*MAX(0,MIN(1,((YEAR($A123)-YEAR(E$3))*12+MONTH($A123)-MONTH(E$3)+1)/'Capacity by month'!$O$2)),0) | F123: =IF(ISNUMBER(F$3),F$2*MAX(0,MIN(1,((YEAR($A123)-YEAR(F$3))*12+MONTH($A123)-MONTH(F$3)+1)/'Capacity by month'!$O$2)),0) | G123: =IF(ISNUMBER(G$3),G$2*MAX(0,MIN(1,((YEAR($A123)-YEAR(G$3))*12+MONTH($A123)-MONTH(G$3)+1)/'Capacity by month'!$O$2)),0) | H123: =IF(ISNUMBER(H$3),H$2*MAX(0,MIN(1,((YEAR($A123)-YEAR(H$3))*12+MONTH($A123)-MONTH(H$3)+1)/'Capacity by month'!$O$2)),0) | I123: =IF(ISNUMBER(I$3),I$2*MAX(0,MIN(1,((YEAR($A123)-YEAR(I$3))*12+MONTH($A123)-MONTH(I$3)+1)/'Capacity by month'!$O$2)),0) | ... Z123: =IF(ISNUMBER(Z$3),Z$2*MAX(0,MIN(1,((YEAR($A123)-YEAR(Z$3))*12+MONTH($A123)-MONTH(Z$3)+1)/'Capacity by month'!$O$2)),0) | AA123: =SUM(B123:Z123) | AB123: 0
