Workbook

Sheet Units
A1: Notes
A2: UNITS
A3: Breakeven: US$ per MMBtu at Henry Hub (HH = needed wellhead price - basis), pre-tax, at the discount rate on 'Inputs'. Capacity: Bcf/d. Inventory: locations and 1,000 lateral ft.
A5: WHAT THIS IS
A6: APPROXIMATE - built from company disclosures and BEG tiering; breakevens are pre-tax model results, not a vendor curve. Question: what breakeven price does the extra Haynesville supply in gulf_coast_gas_balance.xlsx 'Key question' imply if only COST limited it?
A7: The curve is a COST curve. It is NOT constrained by rigs, crews, sand, takeaway pipelines, leasing or midstream: with H = years to the Key-question date it assumes the whole developable inventory of a tier could be drilled evenly over those years.
A8: NOT modelled: replacement of the base-production decline (maintenance drilling; the last EIA DPR, May 2024, showed legacy Haynesville gas falling 739 MMcf/d in one month on 15.6 Bcf/d), taxes, hedges, midstream returns, well-to-well variance inside a tier, inventory used since 2012, interference between tiers. The marginal prices are therefore LOWER bounds for a net increase in output.
A10: HOW TO READ THE TABS
A11: Chart / Chart - Marginal price: native Excel charts (no borders); their cells are formulas, so editing 'Inputs' redraws them in Excel. Sources: every opened document with value, unit, as-of, publisher, URL and type; then snippet-only claims (never used) and what was not reachable.
A12: Inputs: yellow cells editable and kept on the next run. Block A assumptions (status SOURCED / ASSUMPTION), block B tiers. To use your own (paid) curve overwrite the 'Breakeven override' and 'Capacity override' columns of block B (and rename/add rows by overwriting the tier counts): override cells win over the model.
A13: Profile: decline shape (stretched exponential fitted to BEG's 5- and 10-year recovery anchors), PV factor and the Tier 1 EUR anchor. Curve: live per-tier breakeven, capacity for H = 1..10 years, sorted curve. Capacity over time: Bcf/d build of a programme (live). Mapping: the Key-question increments and the implied marginal breakeven (live) beside Henry Hub. BEG check: BEG's published tiers and the formula run on BEG's own 2015 inputs. Cross-checks: company figures that were NOT used as inputs.
A15: STATUS COUNTS
... A20: Yellow cells on 'Inputs' only. Set the override columns blank to return to the model. Sheets Curve values / Mapping values / Sensitivity values (inventory haircut x Western productivity; NaN = beyond inventory) are the script's own copy of the same arithmetic (used by the PNG charts); after editing in Excel the live tabs and native charts follow, the values tabs do not.

Sheet Chart
A1: APPROXIMATE - built from company disclosures and BEG tiering; breakevens are pre-tax model results, not a vendor curve. Cost curve only: NOT constrained by rigs, crews or takeaway. Step chart data and the editable horizons are on 'Chart data'.

Sheet Chart - Marginal price
A1: APPROXIMATE - built from company disclosures and BEG tiering; breakevens are pre-tax model results, not a vendor curve. Marginal tier = STEO Haynesville growth + extra supply (Gulf 'Key question'), see 'Mapping'.

Sheet Sources
A1: ID | B1: Type | C1: Item | D1: Value | E1: Unit | F1: As-of | G1: Publisher | H1: Document | I1: URL | J1: Status | K1: Used where
A2: B1 | B2: EUR | C2: Average EUR per 4,800-ft well, Tier 1 / 2 / 3 / 4 / 5 / 6 | D2: 7.9 / 5.9 / 4.5 / 3.3 / 2.4 / 1.4 | E2: Bcf per 4,800-ft well | F2: Dec 2015 (wells to 2012) | G2: Bureau of Economic Geology, UT Austin (Browning, Ikonnikova et al.) | H2: Oil & Gas Journal 7 Dec 2015, 'Study forecasts gradual Haynesville production recovery before final decline', Fig. 7 legend | I2: https://www.beg.utexas.edu/files/content/beg/research/shale/Haynesville%20Shale%20Gas%20Play.pdf | J2: OPENED in GitHub Actions 6 Oct 2026 | K2: Inputs (tier productivity ratios), BEG check
A3: B2 | B3: inventory | C3: Remaining potential wells by tier: partly drilled blocks / undrilled blocks / drilled to 2012 | D3: see 'BEG check' (T1 1,700/2,250/450 ... T6 1,170/5,700/180) | E3: wells (4,800-ft) | F3: 2012 well data | G3: Bureau of Economic Geology | H3: OGJ 7 Dec 2015, Fig. 6 stacked bars | I3: https://www.beg.utexas.edu/files/content/beg/research/shale/Haynesville%20Shale%20Gas%20Play.pdf | J3: OPENED in GitHub Actions 6 Oct 2026; value READ OFF A CHART IMAGE (rendered page, approx. +/-3%) | K3: Inputs (tier inventory)
A4: B3 | B4: breakeven | C4: Breakeven Henry Hub price by tier at 0% / 10% / 20% IRR (2011 $) | D4: see 'BEG check' (10% IRR: T1 3.5, T2 4.4, T3 5.4, T4 6.8, T5 9.0, T6 15.2) | E4: $/MMBtu | F4: 2011 $, 2015 study | G4: Bureau of Economic Geology | H4: OGJ 7 Dec 2015, Fig. 8 | I4: https://www.beg.utexas.edu/files/content/beg/research/shale/Haynesville%20Shale%20Gas%20Play.pdf | J4: OPENED in GitHub Actions 6 Oct 2026; value READ OFF A CHART IMAGE (rendered page, approx. +/-3%) | K4: BEG check (validation of the formula)
A5: B4 | B5: well cost | C5: Drilling cost 12,000-ft TVD $10.5 million (20% tangible), related capex 13%, expense $82,500/well/yr +13% overhead, gathering/compression/treatment $0.49/Mcf, royalty 25%, severance 4% (2 yrs exempt), basis HH -$0.07, tax 40.2% | D5: 10.5 / 13% / 82,500 / 0.49 / 25% / -0.07 | E5: mixed | F5: 2015 study | G5: Bureau of Economic Geology | H5: OGJ 7 Dec 2015, Table 1 | I5: https://www.beg.utexas.edu/files/content/beg/research/shale/Haynesville%20Shale%20Gas%20Play.pdf | J5: OPENED in GitHub Actions 6 Oct 2026 | K5: Inputs (royalty, basis, related capex), BEG check
A6: B5 | B6: inventory | C6: Development ceilings: 80% of partly drilled blocks, 40% of undrilled blocks; 20-yr well life; 4,800-ft normalised lateral | D6: 80% / 40% / 20 / 4,800 | E6: % / years / ft | F6: 2015 study | G6: Bureau of Economic Geology | H6: OGJ 7 Dec 2015, Table 2 and text | I6: https://www.beg.utexas.edu/files/content/beg/research/shale/Haynesville%20Shale%20Gas%20Play.pdf | J6: OPENED in GitHub Actions 6 Oct 2026 | K6: Inputs (developable shares, lateral)
A7: B6 | B7: EUR | C7: Share of EUR recovered in first 5 years: >80% (Tier 1: 78%); nearly depleted by year 10 with >90% produced | D7: >80% (78% T1) / >90% | E7: % of EUR | F7: 2015 study | G7: Bureau of Economic Geology | H7: OGJ 7 Dec 2015, 'Well economics' | I7: https://www.beg.utexas.edu/files/content/beg/research/shale/Haynesville%20Shale%20Gas%20Play.pdf | J7: OPENED in GitHub Actions 6 Oct 2026 | K7: Inputs (decline anchors C(5), C(10)) - anchors chosen inside BEG's bounds = ASSUMPTION
A8: B7 | B8: breakeven | C8: 'A substantial portion of the reservoir has breakeven gas prices of $4-6/MMbtu'; remaining technically recoverable resource 177 Tcf; 2,527 wells to 2012 EUR 10.3 Tcf | D8: 4-6 / 177 / 10.3 | E8: $/MMBtu / Tcf | F8: Dec 2015 | G8: Bureau of Economic Geology | H8: OGJ 7 Dec 2015 (also SNL 23 Dec 2015 summary) | I8: https://www.beg.utexas.edu/files/content/beg/research/shale/Haynesville%20Shale%20Gas%20Play.pdf | J8: OPENED in GitHub Actions 6 Oct 2026 | K8: context (2011-15 costs)
A9: C1 | B9: inventory | C9: Legacy Haynesville + Bossier drilling inventory 30 Jun 2026: 1,705 gross / 816 net locations, average lateral 10,153 ft (Haynesville 881, Bossier 824 gross) | D9: 1,705 / 816 / 10,153 | E9: locations / ft | F9: 30 Jun 2026 | G9: Comstock Resources | H9: Investor Presentation October 2026, slide 13 | I9: https://investors.comstockresources.com/static-files/5a596a22-02f6-4b49-a9cc-93ecfe0179c0 | J9: OPENED in GitHub Actions 6 Oct 2026; value READ OFF A CHART IMAGE (rendered page, approx. +/-3%) | K9: Cross-check table (inside BEG's legacy inventory, not added)
A10: C2 | B10: inventory | C10: Western Haynesville operated drilling locations 30 Jun 2026: 3,277 gross / 2,528 net (Haynesville 1,206, Bossier 2,071 gross), average lateral 8,875 ft; assumes 70-90% WI | D10: 3,277 / 2,528 / 8,875 | E10: locations / ft | F10: 30 Jun 2026 | G10: Comstock Resources | H10: Investor Presentation October 2026, slide 14 | I10: https://investors.comstockresources.com/static-files/5a596a22-02f6-4b49-a9cc-93ecfe0179c0 | J10: OPENED in GitHub Actions 6 Oct 2026; value READ OFF A CHART IMAGE (rendered page, approx. +/-3%) | K10: Inputs (Western Haynesville row)
A11: C3 | B11: well cost | C11: Legacy Haynesville D&C cost, laterals >8,500 ft, Q2 2026: drilling $710 + completion $680 per lateral foot | D11: 1,390 | E11: $ per lateral ft | F11: Q2 2026 | G11: Comstock Resources | H11: Investor Presentation October 2026, slide 21 (bar labels) | I11: https://investors.comstockresources.com/static-files/5a596a22-02f6-4b49-a9cc-93ecfe0179c0 | J11: OPENED in GitHub Actions 6 Oct 2026; value READ OFF A CHART IMAGE (rendered page, approx. +/-3%) | K11: Inputs (Legacy tiers $/ft)
A12: C4 | B12: well cost | C12: Western Haynesville D&C cost Q2 2026: drilling $1,738 + completion $1,609 per lateral foot (Q1 2026: 1,534 + 1,537; 2025 Q2: 1,817 + 1,305) | D12: 3,347 | E12: $ per lateral ft | F12: Q2 2026 | G12: Comstock Resources | H12: Investor Presentation October 2026, slide 22 (bar labels) | I12: https://investors.comstockresources.com/static-files/5a596a22-02f6-4b49-a9cc-93ecfe0179c0 | J12: OPENED in GitHub Actions 6 Oct 2026; value READ OFF A CHART IMAGE (rendered page, approx. +/-3%) | K12: Inputs (Western Haynesville $/ft)
... A28: S2 | B28: breakeven (old) | C28: BTU Analytics (Feb 2016): best Haynesville acreage breakeven $1.50-3.00/MMBtu, plenty of areas above $5; only 20% of sub-$2 locations (177 wells) drilled | D28: 1.5-3.0 / >5 | E28: $/MMBtu | F28: 19 Feb 2016 | G28: NGI Shale Daily (via BEG ext-aff copy) | H28: 'Haynesville An Able Price Competitor With Northeast NatGas in Plenty of Areas' | I28: https://www.beg.utexas.edu/files/content/beg/ext-aff/16-02/Haynesville%20An%20Able%20Price%20Competitor%20With%20Northeast%20NatGas%20in%20'Plenty%20of%20Areas'.pdf | J28: OPENED (2016 costs, stale) | K28: not used

Sheet Inputs
A1: Inputs - yellow cells are editable and survive reruns. APPROXIMATE - built from company disclosures and BEG tiering; breakevens are pre-tax model results, not a vendor curve
A2: Block A: assumptions. Block B: tiers (rows can be overwritten with your own curve: use the two override columns).
A4: Assumption | B4: Value | C4: Unit | D4: Status | E4: Source / note
A5: Discount rate for breakeven (pre-tax NPV = 0) | B5: 0.1 | C5: share | D5: ASSUMPTION | E5: BEG and the EIA study quoted by Evaluate Energy use a 10% IRR hurdle; Expand's own breakeven basis is not stated.
A6: Royalty rate | B6: 0.25 | C6: share of revenue | D6: SOURCED | E6: BEG Table 1 (2015). Current lease royalties are not in the opened company documents.
A7: Basis, Henry Hub to wellhead (negative = wellhead below HH) | B7: -0.07 | C7: $/MMBtu | D7: SOURCED | E7: BEG Table 1 (2015); present-day Gulf Coast basis not sourced. Breakeven is quoted at Henry Hub: HH = needed realised price - basis.
A8: Lease operating cost | B8: 0.25 | C8: $/Mcf | D8: SOURCED | E8: Comstock Q2 2026 release (per Mcfe, ~96% gas).
A9: Gathering & transportation | B9: 0.38 | C9: $/Mcf | D9: SOURCED | E9: Comstock Q2 2026 release (company-owned midstream; third-party rates will differ).
A10: Production & other taxes | B10: 0.06 | C10: $/Mcf | D10: SOURCED | E10: Comstock Q2 2026 release (guidance 2026: 0.10-0.15).
A11: Facilities & other capex as share of D&C | B11: 0.13 | C11: share | D11: ASSUMPTION | E11: BEG Table 1 'related capital expenditures 13%' (2015) applied to today's D&C; Comstock's $/ft is drilling + completion only.
A12: Cumulative share of EUR recovered after 5 years | B12: 0.8 | C12: share | D12: ASSUMPTION | E12: BEG text: 'more than 80%' (Tier 1 78%). Anchor for the decline shape.
A13: Cumulative share of EUR recovered after 10 years | B13: 0.92 | C13: share | D13: ASSUMPTION | E13: BEG text: 'more than 90%'. Anchor for the decline shape.
A14: 12-month cumulative production of a modern Tier 1 well | B14: 0.855 | C14: Bcfe per 1,000 lateral ft | D14: SOURCED | E14: Expand 3Q25 deck slide 12: ~855 Mcfe/ft (2026E, company estimate; Mcfe ~ Mcf, Expand is ~92% gas).
A15: D&C cost per lateral foot, Legacy tiers | B15: 1390 | C15: $/ft | D15: SOURCED | E15: Comstock Oct 2026 deck slide 21, Q2 2026: $710 drilling + $680 completion (laterals >8,500 ft). Expand 2026E ~$1,340 (cross-check).
A16: D&C cost per lateral foot, Western Haynesville | B16: 3347 | C16: $/ft | D16: SOURCED | E16: Comstock Oct 2026 deck slide 22, Q2 2026: $1,738 + $1,609.
... A22: Programme length for the 'Capacity over time' tab | B22: 8 | C22: years | D22: ASSUMPTION | E22: Demonstration only; the curve and mapping use H = years to each Key-question date.
A24: Block B: tiers
A25: Tier / block | B25: Basis | C25: Partly drilled / counted locations | D25: Undrilled locations | E25: Developable share of partly/counted | F25: Developable share of undrilled | G25: Lateral per location (1,000 ft) | H25: Relative productivity vs Tier 1 (EUR per ft) | I25: D&C cost ($ per lateral ft) | J25: Breakeven override ($/MMBtu HH; blank = model) | K25: Capacity override (Bcf/d, all horizons; blank = model) | L25: Source / status
A26: Legacy Tier 1 (BEG) | B26: BEG tier, legacy Haynesville | C26: 1700 | D26: 2250 | E26: =Inputs!$B$18*Inputs!$B$20 | F26: =Inputs!$B$19*Inputs!$B$20 | G26: =Inputs!$B$21 | H26: ='BEG check'!$C$6/'BEG check'!$C$6 | I26: =Inputs!$B$15 | L26: Inventory: BEG Fig. 6 (chart-read, 2012 data, wells drilled since 2012 NOT deducted); productivity: BEG EUR ratio x Expand anchor; cost: Comstock Legacy Q2 2026.
A27: Legacy Tier 2 (BEG) | B27: BEG tier, legacy Haynesville | C27: 1470 | D27: 2000 | E27: =Inputs!$B$18*Inputs!$B$20 | F27: =Inputs!$B$19*Inputs!$B$20 | G27: =Inputs!$B$21 | H27: ='BEG check'!$C$7/'BEG check'!$C$6 | I27: =Inputs!$B$15 | L27: Inventory: BEG Fig. 6 (chart-read, 2012 data, wells drilled since 2012 NOT deducted); productivity: BEG EUR ratio x Expand anchor; cost: Comstock Legacy Q2 2026.
A28: Legacy Tier 3 (BEG) | B28: BEG tier, legacy Haynesville | C28: 2550 | D28: 3200 | E28: =Inputs!$B$18*Inputs!$B$20 | F28: =Inputs!$B$19*Inputs!$B$20 | G28: =Inputs!$B$21 | H28: ='BEG check'!$C$8/'BEG check'!$C$6 | I28: =Inputs!$B$15 | L28: Inventory: BEG Fig. 6 (chart-read, 2012 data, wells drilled since 2012 NOT deducted); productivity: BEG EUR ratio x Expand anchor; cost: Comstock Legacy Q2 2026.
A29: Legacy Tier 4 (BEG) | B29: BEG tier, legacy Haynesville | C29: 2050 | D29: 3250 | E29: =Inputs!$B$18*Inputs!$B$20 | F29: =Inputs!$B$19*Inputs!$B$20 | G29: =Inputs!$B$21 | H29: ='BEG check'!$C$9/'BEG check'!$C$6 | I29: =Inputs!$B$15 | L29: Inventory: BEG Fig. 6 (chart-read, 2012 data, wells drilled since 2012 NOT deducted); productivity: BEG EUR ratio x Expand anchor; cost: Comstock Legacy Q2 2026.
A30: Legacy Tier 5 (BEG) | B30: BEG tier, legacy Haynesville | C30: 1900 | D30: 4500 | E30: =Inputs!$B$18*Inputs!$B$20 | F30: =Inputs!$B$19*Inputs!$B$20 | G30: =Inputs!$B$21 | H30: ='BEG check'!$C$10/'BEG check'!$C$6 | I30: =Inputs!$B$15 | L30: Inventory: BEG Fig. 6 (chart-read, 2012 data, wells drilled since 2012 NOT deducted); productivity: BEG EUR ratio x Expand anchor; cost: Comstock Legacy Q2 2026.
A31: Legacy Tier 6 (BEG) | B31: BEG tier, legacy Haynesville | C31: 1170 | D31: 5700 | E31: =Inputs!$B$18*Inputs!$B$20 | F31: =Inputs!$B$19*Inputs!$B$20 | G31: =Inputs!$B$21 | H31: ='BEG check'!$C$11/'BEG check'!$C$6 | I31: =Inputs!$B$15 | L31: Inventory: BEG Fig. 6 (chart-read, 2012 data, wells drilled since 2012 NOT deducted); productivity: BEG EUR ratio x Expand anchor; cost: Comstock Legacy Q2 2026.
A32: Western Haynesville - Comstock operated | B32: Western Haynesville | C32: 3277 | D32: 0 | E32: 1 | F32: 0 | G32: 8.875 | H32: =Inputs!$B$17 | I32: =Inputs!$B$16 | L32: Inventory: Comstock slide 14 (3,277 gross operated locations, 30 Jun 2026; counted inventory, so shares 1/0); productivity ASSUMED; cost: Comstock slide 22.
A33: Western Haynesville - Expand prospective | B33: Western Haynesville | C33: 200 | D33: 0 | E33: 1 | F33: 0 | G33: 10 | H33: =Inputs!$B$17 | I33: =Inputs!$B$16 | L33: Inventory: Expand 3Q25 slide 13 '>200 locations' (10k-ft normalised, prospective acreage, undelineated); productivity and cost as Comstock Western Haynesville (ASSUMED).

Sheet Profile
A1: Per-well production profile (shared by all tiers): cumulative share of EUR C(n) = 1 - exp(-(n/tau)^beta), fitted to the two BEG recovery anchors on 'Inputs'. Live formulas.
A3: beta = ln( ln(1-C10) / ln(1-C5) ) / ln 2 | B3: =LN(LN(1-Inputs!$B$13)/LN(1-Inputs!$B$12))/LN(2)
A4: tau (years) = 5 / (-ln(1-C5))^(1/beta) | B4: =5/(-LN(1-Inputs!$B$12))^(1/B3)
A5: Year-1 share of EUR f(1) | B5: =C9
A6: PV factor: sum f(n)/(1+d)^(n-0.5) (mid-year discounting, capex at t=0) | B6: =SUMPRODUCT(C9:C28/(1+Inputs!$B$5)^(A9:A28-0.5))
A7: Modern Tier 1 EUR (Bcf per 1,000 lateral ft) = 12-month cumulative / f(1) | B7: =Inputs!$B$14/B5
A8: Year n | B8: Cumulative share C(n) | C8: Annual share f(n)
A9: 1 | B9: =1-EXP(-((A9/$B$4)^$B$3)) | C9: =B9
A10: 2 | B10: =1-EXP(-((A10/$B$4)^$B$3)) | C10: =B10-B9
A11: 3 | B11: =1-EXP(-((A11/$B$4)^$B$3)) | C11: =B11-B10
A12: 4 | B12: =1-EXP(-((A12/$B$4)^$B$3)) | C12: =B12-B11
A13: 5 | B13: =1-EXP(-((A13/$B$4)^$B$3)) | C13: =B13-B12
A14: 6 | B14: =1-EXP(-((A14/$B$4)^$B$3)) | C14: =B14-B13
A15: 7 | B15: =1-EXP(-((A15/$B$4)^$B$3)) | C15: =B15-B14
A16: 8 | B16: =1-EXP(-((A16/$B$4)^$B$3)) | C16: =B16-B15
A17: 9 | B17: =1-EXP(-((A17/$B$4)^$B$3)) | C17: =B17-B16
A18: 10 | B18: =1-EXP(-((A18/$B$4)^$B$3)) | C18: =B18-B17
A19: 11 | B19: =1-EXP(-((A19/$B$4)^$B$3)) | C19: =B19-B18
A20: 12 | B20: =1-EXP(-((A20/$B$4)^$B$3)) | C20: =B20-B19
A21: 13 | B21: =1-EXP(-((A21/$B$4)^$B$3)) | C21: =B21-B20
... A28: 20 | B28: =1-EXP(-((A28/$B$4)^$B$3)) | C28: =B28-B27

Sheet Curve
A1: Curve - live per-tier breakeven and capacity (formulas). APPROXIMATE - built from company disclosures and BEG tiering; breakevens are pre-tax model results, not a vendor curve
A2: Breakeven (HH) = ((LOE + gathering + taxes) + capex per 1,000 ft / PV volume per 1,000 ft) / (1 - royalty) - basis, with capex = $/ft x 1,000 x (1 + other capex) and PV volume = EUR x 1e6 Mcf x PV factor. Capacity(H) = developable lateral x EUR x C(H) / H / 365 (Bcf/d in year H of a programme drilling the inventory evenly over H years).
L3: Capacity by horizon H (years) - Bcf/d
A4: Tier / block | B4: Developable lateral (1,000 ft) | C4: EUR (Bcf per 1,000 ft) | D4: Capex per 1,000 ft ($) | E4: PV volume per 1,000 ft (Mcf) | F4: Breakeven, model ($/MMBtu HH) | G4: Breakeven used | H4: Source of breakeven | I4: Rank | J4: Developable EUR (Tcf) | K4: Developable locations | L4: 1 | M4: 2 | N4: 3 | O4: 4 | P4: 5 | Q4: 6 | R4: 7 | S4: 8 | T4: 9 | U4: 10
A5: =Inputs!A26 | B5: =(Inputs!C26*Inputs!E26+Inputs!D26*Inputs!F26)*Inputs!G26 | C5: =Profile!$B$7*Inputs!H26 | D5: =Inputs!I26*1000*(1+Inputs!$B$11) | E5: =C5*1000000*Profile!$B$6 | F5: =((Inputs!$B$8+Inputs!$B$9+Inputs!$B$10)+D5/E5)/(1-Inputs!$B$6)-Inputs!$B$7 | G5: =IF(ISNUMBER(Inputs!J26),Inputs!J26,F5) | H5: =IF(ISNUMBER(Inputs!J26),"OWNER OVERRIDE","MODEL") | I5: =COUNTIF($G$5:$G$12,"<"&G5)+COUNTIF($G$5:G5,G5) | J5: =B5*C5/1000 | K5: =B5/Inputs!G26 | L5: =IF(ISNUMBER(Inputs!$K26),Inputs!$K26,$B5*$C5*INDEX(Profile!$B$9:$B$28,L$4)/L$4/365) | M5: =IF(ISNUMBER(Inputs!$K26),Inputs!$K26,$B5*$C5*INDEX(Profile!$B$9:$B$28,M$4)/M$4/365) | N5: =IF(ISNUMBER(Inputs!$K26),Inputs!$K26,$B5*$C5*INDEX(Profile!$B$9:$B$28,N$4)/N$4/365) | O5: =IF(ISNUMBER(Inputs!$K26),Inputs!$K26,$B5*$C5*INDEX(Profile!$B$9:$B$28,O$4)/O$4/365) | P5: =IF(ISNUMBER(Inputs!$K26),Inputs!$K26,$B5*$C5*INDEX(Profile!$B$9:$B$28,P$4)/P$4/365) | Q5: =IF(ISNUMBER(Inputs!$K26),Inputs!$K26,$B5*$C5*INDEX(Profile!$B$9:$B$28,Q$4)/Q$4/365) | R5: =IF(ISNUMBER(Inputs!$K26),Inputs!$K26,$B5*$C5*INDEX(Profile!$B$9:$B$28,R$4)/R$4/365) | S5: =IF(ISNUMBER(Inputs!$K26),Inputs!$K26,$B5*$C5*INDEX(Profile!$B$9:$B$28,S$4)/S$4/365) | ... U5: =IF(ISNUMBER(Inputs!$K26),Inputs!$K26,$B5*$C5*INDEX(Profile!$B$9:$B$28,U$4)/U$4/365)
A6: =Inputs!A27 | B6: =(Inputs!C27*Inputs!E27+Inputs!D27*Inputs!F27)*Inputs!G27 | C6: =Profile!$B$7*Inputs!H27 | D6: =Inputs!I27*1000*(1+Inputs!$B$11) | E6: =C6*1000000*Profile!$B$6 | F6: =((Inputs!$B$8+Inputs!$B$9+Inputs!$B$10)+D6/E6)/(1-Inputs!$B$6)-Inputs!$B$7 | G6: =IF(ISNUMBER(Inputs!J27),Inputs!J27,F6) | H6: =IF(ISNUMBER(Inputs!J27),"OWNER OVERRIDE","MODEL") | I6: =COUNTIF($G$5:$G$12,"<"&G6)+COUNTIF($G$5:G6,G6) | J6: =B6*C6/1000 | K6: =B6/Inputs!G27 | L6: =IF(ISNUMBER(Inputs!$K27),Inputs!$K27,$B6*$C6*INDEX(Profile!$B$9:$B$28,L$4)/L$4/365) | M6: =IF(ISNUMBER(Inputs!$K27),Inputs!$K27,$B6*$C6*INDEX(Profile!$B$9:$B$28,M$4)/M$4/365) | N6: =IF(ISNUMBER(Inputs!$K27),Inputs!$K27,$B6*$C6*INDEX(Profile!$B$9:$B$28,N$4)/N$4/365) | O6: =IF(ISNUMBER(Inputs!$K27),Inputs!$K27,$B6*$C6*INDEX(Profile!$B$9:$B$28,O$4)/O$4/365) | P6: =IF(ISNUMBER(Inputs!$K27),Inputs!$K27,$B6*$C6*INDEX(Profile!$B$9:$B$28,P$4)/P$4/365) | Q6: =IF(ISNUMBER(Inputs!$K27),Inputs!$K27,$B6*$C6*INDEX(Profile!$B$9:$B$28,Q$4)/Q$4/365) | R6: =IF(ISNUMBER(Inputs!$K27),Inputs!$K27,$B6*$C6*INDEX(Profile!$B$9:$B$28,R$4)/R$4/365) | S6: =IF(ISNUMBER(Inputs!$K27),Inputs!$K27,$B6*$C6*INDEX(Profile!$B$9:$B$28,S$4)/S$4/365) | ... U6: =IF(ISNUMBER(Inputs!$K27),Inputs!$K27,$B6*$C6*INDEX(Profile!$B$9:$B$28,U$4)/U$4/365)
A7: =Inputs!A28 | B7: =(Inputs!C28*Inputs!E28+Inputs!D28*Inputs!F28)*Inputs!G28 | C7: =Profile!$B$7*Inputs!H28 | D7: =Inputs!I28*1000*(1+Inputs!$B$11) | E7: =C7*1000000*Profile!$B$6 | F7: =((Inputs!$B$8+Inputs!$B$9+Inputs!$B$10)+D7/E7)/(1-Inputs!$B$6)-Inputs!$B$7 | G7: =IF(ISNUMBER(Inputs!J28),Inputs!J28,F7) | H7: =IF(ISNUMBER(Inputs!J28),"OWNER OVERRIDE","MODEL") | I7: =COUNTIF($G$5:$G$12,"<"&G7)+COUNTIF($G$5:G7,G7) | J7: =B7*C7/1000 | K7: =B7/Inputs!G28 | L7: =IF(ISNUMBER(Inputs!$K28),Inputs!$K28,$B7*$C7*INDEX(Profile!$B$9:$B$28,L$4)/L$4/365) | M7: =IF(ISNUMBER(Inputs!$K28),Inputs!$K28,$B7*$C7*INDEX(Profile!$B$9:$B$28,M$4)/M$4/365) | N7: =IF(ISNUMBER(Inputs!$K28),Inputs!$K28,$B7*$C7*INDEX(Profile!$B$9:$B$28,N$4)/N$4/365) | O7: =IF(ISNUMBER(Inputs!$K28),Inputs!$K28,$B7*$C7*INDEX(Profile!$B$9:$B$28,O$4)/O$4/365) | P7: =IF(ISNUMBER(Inputs!$K28),Inputs!$K28,$B7*$C7*INDEX(Profile!$B$9:$B$28,P$4)/P$4/365) | Q7: =IF(ISNUMBER(Inputs!$K28),Inputs!$K28,$B7*$C7*INDEX(Profile!$B$9:$B$28,Q$4)/Q$4/365) | R7: =IF(ISNUMBER(Inputs!$K28),Inputs!$K28,$B7*$C7*INDEX(Profile!$B$9:$B$28,R$4)/R$4/365) | S7: =IF(ISNUMBER(Inputs!$K28),Inputs!$K28,$B7*$C7*INDEX(Profile!$B$9:$B$28,S$4)/S$4/365) | ... U7: =IF(ISNUMBER(Inputs!$K28),Inputs!$K28,$B7*$C7*INDEX(Profile!$B$9:$B$28,U$4)/U$4/365)
A8: =Inputs!A29 | B8: =(Inputs!C29*Inputs!E29+Inputs!D29*Inputs!F29)*Inputs!G29 | C8: =Profile!$B$7*Inputs!H29 | D8: =Inputs!I29*1000*(1+Inputs!$B$11) | E8: =C8*1000000*Profile!$B$6 | F8: =((Inputs!$B$8+Inputs!$B$9+Inputs!$B$10)+D8/E8)/(1-Inputs!$B$6)-Inputs!$B$7 | G8: =IF(ISNUMBER(Inputs!J29),Inputs!J29,F8) | H8: =IF(ISNUMBER(Inputs!J29),"OWNER OVERRIDE","MODEL") | I8: =COUNTIF($G$5:$G$12,"<"&G8)+COUNTIF($G$5:G8,G8) | J8: =B8*C8/1000 | K8: =B8/Inputs!G29 | L8: =IF(ISNUMBER(Inputs!$K29),Inputs!$K29,$B8*$C8*INDEX(Profile!$B$9:$B$28,L$4)/L$4/365) | M8: =IF(ISNUMBER(Inputs!$K29),Inputs!$K29,$B8*$C8*INDEX(Profile!$B$9:$B$28,M$4)/M$4/365) | N8: =IF(ISNUMBER(Inputs!$K29),Inputs!$K29,$B8*$C8*INDEX(Profile!$B$9:$B$28,N$4)/N$4/365) | O8: =IF(ISNUMBER(Inputs!$K29),Inputs!$K29,$B8*$C8*INDEX(Profile!$B$9:$B$28,O$4)/O$4/365) | P8: =IF(ISNUMBER(Inputs!$K29),Inputs!$K29,$B8*$C8*INDEX(Profile!$B$9:$B$28,P$4)/P$4/365) | Q8: =IF(ISNUMBER(Inputs!$K29),Inputs!$K29,$B8*$C8*INDEX(Profile!$B$9:$B$28,Q$4)/Q$4/365) | R8: =IF(ISNUMBER(Inputs!$K29),Inputs!$K29,$B8*$C8*INDEX(Profile!$B$9:$B$28,R$4)/R$4/365) | S8: =IF(ISNUMBER(Inputs!$K29),Inputs!$K29,$B8*$C8*INDEX(Profile!$B$9:$B$28,S$4)/S$4/365) | ... U8: =IF(ISNUMBER(Inputs!$K29),Inputs!$K29,$B8*$C8*INDEX(Profile!$B$9:$B$28,U$4)/U$4/365)
A9: =Inputs!A30 | B9: =(Inputs!C30*Inputs!E30+Inputs!D30*Inputs!F30)*Inputs!G30 | C9: =Profile!$B$7*Inputs!H30 | D9: =Inputs!I30*1000*(1+Inputs!$B$11) | E9: =C9*1000000*Profile!$B$6 | F9: =((Inputs!$B$8+Inputs!$B$9+Inputs!$B$10)+D9/E9)/(1-Inputs!$B$6)-Inputs!$B$7 | G9: =IF(ISNUMBER(Inputs!J30),Inputs!J30,F9) | H9: =IF(ISNUMBER(Inputs!J30),"OWNER OVERRIDE","MODEL") | I9: =COUNTIF($G$5:$G$12,"<"&G9)+COUNTIF($G$5:G9,G9) | J9: =B9*C9/1000 | K9: =B9/Inputs!G30 | L9: =IF(ISNUMBER(Inputs!$K30),Inputs!$K30,$B9*$C9*INDEX(Profile!$B$9:$B$28,L$4)/L$4/365) | M9: =IF(ISNUMBER(Inputs!$K30),Inputs!$K30,$B9*$C9*INDEX(Profile!$B$9:$B$28,M$4)/M$4/365) | N9: =IF(ISNUMBER(Inputs!$K30),Inputs!$K30,$B9*$C9*INDEX(Profile!$B$9:$B$28,N$4)/N$4/365) | O9: =IF(ISNUMBER(Inputs!$K30),Inputs!$K30,$B9*$C9*INDEX(Profile!$B$9:$B$28,O$4)/O$4/365) | P9: =IF(ISNUMBER(Inputs!$K30),Inputs!$K30,$B9*$C9*INDEX(Profile!$B$9:$B$28,P$4)/P$4/365) | Q9: =IF(ISNUMBER(Inputs!$K30),Inputs!$K30,$B9*$C9*INDEX(Profile!$B$9:$B$28,Q$4)/Q$4/365) | R9: =IF(ISNUMBER(Inputs!$K30),Inputs!$K30,$B9*$C9*INDEX(Profile!$B$9:$B$28,R$4)/R$4/365) | S9: =IF(ISNUMBER(Inputs!$K30),Inputs!$K30,$B9*$C9*INDEX(Profile!$B$9:$B$28,S$4)/S$4/365) | ... U9: =IF(ISNUMBER(Inputs!$K30),Inputs!$K30,$B9*$C9*INDEX(Profile!$B$9:$B$28,U$4)/U$4/365)
A10: =Inputs!A31 | B10: =(Inputs!C31*Inputs!E31+Inputs!D31*Inputs!F31)*Inputs!G31 | C10: =Profile!$B$7*Inputs!H31 | D10: =Inputs!I31*1000*(1+Inputs!$B$11) | E10: =C10*1000000*Profile!$B$6 | F10: =((Inputs!$B$8+Inputs!$B$9+Inputs!$B$10)+D10/E10)/(1-Inputs!$B$6)-Inputs!$B$7 | G10: =IF(ISNUMBER(Inputs!J31),Inputs!J31,F10) | H10: =IF(ISNUMBER(Inputs!J31),"OWNER OVERRIDE","MODEL") | I10: =COUNTIF($G$5:$G$12,"<"&G10)+COUNTIF($G$5:G10,G10) | J10: =B10*C10/1000 | K10: =B10/Inputs!G31 | L10: =IF(ISNUMBER(Inputs!$K31),Inputs!$K31,$B10*$C10*INDEX(Profile!$B$9:$B$28,L$4)/L$4/365) | M10: =IF(ISNUMBER(Inputs!$K31),Inputs!$K31,$B10*$C10*INDEX(Profile!$B$9:$B$28,M$4)/M$4/365) | N10: =IF(ISNUMBER(Inputs!$K31),Inputs!$K31,$B10*$C10*INDEX(Profile!$B$9:$B$28,N$4)/N$4/365) | O10: =IF(ISNUMBER(Inputs!$K31),Inputs!$K31,$B10*$C10*INDEX(Profile!$B$9:$B$28,O$4)/O$4/365) | P10: =IF(ISNUMBER(Inputs!$K31),Inputs!$K31,$B10*$C10*INDEX(Profile!$B$9:$B$28,P$4)/P$4/365) | Q10: =IF(ISNUMBER(Inputs!$K31),Inputs!$K31,$B10*$C10*INDEX(Profile!$B$9:$B$28,Q$4)/Q$4/365) | R10: =IF(ISNUMBER(Inputs!$K31),Inputs!$K31,$B10*$C10*INDEX(Profile!$B$9:$B$28,R$4)/R$4/365) | S10: =IF(ISNUMBER(Inputs!$K31),Inputs!$K31,$B10*$C10*INDEX(Profile!$B$9:$B$28,S$4)/S$4/365) | ... U10: =IF(ISNUMBER(Inputs!$K31),Inputs!$K31,$B10*$C10*INDEX(Profile!$B$9:$B$28,U$4)/U$4/365)
A11: =Inputs!A32 | B11: =(Inputs!C32*Inputs!E32+Inputs!D32*Inputs!F32)*Inputs!G32 | C11: =Profile!$B$7*Inputs!H32 | D11: =Inputs!I32*1000*(1+Inputs!$B$11) | E11: =C11*1000000*Profile!$B$6 | F11: =((Inputs!$B$8+Inputs!$B$9+Inputs!$B$10)+D11/E11)/(1-Inputs!$B$6)-Inputs!$B$7 | G11: =IF(ISNUMBER(Inputs!J32),Inputs!J32,F11) | H11: =IF(ISNUMBER(Inputs!J32),"OWNER OVERRIDE","MODEL") | I11: =COUNTIF($G$5:$G$12,"<"&G11)+COUNTIF($G$5:G11,G11) | J11: =B11*C11/1000 | K11: =B11/Inputs!G32 | L11: =IF(ISNUMBER(Inputs!$K32),Inputs!$K32,$B11*$C11*INDEX(Profile!$B$9:$B$28,L$4)/L$4/365) | M11: =IF(ISNUMBER(Inputs!$K32),Inputs!$K32,$B11*$C11*INDEX(Profile!$B$9:$B$28,M$4)/M$4/365) | N11: =IF(ISNUMBER(Inputs!$K32),Inputs!$K32,$B11*$C11*INDEX(Profile!$B$9:$B$28,N$4)/N$4/365) | O11: =IF(ISNUMBER(Inputs!$K32),Inputs!$K32,$B11*$C11*INDEX(Profile!$B$9:$B$28,O$4)/O$4/365) | P11: =IF(ISNUMBER(Inputs!$K32),Inputs!$K32,$B11*$C11*INDEX(Profile!$B$9:$B$28,P$4)/P$4/365) | Q11: =IF(ISNUMBER(Inputs!$K32),Inputs!$K32,$B11*$C11*INDEX(Profile!$B$9:$B$28,Q$4)/Q$4/365) | R11: =IF(ISNUMBER(Inputs!$K32),Inputs!$K32,$B11*$C11*INDEX(Profile!$B$9:$B$28,R$4)/R$4/365) | S11: =IF(ISNUMBER(Inputs!$K32),Inputs!$K32,$B11*$C11*INDEX(Profile!$B$9:$B$28,S$4)/S$4/365) | ... U11: =IF(ISNUMBER(Inputs!$K32),Inputs!$K32,$B11*$C11*INDEX(Profile!$B$9:$B$28,U$4)/U$4/365)
A12: =Inputs!A33 | B12: =(Inputs!C33*Inputs!E33+Inputs!D33*Inputs!F33)*Inputs!G33 | C12: =Profile!$B$7*Inputs!H33 | D12: =Inputs!I33*1000*(1+Inputs!$B$11) | E12: =C12*1000000*Profile!$B$6 | F12: =((Inputs!$B$8+Inputs!$B$9+Inputs!$B$10)+D12/E12)/(1-Inputs!$B$6)-Inputs!$B$7 | G12: =IF(ISNUMBER(Inputs!J33),Inputs!J33,F12) | H12: =IF(ISNUMBER(Inputs!J33),"OWNER OVERRIDE","MODEL") | I12: =COUNTIF($G$5:$G$12,"<"&G12)+COUNTIF($G$5:G12,G12) | J12: =B12*C12/1000 | K12: =B12/Inputs!G33 | L12: =IF(ISNUMBER(Inputs!$K33),Inputs!$K33,$B12*$C12*INDEX(Profile!$B$9:$B$28,L$4)/L$4/365) | M12: =IF(ISNUMBER(Inputs!$K33),Inputs!$K33,$B12*$C12*INDEX(Profile!$B$9:$B$28,M$4)/M$4/365) | N12: =IF(ISNUMBER(Inputs!$K33),Inputs!$K33,$B12*$C12*INDEX(Profile!$B$9:$B$28,N$4)/N$4/365) | O12: =IF(ISNUMBER(Inputs!$K33),Inputs!$K33,$B12*$C12*INDEX(Profile!$B$9:$B$28,O$4)/O$4/365) | P12: =IF(ISNUMBER(Inputs!$K33),Inputs!$K33,$B12*$C12*INDEX(Profile!$B$9:$B$28,P$4)/P$4/365) | Q12: =IF(ISNUMBER(Inputs!$K33),Inputs!$K33,$B12*$C12*INDEX(Profile!$B$9:$B$28,Q$4)/Q$4/365) | R12: =IF(ISNUMBER(Inputs!$K33),Inputs!$K33,$B12*$C12*INDEX(Profile!$B$9:$B$28,R$4)/R$4/365) | S12: =IF(ISNUMBER(Inputs!$K33),Inputs!$K33,$B12*$C12*INDEX(Profile!$B$9:$B$28,S$4)/S$4/365) | ... U12: =IF(ISNUMBER(Inputs!$K33),Inputs!$K33,$B12*$C12*INDEX(Profile!$B$9:$B$28,U$4)/U$4/365)
L13: Cumulative capacity, Bcf/d, by horizon H (years)
A14: Sorted curve (cheapest first) - cumulative capacity by horizon H
A15: Rank | B15: Row in table above | C15: Tier / block | D15: Breakeven used ($/MMBtu HH) | E15: Developable lateral (1,000 ft) | F15: Developable EUR (Tcf) | G15: Cumulative locations | L15: 1 | M15: 2 | N15: 3 | O15: 4 | P15: 5 | Q15: 6 | R15: 7 | S15: 8 | T15: 9 | U15: 10
A16: 1 | B16: =MATCH(A16,$I$5:$I$12,0) | C16: =INDEX($A$5:$A$12,B16) | D16: =INDEX($G$5:$G$12,B16) | E16: =INDEX($B$5:$B$12,B16) | F16: =INDEX($J$5:$J$12,B16) | G16: =INDEX($K$5:$K$12,B16) | L16: =INDEX(L$5:L$12,$B16) | M16: =INDEX(M$5:M$12,$B16) | N16: =INDEX(N$5:N$12,$B16) | O16: =INDEX(O$5:O$12,$B16) | P16: =INDEX(P$5:P$12,$B16) | Q16: =INDEX(Q$5:Q$12,$B16) | R16: =INDEX(R$5:R$12,$B16) | S16: =INDEX(S$5:S$12,$B16) | ... U16: =INDEX(U$5:U$12,$B16)
A17: 2 | B17: =MATCH(A17,$I$5:$I$12,0) | C17: =INDEX($A$5:$A$12,B17) | D17: =INDEX($G$5:$G$12,B17) | E17: =INDEX($B$5:$B$12,B17) | F17: =INDEX($J$5:$J$12,B17) | G17: =G16+INDEX($K$5:$K$12,B17) | L17: =L16+INDEX(L$5:L$12,$B17) | M17: =M16+INDEX(M$5:M$12,$B17) | N17: =N16+INDEX(N$5:N$12,$B17) | O17: =O16+INDEX(O$5:O$12,$B17) | P17: =P16+INDEX(P$5:P$12,$B17) | Q17: =Q16+INDEX(Q$5:Q$12,$B17) | R17: =R16+INDEX(R$5:R$12,$B17) | S17: =S16+INDEX(S$5:S$12,$B17) | ... U17: =U16+INDEX(U$5:U$12,$B17)
A18: 3 | B18: =MATCH(A18,$I$5:$I$12,0) | C18: =INDEX($A$5:$A$12,B18) | D18: =INDEX($G$5:$G$12,B18) | E18: =INDEX($B$5:$B$12,B18) | F18: =INDEX($J$5:$J$12,B18) | G18: =G17+INDEX($K$5:$K$12,B18) | L18: =L17+INDEX(L$5:L$12,$B18) | M18: =M17+INDEX(M$5:M$12,$B18) | N18: =N17+INDEX(N$5:N$12,$B18) | O18: =O17+INDEX(O$5:O$12,$B18) | P18: =P17+INDEX(P$5:P$12,$B18) | Q18: =Q17+INDEX(Q$5:Q$12,$B18) | R18: =R17+INDEX(R$5:R$12,$B18) | S18: =S17+INDEX(S$5:S$12,$B18) | ... U18: =U17+INDEX(U$5:U$12,$B18)
A19: 4 | B19: =MATCH(A19,$I$5:$I$12,0) | C19: =INDEX($A$5:$A$12,B19) | D19: =INDEX($G$5:$G$12,B19) | E19: =INDEX($B$5:$B$12,B19) | F19: =INDEX($J$5:$J$12,B19) | G19: =G18+INDEX($K$5:$K$12,B19) | L19: =L18+INDEX(L$5:L$12,$B19) | M19: =M18+INDEX(M$5:M$12,$B19) | N19: =N18+INDEX(N$5:N$12,$B19) | O19: =O18+INDEX(O$5:O$12,$B19) | P19: =P18+INDEX(P$5:P$12,$B19) | Q19: =Q18+INDEX(Q$5:Q$12,$B19) | R19: =R18+INDEX(R$5:R$12,$B19) | S19: =S18+INDEX(S$5:S$12,$B19) | ... U19: =U18+INDEX(U$5:U$12,$B19)
A20: 5 | B20: =MATCH(A20,$I$5:$I$12,0) | C20: =INDEX($A$5:$A$12,B20) | D20: =INDEX($G$5:$G$12,B20) | E20: =INDEX($B$5:$B$12,B20) | F20: =INDEX($J$5:$J$12,B20) | G20: =G19+INDEX($K$5:$K$12,B20) | L20: =L19+INDEX(L$5:L$12,$B20) | M20: =M19+INDEX(M$5:M$12,$B20) | N20: =N19+INDEX(N$5:N$12,$B20) | O20: =O19+INDEX(O$5:O$12,$B20) | P20: =P19+INDEX(P$5:P$12,$B20) | Q20: =Q19+INDEX(Q$5:Q$12,$B20) | R20: =R19+INDEX(R$5:R$12,$B20) | S20: =S19+INDEX(S$5:S$12,$B20) | ... U20: =U19+INDEX(U$5:U$12,$B20)
A21: 6 | B21: =MATCH(A21,$I$5:$I$12,0) | C21: =INDEX($A$5:$A$12,B21) | D21: =INDEX($G$5:$G$12,B21) | E21: =INDEX($B$5:$B$12,B21) | F21: =INDEX($J$5:$J$12,B21) | G21: =G20+INDEX($K$5:$K$12,B21) | L21: =L20+INDEX(L$5:L$12,$B21) | M21: =M20+INDEX(M$5:M$12,$B21) | N21: =N20+INDEX(N$5:N$12,$B21) | O21: =O20+INDEX(O$5:O$12,$B21) | P21: =P20+INDEX(P$5:P$12,$B21) | Q21: =Q20+INDEX(Q$5:Q$12,$B21) | R21: =R20+INDEX(R$5:R$12,$B21) | S21: =S20+INDEX(S$5:S$12,$B21) | ... U21: =U20+INDEX(U$5:U$12,$B21)
A22: 7 | B22: =MATCH(A22,$I$5:$I$12,0) | C22: =INDEX($A$5:$A$12,B22) | D22: =INDEX($G$5:$G$12,B22) | E22: =INDEX($B$5:$B$12,B22) | F22: =INDEX($J$5:$J$12,B22) | G22: =G21+INDEX($K$5:$K$12,B22) | L22: =L21+INDEX(L$5:L$12,$B22) | M22: =M21+INDEX(M$5:M$12,$B22) | N22: =N21+INDEX(N$5:N$12,$B22) | O22: =O21+INDEX(O$5:O$12,$B22) | P22: =P21+INDEX(P$5:P$12,$B22) | Q22: =Q21+INDEX(Q$5:Q$12,$B22) | R22: =R21+INDEX(R$5:R$12,$B22) | S22: =S21+INDEX(S$5:S$12,$B22) | ... U22: =U21+INDEX(U$5:U$12,$B22)
A23: 8 | B23: =MATCH(A23,$I$5:$I$12,0) | C23: =INDEX($A$5:$A$12,B23) | D23: =INDEX($G$5:$G$12,B23) | E23: =INDEX($B$5:$B$12,B23) | F23: =INDEX($J$5:$J$12,B23) | G23: =G22+INDEX($K$5:$K$12,B23) | L23: =L22+INDEX(L$5:L$12,$B23) | M23: =M22+INDEX(M$5:M$12,$B23) | N23: =N22+INDEX(N$5:N$12,$B23) | O23: =O22+INDEX(O$5:O$12,$B23) | P23: =P22+INDEX(P$5:P$12,$B23) | Q23: =Q22+INDEX(Q$5:Q$12,$B23) | R23: =R22+INDEX(R$5:R$12,$B23) | S23: =S22+INDEX(S$5:S$12,$B23) | ... U23: =U22+INDEX(U$5:U$12,$B23)

Sheet Capacity over time
A1: Capacity over time (live): Bcf/d of a programme that drills each tier's developable inventory evenly over H years (H on 'Inputs'), year n = wells x EUR x [C(n) - C(n - min(n, H))] / 365. Cost-only upper bound on speed: no rig, crew or takeaway limit.
A2: Programme length H (years): | B2: =Inputs!$B$22
A4: Year of programme | B4: =Curve!A5 | C4: =Curve!A6 | D4: =Curve!A7 | E4: =Curve!A8 | F4: =Curve!A9 | G4: =Curve!A10 | H4: =Curve!A11 | I4: =Curve!A12 | J4: Total, Bcf/d
A5: 1 | B5: =IF(ISNUMBER(Inputs!$K26),Inputs!$K26,Curve!$B$5*Curve!$C$5*(INDEX(Profile!$B$9:$B$28,$A5)-IF($A5-MIN($A5,$B$2)=0,0,INDEX(Profile!$B$9:$B$28,$A5-MIN($A5,$B$2))))/$B$2/365) | C5: =IF(ISNUMBER(Inputs!$K27),Inputs!$K27,Curve!$B$6*Curve!$C$6*(INDEX(Profile!$B$9:$B$28,$A5)-IF($A5-MIN($A5,$B$2)=0,0,INDEX(Profile!$B$9:$B$28,$A5-MIN($A5,$B$2))))/$B$2/365) | D5: =IF(ISNUMBER(Inputs!$K28),Inputs!$K28,Curve!$B$7*Curve!$C$7*(INDEX(Profile!$B$9:$B$28,$A5)-IF($A5-MIN($A5,$B$2)=0,0,INDEX(Profile!$B$9:$B$28,$A5-MIN($A5,$B$2))))/$B$2/365) | E5: =IF(ISNUMBER(Inputs!$K29),Inputs!$K29,Curve!$B$8*Curve!$C$8*(INDEX(Profile!$B$9:$B$28,$A5)-IF($A5-MIN($A5,$B$2)=0,0,INDEX(Profile!$B$9:$B$28,$A5-MIN($A5,$B$2))))/$B$2/365) | F5: =IF(ISNUMBER(Inputs!$K30),Inputs!$K30,Curve!$B$9*Curve!$C$9*(INDEX(Profile!$B$9:$B$28,$A5)-IF($A5-MIN($A5,$B$2)=0,0,INDEX(Profile!$B$9:$B$28,$A5-MIN($A5,$B$2))))/$B$2/365) | G5: =IF(ISNUMBER(Inputs!$K31),Inputs!$K31,Curve!$B$10*Curve!$C$10*(INDEX(Profile!$B$9:$B$28,$A5)-IF($A5-MIN($A5,$B$2)=0,0,INDEX(Profile!$B$9:$B$28,$A5-MIN($A5,$B$2))))/$B$2/365) | H5: =IF(ISNUMBER(Inputs!$K32),Inputs!$K32,Curve!$B$11*Curve!$C$11*(INDEX(Profile!$B$9:$B$28,$A5)-IF($A5-MIN($A5,$B$2)=0,0,INDEX(Profile!$B$9:$B$28,$A5-MIN($A5,$B$2))))/$B$2/365) | I5: =IF(ISNUMBER(Inputs!$K33),Inputs!$K33,Curve!$B$12*Curve!$C$12*(INDEX(Profile!$B$9:$B$28,$A5)-IF($A5-MIN($A5,$B$2)=0,0,INDEX(Profile!$B$9:$B$28,$A5-MIN($A5,$B$2))))/$B$2/365) | J5: =SUM(B5:I5)
A6: 2 | B6: =IF(ISNUMBER(Inputs!$K26),Inputs!$K26,Curve!$B$5*Curve!$C$5*(INDEX(Profile!$B$9:$B$28,$A6)-IF($A6-MIN($A6,$B$2)=0,0,INDEX(Profile!$B$9:$B$28,$A6-MIN($A6,$B$2))))/$B$2/365) | C6: =IF(ISNUMBER(Inputs!$K27),Inputs!$K27,Curve!$B$6*Curve!$C$6*(INDEX(Profile!$B$9:$B$28,$A6)-IF($A6-MIN($A6,$B$2)=0,0,INDEX(Profile!$B$9:$B$28,$A6-MIN($A6,$B$2))))/$B$2/365) | D6: =IF(ISNUMBER(Inputs!$K28),Inputs!$K28,Curve!$B$7*Curve!$C$7*(INDEX(Profile!$B$9:$B$28,$A6)-IF($A6-MIN($A6,$B$2)=0,0,INDEX(Profile!$B$9:$B$28,$A6-MIN($A6,$B$2))))/$B$2/365) | E6: =IF(ISNUMBER(Inputs!$K29),Inputs!$K29,Curve!$B$8*Curve!$C$8*(INDEX(Profile!$B$9:$B$28,$A6)-IF($A6-MIN($A6,$B$2)=0,0,INDEX(Profile!$B$9:$B$28,$A6-MIN($A6,$B$2))))/$B$2/365) | F6: =IF(ISNUMBER(Inputs!$K30),Inputs!$K30,Curve!$B$9*Curve!$C$9*(INDEX(Profile!$B$9:$B$28,$A6)-IF($A6-MIN($A6,$B$2)=0,0,INDEX(Profile!$B$9:$B$28,$A6-MIN($A6,$B$2))))/$B$2/365) | G6: =IF(ISNUMBER(Inputs!$K31),Inputs!$K31,Curve!$B$10*Curve!$C$10*(INDEX(Profile!$B$9:$B$28,$A6)-IF($A6-MIN($A6,$B$2)=0,0,INDEX(Profile!$B$9:$B$28,$A6-MIN($A6,$B$2))))/$B$2/365) | H6: =IF(ISNUMBER(Inputs!$K32),Inputs!$K32,Curve!$B$11*Curve!$C$11*(INDEX(Profile!$B$9:$B$28,$A6)-IF($A6-MIN($A6,$B$2)=0,0,INDEX(Profile!$B$9:$B$28,$A6-MIN($A6,$B$2))))/$B$2/365) | I6: =IF(ISNUMBER(Inputs!$K33),Inputs!$K33,Curve!$B$12*Curve!$C$12*(INDEX(Profile!$B$9:$B$28,$A6)-IF($A6-MIN($A6,$B$2)=0,0,INDEX(Profile!$B$9:$B$28,$A6-MIN($A6,$B$2))))/$B$2/365) | J6: =SUM(B6:I6)
A7: 3 | B7: =IF(ISNUMBER(Inputs!$K26),Inputs!$K26,Curve!$B$5*Curve!$C$5*(INDEX(Profile!$B$9:$B$28,$A7)-IF($A7-MIN($A7,$B$2)=0,0,INDEX(Profile!$B$9:$B$28,$A7-MIN($A7,$B$2))))/$B$2/365) | C7: =IF(ISNUMBER(Inputs!$K27),Inputs!$K27,Curve!$B$6*Curve!$C$6*(INDEX(Profile!$B$9:$B$28,$A7)-IF($A7-MIN($A7,$B$2)=0,0,INDEX(Profile!$B$9:$B$28,$A7-MIN($A7,$B$2))))/$B$2/365) | D7: =IF(ISNUMBER(Inputs!$K28),Inputs!$K28,Curve!$B$7*Curve!$C$7*(INDEX(Profile!$B$9:$B$28,$A7)-IF($A7-MIN($A7,$B$2)=0,0,INDEX(Profile!$B$9:$B$28,$A7-MIN($A7,$B$2))))/$B$2/365) | E7: =IF(ISNUMBER(Inputs!$K29),Inputs!$K29,Curve!$B$8*Curve!$C$8*(INDEX(Profile!$B$9:$B$28,$A7)-IF($A7-MIN($A7,$B$2)=0,0,INDEX(Profile!$B$9:$B$28,$A7-MIN($A7,$B$2))))/$B$2/365) | F7: =IF(ISNUMBER(Inputs!$K30),Inputs!$K30,Curve!$B$9*Curve!$C$9*(INDEX(Profile!$B$9:$B$28,$A7)-IF($A7-MIN($A7,$B$2)=0,0,INDEX(Profile!$B$9:$B$28,$A7-MIN($A7,$B$2))))/$B$2/365) | G7: =IF(ISNUMBER(Inputs!$K31),Inputs!$K31,Curve!$B$10*Curve!$C$10*(INDEX(Profile!$B$9:$B$28,$A7)-IF($A7-MIN($A7,$B$2)=0,0,INDEX(Profile!$B$9:$B$28,$A7-MIN($A7,$B$2))))/$B$2/365) | H7: =IF(ISNUMBER(Inputs!$K32),Inputs!$K32,Curve!$B$11*Curve!$C$11*(INDEX(Profile!$B$9:$B$28,$A7)-IF($A7-MIN($A7,$B$2)=0,0,INDEX(Profile!$B$9:$B$28,$A7-MIN($A7,$B$2))))/$B$2/365) | I7: =IF(ISNUMBER(Inputs!$K33),Inputs!$K33,Curve!$B$12*Curve!$C$12*(INDEX(Profile!$B$9:$B$28,$A7)-IF($A7-MIN($A7,$B$2)=0,0,INDEX(Profile!$B$9:$B$28,$A7-MIN($A7,$B$2))))/$B$2/365) | J7: =SUM(B7:I7)
A8: 4 | B8: =IF(ISNUMBER(Inputs!$K26),Inputs!$K26,Curve!$B$5*Curve!$C$5*(INDEX(Profile!$B$9:$B$28,$A8)-IF($A8-MIN($A8,$B$2)=0,0,INDEX(Profile!$B$9:$B$28,$A8-MIN($A8,$B$2))))/$B$2/365) | C8: =IF(ISNUMBER(Inputs!$K27),Inputs!$K27,Curve!$B$6*Curve!$C$6*(INDEX(Profile!$B$9:$B$28,$A8)-IF($A8-MIN($A8,$B$2)=0,0,INDEX(Profile!$B$9:$B$28,$A8-MIN($A8,$B$2))))/$B$2/365) | D8: =IF(ISNUMBER(Inputs!$K28),Inputs!$K28,Curve!$B$7*Curve!$C$7*(INDEX(Profile!$B$9:$B$28,$A8)-IF($A8-MIN($A8,$B$2)=0,0,INDEX(Profile!$B$9:$B$28,$A8-MIN($A8,$B$2))))/$B$2/365) | E8: =IF(ISNUMBER(Inputs!$K29),Inputs!$K29,Curve!$B$8*Curve!$C$8*(INDEX(Profile!$B$9:$B$28,$A8)-IF($A8-MIN($A8,$B$2)=0,0,INDEX(Profile!$B$9:$B$28,$A8-MIN($A8,$B$2))))/$B$2/365) | F8: =IF(ISNUMBER(Inputs!$K30),Inputs!$K30,Curve!$B$9*Curve!$C$9*(INDEX(Profile!$B$9:$B$28,$A8)-IF($A8-MIN($A8,$B$2)=0,0,INDEX(Profile!$B$9:$B$28,$A8-MIN($A8,$B$2))))/$B$2/365) | G8: =IF(ISNUMBER(Inputs!$K31),Inputs!$K31,Curve!$B$10*Curve!$C$10*(INDEX(Profile!$B$9:$B$28,$A8)-IF($A8-MIN($A8,$B$2)=0,0,INDEX(Profile!$B$9:$B$28,$A8-MIN($A8,$B$2))))/$B$2/365) | H8: =IF(ISNUMBER(Inputs!$K32),Inputs!$K32,Curve!$B$11*Curve!$C$11*(INDEX(Profile!$B$9:$B$28,$A8)-IF($A8-MIN($A8,$B$2)=0,0,INDEX(Profile!$B$9:$B$28,$A8-MIN($A8,$B$2))))/$B$2/365) | I8: =IF(ISNUMBER(Inputs!$K33),Inputs!$K33,Curve!$B$12*Curve!$C$12*(INDEX(Profile!$B$9:$B$28,$A8)-IF($A8-MIN($A8,$B$2)=0,0,INDEX(Profile!$B$9:$B$28,$A8-MIN($A8,$B$2))))/$B$2/365) | J8: =SUM(B8:I8)
A9: 5 | B9: =IF(ISNUMBER(Inputs!$K26),Inputs!$K26,Curve!$B$5*Curve!$C$5*(INDEX(Profile!$B$9:$B$28,$A9)-IF($A9-MIN($A9,$B$2)=0,0,INDEX(Profile!$B$9:$B$28,$A9-MIN($A9,$B$2))))/$B$2/365) | C9: =IF(ISNUMBER(Inputs!$K27),Inputs!$K27,Curve!$B$6*Curve!$C$6*(INDEX(Profile!$B$9:$B$28,$A9)-IF($A9-MIN($A9,$B$2)=0,0,INDEX(Profile!$B$9:$B$28,$A9-MIN($A9,$B$2))))/$B$2/365) | D9: =IF(ISNUMBER(Inputs!$K28),Inputs!$K28,Curve!$B$7*Curve!$C$7*(INDEX(Profile!$B$9:$B$28,$A9)-IF($A9-MIN($A9,$B$2)=0,0,INDEX(Profile!$B$9:$B$28,$A9-MIN($A9,$B$2))))/$B$2/365) | E9: =IF(ISNUMBER(Inputs!$K29),Inputs!$K29,Curve!$B$8*Curve!$C$8*(INDEX(Profile!$B$9:$B$28,$A9)-IF($A9-MIN($A9,$B$2)=0,0,INDEX(Profile!$B$9:$B$28,$A9-MIN($A9,$B$2))))/$B$2/365) | F9: =IF(ISNUMBER(Inputs!$K30),Inputs!$K30,Curve!$B$9*Curve!$C$9*(INDEX(Profile!$B$9:$B$28,$A9)-IF($A9-MIN($A9,$B$2)=0,0,INDEX(Profile!$B$9:$B$28,$A9-MIN($A9,$B$2))))/$B$2/365) | G9: =IF(ISNUMBER(Inputs!$K31),Inputs!$K31,Curve!$B$10*Curve!$C$10*(INDEX(Profile!$B$9:$B$28,$A9)-IF($A9-MIN($A9,$B$2)=0,0,INDEX(Profile!$B$9:$B$28,$A9-MIN($A9,$B$2))))/$B$2/365) | H9: =IF(ISNUMBER(Inputs!$K32),Inputs!$K32,Curve!$B$11*Curve!$C$11*(INDEX(Profile!$B$9:$B$28,$A9)-IF($A9-MIN($A9,$B$2)=0,0,INDEX(Profile!$B$9:$B$28,$A9-MIN($A9,$B$2))))/$B$2/365) | I9: =IF(ISNUMBER(Inputs!$K33),Inputs!$K33,Curve!$B$12*Curve!$C$12*(INDEX(Profile!$B$9:$B$28,$A9)-IF($A9-MIN($A9,$B$2)=0,0,INDEX(Profile!$B$9:$B$28,$A9-MIN($A9,$B$2))))/$B$2/365) | J9: =SUM(B9:I9)
A10: 6 | B10: =IF(ISNUMBER(Inputs!$K26),Inputs!$K26,Curve!$B$5*Curve!$C$5*(INDEX(Profile!$B$9:$B$28,$A10)-IF($A10-MIN($A10,$B$2)=0,0,INDEX(Profile!$B$9:$B$28,$A10-MIN($A10,$B$2))))/$B$2/365) | C10: =IF(ISNUMBER(Inputs!$K27),Inputs!$K27,Curve!$B$6*Curve!$C$6*(INDEX(Profile!$B$9:$B$28,$A10)-IF($A10-MIN($A10,$B$2)=0,0,INDEX(Profile!$B$9:$B$28,$A10-MIN($A10,$B$2))))/$B$2/365) | D10: =IF(ISNUMBER(Inputs!$K28),Inputs!$K28,Curve!$B$7*Curve!$C$7*(INDEX(Profile!$B$9:$B$28,$A10)-IF($A10-MIN($A10,$B$2)=0,0,INDEX(Profile!$B$9:$B$28,$A10-MIN($A10,$B$2))))/$B$2/365) | E10: =IF(ISNUMBER(Inputs!$K29),Inputs!$K29,Curve!$B$8*Curve!$C$8*(INDEX(Profile!$B$9:$B$28,$A10)-IF($A10-MIN($A10,$B$2)=0,0,INDEX(Profile!$B$9:$B$28,$A10-MIN($A10,$B$2))))/$B$2/365) | F10: =IF(ISNUMBER(Inputs!$K30),Inputs!$K30,Curve!$B$9*Curve!$C$9*(INDEX(Profile!$B$9:$B$28,$A10)-IF($A10-MIN($A10,$B$2)=0,0,INDEX(Profile!$B$9:$B$28,$A10-MIN($A10,$B$2))))/$B$2/365) | G10: =IF(ISNUMBER(Inputs!$K31),Inputs!$K31,Curve!$B$10*Curve!$C$10*(INDEX(Profile!$B$9:$B$28,$A10)-IF($A10-MIN($A10,$B$2)=0,0,INDEX(Profile!$B$9:$B$28,$A10-MIN($A10,$B$2))))/$B$2/365) | H10: =IF(ISNUMBER(Inputs!$K32),Inputs!$K32,Curve!$B$11*Curve!$C$11*(INDEX(Profile!$B$9:$B$28,$A10)-IF($A10-MIN($A10,$B$2)=0,0,INDEX(Profile!$B$9:$B$28,$A10-MIN($A10,$B$2))))/$B$2/365) | I10: =IF(ISNUMBER(Inputs!$K33),Inputs!$K33,Curve!$B$12*Curve!$C$12*(INDEX(Profile!$B$9:$B$28,$A10)-IF($A10-MIN($A10,$B$2)=0,0,INDEX(Profile!$B$9:$B$28,$A10-MIN($A10,$B$2))))/$B$2/365) | J10: =SUM(B10:I10)
A11: 7 | B11: =IF(ISNUMBER(Inputs!$K26),Inputs!$K26,Curve!$B$5*Curve!$C$5*(INDEX(Profile!$B$9:$B$28,$A11)-IF($A11-MIN($A11,$B$2)=0,0,INDEX(Profile!$B$9:$B$28,$A11-MIN($A11,$B$2))))/$B$2/365) | C11: =IF(ISNUMBER(Inputs!$K27),Inputs!$K27,Curve!$B$6*Curve!$C$6*(INDEX(Profile!$B$9:$B$28,$A11)-IF($A11-MIN($A11,$B$2)=0,0,INDEX(Profile!$B$9:$B$28,$A11-MIN($A11,$B$2))))/$B$2/365) | D11: =IF(ISNUMBER(Inputs!$K28),Inputs!$K28,Curve!$B$7*Curve!$C$7*(INDEX(Profile!$B$9:$B$28,$A11)-IF($A11-MIN($A11,$B$2)=0,0,INDEX(Profile!$B$9:$B$28,$A11-MIN($A11,$B$2))))/$B$2/365) | E11: =IF(ISNUMBER(Inputs!$K29),Inputs!$K29,Curve!$B$8*Curve!$C$8*(INDEX(Profile!$B$9:$B$28,$A11)-IF($A11-MIN($A11,$B$2)=0,0,INDEX(Profile!$B$9:$B$28,$A11-MIN($A11,$B$2))))/$B$2/365) | F11: =IF(ISNUMBER(Inputs!$K30),Inputs!$K30,Curve!$B$9*Curve!$C$9*(INDEX(Profile!$B$9:$B$28,$A11)-IF($A11-MIN($A11,$B$2)=0,0,INDEX(Profile!$B$9:$B$28,$A11-MIN($A11,$B$2))))/$B$2/365) | G11: =IF(ISNUMBER(Inputs!$K31),Inputs!$K31,Curve!$B$10*Curve!$C$10*(INDEX(Profile!$B$9:$B$28,$A11)-IF($A11-MIN($A11,$B$2)=0,0,INDEX(Profile!$B$9:$B$28,$A11-MIN($A11,$B$2))))/$B$2/365) | H11: =IF(ISNUMBER(Inputs!$K32),Inputs!$K32,Curve!$B$11*Curve!$C$11*(INDEX(Profile!$B$9:$B$28,$A11)-IF($A11-MIN($A11,$B$2)=0,0,INDEX(Profile!$B$9:$B$28,$A11-MIN($A11,$B$2))))/$B$2/365) | I11: =IF(ISNUMBER(Inputs!$K33),Inputs!$K33,Curve!$B$12*Curve!$C$12*(INDEX(Profile!$B$9:$B$28,$A11)-IF($A11-MIN($A11,$B$2)=0,0,INDEX(Profile!$B$9:$B$28,$A11-MIN($A11,$B$2))))/$B$2/365) | J11: =SUM(B11:I11)
A12: 8 | B12: =IF(ISNUMBER(Inputs!$K26),Inputs!$K26,Curve!$B$5*Curve!$C$5*(INDEX(Profile!$B$9:$B$28,$A12)-IF($A12-MIN($A12,$B$2)=0,0,INDEX(Profile!$B$9:$B$28,$A12-MIN($A12,$B$2))))/$B$2/365) | C12: =IF(ISNUMBER(Inputs!$K27),Inputs!$K27,Curve!$B$6*Curve!$C$6*(INDEX(Profile!$B$9:$B$28,$A12)-IF($A12-MIN($A12,$B$2)=0,0,INDEX(Profile!$B$9:$B$28,$A12-MIN($A12,$B$2))))/$B$2/365) | D12: =IF(ISNUMBER(Inputs!$K28),Inputs!$K28,Curve!$B$7*Curve!$C$7*(INDEX(Profile!$B$9:$B$28,$A12)-IF($A12-MIN($A12,$B$2)=0,0,INDEX(Profile!$B$9:$B$28,$A12-MIN($A12,$B$2))))/$B$2/365) | E12: =IF(ISNUMBER(Inputs!$K29),Inputs!$K29,Curve!$B$8*Curve!$C$8*(INDEX(Profile!$B$9:$B$28,$A12)-IF($A12-MIN($A12,$B$2)=0,0,INDEX(Profile!$B$9:$B$28,$A12-MIN($A12,$B$2))))/$B$2/365) | F12: =IF(ISNUMBER(Inputs!$K30),Inputs!$K30,Curve!$B$9*Curve!$C$9*(INDEX(Profile!$B$9:$B$28,$A12)-IF($A12-MIN($A12,$B$2)=0,0,INDEX(Profile!$B$9:$B$28,$A12-MIN($A12,$B$2))))/$B$2/365) | G12: =IF(ISNUMBER(Inputs!$K31),Inputs!$K31,Curve!$B$10*Curve!$C$10*(INDEX(Profile!$B$9:$B$28,$A12)-IF($A12-MIN($A12,$B$2)=0,0,INDEX(Profile!$B$9:$B$28,$A12-MIN($A12,$B$2))))/$B$2/365) | H12: =IF(ISNUMBER(Inputs!$K32),Inputs!$K32,Curve!$B$11*Curve!$C$11*(INDEX(Profile!$B$9:$B$28,$A12)-IF($A12-MIN($A12,$B$2)=0,0,INDEX(Profile!$B$9:$B$28,$A12-MIN($A12,$B$2))))/$B$2/365) | I12: =IF(ISNUMBER(Inputs!$K33),Inputs!$K33,Curve!$B$12*Curve!$C$12*(INDEX(Profile!$B$9:$B$28,$A12)-IF($A12-MIN($A12,$B$2)=0,0,INDEX(Profile!$B$9:$B$28,$A12-MIN($A12,$B$2))))/$B$2/365) | J12: =SUM(B12:I12)
A13: 9 | B13: =IF(ISNUMBER(Inputs!$K26),Inputs!$K26,Curve!$B$5*Curve!$C$5*(INDEX(Profile!$B$9:$B$28,$A13)-IF($A13-MIN($A13,$B$2)=0,0,INDEX(Profile!$B$9:$B$28,$A13-MIN($A13,$B$2))))/$B$2/365) | C13: =IF(ISNUMBER(Inputs!$K27),Inputs!$K27,Curve!$B$6*Curve!$C$6*(INDEX(Profile!$B$9:$B$28,$A13)-IF($A13-MIN($A13,$B$2)=0,0,INDEX(Profile!$B$9:$B$28,$A13-MIN($A13,$B$2))))/$B$2/365) | D13: =IF(ISNUMBER(Inputs!$K28),Inputs!$K28,Curve!$B$7*Curve!$C$7*(INDEX(Profile!$B$9:$B$28,$A13)-IF($A13-MIN($A13,$B$2)=0,0,INDEX(Profile!$B$9:$B$28,$A13-MIN($A13,$B$2))))/$B$2/365) | E13: =IF(ISNUMBER(Inputs!$K29),Inputs!$K29,Curve!$B$8*Curve!$C$8*(INDEX(Profile!$B$9:$B$28,$A13)-IF($A13-MIN($A13,$B$2)=0,0,INDEX(Profile!$B$9:$B$28,$A13-MIN($A13,$B$2))))/$B$2/365) | F13: =IF(ISNUMBER(Inputs!$K30),Inputs!$K30,Curve!$B$9*Curve!$C$9*(INDEX(Profile!$B$9:$B$28,$A13)-IF($A13-MIN($A13,$B$2)=0,0,INDEX(Profile!$B$9:$B$28,$A13-MIN($A13,$B$2))))/$B$2/365) | G13: =IF(ISNUMBER(Inputs!$K31),Inputs!$K31,Curve!$B$10*Curve!$C$10*(INDEX(Profile!$B$9:$B$28,$A13)-IF($A13-MIN($A13,$B$2)=0,0,INDEX(Profile!$B$9:$B$28,$A13-MIN($A13,$B$2))))/$B$2/365) | H13: =IF(ISNUMBER(Inputs!$K32),Inputs!$K32,Curve!$B$11*Curve!$C$11*(INDEX(Profile!$B$9:$B$28,$A13)-IF($A13-MIN($A13,$B$2)=0,0,INDEX(Profile!$B$9:$B$28,$A13-MIN($A13,$B$2))))/$B$2/365) | I13: =IF(ISNUMBER(Inputs!$K33),Inputs!$K33,Curve!$B$12*Curve!$C$12*(INDEX(Profile!$B$9:$B$28,$A13)-IF($A13-MIN($A13,$B$2)=0,0,INDEX(Profile!$B$9:$B$28,$A13-MIN($A13,$B$2))))/$B$2/365) | J13: =SUM(B13:I13)
A14: 10 | B14: =IF(ISNUMBER(Inputs!$K26),Inputs!$K26,Curve!$B$5*Curve!$C$5*(INDEX(Profile!$B$9:$B$28,$A14)-IF($A14-MIN($A14,$B$2)=0,0,INDEX(Profile!$B$9:$B$28,$A14-MIN($A14,$B$2))))/$B$2/365) | C14: =IF(ISNUMBER(Inputs!$K27),Inputs!$K27,Curve!$B$6*Curve!$C$6*(INDEX(Profile!$B$9:$B$28,$A14)-IF($A14-MIN($A14,$B$2)=0,0,INDEX(Profile!$B$9:$B$28,$A14-MIN($A14,$B$2))))/$B$2/365) | D14: =IF(ISNUMBER(Inputs!$K28),Inputs!$K28,Curve!$B$7*Curve!$C$7*(INDEX(Profile!$B$9:$B$28,$A14)-IF($A14-MIN($A14,$B$2)=0,0,INDEX(Profile!$B$9:$B$28,$A14-MIN($A14,$B$2))))/$B$2/365) | E14: =IF(ISNUMBER(Inputs!$K29),Inputs!$K29,Curve!$B$8*Curve!$C$8*(INDEX(Profile!$B$9:$B$28,$A14)-IF($A14-MIN($A14,$B$2)=0,0,INDEX(Profile!$B$9:$B$28,$A14-MIN($A14,$B$2))))/$B$2/365) | F14: =IF(ISNUMBER(Inputs!$K30),Inputs!$K30,Curve!$B$9*Curve!$C$9*(INDEX(Profile!$B$9:$B$28,$A14)-IF($A14-MIN($A14,$B$2)=0,0,INDEX(Profile!$B$9:$B$28,$A14-MIN($A14,$B$2))))/$B$2/365) | G14: =IF(ISNUMBER(Inputs!$K31),Inputs!$K31,Curve!$B$10*Curve!$C$10*(INDEX(Profile!$B$9:$B$28,$A14)-IF($A14-MIN($A14,$B$2)=0,0,INDEX(Profile!$B$9:$B$28,$A14-MIN($A14,$B$2))))/$B$2/365) | H14: =IF(ISNUMBER(Inputs!$K32),Inputs!$K32,Curve!$B$11*Curve!$C$11*(INDEX(Profile!$B$9:$B$28,$A14)-IF($A14-MIN($A14,$B$2)=0,0,INDEX(Profile!$B$9:$B$28,$A14-MIN($A14,$B$2))))/$B$2/365) | I14: =IF(ISNUMBER(Inputs!$K33),Inputs!$K33,Curve!$B$12*Curve!$C$12*(INDEX(Profile!$B$9:$B$28,$A14)-IF($A14-MIN($A14,$B$2)=0,0,INDEX(Profile!$B$9:$B$28,$A14-MIN($A14,$B$2))))/$B$2/365) | J14: =SUM(B14:I14)
A15: 11 | B15: =IF(ISNUMBER(Inputs!$K26),Inputs!$K26,Curve!$B$5*Curve!$C$5*(INDEX(Profile!$B$9:$B$28,$A15)-IF($A15-MIN($A15,$B$2)=0,0,INDEX(Profile!$B$9:$B$28,$A15-MIN($A15,$B$2))))/$B$2/365) | C15: =IF(ISNUMBER(Inputs!$K27),Inputs!$K27,Curve!$B$6*Curve!$C$6*(INDEX(Profile!$B$9:$B$28,$A15)-IF($A15-MIN($A15,$B$2)=0,0,INDEX(Profile!$B$9:$B$28,$A15-MIN($A15,$B$2))))/$B$2/365) | D15: =IF(ISNUMBER(Inputs!$K28),Inputs!$K28,Curve!$B$7*Curve!$C$7*(INDEX(Profile!$B$9:$B$28,$A15)-IF($A15-MIN($A15,$B$2)=0,0,INDEX(Profile!$B$9:$B$28,$A15-MIN($A15,$B$2))))/$B$2/365) | E15: =IF(ISNUMBER(Inputs!$K29),Inputs!$K29,Curve!$B$8*Curve!$C$8*(INDEX(Profile!$B$9:$B$28,$A15)-IF($A15-MIN($A15,$B$2)=0,0,INDEX(Profile!$B$9:$B$28,$A15-MIN($A15,$B$2))))/$B$2/365) | F15: =IF(ISNUMBER(Inputs!$K30),Inputs!$K30,Curve!$B$9*Curve!$C$9*(INDEX(Profile!$B$9:$B$28,$A15)-IF($A15-MIN($A15,$B$2)=0,0,INDEX(Profile!$B$9:$B$28,$A15-MIN($A15,$B$2))))/$B$2/365) | G15: =IF(ISNUMBER(Inputs!$K31),Inputs!$K31,Curve!$B$10*Curve!$C$10*(INDEX(Profile!$B$9:$B$28,$A15)-IF($A15-MIN($A15,$B$2)=0,0,INDEX(Profile!$B$9:$B$28,$A15-MIN($A15,$B$2))))/$B$2/365) | H15: =IF(ISNUMBER(Inputs!$K32),Inputs!$K32,Curve!$B$11*Curve!$C$11*(INDEX(Profile!$B$9:$B$28,$A15)-IF($A15-MIN($A15,$B$2)=0,0,INDEX(Profile!$B$9:$B$28,$A15-MIN($A15,$B$2))))/$B$2/365) | I15: =IF(ISNUMBER(Inputs!$K33),Inputs!$K33,Curve!$B$12*Curve!$C$12*(INDEX(Profile!$B$9:$B$28,$A15)-IF($A15-MIN($A15,$B$2)=0,0,INDEX(Profile!$B$9:$B$28,$A15-MIN($A15,$B$2))))/$B$2/365) | J15: =SUM(B15:I15)
A16: 12 | B16: =IF(ISNUMBER(Inputs!$K26),Inputs!$K26,Curve!$B$5*Curve!$C$5*(INDEX(Profile!$B$9:$B$28,$A16)-IF($A16-MIN($A16,$B$2)=0,0,INDEX(Profile!$B$9:$B$28,$A16-MIN($A16,$B$2))))/$B$2/365) | C16: =IF(ISNUMBER(Inputs!$K27),Inputs!$K27,Curve!$B$6*Curve!$C$6*(INDEX(Profile!$B$9:$B$28,$A16)-IF($A16-MIN($A16,$B$2)=0,0,INDEX(Profile!$B$9:$B$28,$A16-MIN($A16,$B$2))))/$B$2/365) | D16: =IF(ISNUMBER(Inputs!$K28),Inputs!$K28,Curve!$B$7*Curve!$C$7*(INDEX(Profile!$B$9:$B$28,$A16)-IF($A16-MIN($A16,$B$2)=0,0,INDEX(Profile!$B$9:$B$28,$A16-MIN($A16,$B$2))))/$B$2/365) | E16: =IF(ISNUMBER(Inputs!$K29),Inputs!$K29,Curve!$B$8*Curve!$C$8*(INDEX(Profile!$B$9:$B$28,$A16)-IF($A16-MIN($A16,$B$2)=0,0,INDEX(Profile!$B$9:$B$28,$A16-MIN($A16,$B$2))))/$B$2/365) | F16: =IF(ISNUMBER(Inputs!$K30),Inputs!$K30,Curve!$B$9*Curve!$C$9*(INDEX(Profile!$B$9:$B$28,$A16)-IF($A16-MIN($A16,$B$2)=0,0,INDEX(Profile!$B$9:$B$28,$A16-MIN($A16,$B$2))))/$B$2/365) | G16: =IF(ISNUMBER(Inputs!$K31),Inputs!$K31,Curve!$B$10*Curve!$C$10*(INDEX(Profile!$B$9:$B$28,$A16)-IF($A16-MIN($A16,$B$2)=0,0,INDEX(Profile!$B$9:$B$28,$A16-MIN($A16,$B$2))))/$B$2/365) | H16: =IF(ISNUMBER(Inputs!$K32),Inputs!$K32,Curve!$B$11*Curve!$C$11*(INDEX(Profile!$B$9:$B$28,$A16)-IF($A16-MIN($A16,$B$2)=0,0,INDEX(Profile!$B$9:$B$28,$A16-MIN($A16,$B$2))))/$B$2/365) | I16: =IF(ISNUMBER(Inputs!$K33),Inputs!$K33,Curve!$B$12*Curve!$C$12*(INDEX(Profile!$B$9:$B$28,$A16)-IF($A16-MIN($A16,$B$2)=0,0,INDEX(Profile!$B$9:$B$28,$A16-MIN($A16,$B$2))))/$B$2/365) | J16: =SUM(B16:I16)
A17: 13 | B17: =IF(ISNUMBER(Inputs!$K26),Inputs!$K26,Curve!$B$5*Curve!$C$5*(INDEX(Profile!$B$9:$B$28,$A17)-IF($A17-MIN($A17,$B$2)=0,0,INDEX(Profile!$B$9:$B$28,$A17-MIN($A17,$B$2))))/$B$2/365) | C17: =IF(ISNUMBER(Inputs!$K27),Inputs!$K27,Curve!$B$6*Curve!$C$6*(INDEX(Profile!$B$9:$B$28,$A17)-IF($A17-MIN($A17,$B$2)=0,0,INDEX(Profile!$B$9:$B$28,$A17-MIN($A17,$B$2))))/$B$2/365) | D17: =IF(ISNUMBER(Inputs!$K28),Inputs!$K28,Curve!$B$7*Curve!$C$7*(INDEX(Profile!$B$9:$B$28,$A17)-IF($A17-MIN($A17,$B$2)=0,0,INDEX(Profile!$B$9:$B$28,$A17-MIN($A17,$B$2))))/$B$2/365) | E17: =IF(ISNUMBER(Inputs!$K29),Inputs!$K29,Curve!$B$8*Curve!$C$8*(INDEX(Profile!$B$9:$B$28,$A17)-IF($A17-MIN($A17,$B$2)=0,0,INDEX(Profile!$B$9:$B$28,$A17-MIN($A17,$B$2))))/$B$2/365) | F17: =IF(ISNUMBER(Inputs!$K30),Inputs!$K30,Curve!$B$9*Curve!$C$9*(INDEX(Profile!$B$9:$B$28,$A17)-IF($A17-MIN($A17,$B$2)=0,0,INDEX(Profile!$B$9:$B$28,$A17-MIN($A17,$B$2))))/$B$2/365) | G17: =IF(ISNUMBER(Inputs!$K31),Inputs!$K31,Curve!$B$10*Curve!$C$10*(INDEX(Profile!$B$9:$B$28,$A17)-IF($A17-MIN($A17,$B$2)=0,0,INDEX(Profile!$B$9:$B$28,$A17-MIN($A17,$B$2))))/$B$2/365) | H17: =IF(ISNUMBER(Inputs!$K32),Inputs!$K32,Curve!$B$11*Curve!$C$11*(INDEX(Profile!$B$9:$B$28,$A17)-IF($A17-MIN($A17,$B$2)=0,0,INDEX(Profile!$B$9:$B$28,$A17-MIN($A17,$B$2))))/$B$2/365) | I17: =IF(ISNUMBER(Inputs!$K33),Inputs!$K33,Curve!$B$12*Curve!$C$12*(INDEX(Profile!$B$9:$B$28,$A17)-IF($A17-MIN($A17,$B$2)=0,0,INDEX(Profile!$B$9:$B$28,$A17-MIN($A17,$B$2))))/$B$2/365) | J17: =SUM(B17:I17)
A18: 14 | B18: =IF(ISNUMBER(Inputs!$K26),Inputs!$K26,Curve!$B$5*Curve!$C$5*(INDEX(Profile!$B$9:$B$28,$A18)-IF($A18-MIN($A18,$B$2)=0,0,INDEX(Profile!$B$9:$B$28,$A18-MIN($A18,$B$2))))/$B$2/365) | C18: =IF(ISNUMBER(Inputs!$K27),Inputs!$K27,Curve!$B$6*Curve!$C$6*(INDEX(Profile!$B$9:$B$28,$A18)-IF($A18-MIN($A18,$B$2)=0,0,INDEX(Profile!$B$9:$B$28,$A18-MIN($A18,$B$2))))/$B$2/365) | D18: =IF(ISNUMBER(Inputs!$K28),Inputs!$K28,Curve!$B$7*Curve!$C$7*(INDEX(Profile!$B$9:$B$28,$A18)-IF($A18-MIN($A18,$B$2)=0,0,INDEX(Profile!$B$9:$B$28,$A18-MIN($A18,$B$2))))/$B$2/365) | E18: =IF(ISNUMBER(Inputs!$K29),Inputs!$K29,Curve!$B$8*Curve!$C$8*(INDEX(Profile!$B$9:$B$28,$A18)-IF($A18-MIN($A18,$B$2)=0,0,INDEX(Profile!$B$9:$B$28,$A18-MIN($A18,$B$2))))/$B$2/365) | F18: =IF(ISNUMBER(Inputs!$K30),Inputs!$K30,Curve!$B$9*Curve!$C$9*(INDEX(Profile!$B$9:$B$28,$A18)-IF($A18-MIN($A18,$B$2)=0,0,INDEX(Profile!$B$9:$B$28,$A18-MIN($A18,$B$2))))/$B$2/365) | G18: =IF(ISNUMBER(Inputs!$K31),Inputs!$K31,Curve!$B$10*Curve!$C$10*(INDEX(Profile!$B$9:$B$28,$A18)-IF($A18-MIN($A18,$B$2)=0,0,INDEX(Profile!$B$9:$B$28,$A18-MIN($A18,$B$2))))/$B$2/365) | H18: =IF(ISNUMBER(Inputs!$K32),Inputs!$K32,Curve!$B$11*Curve!$C$11*(INDEX(Profile!$B$9:$B$28,$A18)-IF($A18-MIN($A18,$B$2)=0,0,INDEX(Profile!$B$9:$B$28,$A18-MIN($A18,$B$2))))/$B$2/365) | I18: =IF(ISNUMBER(Inputs!$K33),Inputs!$K33,Curve!$B$12*Curve!$C$12*(INDEX(Profile!$B$9:$B$28,$A18)-IF($A18-MIN($A18,$B$2)=0,0,INDEX(Profile!$B$9:$B$28,$A18-MIN($A18,$B$2))))/$B$2/365) | J18: =SUM(B18:I18)
A19: 15 | B19: =IF(ISNUMBER(Inputs!$K26),Inputs!$K26,Curve!$B$5*Curve!$C$5*(INDEX(Profile!$B$9:$B$28,$A19)-IF($A19-MIN($A19,$B$2)=0,0,INDEX(Profile!$B$9:$B$28,$A19-MIN($A19,$B$2))))/$B$2/365) | C19: =IF(ISNUMBER(Inputs!$K27),Inputs!$K27,Curve!$B$6*Curve!$C$6*(INDEX(Profile!$B$9:$B$28,$A19)-IF($A19-MIN($A19,$B$2)=0,0,INDEX(Profile!$B$9:$B$28,$A19-MIN($A19,$B$2))))/$B$2/365) | D19: =IF(ISNUMBER(Inputs!$K28),Inputs!$K28,Curve!$B$7*Curve!$C$7*(INDEX(Profile!$B$9:$B$28,$A19)-IF($A19-MIN($A19,$B$2)=0,0,INDEX(Profile!$B$9:$B$28,$A19-MIN($A19,$B$2))))/$B$2/365) | E19: =IF(ISNUMBER(Inputs!$K29),Inputs!$K29,Curve!$B$8*Curve!$C$8*(INDEX(Profile!$B$9:$B$28,$A19)-IF($A19-MIN($A19,$B$2)=0,0,INDEX(Profile!$B$9:$B$28,$A19-MIN($A19,$B$2))))/$B$2/365) | F19: =IF(ISNUMBER(Inputs!$K30),Inputs!$K30,Curve!$B$9*Curve!$C$9*(INDEX(Profile!$B$9:$B$28,$A19)-IF($A19-MIN($A19,$B$2)=0,0,INDEX(Profile!$B$9:$B$28,$A19-MIN($A19,$B$2))))/$B$2/365) | G19: =IF(ISNUMBER(Inputs!$K31),Inputs!$K31,Curve!$B$10*Curve!$C$10*(INDEX(Profile!$B$9:$B$28,$A19)-IF($A19-MIN($A19,$B$2)=0,0,INDEX(Profile!$B$9:$B$28,$A19-MIN($A19,$B$2))))/$B$2/365) | H19: =IF(ISNUMBER(Inputs!$K32),Inputs!$K32,Curve!$B$11*Curve!$C$11*(INDEX(Profile!$B$9:$B$28,$A19)-IF($A19-MIN($A19,$B$2)=0,0,INDEX(Profile!$B$9:$B$28,$A19-MIN($A19,$B$2))))/$B$2/365) | I19: =IF(ISNUMBER(Inputs!$K33),Inputs!$K33,Curve!$B$12*Curve!$C$12*(INDEX(Profile!$B$9:$B$28,$A19)-IF($A19-MIN($A19,$B$2)=0,0,INDEX(Profile!$B$9:$B$28,$A19-MIN($A19,$B$2))))/$B$2/365) | J19: =SUM(B19:I19)
A20: 16 | B20: =IF(ISNUMBER(Inputs!$K26),Inputs!$K26,Curve!$B$5*Curve!$C$5*(INDEX(Profile!$B$9:$B$28,$A20)-IF($A20-MIN($A20,$B$2)=0,0,INDEX(Profile!$B$9:$B$28,$A20-MIN($A20,$B$2))))/$B$2/365) | C20: =IF(ISNUMBER(Inputs!$K27),Inputs!$K27,Curve!$B$6*Curve!$C$6*(INDEX(Profile!$B$9:$B$28,$A20)-IF($A20-MIN($A20,$B$2)=0,0,INDEX(Profile!$B$9:$B$28,$A20-MIN($A20,$B$2))))/$B$2/365) | D20: =IF(ISNUMBER(Inputs!$K28),Inputs!$K28,Curve!$B$7*Curve!$C$7*(INDEX(Profile!$B$9:$B$28,$A20)-IF($A20-MIN($A20,$B$2)=0,0,INDEX(Profile!$B$9:$B$28,$A20-MIN($A20,$B$2))))/$B$2/365) | E20: =IF(ISNUMBER(Inputs!$K29),Inputs!$K29,Curve!$B$8*Curve!$C$8*(INDEX(Profile!$B$9:$B$28,$A20)-IF($A20-MIN($A20,$B$2)=0,0,INDEX(Profile!$B$9:$B$28,$A20-MIN($A20,$B$2))))/$B$2/365) | F20: =IF(ISNUMBER(Inputs!$K30),Inputs!$K30,Curve!$B$9*Curve!$C$9*(INDEX(Profile!$B$9:$B$28,$A20)-IF($A20-MIN($A20,$B$2)=0,0,INDEX(Profile!$B$9:$B$28,$A20-MIN($A20,$B$2))))/$B$2/365) | G20: =IF(ISNUMBER(Inputs!$K31),Inputs!$K31,Curve!$B$10*Curve!$C$10*(INDEX(Profile!$B$9:$B$28,$A20)-IF($A20-MIN($A20,$B$2)=0,0,INDEX(Profile!$B$9:$B$28,$A20-MIN($A20,$B$2))))/$B$2/365) | H20: =IF(ISNUMBER(Inputs!$K32),Inputs!$K32,Curve!$B$11*Curve!$C$11*(INDEX(Profile!$B$9:$B$28,$A20)-IF($A20-MIN($A20,$B$2)=0,0,INDEX(Profile!$B$9:$B$28,$A20-MIN($A20,$B$2))))/$B$2/365) | I20: =IF(ISNUMBER(Inputs!$K33),Inputs!$K33,Curve!$B$12*Curve!$C$12*(INDEX(Profile!$B$9:$B$28,$A20)-IF($A20-MIN($A20,$B$2)=0,0,INDEX(Profile!$B$9:$B$28,$A20-MIN($A20,$B$2))))/$B$2/365) | J20: =SUM(B20:I20)
A21: 17 | B21: =IF(ISNUMBER(Inputs!$K26),Inputs!$K26,Curve!$B$5*Curve!$C$5*(INDEX(Profile!$B$9:$B$28,$A21)-IF($A21-MIN($A21,$B$2)=0,0,INDEX(Profile!$B$9:$B$28,$A21-MIN($A21,$B$2))))/$B$2/365) | C21: =IF(ISNUMBER(Inputs!$K27),Inputs!$K27,Curve!$B$6*Curve!$C$6*(INDEX(Profile!$B$9:$B$28,$A21)-IF($A21-MIN($A21,$B$2)=0,0,INDEX(Profile!$B$9:$B$28,$A21-MIN($A21,$B$2))))/$B$2/365) | D21: =IF(ISNUMBER(Inputs!$K28),Inputs!$K28,Curve!$B$7*Curve!$C$7*(INDEX(Profile!$B$9:$B$28,$A21)-IF($A21-MIN($A21,$B$2)=0,0,INDEX(Profile!$B$9:$B$28,$A21-MIN($A21,$B$2))))/$B$2/365) | E21: =IF(ISNUMBER(Inputs!$K29),Inputs!$K29,Curve!$B$8*Curve!$C$8*(INDEX(Profile!$B$9:$B$28,$A21)-IF($A21-MIN($A21,$B$2)=0,0,INDEX(Profile!$B$9:$B$28,$A21-MIN($A21,$B$2))))/$B$2/365) | F21: =IF(ISNUMBER(Inputs!$K30),Inputs!$K30,Curve!$B$9*Curve!$C$9*(INDEX(Profile!$B$9:$B$28,$A21)-IF($A21-MIN($A21,$B$2)=0,0,INDEX(Profile!$B$9:$B$28,$A21-MIN($A21,$B$2))))/$B$2/365) | G21: =IF(ISNUMBER(Inputs!$K31),Inputs!$K31,Curve!$B$10*Curve!$C$10*(INDEX(Profile!$B$9:$B$28,$A21)-IF($A21-MIN($A21,$B$2)=0,0,INDEX(Profile!$B$9:$B$28,$A21-MIN($A21,$B$2))))/$B$2/365) | H21: =IF(ISNUMBER(Inputs!$K32),Inputs!$K32,Curve!$B$11*Curve!$C$11*(INDEX(Profile!$B$9:$B$28,$A21)-IF($A21-MIN($A21,$B$2)=0,0,INDEX(Profile!$B$9:$B$28,$A21-MIN($A21,$B$2))))/$B$2/365) | I21: =IF(ISNUMBER(Inputs!$K33),Inputs!$K33,Curve!$B$12*Curve!$C$12*(INDEX(Profile!$B$9:$B$28,$A21)-IF($A21-MIN($A21,$B$2)=0,0,INDEX(Profile!$B$9:$B$28,$A21-MIN($A21,$B$2))))/$B$2/365) | J21: =SUM(B21:I21)
A22: 18 | B22: =IF(ISNUMBER(Inputs!$K26),Inputs!$K26,Curve!$B$5*Curve!$C$5*(INDEX(Profile!$B$9:$B$28,$A22)-IF($A22-MIN($A22,$B$2)=0,0,INDEX(Profile!$B$9:$B$28,$A22-MIN($A22,$B$2))))/$B$2/365) | C22: =IF(ISNUMBER(Inputs!$K27),Inputs!$K27,Curve!$B$6*Curve!$C$6*(INDEX(Profile!$B$9:$B$28,$A22)-IF($A22-MIN($A22,$B$2)=0,0,INDEX(Profile!$B$9:$B$28,$A22-MIN($A22,$B$2))))/$B$2/365) | D22: =IF(ISNUMBER(Inputs!$K28),Inputs!$K28,Curve!$B$7*Curve!$C$7*(INDEX(Profile!$B$9:$B$28,$A22)-IF($A22-MIN($A22,$B$2)=0,0,INDEX(Profile!$B$9:$B$28,$A22-MIN($A22,$B$2))))/$B$2/365) | E22: =IF(ISNUMBER(Inputs!$K29),Inputs!$K29,Curve!$B$8*Curve!$C$8*(INDEX(Profile!$B$9:$B$28,$A22)-IF($A22-MIN($A22,$B$2)=0,0,INDEX(Profile!$B$9:$B$28,$A22-MIN($A22,$B$2))))/$B$2/365) | F22: =IF(ISNUMBER(Inputs!$K30),Inputs!$K30,Curve!$B$9*Curve!$C$9*(INDEX(Profile!$B$9:$B$28,$A22)-IF($A22-MIN($A22,$B$2)=0,0,INDEX(Profile!$B$9:$B$28,$A22-MIN($A22,$B$2))))/$B$2/365) | G22: =IF(ISNUMBER(Inputs!$K31),Inputs!$K31,Curve!$B$10*Curve!$C$10*(INDEX(Profile!$B$9:$B$28,$A22)-IF($A22-MIN($A22,$B$2)=0,0,INDEX(Profile!$B$9:$B$28,$A22-MIN($A22,$B$2))))/$B$2/365) | H22: =IF(ISNUMBER(Inputs!$K32),Inputs!$K32,Curve!$B$11*Curve!$C$11*(INDEX(Profile!$B$9:$B$28,$A22)-IF($A22-MIN($A22,$B$2)=0,0,INDEX(Profile!$B$9:$B$28,$A22-MIN($A22,$B$2))))/$B$2/365) | I22: =IF(ISNUMBER(Inputs!$K33),Inputs!$K33,Curve!$B$12*Curve!$C$12*(INDEX(Profile!$B$9:$B$28,$A22)-IF($A22-MIN($A22,$B$2)=0,0,INDEX(Profile!$B$9:$B$28,$A22-MIN($A22,$B$2))))/$B$2/365) | J22: =SUM(B22:I22)
A23: 19 | B23: =IF(ISNUMBER(Inputs!$K26),Inputs!$K26,Curve!$B$5*Curve!$C$5*(INDEX(Profile!$B$9:$B$28,$A23)-IF($A23-MIN($A23,$B$2)=0,0,INDEX(Profile!$B$9:$B$28,$A23-MIN($A23,$B$2))))/$B$2/365) | C23: =IF(ISNUMBER(Inputs!$K27),Inputs!$K27,Curve!$B$6*Curve!$C$6*(INDEX(Profile!$B$9:$B$28,$A23)-IF($A23-MIN($A23,$B$2)=0,0,INDEX(Profile!$B$9:$B$28,$A23-MIN($A23,$B$2))))/$B$2/365) | D23: =IF(ISNUMBER(Inputs!$K28),Inputs!$K28,Curve!$B$7*Curve!$C$7*(INDEX(Profile!$B$9:$B$28,$A23)-IF($A23-MIN($A23,$B$2)=0,0,INDEX(Profile!$B$9:$B$28,$A23-MIN($A23,$B$2))))/$B$2/365) | E23: =IF(ISNUMBER(Inputs!$K29),Inputs!$K29,Curve!$B$8*Curve!$C$8*(INDEX(Profile!$B$9:$B$28,$A23)-IF($A23-MIN($A23,$B$2)=0,0,INDEX(Profile!$B$9:$B$28,$A23-MIN($A23,$B$2))))/$B$2/365) | F23: =IF(ISNUMBER(Inputs!$K30),Inputs!$K30,Curve!$B$9*Curve!$C$9*(INDEX(Profile!$B$9:$B$28,$A23)-IF($A23-MIN($A23,$B$2)=0,0,INDEX(Profile!$B$9:$B$28,$A23-MIN($A23,$B$2))))/$B$2/365) | G23: =IF(ISNUMBER(Inputs!$K31),Inputs!$K31,Curve!$B$10*Curve!$C$10*(INDEX(Profile!$B$9:$B$28,$A23)-IF($A23-MIN($A23,$B$2)=0,0,INDEX(Profile!$B$9:$B$28,$A23-MIN($A23,$B$2))))/$B$2/365) | H23: =IF(ISNUMBER(Inputs!$K32),Inputs!$K32,Curve!$B$11*Curve!$C$11*(INDEX(Profile!$B$9:$B$28,$A23)-IF($A23-MIN($A23,$B$2)=0,0,INDEX(Profile!$B$9:$B$28,$A23-MIN($A23,$B$2))))/$B$2/365) | I23: =IF(ISNUMBER(Inputs!$K33),Inputs!$K33,Curve!$B$12*Curve!$C$12*(INDEX(Profile!$B$9:$B$28,$A23)-IF($A23-MIN($A23,$B$2)=0,0,INDEX(Profile!$B$9:$B$28,$A23-MIN($A23,$B$2))))/$B$2/365) | J23: =SUM(B23:I23)
A24: 20 | B24: =IF(ISNUMBER(Inputs!$K26),Inputs!$K26,Curve!$B$5*Curve!$C$5*(INDEX(Profile!$B$9:$B$28,$A24)-IF($A24-MIN($A24,$B$2)=0,0,INDEX(Profile!$B$9:$B$28,$A24-MIN($A24,$B$2))))/$B$2/365) | C24: =IF(ISNUMBER(Inputs!$K27),Inputs!$K27,Curve!$B$6*Curve!$C$6*(INDEX(Profile!$B$9:$B$28,$A24)-IF($A24-MIN($A24,$B$2)=0,0,INDEX(Profile!$B$9:$B$28,$A24-MIN($A24,$B$2))))/$B$2/365) | D24: =IF(ISNUMBER(Inputs!$K28),Inputs!$K28,Curve!$B$7*Curve!$C$7*(INDEX(Profile!$B$9:$B$28,$A24)-IF($A24-MIN($A24,$B$2)=0,0,INDEX(Profile!$B$9:$B$28,$A24-MIN($A24,$B$2))))/$B$2/365) | E24: =IF(ISNUMBER(Inputs!$K29),Inputs!$K29,Curve!$B$8*Curve!$C$8*(INDEX(Profile!$B$9:$B$28,$A24)-IF($A24-MIN($A24,$B$2)=0,0,INDEX(Profile!$B$9:$B$28,$A24-MIN($A24,$B$2))))/$B$2/365) | F24: =IF(ISNUMBER(Inputs!$K30),Inputs!$K30,Curve!$B$9*Curve!$C$9*(INDEX(Profile!$B$9:$B$28,$A24)-IF($A24-MIN($A24,$B$2)=0,0,INDEX(Profile!$B$9:$B$28,$A24-MIN($A24,$B$2))))/$B$2/365) | G24: =IF(ISNUMBER(Inputs!$K31),Inputs!$K31,Curve!$B$10*Curve!$C$10*(INDEX(Profile!$B$9:$B$28,$A24)-IF($A24-MIN($A24,$B$2)=0,0,INDEX(Profile!$B$9:$B$28,$A24-MIN($A24,$B$2))))/$B$2/365) | H24: =IF(ISNUMBER(Inputs!$K32),Inputs!$K32,Curve!$B$11*Curve!$C$11*(INDEX(Profile!$B$9:$B$28,$A24)-IF($A24-MIN($A24,$B$2)=0,0,INDEX(Profile!$B$9:$B$28,$A24-MIN($A24,$B$2))))/$B$2/365) | I24: =IF(ISNUMBER(Inputs!$K33),Inputs!$K33,Curve!$B$12*Curve!$C$12*(INDEX(Profile!$B$9:$B$28,$A24)-IF($A24-MIN($A24,$B$2)=0,0,INDEX(Profile!$B$9:$B$28,$A24-MIN($A24,$B$2))))/$B$2/365) | J24: =SUM(B24:I24)

Sheet Mapping
A1: Mapping - implied marginal breakeven of the Gulf 'Key question' Haynesville increments (live). APPROXIMATE - built from company disclosures and BEG tiering; breakevens are pre-tax model results, not a vendor curve
A2: Source of the increments: gulf_coast_gas_balance.xlsx 'Key question' (read-only, file dated 06 Oct 2026; copy on 'Gulf key question'). Year-end increments are vs Dec 2025, Bcf/d. Stack position: the curve is filled cheapest first. 'STEO growth' is the Haynesville growth already in EIA STEO / its extension; the EXTRA supply sits on top of it, so the marginal tier for the extra volume is found at STEO growth + extra (headline); 'extra alone' (curve from zero) is the lower bound. Layers: cumulative extra with each Louisiana LNG layer (ILLUSTRATIVE). H = years from Dec 2025: capacity on the curve is what a cost-only (not rig / takeaway constrained) programme could add in that time. Price cells show 'beyond inventory' when the stack runs out.
A4: Rows in the same order as 'Gulf key question' (Dec 2026, 2028, 2030, 2033; base then delayed)
A5: Scenario | B5: Year-end | C5: H (years) | D5: STEO Haynesville growth | E5: Extra supply required | F5: Extra with layers up to Cameron LNG Train 4 | G5: Extra with layers up to Woodside Louisiana LNG Phase 2 | H5: Extra with layers up to Lake Charles LNG (SUSPENDED) | I5: Extra with layers up to Delfin FLNG vessels 2-3 | J5: Marginal breakeven - extra supply alone | K5: Marginal breakeven - STEO growth + extra | L5: Marginal breakeven - STEO growth + layers up to Cameron LNG Train 4 | M5: Marginal breakeven - STEO growth + layers up to Woodside Louisiana LNG Phase 2 | N5: Marginal breakeven - STEO growth + layers up to Lake Charles LNG (SUSPENDED) | O5: Marginal breakeven - STEO growth + layers up to Delfin FLNG vessels 2-3 | P5: Henry Hub, last 12 months average | Q5: Headline marginal breakeven less Henry Hub
A6: Base | B6: Dec 2026 | C6: 1 | D6: ='Gulf key question'!C2 | E6: ='Gulf key question'!D2 | F6: ='Gulf key question'!F2 | G6: ='Gulf key question'!G2 | H6: ='Gulf key question'!H2 | I6: ='Gulf key question'!I2 | J6: =IF(NOT(ISNUMBER($E6)),"-",IF($E6<=0,"-",IF(1+(INDEX(Curve!$L$16:$U$23,1,MATCH($C6,Curve!$L$4:$U$4,0))<$E6)+(INDEX(Curve!$L$16:$U$23,2,MATCH($C6,Curve!$L$4:$U$4,0))<$E6)+(INDEX(Curve!$L$16:$U$23,3,MATCH($C6,Curve!$L$4:$U$4,0))<$E6)+(INDEX(Curve!$L$16:$U$23,4,MATCH($C6,Curve!$L$4:$U$4,0))<$E6)+(INDEX(Curve!$L$16:$U$23,5,MATCH($C6,Curve!$L$4:$U$4,0))<$E6)+(INDEX(Curve!$L$16:$U$23,6,MATCH($C6,Curve!$L$4:$U$4,0))<$E6)+(INDEX(Curve!$L$16:$U$23,7,MATCH($C6,Curve!$L$4:$U$4,0))<$E6)+(INDEX(Curve!$L$16:$U$23,8,MATCH($C6,Curve!$L$4:$U$4,0))<$E6)>8,"beyond inventory",INDEX(Curve!$D$16:$D$23,1+(INDEX(Curve!$L$16:$U$23,1,MATCH($C6,Curve!$L$4:$U$4,0))<$E6)+(INDEX(Curve!$L$16:$U$23,2,MATCH($C6,Curve!$L$4:$U$4,0))<$E6)+(INDEX(Curve!$L$16:$U$23,3,MATCH($C6,Curve!$L$4:$U$4,0))<$E6)+(INDEX(Curve!$L$16:$U$23,4,MATCH($C6,Curve!$L$4:$U$4,0))<$E6)+(INDEX(Curve!$L$16:$U$23,5,MATCH($C6,Curve!$L$4:$U$4,0))<$E6)+(INDEX(Curve!$L$16:$U$23,6,MATCH($C6,Curve!$L$4:$U$4,0))<$E6)+(INDEX(Curve!$L$16:$U$23,7,MATCH($C6,Curve!$L$4:$U$4,0))<$E6)+(INDEX(Curve!$L$16:$U$23,8,MATCH($C6,Curve!$L$4:$U$4,0))<$E6))))) | K6: =IF(NOT(ISNUMBER(($D6+$E6))),"-",IF(($D6+$E6)<=0,"-",IF(1+(INDEX(Curve!$L$16:$U$23,1,MATCH($C6,Curve!$L$4:$U$4,0))<($D6+$E6))+(INDEX(Curve!$L$16:$U$23,2,MATCH($C6,Curve!$L$4:$U$4,0))<($D6+$E6))+(INDEX(Curve!$L$16:$U$23,3,MATCH($C6,Curve!$L$4:$U$4,0))<($D6+$E6))+(INDEX(Curve!$L$16:$U$23,4,MATCH($C6,Curve!$L$4:$U$4,0))<($D6+$E6))+(INDEX(Curve!$L$16:$U$23,5,MATCH($C6,Curve!$L$4:$U$4,0))<($D6+$E6))+(INDEX(Curve!$L$16:$U$23,6,MATCH($C6,Curve!$L$4:$U$4,0))<($D6+$E6))+(INDEX(Curve!$L$16:$U$23,7,MATCH($C6,Curve!$L$4:$U$4,0))<($D6+$E6))+(INDEX(Curve!$L$16:$U$23,8,MATCH($C6,Curve!$L$4:$U$4,0))<($D6+$E6))>8,"beyond inventory",INDEX(Curve!$D$16:$D$23,1+(INDEX(Curve!$L$16:$U$23,1,MATCH($C6,Curve!$L$4:$U$4,0))<($D6+$E6))+(INDEX(Curve!$L$16:$U$23,2,MATCH($C6,Curve!$L$4:$U$4,0))<($D6+$E6))+(INDEX(Curve!$L$16:$U$23,3,MATCH($C6,Curve!$L$4:$U$4,0))<($D6+$E6))+(INDEX(Curve!$L$16:$U$23,4,MATCH($C6,Curve!$L$4:$U$4,0))<($D6+$E6))+(INDEX(Curve!$L$16:$U$23,5,MATCH($C6,Curve!$L$4:$U$4,0))<($D6+$E6))+(INDEX(Curve!$L$16:$U$23,6,MATCH($C6,Curve!$L$4:$U$4,0))<($D6+$E6))+(INDEX(Curve!$L$16:$U$23,7,MATCH($C6,Curve!$L$4:$U$4,0))<($D6+$E6))+(INDEX(Curve!$L$16:$U$23,8,MATCH($C6,Curve!$L$4:$U$4,0))<($D6+$E6)))))) | L6: =IF(NOT(ISNUMBER(($D6+F6))),"-",IF(($D6+F6)<=0,"-",IF(1+(INDEX(Curve!$L$16:$U$23,1,MATCH($C6,Curve!$L$4:$U$4,0))<($D6+F6))+(INDEX(Curve!$L$16:$U$23,2,MATCH($C6,Curve!$L$4:$U$4,0))<($D6+F6))+(INDEX(Curve!$L$16:$U$23,3,MATCH($C6,Curve!$L$4:$U$4,0))<($D6+F6))+(INDEX(Curve!$L$16:$U$23,4,MATCH($C6,Curve!$L$4:$U$4,0))<($D6+F6))+(INDEX(Curve!$L$16:$U$23,5,MATCH($C6,Curve!$L$4:$U$4,0))<($D6+F6))+(INDEX(Curve!$L$16:$U$23,6,MATCH($C6,Curve!$L$4:$U$4,0))<($D6+F6))+(INDEX(Curve!$L$16:$U$23,7,MATCH($C6,Curve!$L$4:$U$4,0))<($D6+F6))+(INDEX(Curve!$L$16:$U$23,8,MATCH($C6,Curve!$L$4:$U$4,0))<($D6+F6))>8,"beyond inventory",INDEX(Curve!$D$16:$D$23,1+(INDEX(Curve!$L$16:$U$23,1,MATCH($C6,Curve!$L$4:$U$4,0))<($D6+F6))+(INDEX(Curve!$L$16:$U$23,2,MATCH($C6,Curve!$L$4:$U$4,0))<($D6+F6))+(INDEX(Curve!$L$16:$U$23,3,MATCH($C6,Curve!$L$4:$U$4,0))<($D6+F6))+(INDEX(Curve!$L$16:$U$23,4,MATCH($C6,Curve!$L$4:$U$4,0))<($D6+F6))+(INDEX(Curve!$L$16:$U$23,5,MATCH($C6,Curve!$L$4:$U$4,0))<($D6+F6))+(INDEX(Curve!$L$16:$U$23,6,MATCH($C6,Curve!$L$4:$U$4,0))<($D6+F6))+(INDEX(Curve!$L$16:$U$23,7,MATCH($C6,Curve!$L$4:$U$4,0))<($D6+F6))+(INDEX(Curve!$L$16:$U$23,8,MATCH($C6,Curve!$L$4:$U$4,0))<($D6+F6)))))) | M6: =IF(NOT(ISNUMBER(($D6+G6))),"-",IF(($D6+G6)<=0,"-",IF(1+(INDEX(Curve!$L$16:$U$23,1,MATCH($C6,Curve!$L$4:$U$4,0))<($D6+G6))+(INDEX(Curve!$L$16:$U$23,2,MATCH($C6,Curve!$L$4:$U$4,0))<($D6+G6))+(INDEX(Curve!$L$16:$U$23,3,MATCH($C6,Curve!$L$4:$U$4,0))<($D6+G6))+(INDEX(Curve!$L$16:$U$23,4,MATCH($C6,Curve!$L$4:$U$4,0))<($D6+G6))+(INDEX(Curve!$L$16:$U$23,5,MATCH($C6,Curve!$L$4:$U$4,0))<($D6+G6))+(INDEX(Curve!$L$16:$U$23,6,MATCH($C6,Curve!$L$4:$U$4,0))<($D6+G6))+(INDEX(Curve!$L$16:$U$23,7,MATCH($C6,Curve!$L$4:$U$4,0))<($D6+G6))+(INDEX(Curve!$L$16:$U$23,8,MATCH($C6,Curve!$L$4:$U$4,0))<($D6+G6))>8,"beyond inventory",INDEX(Curve!$D$16:$D$23,1+(INDEX(Curve!$L$16:$U$23,1,MATCH($C6,Curve!$L$4:$U$4,0))<($D6+G6))+(INDEX(Curve!$L$16:$U$23,2,MATCH($C6,Curve!$L$4:$U$4,0))<($D6+G6))+(INDEX(Curve!$L$16:$U$23,3,MATCH($C6,Curve!$L$4:$U$4,0))<($D6+G6))+(INDEX(Curve!$L$16:$U$23,4,MATCH($C6,Curve!$L$4:$U$4,0))<($D6+G6))+(INDEX(Curve!$L$16:$U$23,5,MATCH($C6,Curve!$L$4:$U$4,0))<($D6+G6))+(INDEX(Curve!$L$16:$U$23,6,MATCH($C6,Curve!$L$4:$U$4,0))<($D6+G6))+(INDEX(Curve!$L$16:$U$23,7,MATCH($C6,Curve!$L$4:$U$4,0))<($D6+G6))+(INDEX(Curve!$L$16:$U$23,8,MATCH($C6,Curve!$L$4:$U$4,0))<($D6+G6)))))) | N6: =IF(NOT(ISNUMBER(($D6+H6))),"-",IF(($D6+H6)<=0,"-",IF(1+(INDEX(Curve!$L$16:$U$23,1,MATCH($C6,Curve!$L$4:$U$4,0))<($D6+H6))+(INDEX(Curve!$L$16:$U$23,2,MATCH($C6,Curve!$L$4:$U$4,0))<($D6+H6))+(INDEX(Curve!$L$16:$U$23,3,MATCH($C6,Curve!$L$4:$U$4,0))<($D6+H6))+(INDEX(Curve!$L$16:$U$23,4,MATCH($C6,Curve!$L$4:$U$4,0))<($D6+H6))+(INDEX(Curve!$L$16:$U$23,5,MATCH($C6,Curve!$L$4:$U$4,0))<($D6+H6))+(INDEX(Curve!$L$16:$U$23,6,MATCH($C6,Curve!$L$4:$U$4,0))<($D6+H6))+(INDEX(Curve!$L$16:$U$23,7,MATCH($C6,Curve!$L$4:$U$4,0))<($D6+H6))+(INDEX(Curve!$L$16:$U$23,8,MATCH($C6,Curve!$L$4:$U$4,0))<($D6+H6))>8,"beyond inventory",INDEX(Curve!$D$16:$D$23,1+(INDEX(Curve!$L$16:$U$23,1,MATCH($C6,Curve!$L$4:$U$4,0))<($D6+H6))+(INDEX(Curve!$L$16:$U$23,2,MATCH($C6,Curve!$L$4:$U$4,0))<($D6+H6))+(INDEX(Curve!$L$16:$U$23,3,MATCH($C6,Curve!$L$4:$U$4,0))<($D6+H6))+(INDEX(Curve!$L$16:$U$23,4,MATCH($C6,Curve!$L$4:$U$4,0))<($D6+H6))+(INDEX(Curve!$L$16:$U$23,5,MATCH($C6,Curve!$L$4:$U$4,0))<($D6+H6))+(INDEX(Curve!$L$16:$U$23,6,MATCH($C6,Curve!$L$4:$U$4,0))<($D6+H6))+(INDEX(Curve!$L$16:$U$23,7,MATCH($C6,Curve!$L$4:$U$4,0))<($D6+H6))+(INDEX(Curve!$L$16:$U$23,8,MATCH($C6,Curve!$L$4:$U$4,0))<($D6+H6)))))) | O6: =IF(NOT(ISNUMBER(($D6+I6))),"-",IF(($D6+I6)<=0,"-",IF(1+(INDEX(Curve!$L$16:$U$23,1,MATCH($C6,Curve!$L$4:$U$4,0))<($D6+I6))+(INDEX(Curve!$L$16:$U$23,2,MATCH($C6,Curve!$L$4:$U$4,0))<($D6+I6))+(INDEX(Curve!$L$16:$U$23,3,MATCH($C6,Curve!$L$4:$U$4,0))<($D6+I6))+(INDEX(Curve!$L$16:$U$23,4,MATCH($C6,Curve!$L$4:$U$4,0))<($D6+I6))+(INDEX(Curve!$L$16:$U$23,5,MATCH($C6,Curve!$L$4:$U$4,0))<($D6+I6))+(INDEX(Curve!$L$16:$U$23,6,MATCH($C6,Curve!$L$4:$U$4,0))<($D6+I6))+(INDEX(Curve!$L$16:$U$23,7,MATCH($C6,Curve!$L$4:$U$4,0))<($D6+I6))+(INDEX(Curve!$L$16:$U$23,8,MATCH($C6,Curve!$L$4:$U$4,0))<($D6+I6))>8,"beyond inventory",INDEX(Curve!$D$16:$D$23,1+(INDEX(Curve!$L$16:$U$23,1,MATCH($C6,Curve!$L$4:$U$4,0))<($D6+I6))+(INDEX(Curve!$L$16:$U$23,2,MATCH($C6,Curve!$L$4:$U$4,0))<($D6+I6))+(INDEX(Curve!$L$16:$U$23,3,MATCH($C6,Curve!$L$4:$U$4,0))<($D6+I6))+(INDEX(Curve!$L$16:$U$23,4,MATCH($C6,Curve!$L$4:$U$4,0))<($D6+I6))+(INDEX(Curve!$L$16:$U$23,5,MATCH($C6,Curve!$L$4:$U$4,0))<($D6+I6))+(INDEX(Curve!$L$16:$U$23,6,MATCH($C6,Curve!$L$4:$U$4,0))<($D6+I6))+(INDEX(Curve!$L$16:$U$23,7,MATCH($C6,Curve!$L$4:$U$4,0))<($D6+I6))+(INDEX(Curve!$L$16:$U$23,8,MATCH($C6,Curve!$L$4:$U$4,0))<($D6+I6)))))) | P6: ='Henry Hub'!$B$3 | Q6: =IF(ISNUMBER(K6),K6-P6,"-")
A7: Base | B7: Dec 2028 | C7: 3 | D7: ='Gulf key question'!C4 | E7: ='Gulf key question'!D4 | F7: ='Gulf key question'!F4 | G7: ='Gulf key question'!G4 | H7: ='Gulf key question'!H4 | I7: ='Gulf key question'!I4 | J7: =IF(NOT(ISNUMBER($E7)),"-",IF($E7<=0,"-",IF(1+(INDEX(Curve!$L$16:$U$23,1,MATCH($C7,Curve!$L$4:$U$4,0))<$E7)+(INDEX(Curve!$L$16:$U$23,2,MATCH($C7,Curve!$L$4:$U$4,0))<$E7)+(INDEX(Curve!$L$16:$U$23,3,MATCH($C7,Curve!$L$4:$U$4,0))<$E7)+(INDEX(Curve!$L$16:$U$23,4,MATCH($C7,Curve!$L$4:$U$4,0))<$E7)+(INDEX(Curve!$L$16:$U$23,5,MATCH($C7,Curve!$L$4:$U$4,0))<$E7)+(INDEX(Curve!$L$16:$U$23,6,MATCH($C7,Curve!$L$4:$U$4,0))<$E7)+(INDEX(Curve!$L$16:$U$23,7,MATCH($C7,Curve!$L$4:$U$4,0))<$E7)+(INDEX(Curve!$L$16:$U$23,8,MATCH($C7,Curve!$L$4:$U$4,0))<$E7)>8,"beyond inventory",INDEX(Curve!$D$16:$D$23,1+(INDEX(Curve!$L$16:$U$23,1,MATCH($C7,Curve!$L$4:$U$4,0))<$E7)+(INDEX(Curve!$L$16:$U$23,2,MATCH($C7,Curve!$L$4:$U$4,0))<$E7)+(INDEX(Curve!$L$16:$U$23,3,MATCH($C7,Curve!$L$4:$U$4,0))<$E7)+(INDEX(Curve!$L$16:$U$23,4,MATCH($C7,Curve!$L$4:$U$4,0))<$E7)+(INDEX(Curve!$L$16:$U$23,5,MATCH($C7,Curve!$L$4:$U$4,0))<$E7)+(INDEX(Curve!$L$16:$U$23,6,MATCH($C7,Curve!$L$4:$U$4,0))<$E7)+(INDEX(Curve!$L$16:$U$23,7,MATCH($C7,Curve!$L$4:$U$4,0))<$E7)+(INDEX(Curve!$L$16:$U$23,8,MATCH($C7,Curve!$L$4:$U$4,0))<$E7))))) | K7: =IF(NOT(ISNUMBER(($D7+$E7))),"-",IF(($D7+$E7)<=0,"-",IF(1+(INDEX(Curve!$L$16:$U$23,1,MATCH($C7,Curve!$L$4:$U$4,0))<($D7+$E7))+(INDEX(Curve!$L$16:$U$23,2,MATCH($C7,Curve!$L$4:$U$4,0))<($D7+$E7))+(INDEX(Curve!$L$16:$U$23,3,MATCH($C7,Curve!$L$4:$U$4,0))<($D7+$E7))+(INDEX(Curve!$L$16:$U$23,4,MATCH($C7,Curve!$L$4:$U$4,0))<($D7+$E7))+(INDEX(Curve!$L$16:$U$23,5,MATCH($C7,Curve!$L$4:$U$4,0))<($D7+$E7))+(INDEX(Curve!$L$16:$U$23,6,MATCH($C7,Curve!$L$4:$U$4,0))<($D7+$E7))+(INDEX(Curve!$L$16:$U$23,7,MATCH($C7,Curve!$L$4:$U$4,0))<($D7+$E7))+(INDEX(Curve!$L$16:$U$23,8,MATCH($C7,Curve!$L$4:$U$4,0))<($D7+$E7))>8,"beyond inventory",INDEX(Curve!$D$16:$D$23,1+(INDEX(Curve!$L$16:$U$23,1,MATCH($C7,Curve!$L$4:$U$4,0))<($D7+$E7))+(INDEX(Curve!$L$16:$U$23,2,MATCH($C7,Curve!$L$4:$U$4,0))<($D7+$E7))+(INDEX(Curve!$L$16:$U$23,3,MATCH($C7,Curve!$L$4:$U$4,0))<($D7+$E7))+(INDEX(Curve!$L$16:$U$23,4,MATCH($C7,Curve!$L$4:$U$4,0))<($D7+$E7))+(INDEX(Curve!$L$16:$U$23,5,MATCH($C7,Curve!$L$4:$U$4,0))<($D7+$E7))+(INDEX(Curve!$L$16:$U$23,6,MATCH($C7,Curve!$L$4:$U$4,0))<($D7+$E7))+(INDEX(Curve!$L$16:$U$23,7,MATCH($C7,Curve!$L$4:$U$4,0))<($D7+$E7))+(INDEX(Curve!$L$16:$U$23,8,MATCH($C7,Curve!$L$4:$U$4,0))<($D7+$E7)))))) | L7: =IF(NOT(ISNUMBER(($D7+F7))),"-",IF(($D7+F7)<=0,"-",IF(1+(INDEX(Curve!$L$16:$U$23,1,MATCH($C7,Curve!$L$4:$U$4,0))<($D7+F7))+(INDEX(Curve!$L$16:$U$23,2,MATCH($C7,Curve!$L$4:$U$4,0))<($D7+F7))+(INDEX(Curve!$L$16:$U$23,3,MATCH($C7,Curve!$L$4:$U$4,0))<($D7+F7))+(INDEX(Curve!$L$16:$U$23,4,MATCH($C7,Curve!$L$4:$U$4,0))<($D7+F7))+(INDEX(Curve!$L$16:$U$23,5,MATCH($C7,Curve!$L$4:$U$4,0))<($D7+F7))+(INDEX(Curve!$L$16:$U$23,6,MATCH($C7,Curve!$L$4:$U$4,0))<($D7+F7))+(INDEX(Curve!$L$16:$U$23,7,MATCH($C7,Curve!$L$4:$U$4,0))<($D7+F7))+(INDEX(Curve!$L$16:$U$23,8,MATCH($C7,Curve!$L$4:$U$4,0))<($D7+F7))>8,"beyond inventory",INDEX(Curve!$D$16:$D$23,1+(INDEX(Curve!$L$16:$U$23,1,MATCH($C7,Curve!$L$4:$U$4,0))<($D7+F7))+(INDEX(Curve!$L$16:$U$23,2,MATCH($C7,Curve!$L$4:$U$4,0))<($D7+F7))+(INDEX(Curve!$L$16:$U$23,3,MATCH($C7,Curve!$L$4:$U$4,0))<($D7+F7))+(INDEX(Curve!$L$16:$U$23,4,MATCH($C7,Curve!$L$4:$U$4,0))<($D7+F7))+(INDEX(Curve!$L$16:$U$23,5,MATCH($C7,Curve!$L$4:$U$4,0))<($D7+F7))+(INDEX(Curve!$L$16:$U$23,6,MATCH($C7,Curve!$L$4:$U$4,0))<($D7+F7))+(INDEX(Curve!$L$16:$U$23,7,MATCH($C7,Curve!$L$4:$U$4,0))<($D7+F7))+(INDEX(Curve!$L$16:$U$23,8,MATCH($C7,Curve!$L$4:$U$4,0))<($D7+F7)))))) | M7: =IF(NOT(ISNUMBER(($D7+G7))),"-",IF(($D7+G7)<=0,"-",IF(1+(INDEX(Curve!$L$16:$U$23,1,MATCH($C7,Curve!$L$4:$U$4,0))<($D7+G7))+(INDEX(Curve!$L$16:$U$23,2,MATCH($C7,Curve!$L$4:$U$4,0))<($D7+G7))+(INDEX(Curve!$L$16:$U$23,3,MATCH($C7,Curve!$L$4:$U$4,0))<($D7+G7))+(INDEX(Curve!$L$16:$U$23,4,MATCH($C7,Curve!$L$4:$U$4,0))<($D7+G7))+(INDEX(Curve!$L$16:$U$23,5,MATCH($C7,Curve!$L$4:$U$4,0))<($D7+G7))+(INDEX(Curve!$L$16:$U$23,6,MATCH($C7,Curve!$L$4:$U$4,0))<($D7+G7))+(INDEX(Curve!$L$16:$U$23,7,MATCH($C7,Curve!$L$4:$U$4,0))<($D7+G7))+(INDEX(Curve!$L$16:$U$23,8,MATCH($C7,Curve!$L$4:$U$4,0))<($D7+G7))>8,"beyond inventory",INDEX(Curve!$D$16:$D$23,1+(INDEX(Curve!$L$16:$U$23,1,MATCH($C7,Curve!$L$4:$U$4,0))<($D7+G7))+(INDEX(Curve!$L$16:$U$23,2,MATCH($C7,Curve!$L$4:$U$4,0))<($D7+G7))+(INDEX(Curve!$L$16:$U$23,3,MATCH($C7,Curve!$L$4:$U$4,0))<($D7+G7))+(INDEX(Curve!$L$16:$U$23,4,MATCH($C7,Curve!$L$4:$U$4,0))<($D7+G7))+(INDEX(Curve!$L$16:$U$23,5,MATCH($C7,Curve!$L$4:$U$4,0))<($D7+G7))+(INDEX(Curve!$L$16:$U$23,6,MATCH($C7,Curve!$L$4:$U$4,0))<($D7+G7))+(INDEX(Curve!$L$16:$U$23,7,MATCH($C7,Curve!$L$4:$U$4,0))<($D7+G7))+(INDEX(Curve!$L$16:$U$23,8,MATCH($C7,Curve!$L$4:$U$4,0))<($D7+G7)))))) | N7: =IF(NOT(ISNUMBER(($D7+H7))),"-",IF(($D7+H7)<=0,"-",IF(1+(INDEX(Curve!$L$16:$U$23,1,MATCH($C7,Curve!$L$4:$U$4,0))<($D7+H7))+(INDEX(Curve!$L$16:$U$23,2,MATCH($C7,Curve!$L$4:$U$4,0))<($D7+H7))+(INDEX(Curve!$L$16:$U$23,3,MATCH($C7,Curve!$L$4:$U$4,0))<($D7+H7))+(INDEX(Curve!$L$16:$U$23,4,MATCH($C7,Curve!$L$4:$U$4,0))<($D7+H7))+(INDEX(Curve!$L$16:$U$23,5,MATCH($C7,Curve!$L$4:$U$4,0))<($D7+H7))+(INDEX(Curve!$L$16:$U$23,6,MATCH($C7,Curve!$L$4:$U$4,0))<($D7+H7))+(INDEX(Curve!$L$16:$U$23,7,MATCH($C7,Curve!$L$4:$U$4,0))<($D7+H7))+(INDEX(Curve!$L$16:$U$23,8,MATCH($C7,Curve!$L$4:$U$4,0))<($D7+H7))>8,"beyond inventory",INDEX(Curve!$D$16:$D$23,1+(INDEX(Curve!$L$16:$U$23,1,MATCH($C7,Curve!$L$4:$U$4,0))<($D7+H7))+(INDEX(Curve!$L$16:$U$23,2,MATCH($C7,Curve!$L$4:$U$4,0))<($D7+H7))+(INDEX(Curve!$L$16:$U$23,3,MATCH($C7,Curve!$L$4:$U$4,0))<($D7+H7))+(INDEX(Curve!$L$16:$U$23,4,MATCH($C7,Curve!$L$4:$U$4,0))<($D7+H7))+(INDEX(Curve!$L$16:$U$23,5,MATCH($C7,Curve!$L$4:$U$4,0))<($D7+H7))+(INDEX(Curve!$L$16:$U$23,6,MATCH($C7,Curve!$L$4:$U$4,0))<($D7+H7))+(INDEX(Curve!$L$16:$U$23,7,MATCH($C7,Curve!$L$4:$U$4,0))<($D7+H7))+(INDEX(Curve!$L$16:$U$23,8,MATCH($C7,Curve!$L$4:$U$4,0))<($D7+H7)))))) | O7: =IF(NOT(ISNUMBER(($D7+I7))),"-",IF(($D7+I7)<=0,"-",IF(1+(INDEX(Curve!$L$16:$U$23,1,MATCH($C7,Curve!$L$4:$U$4,0))<($D7+I7))+(INDEX(Curve!$L$16:$U$23,2,MATCH($C7,Curve!$L$4:$U$4,0))<($D7+I7))+(INDEX(Curve!$L$16:$U$23,3,MATCH($C7,Curve!$L$4:$U$4,0))<($D7+I7))+(INDEX(Curve!$L$16:$U$23,4,MATCH($C7,Curve!$L$4:$U$4,0))<($D7+I7))+(INDEX(Curve!$L$16:$U$23,5,MATCH($C7,Curve!$L$4:$U$4,0))<($D7+I7))+(INDEX(Curve!$L$16:$U$23,6,MATCH($C7,Curve!$L$4:$U$4,0))<($D7+I7))+(INDEX(Curve!$L$16:$U$23,7,MATCH($C7,Curve!$L$4:$U$4,0))<($D7+I7))+(INDEX(Curve!$L$16:$U$23,8,MATCH($C7,Curve!$L$4:$U$4,0))<($D7+I7))>8,"beyond inventory",INDEX(Curve!$D$16:$D$23,1+(INDEX(Curve!$L$16:$U$23,1,MATCH($C7,Curve!$L$4:$U$4,0))<($D7+I7))+(INDEX(Curve!$L$16:$U$23,2,MATCH($C7,Curve!$L$4:$U$4,0))<($D7+I7))+(INDEX(Curve!$L$16:$U$23,3,MATCH($C7,Curve!$L$4:$U$4,0))<($D7+I7))+(INDEX(Curve!$L$16:$U$23,4,MATCH($C7,Curve!$L$4:$U$4,0))<($D7+I7))+(INDEX(Curve!$L$16:$U$23,5,MATCH($C7,Curve!$L$4:$U$4,0))<($D7+I7))+(INDEX(Curve!$L$16:$U$23,6,MATCH($C7,Curve!$L$4:$U$4,0))<($D7+I7))+(INDEX(Curve!$L$16:$U$23,7,MATCH($C7,Curve!$L$4:$U$4,0))<($D7+I7))+(INDEX(Curve!$L$16:$U$23,8,MATCH($C7,Curve!$L$4:$U$4,0))<($D7+I7)))))) | P7: ='Henry Hub'!$B$3 | Q7: =IF(ISNUMBER(K7),K7-P7,"-")
A8: Base | B8: Dec 2030 | C8: 5 | D8: ='Gulf key question'!C6 | E8: ='Gulf key question'!D6 | F8: ='Gulf key question'!F6 | G8: ='Gulf key question'!G6 | H8: ='Gulf key question'!H6 | I8: ='Gulf key question'!I6 | J8: =IF(NOT(ISNUMBER($E8)),"-",IF($E8<=0,"-",IF(1+(INDEX(Curve!$L$16:$U$23,1,MATCH($C8,Curve!$L$4:$U$4,0))<$E8)+(INDEX(Curve!$L$16:$U$23,2,MATCH($C8,Curve!$L$4:$U$4,0))<$E8)+(INDEX(Curve!$L$16:$U$23,3,MATCH($C8,Curve!$L$4:$U$4,0))<$E8)+(INDEX(Curve!$L$16:$U$23,4,MATCH($C8,Curve!$L$4:$U$4,0))<$E8)+(INDEX(Curve!$L$16:$U$23,5,MATCH($C8,Curve!$L$4:$U$4,0))<$E8)+(INDEX(Curve!$L$16:$U$23,6,MATCH($C8,Curve!$L$4:$U$4,0))<$E8)+(INDEX(Curve!$L$16:$U$23,7,MATCH($C8,Curve!$L$4:$U$4,0))<$E8)+(INDEX(Curve!$L$16:$U$23,8,MATCH($C8,Curve!$L$4:$U$4,0))<$E8)>8,"beyond inventory",INDEX(Curve!$D$16:$D$23,1+(INDEX(Curve!$L$16:$U$23,1,MATCH($C8,Curve!$L$4:$U$4,0))<$E8)+(INDEX(Curve!$L$16:$U$23,2,MATCH($C8,Curve!$L$4:$U$4,0))<$E8)+(INDEX(Curve!$L$16:$U$23,3,MATCH($C8,Curve!$L$4:$U$4,0))<$E8)+(INDEX(Curve!$L$16:$U$23,4,MATCH($C8,Curve!$L$4:$U$4,0))<$E8)+(INDEX(Curve!$L$16:$U$23,5,MATCH($C8,Curve!$L$4:$U$4,0))<$E8)+(INDEX(Curve!$L$16:$U$23,6,MATCH($C8,Curve!$L$4:$U$4,0))<$E8)+(INDEX(Curve!$L$16:$U$23,7,MATCH($C8,Curve!$L$4:$U$4,0))<$E8)+(INDEX(Curve!$L$16:$U$23,8,MATCH($C8,Curve!$L$4:$U$4,0))<$E8))))) | K8: =IF(NOT(ISNUMBER(($D8+$E8))),"-",IF(($D8+$E8)<=0,"-",IF(1+(INDEX(Curve!$L$16:$U$23,1,MATCH($C8,Curve!$L$4:$U$4,0))<($D8+$E8))+(INDEX(Curve!$L$16:$U$23,2,MATCH($C8,Curve!$L$4:$U$4,0))<($D8+$E8))+(INDEX(Curve!$L$16:$U$23,3,MATCH($C8,Curve!$L$4:$U$4,0))<($D8+$E8))+(INDEX(Curve!$L$16:$U$23,4,MATCH($C8,Curve!$L$4:$U$4,0))<($D8+$E8))+(INDEX(Curve!$L$16:$U$23,5,MATCH($C8,Curve!$L$4:$U$4,0))<($D8+$E8))+(INDEX(Curve!$L$16:$U$23,6,MATCH($C8,Curve!$L$4:$U$4,0))<($D8+$E8))+(INDEX(Curve!$L$16:$U$23,7,MATCH($C8,Curve!$L$4:$U$4,0))<($D8+$E8))+(INDEX(Curve!$L$16:$U$23,8,MATCH($C8,Curve!$L$4:$U$4,0))<($D8+$E8))>8,"beyond inventory",INDEX(Curve!$D$16:$D$23,1+(INDEX(Curve!$L$16:$U$23,1,MATCH($C8,Curve!$L$4:$U$4,0))<($D8+$E8))+(INDEX(Curve!$L$16:$U$23,2,MATCH($C8,Curve!$L$4:$U$4,0))<($D8+$E8))+(INDEX(Curve!$L$16:$U$23,3,MATCH($C8,Curve!$L$4:$U$4,0))<($D8+$E8))+(INDEX(Curve!$L$16:$U$23,4,MATCH($C8,Curve!$L$4:$U$4,0))<($D8+$E8))+(INDEX(Curve!$L$16:$U$23,5,MATCH($C8,Curve!$L$4:$U$4,0))<($D8+$E8))+(INDEX(Curve!$L$16:$U$23,6,MATCH($C8,Curve!$L$4:$U$4,0))<($D8+$E8))+(INDEX(Curve!$L$16:$U$23,7,MATCH($C8,Curve!$L$4:$U$4,0))<($D8+$E8))+(INDEX(Curve!$L$16:$U$23,8,MATCH($C8,Curve!$L$4:$U$4,0))<($D8+$E8)))))) | L8: =IF(NOT(ISNUMBER(($D8+F8))),"-",IF(($D8+F8)<=0,"-",IF(1+(INDEX(Curve!$L$16:$U$23,1,MATCH($C8,Curve!$L$4:$U$4,0))<($D8+F8))+(INDEX(Curve!$L$16:$U$23,2,MATCH($C8,Curve!$L$4:$U$4,0))<($D8+F8))+(INDEX(Curve!$L$16:$U$23,3,MATCH($C8,Curve!$L$4:$U$4,0))<($D8+F8))+(INDEX(Curve!$L$16:$U$23,4,MATCH($C8,Curve!$L$4:$U$4,0))<($D8+F8))+(INDEX(Curve!$L$16:$U$23,5,MATCH($C8,Curve!$L$4:$U$4,0))<($D8+F8))+(INDEX(Curve!$L$16:$U$23,6,MATCH($C8,Curve!$L$4:$U$4,0))<($D8+F8))+(INDEX(Curve!$L$16:$U$23,7,MATCH($C8,Curve!$L$4:$U$4,0))<($D8+F8))+(INDEX(Curve!$L$16:$U$23,8,MATCH($C8,Curve!$L$4:$U$4,0))<($D8+F8))>8,"beyond inventory",INDEX(Curve!$D$16:$D$23,1+(INDEX(Curve!$L$16:$U$23,1,MATCH($C8,Curve!$L$4:$U$4,0))<($D8+F8))+(INDEX(Curve!$L$16:$U$23,2,MATCH($C8,Curve!$L$4:$U$4,0))<($D8+F8))+(INDEX(Curve!$L$16:$U$23,3,MATCH($C8,Curve!$L$4:$U$4,0))<($D8+F8))+(INDEX(Curve!$L$16:$U$23,4,MATCH($C8,Curve!$L$4:$U$4,0))<($D8+F8))+(INDEX(Curve!$L$16:$U$23,5,MATCH($C8,Curve!$L$4:$U$4,0))<($D8+F8))+(INDEX(Curve!$L$16:$U$23,6,MATCH($C8,Curve!$L$4:$U$4,0))<($D8+F8))+(INDEX(Curve!$L$16:$U$23,7,MATCH($C8,Curve!$L$4:$U$4,0))<($D8+F8))+(INDEX(Curve!$L$16:$U$23,8,MATCH($C8,Curve!$L$4:$U$4,0))<($D8+F8)))))) | M8: =IF(NOT(ISNUMBER(($D8+G8))),"-",IF(($D8+G8)<=0,"-",IF(1+(INDEX(Curve!$L$16:$U$23,1,MATCH($C8,Curve!$L$4:$U$4,0))<($D8+G8))+(INDEX(Curve!$L$16:$U$23,2,MATCH($C8,Curve!$L$4:$U$4,0))<($D8+G8))+(INDEX(Curve!$L$16:$U$23,3,MATCH($C8,Curve!$L$4:$U$4,0))<($D8+G8))+(INDEX(Curve!$L$16:$U$23,4,MATCH($C8,Curve!$L$4:$U$4,0))<($D8+G8))+(INDEX(Curve!$L$16:$U$23,5,MATCH($C8,Curve!$L$4:$U$4,0))<($D8+G8))+(INDEX(Curve!$L$16:$U$23,6,MATCH($C8,Curve!$L$4:$U$4,0))<($D8+G8))+(INDEX(Curve!$L$16:$U$23,7,MATCH($C8,Curve!$L$4:$U$4,0))<($D8+G8))+(INDEX(Curve!$L$16:$U$23,8,MATCH($C8,Curve!$L$4:$U$4,0))<($D8+G8))>8,"beyond inventory",INDEX(Curve!$D$16:$D$23,1+(INDEX(Curve!$L$16:$U$23,1,MATCH($C8,Curve!$L$4:$U$4,0))<($D8+G8))+(INDEX(Curve!$L$16:$U$23,2,MATCH($C8,Curve!$L$4:$U$4,0))<($D8+G8))+(INDEX(Curve!$L$16:$U$23,3,MATCH($C8,Curve!$L$4:$U$4,0))<($D8+G8))+(INDEX(Curve!$L$16:$U$23,4,MATCH($C8,Curve!$L$4:$U$4,0))<($D8+G8))+(INDEX(Curve!$L$16:$U$23,5,MATCH($C8,Curve!$L$4:$U$4,0))<($D8+G8))+(INDEX(Curve!$L$16:$U$23,6,MATCH($C8,Curve!$L$4:$U$4,0))<($D8+G8))+(INDEX(Curve!$L$16:$U$23,7,MATCH($C8,Curve!$L$4:$U$4,0))<($D8+G8))+(INDEX(Curve!$L$16:$U$23,8,MATCH($C8,Curve!$L$4:$U$4,0))<($D8+G8)))))) | N8: =IF(NOT(ISNUMBER(($D8+H8))),"-",IF(($D8+H8)<=0,"-",IF(1+(INDEX(Curve!$L$16:$U$23,1,MATCH($C8,Curve!$L$4:$U$4,0))<($D8+H8))+(INDEX(Curve!$L$16:$U$23,2,MATCH($C8,Curve!$L$4:$U$4,0))<($D8+H8))+(INDEX(Curve!$L$16:$U$23,3,MATCH($C8,Curve!$L$4:$U$4,0))<($D8+H8))+(INDEX(Curve!$L$16:$U$23,4,MATCH($C8,Curve!$L$4:$U$4,0))<($D8+H8))+(INDEX(Curve!$L$16:$U$23,5,MATCH($C8,Curve!$L$4:$U$4,0))<($D8+H8))+(INDEX(Curve!$L$16:$U$23,6,MATCH($C8,Curve!$L$4:$U$4,0))<($D8+H8))+(INDEX(Curve!$L$16:$U$23,7,MATCH($C8,Curve!$L$4:$U$4,0))<($D8+H8))+(INDEX(Curve!$L$16:$U$23,8,MATCH($C8,Curve!$L$4:$U$4,0))<($D8+H8))>8,"beyond inventory",INDEX(Curve!$D$16:$D$23,1+(INDEX(Curve!$L$16:$U$23,1,MATCH($C8,Curve!$L$4:$U$4,0))<($D8+H8))+(INDEX(Curve!$L$16:$U$23,2,MATCH($C8,Curve!$L$4:$U$4,0))<($D8+H8))+(INDEX(Curve!$L$16:$U$23,3,MATCH($C8,Curve!$L$4:$U$4,0))<($D8+H8))+(INDEX(Curve!$L$16:$U$23,4,MATCH($C8,Curve!$L$4:$U$4,0))<($D8+H8))+(INDEX(Curve!$L$16:$U$23,5,MATCH($C8,Curve!$L$4:$U$4,0))<($D8+H8))+(INDEX(Curve!$L$16:$U$23,6,MATCH($C8,Curve!$L$4:$U$4,0))<($D8+H8))+(INDEX(Curve!$L$16:$U$23,7,MATCH($C8,Curve!$L$4:$U$4,0))<($D8+H8))+(INDEX(Curve!$L$16:$U$23,8,MATCH($C8,Curve!$L$4:$U$4,0))<($D8+H8)))))) | O8: =IF(NOT(ISNUMBER(($D8+I8))),"-",IF(($D8+I8)<=0,"-",IF(1+(INDEX(Curve!$L$16:$U$23,1,MATCH($C8,Curve!$L$4:$U$4,0))<($D8+I8))+(INDEX(Curve!$L$16:$U$23,2,MATCH($C8,Curve!$L$4:$U$4,0))<($D8+I8))+(INDEX(Curve!$L$16:$U$23,3,MATCH($C8,Curve!$L$4:$U$4,0))<($D8+I8))+(INDEX(Curve!$L$16:$U$23,4,MATCH($C8,Curve!$L$4:$U$4,0))<($D8+I8))+(INDEX(Curve!$L$16:$U$23,5,MATCH($C8,Curve!$L$4:$U$4,0))<($D8+I8))+(INDEX(Curve!$L$16:$U$23,6,MATCH($C8,Curve!$L$4:$U$4,0))<($D8+I8))+(INDEX(Curve!$L$16:$U$23,7,MATCH($C8,Curve!$L$4:$U$4,0))<($D8+I8))+(INDEX(Curve!$L$16:$U$23,8,MATCH($C8,Curve!$L$4:$U$4,0))<($D8+I8))>8,"beyond inventory",INDEX(Curve!$D$16:$D$23,1+(INDEX(Curve!$L$16:$U$23,1,MATCH($C8,Curve!$L$4:$U$4,0))<($D8+I8))+(INDEX(Curve!$L$16:$U$23,2,MATCH($C8,Curve!$L$4:$U$4,0))<($D8+I8))+(INDEX(Curve!$L$16:$U$23,3,MATCH($C8,Curve!$L$4:$U$4,0))<($D8+I8))+(INDEX(Curve!$L$16:$U$23,4,MATCH($C8,Curve!$L$4:$U$4,0))<($D8+I8))+(INDEX(Curve!$L$16:$U$23,5,MATCH($C8,Curve!$L$4:$U$4,0))<($D8+I8))+(INDEX(Curve!$L$16:$U$23,6,MATCH($C8,Curve!$L$4:$U$4,0))<($D8+I8))+(INDEX(Curve!$L$16:$U$23,7,MATCH($C8,Curve!$L$4:$U$4,0))<($D8+I8))+(INDEX(Curve!$L$16:$U$23,8,MATCH($C8,Curve!$L$4:$U$4,0))<($D8+I8)))))) | P8: ='Henry Hub'!$B$3 | Q8: =IF(ISNUMBER(K8),K8-P8,"-")
A9: Base | B9: Dec 2033 | C9: 8 | D9: ='Gulf key question'!C9 | E9: ='Gulf key question'!D9 | F9: ='Gulf key question'!F9 | G9: ='Gulf key question'!G9 | H9: ='Gulf key question'!H9 | I9: ='Gulf key question'!I9 | J9: =IF(NOT(ISNUMBER($E9)),"-",IF($E9<=0,"-",IF(1+(INDEX(Curve!$L$16:$U$23,1,MATCH($C9,Curve!$L$4:$U$4,0))<$E9)+(INDEX(Curve!$L$16:$U$23,2,MATCH($C9,Curve!$L$4:$U$4,0))<$E9)+(INDEX(Curve!$L$16:$U$23,3,MATCH($C9,Curve!$L$4:$U$4,0))<$E9)+(INDEX(Curve!$L$16:$U$23,4,MATCH($C9,Curve!$L$4:$U$4,0))<$E9)+(INDEX(Curve!$L$16:$U$23,5,MATCH($C9,Curve!$L$4:$U$4,0))<$E9)+(INDEX(Curve!$L$16:$U$23,6,MATCH($C9,Curve!$L$4:$U$4,0))<$E9)+(INDEX(Curve!$L$16:$U$23,7,MATCH($C9,Curve!$L$4:$U$4,0))<$E9)+(INDEX(Curve!$L$16:$U$23,8,MATCH($C9,Curve!$L$4:$U$4,0))<$E9)>8,"beyond inventory",INDEX(Curve!$D$16:$D$23,1+(INDEX(Curve!$L$16:$U$23,1,MATCH($C9,Curve!$L$4:$U$4,0))<$E9)+(INDEX(Curve!$L$16:$U$23,2,MATCH($C9,Curve!$L$4:$U$4,0))<$E9)+(INDEX(Curve!$L$16:$U$23,3,MATCH($C9,Curve!$L$4:$U$4,0))<$E9)+(INDEX(Curve!$L$16:$U$23,4,MATCH($C9,Curve!$L$4:$U$4,0))<$E9)+(INDEX(Curve!$L$16:$U$23,5,MATCH($C9,Curve!$L$4:$U$4,0))<$E9)+(INDEX(Curve!$L$16:$U$23,6,MATCH($C9,Curve!$L$4:$U$4,0))<$E9)+(INDEX(Curve!$L$16:$U$23,7,MATCH($C9,Curve!$L$4:$U$4,0))<$E9)+(INDEX(Curve!$L$16:$U$23,8,MATCH($C9,Curve!$L$4:$U$4,0))<$E9))))) | K9: =IF(NOT(ISNUMBER(($D9+$E9))),"-",IF(($D9+$E9)<=0,"-",IF(1+(INDEX(Curve!$L$16:$U$23,1,MATCH($C9,Curve!$L$4:$U$4,0))<($D9+$E9))+(INDEX(Curve!$L$16:$U$23,2,MATCH($C9,Curve!$L$4:$U$4,0))<($D9+$E9))+(INDEX(Curve!$L$16:$U$23,3,MATCH($C9,Curve!$L$4:$U$4,0))<($D9+$E9))+(INDEX(Curve!$L$16:$U$23,4,MATCH($C9,Curve!$L$4:$U$4,0))<($D9+$E9))+(INDEX(Curve!$L$16:$U$23,5,MATCH($C9,Curve!$L$4:$U$4,0))<($D9+$E9))+(INDEX(Curve!$L$16:$U$23,6,MATCH($C9,Curve!$L$4:$U$4,0))<($D9+$E9))+(INDEX(Curve!$L$16:$U$23,7,MATCH($C9,Curve!$L$4:$U$4,0))<($D9+$E9))+(INDEX(Curve!$L$16:$U$23,8,MATCH($C9,Curve!$L$4:$U$4,0))<($D9+$E9))>8,"beyond inventory",INDEX(Curve!$D$16:$D$23,1+(INDEX(Curve!$L$16:$U$23,1,MATCH($C9,Curve!$L$4:$U$4,0))<($D9+$E9))+(INDEX(Curve!$L$16:$U$23,2,MATCH($C9,Curve!$L$4:$U$4,0))<($D9+$E9))+(INDEX(Curve!$L$16:$U$23,3,MATCH($C9,Curve!$L$4:$U$4,0))<($D9+$E9))+(INDEX(Curve!$L$16:$U$23,4,MATCH($C9,Curve!$L$4:$U$4,0))<($D9+$E9))+(INDEX(Curve!$L$16:$U$23,5,MATCH($C9,Curve!$L$4:$U$4,0))<($D9+$E9))+(INDEX(Curve!$L$16:$U$23,6,MATCH($C9,Curve!$L$4:$U$4,0))<($D9+$E9))+(INDEX(Curve!$L$16:$U$23,7,MATCH($C9,Curve!$L$4:$U$4,0))<($D9+$E9))+(INDEX(Curve!$L$16:$U$23,8,MATCH($C9,Curve!$L$4:$U$4,0))<($D9+$E9)))))) | L9: =IF(NOT(ISNUMBER(($D9+F9))),"-",IF(($D9+F9)<=0,"-",IF(1+(INDEX(Curve!$L$16:$U$23,1,MATCH($C9,Curve!$L$4:$U$4,0))<($D9+F9))+(INDEX(Curve!$L$16:$U$23,2,MATCH($C9,Curve!$L$4:$U$4,0))<($D9+F9))+(INDEX(Curve!$L$16:$U$23,3,MATCH($C9,Curve!$L$4:$U$4,0))<($D9+F9))+(INDEX(Curve!$L$16:$U$23,4,MATCH($C9,Curve!$L$4:$U$4,0))<($D9+F9))+(INDEX(Curve!$L$16:$U$23,5,MATCH($C9,Curve!$L$4:$U$4,0))<($D9+F9))+(INDEX(Curve!$L$16:$U$23,6,MATCH($C9,Curve!$L$4:$U$4,0))<($D9+F9))+(INDEX(Curve!$L$16:$U$23,7,MATCH($C9,Curve!$L$4:$U$4,0))<($D9+F9))+(INDEX(Curve!$L$16:$U$23,8,MATCH($C9,Curve!$L$4:$U$4,0))<($D9+F9))>8,"beyond inventory",INDEX(Curve!$D$16:$D$23,1+(INDEX(Curve!$L$16:$U$23,1,MATCH($C9,Curve!$L$4:$U$4,0))<($D9+F9))+(INDEX(Curve!$L$16:$U$23,2,MATCH($C9,Curve!$L$4:$U$4,0))<($D9+F9))+(INDEX(Curve!$L$16:$U$23,3,MATCH($C9,Curve!$L$4:$U$4,0))<($D9+F9))+(INDEX(Curve!$L$16:$U$23,4,MATCH($C9,Curve!$L$4:$U$4,0))<($D9+F9))+(INDEX(Curve!$L$16:$U$23,5,MATCH($C9,Curve!$L$4:$U$4,0))<($D9+F9))+(INDEX(Curve!$L$16:$U$23,6,MATCH($C9,Curve!$L$4:$U$4,0))<($D9+F9))+(INDEX(Curve!$L$16:$U$23,7,MATCH($C9,Curve!$L$4:$U$4,0))<($D9+F9))+(INDEX(Curve!$L$16:$U$23,8,MATCH($C9,Curve!$L$4:$U$4,0))<($D9+F9)))))) | M9: =IF(NOT(ISNUMBER(($D9+G9))),"-",IF(($D9+G9)<=0,"-",IF(1+(INDEX(Curve!$L$16:$U$23,1,MATCH($C9,Curve!$L$4:$U$4,0))<($D9+G9))+(INDEX(Curve!$L$16:$U$23,2,MATCH($C9,Curve!$L$4:$U$4,0))<($D9+G9))+(INDEX(Curve!$L$16:$U$23,3,MATCH($C9,Curve!$L$4:$U$4,0))<($D9+G9))+(INDEX(Curve!$L$16:$U$23,4,MATCH($C9,Curve!$L$4:$U$4,0))<($D9+G9))+(INDEX(Curve!$L$16:$U$23,5,MATCH($C9,Curve!$L$4:$U$4,0))<($D9+G9))+(INDEX(Curve!$L$16:$U$23,6,MATCH($C9,Curve!$L$4:$U$4,0))<($D9+G9))+(INDEX(Curve!$L$16:$U$23,7,MATCH($C9,Curve!$L$4:$U$4,0))<($D9+G9))+(INDEX(Curve!$L$16:$U$23,8,MATCH($C9,Curve!$L$4:$U$4,0))<($D9+G9))>8,"beyond inventory",INDEX(Curve!$D$16:$D$23,1+(INDEX(Curve!$L$16:$U$23,1,MATCH($C9,Curve!$L$4:$U$4,0))<($D9+G9))+(INDEX(Curve!$L$16:$U$23,2,MATCH($C9,Curve!$L$4:$U$4,0))<($D9+G9))+(INDEX(Curve!$L$16:$U$23,3,MATCH($C9,Curve!$L$4:$U$4,0))<($D9+G9))+(INDEX(Curve!$L$16:$U$23,4,MATCH($C9,Curve!$L$4:$U$4,0))<($D9+G9))+(INDEX(Curve!$L$16:$U$23,5,MATCH($C9,Curve!$L$4:$U$4,0))<($D9+G9))+(INDEX(Curve!$L$16:$U$23,6,MATCH($C9,Curve!$L$4:$U$4,0))<($D9+G9))+(INDEX(Curve!$L$16:$U$23,7,MATCH($C9,Curve!$L$4:$U$4,0))<($D9+G9))+(INDEX(Curve!$L$16:$U$23,8,MATCH($C9,Curve!$L$4:$U$4,0))<($D9+G9)))))) | N9: =IF(NOT(ISNUMBER(($D9+H9))),"-",IF(($D9+H9)<=0,"-",IF(1+(INDEX(Curve!$L$16:$U$23,1,MATCH($C9,Curve!$L$4:$U$4,0))<($D9+H9))+(INDEX(Curve!$L$16:$U$23,2,MATCH($C9,Curve!$L$4:$U$4,0))<($D9+H9))+(INDEX(Curve!$L$16:$U$23,3,MATCH($C9,Curve!$L$4:$U$4,0))<($D9+H9))+(INDEX(Curve!$L$16:$U$23,4,MATCH($C9,Curve!$L$4:$U$4,0))<($D9+H9))+(INDEX(Curve!$L$16:$U$23,5,MATCH($C9,Curve!$L$4:$U$4,0))<($D9+H9))+(INDEX(Curve!$L$16:$U$23,6,MATCH($C9,Curve!$L$4:$U$4,0))<($D9+H9))+(INDEX(Curve!$L$16:$U$23,7,MATCH($C9,Curve!$L$4:$U$4,0))<($D9+H9))+(INDEX(Curve!$L$16:$U$23,8,MATCH($C9,Curve!$L$4:$U$4,0))<($D9+H9))>8,"beyond inventory",INDEX(Curve!$D$16:$D$23,1+(INDEX(Curve!$L$16:$U$23,1,MATCH($C9,Curve!$L$4:$U$4,0))<($D9+H9))+(INDEX(Curve!$L$16:$U$23,2,MATCH($C9,Curve!$L$4:$U$4,0))<($D9+H9))+(INDEX(Curve!$L$16:$U$23,3,MATCH($C9,Curve!$L$4:$U$4,0))<($D9+H9))+(INDEX(Curve!$L$16:$U$23,4,MATCH($C9,Curve!$L$4:$U$4,0))<($D9+H9))+(INDEX(Curve!$L$16:$U$23,5,MATCH($C9,Curve!$L$4:$U$4,0))<($D9+H9))+(INDEX(Curve!$L$16:$U$23,6,MATCH($C9,Curve!$L$4:$U$4,0))<($D9+H9))+(INDEX(Curve!$L$16:$U$23,7,MATCH($C9,Curve!$L$4:$U$4,0))<($D9+H9))+(INDEX(Curve!$L$16:$U$23,8,MATCH($C9,Curve!$L$4:$U$4,0))<($D9+H9)))))) | O9: =IF(NOT(ISNUMBER(($D9+I9))),"-",IF(($D9+I9)<=0,"-",IF(1+(INDEX(Curve!$L$16:$U$23,1,MATCH($C9,Curve!$L$4:$U$4,0))<($D9+I9))+(INDEX(Curve!$L$16:$U$23,2,MATCH($C9,Curve!$L$4:$U$4,0))<($D9+I9))+(INDEX(Curve!$L$16:$U$23,3,MATCH($C9,Curve!$L$4:$U$4,0))<($D9+I9))+(INDEX(Curve!$L$16:$U$23,4,MATCH($C9,Curve!$L$4:$U$4,0))<($D9+I9))+(INDEX(Curve!$L$16:$U$23,5,MATCH($C9,Curve!$L$4:$U$4,0))<($D9+I9))+(INDEX(Curve!$L$16:$U$23,6,MATCH($C9,Curve!$L$4:$U$4,0))<($D9+I9))+(INDEX(Curve!$L$16:$U$23,7,MATCH($C9,Curve!$L$4:$U$4,0))<($D9+I9))+(INDEX(Curve!$L$16:$U$23,8,MATCH($C9,Curve!$L$4:$U$4,0))<($D9+I9))>8,"beyond inventory",INDEX(Curve!$D$16:$D$23,1+(INDEX(Curve!$L$16:$U$23,1,MATCH($C9,Curve!$L$4:$U$4,0))<($D9+I9))+(INDEX(Curve!$L$16:$U$23,2,MATCH($C9,Curve!$L$4:$U$4,0))<($D9+I9))+(INDEX(Curve!$L$16:$U$23,3,MATCH($C9,Curve!$L$4:$U$4,0))<($D9+I9))+(INDEX(Curve!$L$16:$U$23,4,MATCH($C9,Curve!$L$4:$U$4,0))<($D9+I9))+(INDEX(Curve!$L$16:$U$23,5,MATCH($C9,Curve!$L$4:$U$4,0))<($D9+I9))+(INDEX(Curve!$L$16:$U$23,6,MATCH($C9,Curve!$L$4:$U$4,0))<($D9+I9))+(INDEX(Curve!$L$16:$U$23,7,MATCH($C9,Curve!$L$4:$U$4,0))<($D9+I9))+(INDEX(Curve!$L$16:$U$23,8,MATCH($C9,Curve!$L$4:$U$4,0))<($D9+I9)))))) | P9: ='Henry Hub'!$B$3 | Q9: =IF(ISNUMBER(K9),K9-P9,"-")
A10: LNG and takeaway delayed 6 months | B10: Dec 2026 | C10: 1 | D10: ='Gulf key question'!C10 | E10: ='Gulf key question'!D10 | F10: ='Gulf key question'!F10 | G10: ='Gulf key question'!G10 | H10: ='Gulf key question'!H10 | I10: ='Gulf key question'!I10 | J10: =IF(NOT(ISNUMBER($E10)),"-",IF($E10<=0,"-",IF(1+(INDEX(Curve!$L$16:$U$23,1,MATCH($C10,Curve!$L$4:$U$4,0))<$E10)+(INDEX(Curve!$L$16:$U$23,2,MATCH($C10,Curve!$L$4:$U$4,0))<$E10)+(INDEX(Curve!$L$16:$U$23,3,MATCH($C10,Curve!$L$4:$U$4,0))<$E10)+(INDEX(Curve!$L$16:$U$23,4,MATCH($C10,Curve!$L$4:$U$4,0))<$E10)+(INDEX(Curve!$L$16:$U$23,5,MATCH($C10,Curve!$L$4:$U$4,0))<$E10)+(INDEX(Curve!$L$16:$U$23,6,MATCH($C10,Curve!$L$4:$U$4,0))<$E10)+(INDEX(Curve!$L$16:$U$23,7,MATCH($C10,Curve!$L$4:$U$4,0))<$E10)+(INDEX(Curve!$L$16:$U$23,8,MATCH($C10,Curve!$L$4:$U$4,0))<$E10)>8,"beyond inventory",INDEX(Curve!$D$16:$D$23,1+(INDEX(Curve!$L$16:$U$23,1,MATCH($C10,Curve!$L$4:$U$4,0))<$E10)+(INDEX(Curve!$L$16:$U$23,2,MATCH($C10,Curve!$L$4:$U$4,0))<$E10)+(INDEX(Curve!$L$16:$U$23,3,MATCH($C10,Curve!$L$4:$U$4,0))<$E10)+(INDEX(Curve!$L$16:$U$23,4,MATCH($C10,Curve!$L$4:$U$4,0))<$E10)+(INDEX(Curve!$L$16:$U$23,5,MATCH($C10,Curve!$L$4:$U$4,0))<$E10)+(INDEX(Curve!$L$16:$U$23,6,MATCH($C10,Curve!$L$4:$U$4,0))<$E10)+(INDEX(Curve!$L$16:$U$23,7,MATCH($C10,Curve!$L$4:$U$4,0))<$E10)+(INDEX(Curve!$L$16:$U$23,8,MATCH($C10,Curve!$L$4:$U$4,0))<$E10))))) | K10: =IF(NOT(ISNUMBER(($D10+$E10))),"-",IF(($D10+$E10)<=0,"-",IF(1+(INDEX(Curve!$L$16:$U$23,1,MATCH($C10,Curve!$L$4:$U$4,0))<($D10+$E10))+(INDEX(Curve!$L$16:$U$23,2,MATCH($C10,Curve!$L$4:$U$4,0))<($D10+$E10))+(INDEX(Curve!$L$16:$U$23,3,MATCH($C10,Curve!$L$4:$U$4,0))<($D10+$E10))+(INDEX(Curve!$L$16:$U$23,4,MATCH($C10,Curve!$L$4:$U$4,0))<($D10+$E10))+(INDEX(Curve!$L$16:$U$23,5,MATCH($C10,Curve!$L$4:$U$4,0))<($D10+$E10))+(INDEX(Curve!$L$16:$U$23,6,MATCH($C10,Curve!$L$4:$U$4,0))<($D10+$E10))+(INDEX(Curve!$L$16:$U$23,7,MATCH($C10,Curve!$L$4:$U$4,0))<($D10+$E10))+(INDEX(Curve!$L$16:$U$23,8,MATCH($C10,Curve!$L$4:$U$4,0))<($D10+$E10))>8,"beyond inventory",INDEX(Curve!$D$16:$D$23,1+(INDEX(Curve!$L$16:$U$23,1,MATCH($C10,Curve!$L$4:$U$4,0))<($D10+$E10))+(INDEX(Curve!$L$16:$U$23,2,MATCH($C10,Curve!$L$4:$U$4,0))<($D10+$E10))+(INDEX(Curve!$L$16:$U$23,3,MATCH($C10,Curve!$L$4:$U$4,0))<($D10+$E10))+(INDEX(Curve!$L$16:$U$23,4,MATCH($C10,Curve!$L$4:$U$4,0))<($D10+$E10))+(INDEX(Curve!$L$16:$U$23,5,MATCH($C10,Curve!$L$4:$U$4,0))<($D10+$E10))+(INDEX(Curve!$L$16:$U$23,6,MATCH($C10,Curve!$L$4:$U$4,0))<($D10+$E10))+(INDEX(Curve!$L$16:$U$23,7,MATCH($C10,Curve!$L$4:$U$4,0))<($D10+$E10))+(INDEX(Curve!$L$16:$U$23,8,MATCH($C10,Curve!$L$4:$U$4,0))<($D10+$E10)))))) | L10: =IF(NOT(ISNUMBER(($D10+F10))),"-",IF(($D10+F10)<=0,"-",IF(1+(INDEX(Curve!$L$16:$U$23,1,MATCH($C10,Curve!$L$4:$U$4,0))<($D10+F10))+(INDEX(Curve!$L$16:$U$23,2,MATCH($C10,Curve!$L$4:$U$4,0))<($D10+F10))+(INDEX(Curve!$L$16:$U$23,3,MATCH($C10,Curve!$L$4:$U$4,0))<($D10+F10))+(INDEX(Curve!$L$16:$U$23,4,MATCH($C10,Curve!$L$4:$U$4,0))<($D10+F10))+(INDEX(Curve!$L$16:$U$23,5,MATCH($C10,Curve!$L$4:$U$4,0))<($D10+F10))+(INDEX(Curve!$L$16:$U$23,6,MATCH($C10,Curve!$L$4:$U$4,0))<($D10+F10))+(INDEX(Curve!$L$16:$U$23,7,MATCH($C10,Curve!$L$4:$U$4,0))<($D10+F10))+(INDEX(Curve!$L$16:$U$23,8,MATCH($C10,Curve!$L$4:$U$4,0))<($D10+F10))>8,"beyond inventory",INDEX(Curve!$D$16:$D$23,1+(INDEX(Curve!$L$16:$U$23,1,MATCH($C10,Curve!$L$4:$U$4,0))<($D10+F10))+(INDEX(Curve!$L$16:$U$23,2,MATCH($C10,Curve!$L$4:$U$4,0))<($D10+F10))+(INDEX(Curve!$L$16:$U$23,3,MATCH($C10,Curve!$L$4:$U$4,0))<($D10+F10))+(INDEX(Curve!$L$16:$U$23,4,MATCH($C10,Curve!$L$4:$U$4,0))<($D10+F10))+(INDEX(Curve!$L$16:$U$23,5,MATCH($C10,Curve!$L$4:$U$4,0))<($D10+F10))+(INDEX(Curve!$L$16:$U$23,6,MATCH($C10,Curve!$L$4:$U$4,0))<($D10+F10))+(INDEX(Curve!$L$16:$U$23,7,MATCH($C10,Curve!$L$4:$U$4,0))<($D10+F10))+(INDEX(Curve!$L$16:$U$23,8,MATCH($C10,Curve!$L$4:$U$4,0))<($D10+F10)))))) | M10: =IF(NOT(ISNUMBER(($D10+G10))),"-",IF(($D10+G10)<=0,"-",IF(1+(INDEX(Curve!$L$16:$U$23,1,MATCH($C10,Curve!$L$4:$U$4,0))<($D10+G10))+(INDEX(Curve!$L$16:$U$23,2,MATCH($C10,Curve!$L$4:$U$4,0))<($D10+G10))+(INDEX(Curve!$L$16:$U$23,3,MATCH($C10,Curve!$L$4:$U$4,0))<($D10+G10))+(INDEX(Curve!$L$16:$U$23,4,MATCH($C10,Curve!$L$4:$U$4,0))<($D10+G10))+(INDEX(Curve!$L$16:$U$23,5,MATCH($C10,Curve!$L$4:$U$4,0))<($D10+G10))+(INDEX(Curve!$L$16:$U$23,6,MATCH($C10,Curve!$L$4:$U$4,0))<($D10+G10))+(INDEX(Curve!$L$16:$U$23,7,MATCH($C10,Curve!$L$4:$U$4,0))<($D10+G10))+(INDEX(Curve!$L$16:$U$23,8,MATCH($C10,Curve!$L$4:$U$4,0))<($D10+G10))>8,"beyond inventory",INDEX(Curve!$D$16:$D$23,1+(INDEX(Curve!$L$16:$U$23,1,MATCH($C10,Curve!$L$4:$U$4,0))<($D10+G10))+(INDEX(Curve!$L$16:$U$23,2,MATCH($C10,Curve!$L$4:$U$4,0))<($D10+G10))+(INDEX(Curve!$L$16:$U$23,3,MATCH($C10,Curve!$L$4:$U$4,0))<($D10+G10))+(INDEX(Curve!$L$16:$U$23,4,MATCH($C10,Curve!$L$4:$U$4,0))<($D10+G10))+(INDEX(Curve!$L$16:$U$23,5,MATCH($C10,Curve!$L$4:$U$4,0))<($D10+G10))+(INDEX(Curve!$L$16:$U$23,6,MATCH($C10,Curve!$L$4:$U$4,0))<($D10+G10))+(INDEX(Curve!$L$16:$U$23,7,MATCH($C10,Curve!$L$4:$U$4,0))<($D10+G10))+(INDEX(Curve!$L$16:$U$23,8,MATCH($C10,Curve!$L$4:$U$4,0))<($D10+G10)))))) | N10: =IF(NOT(ISNUMBER(($D10+H10))),"-",IF(($D10+H10)<=0,"-",IF(1+(INDEX(Curve!$L$16:$U$23,1,MATCH($C10,Curve!$L$4:$U$4,0))<($D10+H10))+(INDEX(Curve!$L$16:$U$23,2,MATCH($C10,Curve!$L$4:$U$4,0))<($D10+H10))+(INDEX(Curve!$L$16:$U$23,3,MATCH($C10,Curve!$L$4:$U$4,0))<($D10+H10))+(INDEX(Curve!$L$16:$U$23,4,MATCH($C10,Curve!$L$4:$U$4,0))<($D10+H10))+(INDEX(Curve!$L$16:$U$23,5,MATCH($C10,Curve!$L$4:$U$4,0))<($D10+H10))+(INDEX(Curve!$L$16:$U$23,6,MATCH($C10,Curve!$L$4:$U$4,0))<($D10+H10))+(INDEX(Curve!$L$16:$U$23,7,MATCH($C10,Curve!$L$4:$U$4,0))<($D10+H10))+(INDEX(Curve!$L$16:$U$23,8,MATCH($C10,Curve!$L$4:$U$4,0))<($D10+H10))>8,"beyond inventory",INDEX(Curve!$D$16:$D$23,1+(INDEX(Curve!$L$16:$U$23,1,MATCH($C10,Curve!$L$4:$U$4,0))<($D10+H10))+(INDEX(Curve!$L$16:$U$23,2,MATCH($C10,Curve!$L$4:$U$4,0))<($D10+H10))+(INDEX(Curve!$L$16:$U$23,3,MATCH($C10,Curve!$L$4:$U$4,0))<($D10+H10))+(INDEX(Curve!$L$16:$U$23,4,MATCH($C10,Curve!$L$4:$U$4,0))<($D10+H10))+(INDEX(Curve!$L$16:$U$23,5,MATCH($C10,Curve!$L$4:$U$4,0))<($D10+H10))+(INDEX(Curve!$L$16:$U$23,6,MATCH($C10,Curve!$L$4:$U$4,0))<($D10+H10))+(INDEX(Curve!$L$16:$U$23,7,MATCH($C10,Curve!$L$4:$U$4,0))<($D10+H10))+(INDEX(Curve!$L$16:$U$23,8,MATCH($C10,Curve!$L$4:$U$4,0))<($D10+H10)))))) | O10: =IF(NOT(ISNUMBER(($D10+I10))),"-",IF(($D10+I10)<=0,"-",IF(1+(INDEX(Curve!$L$16:$U$23,1,MATCH($C10,Curve!$L$4:$U$4,0))<($D10+I10))+(INDEX(Curve!$L$16:$U$23,2,MATCH($C10,Curve!$L$4:$U$4,0))<($D10+I10))+(INDEX(Curve!$L$16:$U$23,3,MATCH($C10,Curve!$L$4:$U$4,0))<($D10+I10))+(INDEX(Curve!$L$16:$U$23,4,MATCH($C10,Curve!$L$4:$U$4,0))<($D10+I10))+(INDEX(Curve!$L$16:$U$23,5,MATCH($C10,Curve!$L$4:$U$4,0))<($D10+I10))+(INDEX(Curve!$L$16:$U$23,6,MATCH($C10,Curve!$L$4:$U$4,0))<($D10+I10))+(INDEX(Curve!$L$16:$U$23,7,MATCH($C10,Curve!$L$4:$U$4,0))<($D10+I10))+(INDEX(Curve!$L$16:$U$23,8,MATCH($C10,Curve!$L$4:$U$4,0))<($D10+I10))>8,"beyond inventory",INDEX(Curve!$D$16:$D$23,1+(INDEX(Curve!$L$16:$U$23,1,MATCH($C10,Curve!$L$4:$U$4,0))<($D10+I10))+(INDEX(Curve!$L$16:$U$23,2,MATCH($C10,Curve!$L$4:$U$4,0))<($D10+I10))+(INDEX(Curve!$L$16:$U$23,3,MATCH($C10,Curve!$L$4:$U$4,0))<($D10+I10))+(INDEX(Curve!$L$16:$U$23,4,MATCH($C10,Curve!$L$4:$U$4,0))<($D10+I10))+(INDEX(Curve!$L$16:$U$23,5,MATCH($C10,Curve!$L$4:$U$4,0))<($D10+I10))+(INDEX(Curve!$L$16:$U$23,6,MATCH($C10,Curve!$L$4:$U$4,0))<($D10+I10))+(INDEX(Curve!$L$16:$U$23,7,MATCH($C10,Curve!$L$4:$U$4,0))<($D10+I10))+(INDEX(Curve!$L$16:$U$23,8,MATCH($C10,Curve!$L$4:$U$4,0))<($D10+I10)))))) | P10: ='Henry Hub'!$B$3 | Q10: =IF(ISNUMBER(K10),K10-P10,"-")
A11: LNG and takeaway delayed 6 months | B11: Dec 2028 | C11: 3 | D11: ='Gulf key question'!C12 | E11: ='Gulf key question'!D12 | F11: ='Gulf key question'!F12 | G11: ='Gulf key question'!G12 | H11: ='Gulf key question'!H12 | I11: ='Gulf key question'!I12 | J11: =IF(NOT(ISNUMBER($E11)),"-",IF($E11<=0,"-",IF(1+(INDEX(Curve!$L$16:$U$23,1,MATCH($C11,Curve!$L$4:$U$4,0))<$E11)+(INDEX(Curve!$L$16:$U$23,2,MATCH($C11,Curve!$L$4:$U$4,0))<$E11)+(INDEX(Curve!$L$16:$U$23,3,MATCH($C11,Curve!$L$4:$U$4,0))<$E11)+(INDEX(Curve!$L$16:$U$23,4,MATCH($C11,Curve!$L$4:$U$4,0))<$E11)+(INDEX(Curve!$L$16:$U$23,5,MATCH($C11,Curve!$L$4:$U$4,0))<$E11)+(INDEX(Curve!$L$16:$U$23,6,MATCH($C11,Curve!$L$4:$U$4,0))<$E11)+(INDEX(Curve!$L$16:$U$23,7,MATCH($C11,Curve!$L$4:$U$4,0))<$E11)+(INDEX(Curve!$L$16:$U$23,8,MATCH($C11,Curve!$L$4:$U$4,0))<$E11)>8,"beyond inventory",INDEX(Curve!$D$16:$D$23,1+(INDEX(Curve!$L$16:$U$23,1,MATCH($C11,Curve!$L$4:$U$4,0))<$E11)+(INDEX(Curve!$L$16:$U$23,2,MATCH($C11,Curve!$L$4:$U$4,0))<$E11)+(INDEX(Curve!$L$16:$U$23,3,MATCH($C11,Curve!$L$4:$U$4,0))<$E11)+(INDEX(Curve!$L$16:$U$23,4,MATCH($C11,Curve!$L$4:$U$4,0))<$E11)+(INDEX(Curve!$L$16:$U$23,5,MATCH($C11,Curve!$L$4:$U$4,0))<$E11)+(INDEX(Curve!$L$16:$U$23,6,MATCH($C11,Curve!$L$4:$U$4,0))<$E11)+(INDEX(Curve!$L$16:$U$23,7,MATCH($C11,Curve!$L$4:$U$4,0))<$E11)+(INDEX(Curve!$L$16:$U$23,8,MATCH($C11,Curve!$L$4:$U$4,0))<$E11))))) | K11: =IF(NOT(ISNUMBER(($D11+$E11))),"-",IF(($D11+$E11)<=0,"-",IF(1+(INDEX(Curve!$L$16:$U$23,1,MATCH($C11,Curve!$L$4:$U$4,0))<($D11+$E11))+(INDEX(Curve!$L$16:$U$23,2,MATCH($C11,Curve!$L$4:$U$4,0))<($D11+$E11))+(INDEX(Curve!$L$16:$U$23,3,MATCH($C11,Curve!$L$4:$U$4,0))<($D11+$E11))+(INDEX(Curve!$L$16:$U$23,4,MATCH($C11,Curve!$L$4:$U$4,0))<($D11+$E11))+(INDEX(Curve!$L$16:$U$23,5,MATCH($C11,Curve!$L$4:$U$4,0))<($D11+$E11))+(INDEX(Curve!$L$16:$U$23,6,MATCH($C11,Curve!$L$4:$U$4,0))<($D11+$E11))+(INDEX(Curve!$L$16:$U$23,7,MATCH($C11,Curve!$L$4:$U$4,0))<($D11+$E11))+(INDEX(Curve!$L$16:$U$23,8,MATCH($C11,Curve!$L$4:$U$4,0))<($D11+$E11))>8,"beyond inventory",INDEX(Curve!$D$16:$D$23,1+(INDEX(Curve!$L$16:$U$23,1,MATCH($C11,Curve!$L$4:$U$4,0))<($D11+$E11))+(INDEX(Curve!$L$16:$U$23,2,MATCH($C11,Curve!$L$4:$U$4,0))<($D11+$E11))+(INDEX(Curve!$L$16:$U$23,3,MATCH($C11,Curve!$L$4:$U$4,0))<($D11+$E11))+(INDEX(Curve!$L$16:$U$23,4,MATCH($C11,Curve!$L$4:$U$4,0))<($D11+$E11))+(INDEX(Curve!$L$16:$U$23,5,MATCH($C11,Curve!$L$4:$U$4,0))<($D11+$E11))+(INDEX(Curve!$L$16:$U$23,6,MATCH($C11,Curve!$L$4:$U$4,0))<($D11+$E11))+(INDEX(Curve!$L$16:$U$23,7,MATCH($C11,Curve!$L$4:$U$4,0))<($D11+$E11))+(INDEX(Curve!$L$16:$U$23,8,MATCH($C11,Curve!$L$4:$U$4,0))<($D11+$E11)))))) | L11: =IF(NOT(ISNUMBER(($D11+F11))),"-",IF(($D11+F11)<=0,"-",IF(1+(INDEX(Curve!$L$16:$U$23,1,MATCH($C11,Curve!$L$4:$U$4,0))<($D11+F11))+(INDEX(Curve!$L$16:$U$23,2,MATCH($C11,Curve!$L$4:$U$4,0))<($D11+F11))+(INDEX(Curve!$L$16:$U$23,3,MATCH($C11,Curve!$L$4:$U$4,0))<($D11+F11))+(INDEX(Curve!$L$16:$U$23,4,MATCH($C11,Curve!$L$4:$U$4,0))<($D11+F11))+(INDEX(Curve!$L$16:$U$23,5,MATCH($C11,Curve!$L$4:$U$4,0))<($D11+F11))+(INDEX(Curve!$L$16:$U$23,6,MATCH($C11,Curve!$L$4:$U$4,0))<($D11+F11))+(INDEX(Curve!$L$16:$U$23,7,MATCH($C11,Curve!$L$4:$U$4,0))<($D11+F11))+(INDEX(Curve!$L$16:$U$23,8,MATCH($C11,Curve!$L$4:$U$4,0))<($D11+F11))>8,"beyond inventory",INDEX(Curve!$D$16:$D$23,1+(INDEX(Curve!$L$16:$U$23,1,MATCH($C11,Curve!$L$4:$U$4,0))<($D11+F11))+(INDEX(Curve!$L$16:$U$23,2,MATCH($C11,Curve!$L$4:$U$4,0))<($D11+F11))+(INDEX(Curve!$L$16:$U$23,3,MATCH($C11,Curve!$L$4:$U$4,0))<($D11+F11))+(INDEX(Curve!$L$16:$U$23,4,MATCH($C11,Curve!$L$4:$U$4,0))<($D11+F11))+(INDEX(Curve!$L$16:$U$23,5,MATCH($C11,Curve!$L$4:$U$4,0))<($D11+F11))+(INDEX(Curve!$L$16:$U$23,6,MATCH($C11,Curve!$L$4:$U$4,0))<($D11+F11))+(INDEX(Curve!$L$16:$U$23,7,MATCH($C11,Curve!$L$4:$U$4,0))<($D11+F11))+(INDEX(Curve!$L$16:$U$23,8,MATCH($C11,Curve!$L$4:$U$4,0))<($D11+F11)))))) | M11: =IF(NOT(ISNUMBER(($D11+G11))),"-",IF(($D11+G11)<=0,"-",IF(1+(INDEX(Curve!$L$16:$U$23,1,MATCH($C11,Curve!$L$4:$U$4,0))<($D11+G11))+(INDEX(Curve!$L$16:$U$23,2,MATCH($C11,Curve!$L$4:$U$4,0))<($D11+G11))+(INDEX(Curve!$L$16:$U$23,3,MATCH($C11,Curve!$L$4:$U$4,0))<($D11+G11))+(INDEX(Curve!$L$16:$U$23,4,MATCH($C11,Curve!$L$4:$U$4,0))<($D11+G11))+(INDEX(Curve!$L$16:$U$23,5,MATCH($C11,Curve!$L$4:$U$4,0))<($D11+G11))+(INDEX(Curve!$L$16:$U$23,6,MATCH($C11,Curve!$L$4:$U$4,0))<($D11+G11))+(INDEX(Curve!$L$16:$U$23,7,MATCH($C11,Curve!$L$4:$U$4,0))<($D11+G11))+(INDEX(Curve!$L$16:$U$23,8,MATCH($C11,Curve!$L$4:$U$4,0))<($D11+G11))>8,"beyond inventory",INDEX(Curve!$D$16:$D$23,1+(INDEX(Curve!$L$16:$U$23,1,MATCH($C11,Curve!$L$4:$U$4,0))<($D11+G11))+(INDEX(Curve!$L$16:$U$23,2,MATCH($C11,Curve!$L$4:$U$4,0))<($D11+G11))+(INDEX(Curve!$L$16:$U$23,3,MATCH($C11,Curve!$L$4:$U$4,0))<($D11+G11))+(INDEX(Curve!$L$16:$U$23,4,MATCH($C11,Curve!$L$4:$U$4,0))<($D11+G11))+(INDEX(Curve!$L$16:$U$23,5,MATCH($C11,Curve!$L$4:$U$4,0))<($D11+G11))+(INDEX(Curve!$L$16:$U$23,6,MATCH($C11,Curve!$L$4:$U$4,0))<($D11+G11))+(INDEX(Curve!$L$16:$U$23,7,MATCH($C11,Curve!$L$4:$U$4,0))<($D11+G11))+(INDEX(Curve!$L$16:$U$23,8,MATCH($C11,Curve!$L$4:$U$4,0))<($D11+G11)))))) | N11: =IF(NOT(ISNUMBER(($D11+H11))),"-",IF(($D11+H11)<=0,"-",IF(1+(INDEX(Curve!$L$16:$U$23,1,MATCH($C11,Curve!$L$4:$U$4,0))<($D11+H11))+(INDEX(Curve!$L$16:$U$23,2,MATCH($C11,Curve!$L$4:$U$4,0))<($D11+H11))+(INDEX(Curve!$L$16:$U$23,3,MATCH($C11,Curve!$L$4:$U$4,0))<($D11+H11))+(INDEX(Curve!$L$16:$U$23,4,MATCH($C11,Curve!$L$4:$U$4,0))<($D11+H11))+(INDEX(Curve!$L$16:$U$23,5,MATCH($C11,Curve!$L$4:$U$4,0))<($D11+H11))+(INDEX(Curve!$L$16:$U$23,6,MATCH($C11,Curve!$L$4:$U$4,0))<($D11+H11))+(INDEX(Curve!$L$16:$U$23,7,MATCH($C11,Curve!$L$4:$U$4,0))<($D11+H11))+(INDEX(Curve!$L$16:$U$23,8,MATCH($C11,Curve!$L$4:$U$4,0))<($D11+H11))>8,"beyond inventory",INDEX(Curve!$D$16:$D$23,1+(INDEX(Curve!$L$16:$U$23,1,MATCH($C11,Curve!$L$4:$U$4,0))<($D11+H11))+(INDEX(Curve!$L$16:$U$23,2,MATCH($C11,Curve!$L$4:$U$4,0))<($D11+H11))+(INDEX(Curve!$L$16:$U$23,3,MATCH($C11,Curve!$L$4:$U$4,0))<($D11+H11))+(INDEX(Curve!$L$16:$U$23,4,MATCH($C11,Curve!$L$4:$U$4,0))<($D11+H11))+(INDEX(Curve!$L$16:$U$23,5,MATCH($C11,Curve!$L$4:$U$4,0))<($D11+H11))+(INDEX(Curve!$L$16:$U$23,6,MATCH($C11,Curve!$L$4:$U$4,0))<($D11+H11))+(INDEX(Curve!$L$16:$U$23,7,MATCH($C11,Curve!$L$4:$U$4,0))<($D11+H11))+(INDEX(Curve!$L$16:$U$23,8,MATCH($C11,Curve!$L$4:$U$4,0))<($D11+H11)))))) | O11: =IF(NOT(ISNUMBER(($D11+I11))),"-",IF(($D11+I11)<=0,"-",IF(1+(INDEX(Curve!$L$16:$U$23,1,MATCH($C11,Curve!$L$4:$U$4,0))<($D11+I11))+(INDEX(Curve!$L$16:$U$23,2,MATCH($C11,Curve!$L$4:$U$4,0))<($D11+I11))+(INDEX(Curve!$L$16:$U$23,3,MATCH($C11,Curve!$L$4:$U$4,0))<($D11+I11))+(INDEX(Curve!$L$16:$U$23,4,MATCH($C11,Curve!$L$4:$U$4,0))<($D11+I11))+(INDEX(Curve!$L$16:$U$23,5,MATCH($C11,Curve!$L$4:$U$4,0))<($D11+I11))+(INDEX(Curve!$L$16:$U$23,6,MATCH($C11,Curve!$L$4:$U$4,0))<($D11+I11))+(INDEX(Curve!$L$16:$U$23,7,MATCH($C11,Curve!$L$4:$U$4,0))<($D11+I11))+(INDEX(Curve!$L$16:$U$23,8,MATCH($C11,Curve!$L$4:$U$4,0))<($D11+I11))>8,"beyond inventory",INDEX(Curve!$D$16:$D$23,1+(INDEX(Curve!$L$16:$U$23,1,MATCH($C11,Curve!$L$4:$U$4,0))<($D11+I11))+(INDEX(Curve!$L$16:$U$23,2,MATCH($C11,Curve!$L$4:$U$4,0))<($D11+I11))+(INDEX(Curve!$L$16:$U$23,3,MATCH($C11,Curve!$L$4:$U$4,0))<($D11+I11))+(INDEX(Curve!$L$16:$U$23,4,MATCH($C11,Curve!$L$4:$U$4,0))<($D11+I11))+(INDEX(Curve!$L$16:$U$23,5,MATCH($C11,Curve!$L$4:$U$4,0))<($D11+I11))+(INDEX(Curve!$L$16:$U$23,6,MATCH($C11,Curve!$L$4:$U$4,0))<($D11+I11))+(INDEX(Curve!$L$16:$U$23,7,MATCH($C11,Curve!$L$4:$U$4,0))<($D11+I11))+(INDEX(Curve!$L$16:$U$23,8,MATCH($C11,Curve!$L$4:$U$4,0))<($D11+I11)))))) | P11: ='Henry Hub'!$B$3 | Q11: =IF(ISNUMBER(K11),K11-P11,"-")
A12: LNG and takeaway delayed 6 months | B12: Dec 2030 | C12: 5 | D12: ='Gulf key question'!C14 | E12: ='Gulf key question'!D14 | F12: ='Gulf key question'!F14 | G12: ='Gulf key question'!G14 | H12: ='Gulf key question'!H14 | I12: ='Gulf key question'!I14 | J12: =IF(NOT(ISNUMBER($E12)),"-",IF($E12<=0,"-",IF(1+(INDEX(Curve!$L$16:$U$23,1,MATCH($C12,Curve!$L$4:$U$4,0))<$E12)+(INDEX(Curve!$L$16:$U$23,2,MATCH($C12,Curve!$L$4:$U$4,0))<$E12)+(INDEX(Curve!$L$16:$U$23,3,MATCH($C12,Curve!$L$4:$U$4,0))<$E12)+(INDEX(Curve!$L$16:$U$23,4,MATCH($C12,Curve!$L$4:$U$4,0))<$E12)+(INDEX(Curve!$L$16:$U$23,5,MATCH($C12,Curve!$L$4:$U$4,0))<$E12)+(INDEX(Curve!$L$16:$U$23,6,MATCH($C12,Curve!$L$4:$U$4,0))<$E12)+(INDEX(Curve!$L$16:$U$23,7,MATCH($C12,Curve!$L$4:$U$4,0))<$E12)+(INDEX(Curve!$L$16:$U$23,8,MATCH($C12,Curve!$L$4:$U$4,0))<$E12)>8,"beyond inventory",INDEX(Curve!$D$16:$D$23,1+(INDEX(Curve!$L$16:$U$23,1,MATCH($C12,Curve!$L$4:$U$4,0))<$E12)+(INDEX(Curve!$L$16:$U$23,2,MATCH($C12,Curve!$L$4:$U$4,0))<$E12)+(INDEX(Curve!$L$16:$U$23,3,MATCH($C12,Curve!$L$4:$U$4,0))<$E12)+(INDEX(Curve!$L$16:$U$23,4,MATCH($C12,Curve!$L$4:$U$4,0))<$E12)+(INDEX(Curve!$L$16:$U$23,5,MATCH($C12,Curve!$L$4:$U$4,0))<$E12)+(INDEX(Curve!$L$16:$U$23,6,MATCH($C12,Curve!$L$4:$U$4,0))<$E12)+(INDEX(Curve!$L$16:$U$23,7,MATCH($C12,Curve!$L$4:$U$4,0))<$E12)+(INDEX(Curve!$L$16:$U$23,8,MATCH($C12,Curve!$L$4:$U$4,0))<$E12))))) | K12: =IF(NOT(ISNUMBER(($D12+$E12))),"-",IF(($D12+$E12)<=0,"-",IF(1+(INDEX(Curve!$L$16:$U$23,1,MATCH($C12,Curve!$L$4:$U$4,0))<($D12+$E12))+(INDEX(Curve!$L$16:$U$23,2,MATCH($C12,Curve!$L$4:$U$4,0))<($D12+$E12))+(INDEX(Curve!$L$16:$U$23,3,MATCH($C12,Curve!$L$4:$U$4,0))<($D12+$E12))+(INDEX(Curve!$L$16:$U$23,4,MATCH($C12,Curve!$L$4:$U$4,0))<($D12+$E12))+(INDEX(Curve!$L$16:$U$23,5,MATCH($C12,Curve!$L$4:$U$4,0))<($D12+$E12))+(INDEX(Curve!$L$16:$U$23,6,MATCH($C12,Curve!$L$4:$U$4,0))<($D12+$E12))+(INDEX(Curve!$L$16:$U$23,7,MATCH($C12,Curve!$L$4:$U$4,0))<($D12+$E12))+(INDEX(Curve!$L$16:$U$23,8,MATCH($C12,Curve!$L$4:$U$4,0))<($D12+$E12))>8,"beyond inventory",INDEX(Curve!$D$16:$D$23,1+(INDEX(Curve!$L$16:$U$23,1,MATCH($C12,Curve!$L$4:$U$4,0))<($D12+$E12))+(INDEX(Curve!$L$16:$U$23,2,MATCH($C12,Curve!$L$4:$U$4,0))<($D12+$E12))+(INDEX(Curve!$L$16:$U$23,3,MATCH($C12,Curve!$L$4:$U$4,0))<($D12+$E12))+(INDEX(Curve!$L$16:$U$23,4,MATCH($C12,Curve!$L$4:$U$4,0))<($D12+$E12))+(INDEX(Curve!$L$16:$U$23,5,MATCH($C12,Curve!$L$4:$U$4,0))<($D12+$E12))+(INDEX(Curve!$L$16:$U$23,6,MATCH($C12,Curve!$L$4:$U$4,0))<($D12+$E12))+(INDEX(Curve!$L$16:$U$23,7,MATCH($C12,Curve!$L$4:$U$4,0))<($D12+$E12))+(INDEX(Curve!$L$16:$U$23,8,MATCH($C12,Curve!$L$4:$U$4,0))<($D12+$E12)))))) | L12: =IF(NOT(ISNUMBER(($D12+F12))),"-",IF(($D12+F12)<=0,"-",IF(1+(INDEX(Curve!$L$16:$U$23,1,MATCH($C12,Curve!$L$4:$U$4,0))<($D12+F12))+(INDEX(Curve!$L$16:$U$23,2,MATCH($C12,Curve!$L$4:$U$4,0))<($D12+F12))+(INDEX(Curve!$L$16:$U$23,3,MATCH($C12,Curve!$L$4:$U$4,0))<($D12+F12))+(INDEX(Curve!$L$16:$U$23,4,MATCH($C12,Curve!$L$4:$U$4,0))<($D12+F12))+(INDEX(Curve!$L$16:$U$23,5,MATCH($C12,Curve!$L$4:$U$4,0))<($D12+F12))+(INDEX(Curve!$L$16:$U$23,6,MATCH($C12,Curve!$L$4:$U$4,0))<($D12+F12))+(INDEX(Curve!$L$16:$U$23,7,MATCH($C12,Curve!$L$4:$U$4,0))<($D12+F12))+(INDEX(Curve!$L$16:$U$23,8,MATCH($C12,Curve!$L$4:$U$4,0))<($D12+F12))>8,"beyond inventory",INDEX(Curve!$D$16:$D$23,1+(INDEX(Curve!$L$16:$U$23,1,MATCH($C12,Curve!$L$4:$U$4,0))<($D12+F12))+(INDEX(Curve!$L$16:$U$23,2,MATCH($C12,Curve!$L$4:$U$4,0))<($D12+F12))+(INDEX(Curve!$L$16:$U$23,3,MATCH($C12,Curve!$L$4:$U$4,0))<($D12+F12))+(INDEX(Curve!$L$16:$U$23,4,MATCH($C12,Curve!$L$4:$U$4,0))<($D12+F12))+(INDEX(Curve!$L$16:$U$23,5,MATCH($C12,Curve!$L$4:$U$4,0))<($D12+F12))+(INDEX(Curve!$L$16:$U$23,6,MATCH($C12,Curve!$L$4:$U$4,0))<($D12+F12))+(INDEX(Curve!$L$16:$U$23,7,MATCH($C12,Curve!$L$4:$U$4,0))<($D12+F12))+(INDEX(Curve!$L$16:$U$23,8,MATCH($C12,Curve!$L$4:$U$4,0))<($D12+F12)))))) | M12: =IF(NOT(ISNUMBER(($D12+G12))),"-",IF(($D12+G12)<=0,"-",IF(1+(INDEX(Curve!$L$16:$U$23,1,MATCH($C12,Curve!$L$4:$U$4,0))<($D12+G12))+(INDEX(Curve!$L$16:$U$23,2,MATCH($C12,Curve!$L$4:$U$4,0))<($D12+G12))+(INDEX(Curve!$L$16:$U$23,3,MATCH($C12,Curve!$L$4:$U$4,0))<($D12+G12))+(INDEX(Curve!$L$16:$U$23,4,MATCH($C12,Curve!$L$4:$U$4,0))<($D12+G12))+(INDEX(Curve!$L$16:$U$23,5,MATCH($C12,Curve!$L$4:$U$4,0))<($D12+G12))+(INDEX(Curve!$L$16:$U$23,6,MATCH($C12,Curve!$L$4:$U$4,0))<($D12+G12))+(INDEX(Curve!$L$16:$U$23,7,MATCH($C12,Curve!$L$4:$U$4,0))<($D12+G12))+(INDEX(Curve!$L$16:$U$23,8,MATCH($C12,Curve!$L$4:$U$4,0))<($D12+G12))>8,"beyond inventory",INDEX(Curve!$D$16:$D$23,1+(INDEX(Curve!$L$16:$U$23,1,MATCH($C12,Curve!$L$4:$U$4,0))<($D12+G12))+(INDEX(Curve!$L$16:$U$23,2,MATCH($C12,Curve!$L$4:$U$4,0))<($D12+G12))+(INDEX(Curve!$L$16:$U$23,3,MATCH($C12,Curve!$L$4:$U$4,0))<($D12+G12))+(INDEX(Curve!$L$16:$U$23,4,MATCH($C12,Curve!$L$4:$U$4,0))<($D12+G12))+(INDEX(Curve!$L$16:$U$23,5,MATCH($C12,Curve!$L$4:$U$4,0))<($D12+G12))+(INDEX(Curve!$L$16:$U$23,6,MATCH($C12,Curve!$L$4:$U$4,0))<($D12+G12))+(INDEX(Curve!$L$16:$U$23,7,MATCH($C12,Curve!$L$4:$U$4,0))<($D12+G12))+(INDEX(Curve!$L$16:$U$23,8,MATCH($C12,Curve!$L$4:$U$4,0))<($D12+G12)))))) | N12: =IF(NOT(ISNUMBER(($D12+H12))),"-",IF(($D12+H12)<=0,"-",IF(1+(INDEX(Curve!$L$16:$U$23,1,MATCH($C12,Curve!$L$4:$U$4,0))<($D12+H12))+(INDEX(Curve!$L$16:$U$23,2,MATCH($C12,Curve!$L$4:$U$4,0))<($D12+H12))+(INDEX(Curve!$L$16:$U$23,3,MATCH($C12,Curve!$L$4:$U$4,0))<($D12+H12))+(INDEX(Curve!$L$16:$U$23,4,MATCH($C12,Curve!$L$4:$U$4,0))<($D12+H12))+(INDEX(Curve!$L$16:$U$23,5,MATCH($C12,Curve!$L$4:$U$4,0))<($D12+H12))+(INDEX(Curve!$L$16:$U$23,6,MATCH($C12,Curve!$L$4:$U$4,0))<($D12+H12))+(INDEX(Curve!$L$16:$U$23,7,MATCH($C12,Curve!$L$4:$U$4,0))<($D12+H12))+(INDEX(Curve!$L$16:$U$23,8,MATCH($C12,Curve!$L$4:$U$4,0))<($D12+H12))>8,"beyond inventory",INDEX(Curve!$D$16:$D$23,1+(INDEX(Curve!$L$16:$U$23,1,MATCH($C12,Curve!$L$4:$U$4,0))<($D12+H12))+(INDEX(Curve!$L$16:$U$23,2,MATCH($C12,Curve!$L$4:$U$4,0))<($D12+H12))+(INDEX(Curve!$L$16:$U$23,3,MATCH($C12,Curve!$L$4:$U$4,0))<($D12+H12))+(INDEX(Curve!$L$16:$U$23,4,MATCH($C12,Curve!$L$4:$U$4,0))<($D12+H12))+(INDEX(Curve!$L$16:$U$23,5,MATCH($C12,Curve!$L$4:$U$4,0))<($D12+H12))+(INDEX(Curve!$L$16:$U$23,6,MATCH($C12,Curve!$L$4:$U$4,0))<($D12+H12))+(INDEX(Curve!$L$16:$U$23,7,MATCH($C12,Curve!$L$4:$U$4,0))<($D12+H12))+(INDEX(Curve!$L$16:$U$23,8,MATCH($C12,Curve!$L$4:$U$4,0))<($D12+H12)))))) | O12: =IF(NOT(ISNUMBER(($D12+I12))),"-",IF(($D12+I12)<=0,"-",IF(1+(INDEX(Curve!$L$16:$U$23,1,MATCH($C12,Curve!$L$4:$U$4,0))<($D12+I12))+(INDEX(Curve!$L$16:$U$23,2,MATCH($C12,Curve!$L$4:$U$4,0))<($D12+I12))+(INDEX(Curve!$L$16:$U$23,3,MATCH($C12,Curve!$L$4:$U$4,0))<($D12+I12))+(INDEX(Curve!$L$16:$U$23,4,MATCH($C12,Curve!$L$4:$U$4,0))<($D12+I12))+(INDEX(Curve!$L$16:$U$23,5,MATCH($C12,Curve!$L$4:$U$4,0))<($D12+I12))+(INDEX(Curve!$L$16:$U$23,6,MATCH($C12,Curve!$L$4:$U$4,0))<($D12+I12))+(INDEX(Curve!$L$16:$U$23,7,MATCH($C12,Curve!$L$4:$U$4,0))<($D12+I12))+(INDEX(Curve!$L$16:$U$23,8,MATCH($C12,Curve!$L$4:$U$4,0))<($D12+I12))>8,"beyond inventory",INDEX(Curve!$D$16:$D$23,1+(INDEX(Curve!$L$16:$U$23,1,MATCH($C12,Curve!$L$4:$U$4,0))<($D12+I12))+(INDEX(Curve!$L$16:$U$23,2,MATCH($C12,Curve!$L$4:$U$4,0))<($D12+I12))+(INDEX(Curve!$L$16:$U$23,3,MATCH($C12,Curve!$L$4:$U$4,0))<($D12+I12))+(INDEX(Curve!$L$16:$U$23,4,MATCH($C12,Curve!$L$4:$U$4,0))<($D12+I12))+(INDEX(Curve!$L$16:$U$23,5,MATCH($C12,Curve!$L$4:$U$4,0))<($D12+I12))+(INDEX(Curve!$L$16:$U$23,6,MATCH($C12,Curve!$L$4:$U$4,0))<($D12+I12))+(INDEX(Curve!$L$16:$U$23,7,MATCH($C12,Curve!$L$4:$U$4,0))<($D12+I12))+(INDEX(Curve!$L$16:$U$23,8,MATCH($C12,Curve!$L$4:$U$4,0))<($D12+I12)))))) | P12: ='Henry Hub'!$B$3 | Q12: =IF(ISNUMBER(K12),K12-P12,"-")
A13: LNG and takeaway delayed 6 months | B13: Dec 2033 | C13: 8 | D13: ='Gulf key question'!C17 | E13: ='Gulf key question'!D17 | F13: ='Gulf key question'!F17 | G13: ='Gulf key question'!G17 | H13: ='Gulf key question'!H17 | I13: ='Gulf key question'!I17 | J13: =IF(NOT(ISNUMBER($E13)),"-",IF($E13<=0,"-",IF(1+(INDEX(Curve!$L$16:$U$23,1,MATCH($C13,Curve!$L$4:$U$4,0))<$E13)+(INDEX(Curve!$L$16:$U$23,2,MATCH($C13,Curve!$L$4:$U$4,0))<$E13)+(INDEX(Curve!$L$16:$U$23,3,MATCH($C13,Curve!$L$4:$U$4,0))<$E13)+(INDEX(Curve!$L$16:$U$23,4,MATCH($C13,Curve!$L$4:$U$4,0))<$E13)+(INDEX(Curve!$L$16:$U$23,5,MATCH($C13,Curve!$L$4:$U$4,0))<$E13)+(INDEX(Curve!$L$16:$U$23,6,MATCH($C13,Curve!$L$4:$U$4,0))<$E13)+(INDEX(Curve!$L$16:$U$23,7,MATCH($C13,Curve!$L$4:$U$4,0))<$E13)+(INDEX(Curve!$L$16:$U$23,8,MATCH($C13,Curve!$L$4:$U$4,0))<$E13)>8,"beyond inventory",INDEX(Curve!$D$16:$D$23,1+(INDEX(Curve!$L$16:$U$23,1,MATCH($C13,Curve!$L$4:$U$4,0))<$E13)+(INDEX(Curve!$L$16:$U$23,2,MATCH($C13,Curve!$L$4:$U$4,0))<$E13)+(INDEX(Curve!$L$16:$U$23,3,MATCH($C13,Curve!$L$4:$U$4,0))<$E13)+(INDEX(Curve!$L$16:$U$23,4,MATCH($C13,Curve!$L$4:$U$4,0))<$E13)+(INDEX(Curve!$L$16:$U$23,5,MATCH($C13,Curve!$L$4:$U$4,0))<$E13)+(INDEX(Curve!$L$16:$U$23,6,MATCH($C13,Curve!$L$4:$U$4,0))<$E13)+(INDEX(Curve!$L$16:$U$23,7,MATCH($C13,Curve!$L$4:$U$4,0))<$E13)+(INDEX(Curve!$L$16:$U$23,8,MATCH($C13,Curve!$L$4:$U$4,0))<$E13))))) | K13: =IF(NOT(ISNUMBER(($D13+$E13))),"-",IF(($D13+$E13)<=0,"-",IF(1+(INDEX(Curve!$L$16:$U$23,1,MATCH($C13,Curve!$L$4:$U$4,0))<($D13+$E13))+(INDEX(Curve!$L$16:$U$23,2,MATCH($C13,Curve!$L$4:$U$4,0))<($D13+$E13))+(INDEX(Curve!$L$16:$U$23,3,MATCH($C13,Curve!$L$4:$U$4,0))<($D13+$E13))+(INDEX(Curve!$L$16:$U$23,4,MATCH($C13,Curve!$L$4:$U$4,0))<($D13+$E13))+(INDEX(Curve!$L$16:$U$23,5,MATCH($C13,Curve!$L$4:$U$4,0))<($D13+$E13))+(INDEX(Curve!$L$16:$U$23,6,MATCH($C13,Curve!$L$4:$U$4,0))<($D13+$E13))+(INDEX(Curve!$L$16:$U$23,7,MATCH($C13,Curve!$L$4:$U$4,0))<($D13+$E13))+(INDEX(Curve!$L$16:$U$23,8,MATCH($C13,Curve!$L$4:$U$4,0))<($D13+$E13))>8,"beyond inventory",INDEX(Curve!$D$16:$D$23,1+(INDEX(Curve!$L$16:$U$23,1,MATCH($C13,Curve!$L$4:$U$4,0))<($D13+$E13))+(INDEX(Curve!$L$16:$U$23,2,MATCH($C13,Curve!$L$4:$U$4,0))<($D13+$E13))+(INDEX(Curve!$L$16:$U$23,3,MATCH($C13,Curve!$L$4:$U$4,0))<($D13+$E13))+(INDEX(Curve!$L$16:$U$23,4,MATCH($C13,Curve!$L$4:$U$4,0))<($D13+$E13))+(INDEX(Curve!$L$16:$U$23,5,MATCH($C13,Curve!$L$4:$U$4,0))<($D13+$E13))+(INDEX(Curve!$L$16:$U$23,6,MATCH($C13,Curve!$L$4:$U$4,0))<($D13+$E13))+(INDEX(Curve!$L$16:$U$23,7,MATCH($C13,Curve!$L$4:$U$4,0))<($D13+$E13))+(INDEX(Curve!$L$16:$U$23,8,MATCH($C13,Curve!$L$4:$U$4,0))<($D13+$E13)))))) | L13: =IF(NOT(ISNUMBER(($D13+F13))),"-",IF(($D13+F13)<=0,"-",IF(1+(INDEX(Curve!$L$16:$U$23,1,MATCH($C13,Curve!$L$4:$U$4,0))<($D13+F13))+(INDEX(Curve!$L$16:$U$23,2,MATCH($C13,Curve!$L$4:$U$4,0))<($D13+F13))+(INDEX(Curve!$L$16:$U$23,3,MATCH($C13,Curve!$L$4:$U$4,0))<($D13+F13))+(INDEX(Curve!$L$16:$U$23,4,MATCH($C13,Curve!$L$4:$U$4,0))<($D13+F13))+(INDEX(Curve!$L$16:$U$23,5,MATCH($C13,Curve!$L$4:$U$4,0))<($D13+F13))+(INDEX(Curve!$L$16:$U$23,6,MATCH($C13,Curve!$L$4:$U$4,0))<($D13+F13))+(INDEX(Curve!$L$16:$U$23,7,MATCH($C13,Curve!$L$4:$U$4,0))<($D13+F13))+(INDEX(Curve!$L$16:$U$23,8,MATCH($C13,Curve!$L$4:$U$4,0))<($D13+F13))>8,"beyond inventory",INDEX(Curve!$D$16:$D$23,1+(INDEX(Curve!$L$16:$U$23,1,MATCH($C13,Curve!$L$4:$U$4,0))<($D13+F13))+(INDEX(Curve!$L$16:$U$23,2,MATCH($C13,Curve!$L$4:$U$4,0))<($D13+F13))+(INDEX(Curve!$L$16:$U$23,3,MATCH($C13,Curve!$L$4:$U$4,0))<($D13+F13))+(INDEX(Curve!$L$16:$U$23,4,MATCH($C13,Curve!$L$4:$U$4,0))<($D13+F13))+(INDEX(Curve!$L$16:$U$23,5,MATCH($C13,Curve!$L$4:$U$4,0))<($D13+F13))+(INDEX(Curve!$L$16:$U$23,6,MATCH($C13,Curve!$L$4:$U$4,0))<($D13+F13))+(INDEX(Curve!$L$16:$U$23,7,MATCH($C13,Curve!$L$4:$U$4,0))<($D13+F13))+(INDEX(Curve!$L$16:$U$23,8,MATCH($C13,Curve!$L$4:$U$4,0))<($D13+F13)))))) | M13: =IF(NOT(ISNUMBER(($D13+G13))),"-",IF(($D13+G13)<=0,"-",IF(1+(INDEX(Curve!$L$16:$U$23,1,MATCH($C13,Curve!$L$4:$U$4,0))<($D13+G13))+(INDEX(Curve!$L$16:$U$23,2,MATCH($C13,Curve!$L$4:$U$4,0))<($D13+G13))+(INDEX(Curve!$L$16:$U$23,3,MATCH($C13,Curve!$L$4:$U$4,0))<($D13+G13))+(INDEX(Curve!$L$16:$U$23,4,MATCH($C13,Curve!$L$4:$U$4,0))<($D13+G13))+(INDEX(Curve!$L$16:$U$23,5,MATCH($C13,Curve!$L$4:$U$4,0))<($D13+G13))+(INDEX(Curve!$L$16:$U$23,6,MATCH($C13,Curve!$L$4:$U$4,0))<($D13+G13))+(INDEX(Curve!$L$16:$U$23,7,MATCH($C13,Curve!$L$4:$U$4,0))<($D13+G13))+(INDEX(Curve!$L$16:$U$23,8,MATCH($C13,Curve!$L$4:$U$4,0))<($D13+G13))>8,"beyond inventory",INDEX(Curve!$D$16:$D$23,1+(INDEX(Curve!$L$16:$U$23,1,MATCH($C13,Curve!$L$4:$U$4,0))<($D13+G13))+(INDEX(Curve!$L$16:$U$23,2,MATCH($C13,Curve!$L$4:$U$4,0))<($D13+G13))+(INDEX(Curve!$L$16:$U$23,3,MATCH($C13,Curve!$L$4:$U$4,0))<($D13+G13))+(INDEX(Curve!$L$16:$U$23,4,MATCH($C13,Curve!$L$4:$U$4,0))<($D13+G13))+(INDEX(Curve!$L$16:$U$23,5,MATCH($C13,Curve!$L$4:$U$4,0))<($D13+G13))+(INDEX(Curve!$L$16:$U$23,6,MATCH($C13,Curve!$L$4:$U$4,0))<($D13+G13))+(INDEX(Curve!$L$16:$U$23,7,MATCH($C13,Curve!$L$4:$U$4,0))<($D13+G13))+(INDEX(Curve!$L$16:$U$23,8,MATCH($C13,Curve!$L$4:$U$4,0))<($D13+G13)))))) | N13: =IF(NOT(ISNUMBER(($D13+H13))),"-",IF(($D13+H13)<=0,"-",IF(1+(INDEX(Curve!$L$16:$U$23,1,MATCH($C13,Curve!$L$4:$U$4,0))<($D13+H13))+(INDEX(Curve!$L$16:$U$23,2,MATCH($C13,Curve!$L$4:$U$4,0))<($D13+H13))+(INDEX(Curve!$L$16:$U$23,3,MATCH($C13,Curve!$L$4:$U$4,0))<($D13+H13))+(INDEX(Curve!$L$16:$U$23,4,MATCH($C13,Curve!$L$4:$U$4,0))<($D13+H13))+(INDEX(Curve!$L$16:$U$23,5,MATCH($C13,Curve!$L$4:$U$4,0))<($D13+H13))+(INDEX(Curve!$L$16:$U$23,6,MATCH($C13,Curve!$L$4:$U$4,0))<($D13+H13))+(INDEX(Curve!$L$16:$U$23,7,MATCH($C13,Curve!$L$4:$U$4,0))<($D13+H13))+(INDEX(Curve!$L$16:$U$23,8,MATCH($C13,Curve!$L$4:$U$4,0))<($D13+H13))>8,"beyond inventory",INDEX(Curve!$D$16:$D$23,1+(INDEX(Curve!$L$16:$U$23,1,MATCH($C13,Curve!$L$4:$U$4,0))<($D13+H13))+(INDEX(Curve!$L$16:$U$23,2,MATCH($C13,Curve!$L$4:$U$4,0))<($D13+H13))+(INDEX(Curve!$L$16:$U$23,3,MATCH($C13,Curve!$L$4:$U$4,0))<($D13+H13))+(INDEX(Curve!$L$16:$U$23,4,MATCH($C13,Curve!$L$4:$U$4,0))<($D13+H13))+(INDEX(Curve!$L$16:$U$23,5,MATCH($C13,Curve!$L$4:$U$4,0))<($D13+H13))+(INDEX(Curve!$L$16:$U$23,6,MATCH($C13,Curve!$L$4:$U$4,0))<($D13+H13))+(INDEX(Curve!$L$16:$U$23,7,MATCH($C13,Curve!$L$4:$U$4,0))<($D13+H13))+(INDEX(Curve!$L$16:$U$23,8,MATCH($C13,Curve!$L$4:$U$4,0))<($D13+H13)))))) | O13: =IF(NOT(ISNUMBER(($D13+I13))),"-",IF(($D13+I13)<=0,"-",IF(1+(INDEX(Curve!$L$16:$U$23,1,MATCH($C13,Curve!$L$4:$U$4,0))<($D13+I13))+(INDEX(Curve!$L$16:$U$23,2,MATCH($C13,Curve!$L$4:$U$4,0))<($D13+I13))+(INDEX(Curve!$L$16:$U$23,3,MATCH($C13,Curve!$L$4:$U$4,0))<($D13+I13))+(INDEX(Curve!$L$16:$U$23,4,MATCH($C13,Curve!$L$4:$U$4,0))<($D13+I13))+(INDEX(Curve!$L$16:$U$23,5,MATCH($C13,Curve!$L$4:$U$4,0))<($D13+I13))+(INDEX(Curve!$L$16:$U$23,6,MATCH($C13,Curve!$L$4:$U$4,0))<($D13+I13))+(INDEX(Curve!$L$16:$U$23,7,MATCH($C13,Curve!$L$4:$U$4,0))<($D13+I13))+(INDEX(Curve!$L$16:$U$23,8,MATCH($C13,Curve!$L$4:$U$4,0))<($D13+I13))>8,"beyond inventory",INDEX(Curve!$D$16:$D$23,1+(INDEX(Curve!$L$16:$U$23,1,MATCH($C13,Curve!$L$4:$U$4,0))<($D13+I13))+(INDEX(Curve!$L$16:$U$23,2,MATCH($C13,Curve!$L$4:$U$4,0))<($D13+I13))+(INDEX(Curve!$L$16:$U$23,3,MATCH($C13,Curve!$L$4:$U$4,0))<($D13+I13))+(INDEX(Curve!$L$16:$U$23,4,MATCH($C13,Curve!$L$4:$U$4,0))<($D13+I13))+(INDEX(Curve!$L$16:$U$23,5,MATCH($C13,Curve!$L$4:$U$4,0))<($D13+I13))+(INDEX(Curve!$L$16:$U$23,6,MATCH($C13,Curve!$L$4:$U$4,0))<($D13+I13))+(INDEX(Curve!$L$16:$U$23,7,MATCH($C13,Curve!$L$4:$U$4,0))<($D13+I13))+(INDEX(Curve!$L$16:$U$23,8,MATCH($C13,Curve!$L$4:$U$4,0))<($D13+I13)))))) | P13: ='Henry Hub'!$B$3 | Q13: =IF(ISNUMBER(K13),K13-P13,"-")
A15: Reference prices (sourced): Dallas Fed Energy Survey Q3 2026 (30 Sep 2026) expected Henry Hub $3.29 year-end 2026, $3.82 in two years, $4.28 in five years; EIA STEO (Aug 2026) $3.44 average 2026. Haynesville flow is also limited by rigs, pipelines (Gillis, LEAP ...) and midstream - this sheet says only what COST implies.

Sheet BEG check
A1: BEG check: Bureau of Economic Geology tiers (OGJ 7 Dec 2015) and this workbook's breakeven formula run on BEG's own 2015 inputs (validation, 2011 $).
A2: Published text: EUR per tier (Fig. 7 legend). READ OFF CHARTS (approx. +/-3%): wells (Fig. 6) and breakevens (Fig. 8). Model: capex = $10.5 million x 1.13 per 4,800-ft well, gathering $0.49/Mcf, fixed expense $82,500 x 1.13 a year over 20 years, royalty 25%, basis -$0.07, 10% discount, pre-tax, no severance (BEG: 4%, 2 years exempt, and a 40.2% tax rate with a tax shield), BEG's EUR with this workbook's decline shape. Yellow cells are BEG inputs.
A5: Tier | B5: Fig. 6 drilled to 2012 (wells) | C5: EUR per 4,800-ft well (Bcf) - published | D5: Fig. 6 partly drilled (wells) | E5: Fig. 6 undrilled (wells) | F5: Fig. 8 breakeven 0% IRR | G5: Fig. 8 breakeven 10% IRR | H5: Fig. 8 breakeven 20% IRR | I5: Model breakeven (BEG inputs, 10% pre-tax) | J5: Model vs Fig. 8 10% IRR
A6: Tier 1 | B6: 450 | C6: 7.9 | D6: 1700 | E6: 2250 | F6: 2.9 | G6: 3.5 | H6: 4 | I6: =(($B$15+($B$14*1.13*1000000+($B$16*1.13*SUMPRODUCT(1/(1+Inputs!$B$5)^(Profile!$A$9:$A$28-0.5))))/(C6*1000000*Profile!$B$6)))/(1-$B$17)-$B$18 | J6: =I6/G6-1
A7: Tier 2 | B7: 480 | C7: 5.9 | D7: 1470 | E7: 2000 | F7: 3.7 | G7: 4.4 | H7: 4.9 | I7: =(($B$15+($B$14*1.13*1000000+($B$16*1.13*SUMPRODUCT(1/(1+Inputs!$B$5)^(Profile!$A$9:$A$28-0.5))))/(C7*1000000*Profile!$B$6)))/(1-$B$17)-$B$18 | J7: =I7/G7-1
A8: Tier 3 | B8: 600 | C8: 4.5 | D8: 2550 | E8: 3200 | F8: 4.6 | G8: 5.4 | H8: 6 | I8: =(($B$15+($B$14*1.13*1000000+($B$16*1.13*SUMPRODUCT(1/(1+Inputs!$B$5)^(Profile!$A$9:$A$28-0.5))))/(C8*1000000*Profile!$B$6)))/(1-$B$17)-$B$18 | J8: =I8/G8-1
A9: Tier 4 | B9: 450 | C9: 3.3 | D9: 2050 | E9: 3250 | F9: 6 | G9: 6.8 | H9: 7.6 | I9: =(($B$15+($B$14*1.13*1000000+($B$16*1.13*SUMPRODUCT(1/(1+Inputs!$B$5)^(Profile!$A$9:$A$28-0.5))))/(C9*1000000*Profile!$B$6)))/(1-$B$17)-$B$18 | J9: =I9/G9-1
A10: Tier 5 | B10: 300 | C10: 2.4 | D10: 1900 | E10: 4500 | F10: 7.8 | G10: 9 | H10: 10 | I10: =(($B$15+($B$14*1.13*1000000+($B$16*1.13*SUMPRODUCT(1/(1+Inputs!$B$5)^(Profile!$A$9:$A$28-0.5))))/(C10*1000000*Profile!$B$6)))/(1-$B$17)-$B$18 | J10: =I10/G10-1
A11: Tier 6 | B11: 180 | C11: 1.4 | D11: 1170 | E11: 5700 | F11: 13.4 | G11: 15.2 | H11: 16.8 | I11: =(($B$15+($B$14*1.13*1000000+($B$16*1.13*SUMPRODUCT(1/(1+Inputs!$B$5)^(Profile!$A$9:$A$28-0.5))))/(C11*1000000*Profile!$B$6)))/(1-$B$17)-$B$18 | J11: =I11/G11-1
A13: BEG inputs (Table 1)
A14: Drilling cost, 12,000-ft TVD ($ million) | B14: 10.5
A15: Gathering, compression, treatment ($/Mcf) | B15: 0.49
A16: Expense per well per year ($) | B16: 82500
A17: Royalty | B17: 0.25
A18: Basis ($/MMBtu) | B18: -0.07
A20: Reading: the formula reproduces BEG's 10%-IRR breakevens for Tiers 1-3 within a few percent and runs higher for the deepest tiers; BEG's after-tax model and 2011 costs differ in detail. This validates the structure, not the modern inputs.

Sheet Cross-checks
A1: Cross-checks - company and EIA figures NOT used as inputs, set beside what the model implies (values; see Sources for URLs).
A3: Check | B3: Unit | C3: Value | D3: Comment
A4: Model breakeven, Legacy Tier 1 (pre-tax, 10%) | B4: $/MMBtu HH | C4: =Curve!F5 | D4: Expand deck: '<$2.75' (annual asset-level breakeven, hurdle not stated) - consistent with the model if Expand's basis is near 10% pre-tax; NOT the same definition.
A5: Model breakeven, Western Haynesville (Comstock cost, Tier 1 productivity ASSUMED) | B5: $/MMBtu HH | C5: =Curve!F11 | D5: No sourced Western Haynesville EUR. Every +/-20% of EUR per foot moves this by about +/-0.7.
A6: BEG 10% IRR breakeven, Tier 1 (2011 $, chart-read) | B6: $/MMBtu | C6: 3.5 | D6: OGJ 2015 Fig. 8; costs were ~$10.5 million per 4,800-ft well.
A7: Modern Tier 1 EUR used (Expand 12-month cumulative / modelled year-1 share) | B7: Bcf per 1,000 ft | C7: =Profile!$B$7 | D7: DERIVED (depends on the decline shape).
A8: BEG Tier 1 EUR per 1,000 ft (published 7.9 Bcf / 4.8) | B8: Bcf per 1,000 ft | C8: 1.6458333 | D8: 2008-12 wells.
A9: Comstock SEC proved undeveloped: 4.2 Tcf / 332 locations | B9: Bcf per location | C9: 12.650602 | D9: 10-K FY2025; SEC-conservative booking; lateral per location not stated (10,000 ft would be 1.27 Bcf per 1,000 ft).
A10: EIA AEO2023 average EUR, Haynesville-Bossier Louisiana / Texas | B10: Bcf per well | C10: 10.5 / 9.2 | D10: Table 3; lateral length not stated.
A11: Comstock YTD 2026 IP per 1,000 ft: Legacy 31 MMcf/d at 12,052 ft; Western 31 MMcf/d at 10,331 ft | B11: MMcf/d per 1,000 ft | C11: 2.57 / 3.00 | D11: Western / Legacy = 1.17x (IP, not EUR; Western decline unknown).
A12: Comstock Legacy D&C vs Expand 2026E | B12: $/ft | C12: 1,390 vs ~1,340 | D12: Within 4%.
A13: Developable locations, BEG legacy tiers 1-6 (this workbook) | B13: locations (4,800-ft) | C13: =SUM(Curve!K5:K10) | D13: 2012-vintage count; wells since 2012 not deducted.
A14: Operator-disclosed legacy inventory: Comstock 1,705 gross (30 Jun 2026) + Expand >2,000 gross (31 Dec 2024) | B14: locations (~10,000 ft) | C14: 3,705+ | D14: Two operators only; these sit inside BEG's legacy area and are not added to the curve.
A15: Comstock Western Haynesville operated inventory | B15: locations (8,875 ft) | C15: 3277 | D15: In the curve (Western Haynesville - Comstock row).
A16: Dallas Fed Q3 2026 expected Henry Hub in 2 / 5 years | B16: $/MMBtu | C16: 3.82 / 4.28 | D16: Survey of oil and gas executives, 30 Sep 2026.

Sheet Chart data
A1: Chart data (live): step points of the cost curve for two horizons (edit H in the yellow cells) and the Henry Hub line; marginal price by Key-question year.
A3: Horizon A (years) | B3: 5
A4: Horizon B (years) | B4: 8
A5: Henry Hub, last 12 months average ($/MMBtu) | B5: ='Henry Hub'!$B$3
D6: ="Supply added by Dec "&(2025+B3)&" if drilled in "&B3&" years (cost only)" | F6: ="Supply added by Dec "&(2025+B4)&" if drilled in "&B4&" years (cost only)" | H6: Henry Hub, last 12 months average
D7: x A: cumulative capacity (Bcf/d) | E7: y A: breakeven | F7: x B: cumulative capacity (Bcf/d) | G7: y B: breakeven | H7: x HH | I7: y HH
D8: =0 | E8: =Curve!$D$16 | F8: =0 | G8: =Curve!$D$16 | H8: 0 | I8: =$B$5
D9: =INDEX(Curve!$L$16:$U$23,1,MATCH($B$3,Curve!$L$4:$U$4,0)) | E9: =Curve!$D$16 | F9: =INDEX(Curve!$L$16:$U$23,1,MATCH($B$4,Curve!$L$4:$U$4,0)) | G9: =Curve!$D$16 | H9: =MAX(D23,F23) | I9: =$B$5
D10: =INDEX(Curve!$L$16:$U$23,1,MATCH($B$3,Curve!$L$4:$U$4,0)) | E10: =Curve!$D$17 | F10: =INDEX(Curve!$L$16:$U$23,1,MATCH($B$4,Curve!$L$4:$U$4,0)) | G10: =Curve!$D$17
D11: =INDEX(Curve!$L$16:$U$23,2,MATCH($B$3,Curve!$L$4:$U$4,0)) | E11: =Curve!$D$17 | F11: =INDEX(Curve!$L$16:$U$23,2,MATCH($B$4,Curve!$L$4:$U$4,0)) | G11: =Curve!$D$17
D12: =INDEX(Curve!$L$16:$U$23,2,MATCH($B$3,Curve!$L$4:$U$4,0)) | E12: =Curve!$D$18 | F12: =INDEX(Curve!$L$16:$U$23,2,MATCH($B$4,Curve!$L$4:$U$4,0)) | G12: =Curve!$D$18
D13: =INDEX(Curve!$L$16:$U$23,3,MATCH($B$3,Curve!$L$4:$U$4,0)) | E13: =Curve!$D$18 | F13: =INDEX(Curve!$L$16:$U$23,3,MATCH($B$4,Curve!$L$4:$U$4,0)) | G13: =Curve!$D$18
D14: =INDEX(Curve!$L$16:$U$23,3,MATCH($B$3,Curve!$L$4:$U$4,0)) | E14: =Curve!$D$19 | F14: =INDEX(Curve!$L$16:$U$23,3,MATCH($B$4,Curve!$L$4:$U$4,0)) | G14: =Curve!$D$19
D15: =INDEX(Curve!$L$16:$U$23,4,MATCH($B$3,Curve!$L$4:$U$4,0)) | E15: =Curve!$D$19 | F15: =INDEX(Curve!$L$16:$U$23,4,MATCH($B$4,Curve!$L$4:$U$4,0)) | G15: =Curve!$D$19
D16: =INDEX(Curve!$L$16:$U$23,4,MATCH($B$3,Curve!$L$4:$U$4,0)) | E16: =Curve!$D$20 | F16: =INDEX(Curve!$L$16:$U$23,4,MATCH($B$4,Curve!$L$4:$U$4,0)) | G16: =Curve!$D$20
D17: =INDEX(Curve!$L$16:$U$23,5,MATCH($B$3,Curve!$L$4:$U$4,0)) | E17: =Curve!$D$20 | F17: =INDEX(Curve!$L$16:$U$23,5,MATCH($B$4,Curve!$L$4:$U$4,0)) | G17: =Curve!$D$20
D18: =INDEX(Curve!$L$16:$U$23,5,MATCH($B$3,Curve!$L$4:$U$4,0)) | E18: =Curve!$D$21 | F18: =INDEX(Curve!$L$16:$U$23,5,MATCH($B$4,Curve!$L$4:$U$4,0)) | G18: =Curve!$D$21
D19: =INDEX(Curve!$L$16:$U$23,6,MATCH($B$3,Curve!$L$4:$U$4,0)) | E19: =Curve!$D$21 | F19: =INDEX(Curve!$L$16:$U$23,6,MATCH($B$4,Curve!$L$4:$U$4,0)) | G19: =Curve!$D$21
D20: =INDEX(Curve!$L$16:$U$23,6,MATCH($B$3,Curve!$L$4:$U$4,0)) | E20: =Curve!$D$22 | F20: =INDEX(Curve!$L$16:$U$23,6,MATCH($B$4,Curve!$L$4:$U$4,0)) | G20: =Curve!$D$22
D21: =INDEX(Curve!$L$16:$U$23,7,MATCH($B$3,Curve!$L$4:$U$4,0)) | E21: =Curve!$D$22 | F21: =INDEX(Curve!$L$16:$U$23,7,MATCH($B$4,Curve!$L$4:$U$4,0)) | G21: =Curve!$D$22
D22: =INDEX(Curve!$L$16:$U$23,7,MATCH($B$3,Curve!$L$4:$U$4,0)) | E22: =Curve!$D$23 | F22: =INDEX(Curve!$L$16:$U$23,7,MATCH($B$4,Curve!$L$4:$U$4,0)) | G22: =Curve!$D$23
D23: =INDEX(Curve!$L$16:$U$23,8,MATCH($B$3,Curve!$L$4:$U$4,0)) | E23: =Curve!$D$23 | F23: =INDEX(Curve!$L$16:$U$23,8,MATCH($B$4,Curve!$L$4:$U$4,0)) | G23: =Curve!$D$23
A25: Marginal breakeven by Key-question date ($/MMBtu HH; STEO growth + extra supply)
A26: Year-end | B26: Base case | C26: LNG and takeaway delayed 6 months | D26: Henry Hub, last 12 months average
A27: Dec 2026 | B27: =IF(ISNUMBER(Mapping!K6),Mapping!K6,0) | C27: =IF(ISNUMBER(Mapping!K10),Mapping!K10,0) | D27: =$B$5
A28: Dec 2028 | B28: =IF(ISNUMBER(Mapping!K7),Mapping!K7,0) | C28: =IF(ISNUMBER(Mapping!K11),Mapping!K11,0) | D28: =$B$5
A29: Dec 2030 | B29: =IF(ISNUMBER(Mapping!K8),Mapping!K8,0) | C29: =IF(ISNUMBER(Mapping!K12),Mapping!K12,0) | D29: =$B$5
A30: Dec 2033 | B30: =IF(ISNUMBER(Mapping!K9),Mapping!K9,0) | C30: =IF(ISNUMBER(Mapping!K13),Mapping!K13,0) | D30: =$B$5

Sheet Not reachable
A1: Source | B1: What happened (Actions, 6 Oct 2026)
A2: Comstock IR website www.comstockresources.com/investors/presentations | B2: HTTP 404 from Actions; ir.comstockresources.com does not resolve. The investor presentations ARE on investors.comstockresources.com/static-files/..., opened with curl_cffi (browser impersonation) - plain requests are refused.
A3: Expand IR website investors.expandenergy.com | B3: plain requests read-timed out from Actions; the 3Q 2025 deck opened with curl_cffi. The 4Q25 and 2Q26 decks were not located (only the press releases, which carry no breakeven figure, were opened).
A4: IEA Gas Market Report / World Energy Outlook US supply cost charts | B4: iea.org returned HTTP 403 from Actions (guessed report URL); no IEA document with Haynesville cost data opened.
A5: Oxford Institute for Energy Studies | B5: oxfordenergy.org returned HTTP 403; a web search found no OIES Haynesville breakeven publication.
A6: Baker Institute (Rice) | B6: site root opened but no Haynesville cost document found.
A7: Kansas City Fed Energy Survey | B7: page opened; no Haynesville or gas-basin breakeven in the text. Dallas Fed: oil breakevens by basin only.
A8: EIA 'Trends in U.S. Oil and Natural Gas Upstream Costs' (2016 edition) | B8: opened (8 MB PDF); oil-focused, no Haynesville gas breakeven. The AEO OGSM file served is the 2023 edition.
A9: EIA 2023 study quoted by Evaluate Energy (13% of acreage profitable at $4, 72% at $8) | B9: underlying study not found; only the secondary quote was opened.
A10: Aethon, BPX (BP), TG Natural Resources, other private/foreign-owned operators | B10: no public filings with inventory or breakeven; Aethon appears only through the secondary quote above. BP investor materials were not probed.
A11: Rystad, Enverus, Kayrros, Wood Mackenzie curves | B11: paywalled; no public document with data opened. This is the gap the editable override columns are for.
A12: Goodrich Petroleum | B12: acquired (2021); no current filings.

Sheet Snippets (unused)
A1: Status | B1: Claim seen | C1: Why not used
A2: SNIPPET - unopened | B2: Expand: 'owns 72% of the lowest breakeven inventory in the Haynesville' and 'breakevens below $3 and <$2.75' | C2: web-search result summary only (gurufocus / transcripts); the opened Expand deck above gives <$2.75 but not the 72%
A3: SNIPPET - unopened | B3: Comstock Q3 2024 Western Haynesville cost $2,814 per completed lateral foot; horseshoe $1,740 vs $2,270 per lateral foot; D&C 24.8 Bcf EUR for 10,000-ft Gen II wells | C3: web-search result summaries; the Q3 2024 release (SEC 000095017024119021) was not opened
A4: SNIPPET - unopened | B4: Comstock investor-presentation 'big hole' lateral at $1,306 per lateral foot (Q2 2026 call) | C4: the Nasdaq call summary was opened (secondary) and states it; not used in the model
A5: SNIPPET - unopened | B5: Haynesville breakeven ~$3.75 / class-1 $3.21, class-2 $3.57 at 30% FCF / 'S&P Global core acreage ~$3' | C5: search-result snippets from unnamed articles; not opened

Sheet Gulf key question
A1: Scenario | B1: Year | C1: STEO Haynesville growth | D1: Extra supply required | E1: Haynesville growth required (STEO + extra) | F1: Extra with layers up to Cameron LNG Train 4 | G1: Extra with layers up to Woodside Louisiana LNG Phase 2 | H1: Extra with layers up to Lake Charles LNG (SUSPENDED) | I1: Extra with layers up to Delfin FLNG vessels 2-3
A2: Base | B2: 2026 | C2: 1.2924834 | D2: 0 | E2: 1.2924834 | F2: 0 | G2: 0 | H2: 0 | I2: 0
A3: Base | B3: 2027 | C3: 2.3613907 | D3: 0 | E3: 2.3613907 | F3: 0 | G3: 0 | H3: 0 | I3: 0
A4: Base | B4: 2028 | C4: 3.7806313 | D4: 1.0522888 | E4: 4.8329201 | F4: 1.0522888 | G4: 1.0522888 | H4: 1.0522888 | I4: 1.0522888
A5: Base | B5: 2029 | C5: 4.5484481 | D5: 1.6796656 | E5: 6.2281136 | F5: 1.6796656 | G5: 1.6796656 | H5: 1.6796656 | I5: 1.6796656
A6: Base | B6: 2030 | C6: 4.9480987 | D6: 4.6746252 | E6: 9.6227239 | F6: 4.6746252 | G6: 4.6746252 | H6: 4.6746252 | I6: 4.6746252
A7: Base | B7: 2031 | C7: 5.152021 | D7: 6.6792291 | E7: 11.83125 | F7: 7.7464726 | G7: 9.2426101 | H7: 11.478685 | I7: 12.649688
A8: Base | B8: 2032 | C8: 5.2550274 | D8: 6.5007393 | E8: 11.755767 | F8: 7.5679828 | G8: 9.1846622 | H8: 11.600895 | I8: 12.771898
A9: Base | B9: 2033 | C9: 5.3067946 | D9: 6.4544726 | E9: 11.761267 | F9: 7.5217161 | G9: 9.1383955 | H9: 11.554628 | I9: 12.725632
A10: LNG and takeaway delayed 6 months | B10: 2026 | C10: 1.2924834 | D10: 0 | E10: 1.2924834 | F10: 0 | G10: 0 | H10: 0 | I10: 0
A11: LNG and takeaway delayed 6 months | B11: 2027 | C11: 2.3613907 | D11: 0 | E11: 2.3613907 | F11: 0 | G11: 0 | H11: 0 | I11: 0
A12: LNG and takeaway delayed 6 months | B12: 2028 | C12: 3.7806313 | D12: 0 | E12: 3.7806313 | F12: 0 | G12: 0 | H12: 0 | I12: 0
A13: LNG and takeaway delayed 6 months | B13: 2029 | C13: 4.5484481 | D13: 0 | E13: 4.5484481 | F13: 0 | G13: 0 | H13: 0 | I13: 0
... A17: LNG and takeaway delayed 6 months | B17: 2033 | C17: 5.3067946 | D17: 6.4544726 | E17: 11.761267 | F17: 7.5217161 | G17: 9.1383955 | H17: 11.554628 | I17: 12.725632

Sheet Henry Hub
B1: Henry Hub average (USD/MMBtu)
A2: Last daily spot (29 Sep 2026) | B2: 3.18
A3: Last 12 months average | B3: 3.5495142
A4: Last 12 months min | B4: 2.54
A5: Last 12 months max | B5: 30.72
A6: 2025 average | B6: 3.516129
A7: 2024 average | B7: 2.1904781
A8: Jan 2021 - latest average | B8: 3.6876778

Sheet Curve values
A1: Rank | B1: Tier (sorted by breakeven) | C1: Breakeven $/MMBtu HH | D1: Developable locations | E1: Cumulative locations | F1: Developable lateral (1,000 ft) | G1: EUR (Bcf per 1,000 ft) | H1: Developable EUR (Tcf) | I1: Capacity H=1 (Bcf/d) | J1: Capacity H=2 (Bcf/d) | K1: Capacity H=3 (Bcf/d) | L1: Capacity H=4 (Bcf/d) | M1: Capacity H=5 (Bcf/d) | N1: Capacity H=6 (Bcf/d) | O1: Capacity H=7 (Bcf/d) | P1: Capacity H=8 (Bcf/d) | Q1: Capacity H=9 (Bcf/d) | R1: Capacity H=10 (Bcf/d) | S1: Cumulative capacity H=1 (Bcf/d) | T1: Cumulative capacity H=2 (Bcf/d) | U1: Cumulative capacity H=3 (Bcf/d) | V1: Cumulative capacity H=4 (Bcf/d) | W1: Cumulative capacity H=5 (Bcf/d) | X1: Cumulative capacity H=6 (Bcf/d) | Y1: Cumulative capacity H=7 (Bcf/d) | Z1: Cumulative capacity H=8 (Bcf/d) | AA1: Cumulative capacity H=9 (Bcf/d) | AB1: Cumulative capacity H=10 (Bcf/d)
A2: 1 | B2: Legacy Tier 1 (BEG) | C2: 2.3429808 | D2: 2260 | E2: 2260 | F2: 10848 | G2: 1.9801548 | H2: 21.480719 | I2: 25.411068 | J2: 17.306339 | K2: 13.434262 | L2: 11.05589 | M2: 9.4162055 | N2: 8.2065128 | O2: 7.2729129 | P2: 6.5286863 | Q2: 5.9206944 | R2: 5.4143182 | S2: 25.411068 | T2: 17.306339 | U2: 13.434262 | V2: 11.05589 | W2: 9.4162055 | X2: 8.2065128 | Y2: 7.2729129 | Z2: 6.5286863 | AA2: 5.9206944 | AB2: 5.4143182
A3: 2 | B3: Legacy Tier 2 (BEG) | C3: 2.8016184 | D3: 1976 | E3: 4236 | F3: 9484.8 | G3: 1.4788498 | H3: 14.026594 | I3: 16.593055 | J3: 11.300785 | K3: 8.7723758 | L3: 7.219334 | M3: 6.148644 | N3: 5.3587324 | O3: 4.7491054 | P3: 4.2631364 | Q3: 3.8661265 | R3: 3.5354703 | S3: 42.004123 | T3: 28.607125 | U3: 22.206638 | V3: 18.275224 | W3: 15.564849 | X3: 13.565245 | Y3: 12.022018 | Z3: 10.791823 | AA3: 9.7868209 | AB3: 8.9497885
A4: 3 | B4: Legacy Tier 3 (BEG) | C4: 3.365233 | D4: 3320 | E4: 7556 | F4: 15936 | G4: 1.1279363 | H4: 17.974792 | I4: 21.263659 | J4: 14.481724 | K4: 11.241619 | L4: 9.2514282 | M4: 7.8793609 | N4: 6.8671055 | O4: 6.085881 | P4: 5.4631216 | Q4: 4.9543617 | R4: 4.5306325 | S4: 63.267782 | T4: 43.088849 | U4: 33.448257 | V4: 27.526652 | W4: 23.44421 | X4: 20.432351 | Y4: 18.107899 | Z4: 16.254944 | AA4: 14.741183 | AB4: 13.480421
A5: 4 | B5: Legacy Tier 4 (BEG) | C5: 4.2289541 | D5: 2940 | E5: 10496 | F5: 14112 | G5: 0.82715325 | H5: 11.672787 | I5: 13.808569 | J5: 9.4043969 | K5: 7.3002805 | L5: 6.0078552 | M5: 5.116838 | N5: 4.4594817 | O5: 3.9521564 | P5: 3.547738 | Q5: 3.2173505 | R5: 2.9421818 | S5: 77.076351 | T5: 52.493246 | U5: 40.748537 | V5: 33.534508 | W5: 28.561048 | X5: 24.891832 | Y5: 22.060056 | Z5: 19.802682 | AA5: 17.958533 | AB5: 16.422603
A6: 5 | B6: Western Haynesville - Comstock operated | C6: 4.247861 | D6: 3277 | E6: 13773 | F6: 29083.375 | G6: 1.9801548 | H6: 57.589583 | I6: 68.12681 | J6: 46.398115 | K6: 36.017116 | L6: 29.640726 | M6: 25.244749 | N6: 22.001575 | O6: 19.498604 | P6: 17.50334 | Q6: 15.87332 | R6: 14.515731 | S6: 145.20316 | T6: 98.891361 | U6: 76.765653 | V6: 63.175234 | W6: 53.805797 | X6: 46.893408 | Y6: 41.55866 | Z6: 37.306022 | AA6: 33.831853 | AB6: 30.938333
A7: 6 | B7: Western Haynesville - Expand prospective | C7: 4.247861 | D7: 200 | E7: 13973 | F7: 2000 | G7: 1.9801548 | H7: 3.9603095 | I7: 4.6849315 | J7: 3.1906967 | K7: 2.4768182 | L7: 2.0383278 | M7: 1.7360261 | N7: 1.5130001 | O7: 1.3408763 | P7: 1.2036664 | Q7: 1.0915734 | R7: 0.998215 | S7: 149.88809 | T7: 102.08206 | U7: 79.242471 | V7: 65.213562 | W7: 55.541823 | X7: 48.406408 | Y7: 42.899536 | Z7: 38.509689 | AA7: 34.923426 | AB7: 31.936548
A8: 7 | B8: Legacy Tier 5 (BEG) | C8: 5.4435619 | D8: 3320 | E8: 17293 | F8: 15936 | G8: 0.601566 | H8: 9.5865558 | I8: 11.340618 | J8: 7.7235863 | K8: 5.9955303 | L8: 4.934095 | M8: 4.2023258 | N8: 3.6624563 | O8: 3.2458032 | P8: 2.9136649 | Q8: 2.6423262 | R8: 2.4163374 | S8: 161.22871 | T8: 109.80564 | U8: 85.238002 | V8: 70.147657 | W8: 59.744149 | X8: 52.068864 | Y8: 46.145339 | Z8: 41.423354 | AA8: 37.565753 | AB8: 34.352886
A9: 8 | B9: Legacy Tier 6 (BEG) | C9: 8.6246775 | D9: 3216 | E9: 20509 | F9: 15436.8 | G9: 0.3509135 | H9: 5.4169815 | I9: 6.4081323 | J9: 4.3642915 | K9: 3.3878358 | L9: 2.7880609 | M9: 2.3745672 | N9: 2.0695084 | O9: 1.8340743 | P9: 1.6463962 | Q9: 1.4930735 | R9: 1.3653762 | S9: 167.63684 | T9: 114.16994 | U9: 88.625837 | V9: 72.935718 | W9: 62.118716 | X9: 54.138373 | Y9: 47.979413 | Z9: 43.06975 | AA9: 39.058826 | AB9: 35.718262

Sheet Mapping values
A1: Scenario | B1: Year-end | C1: H (years) | D1: STEO Haynesville growth | E1: Extra supply required | F1: Extra with layers up to Cameron LNG Train 4 | G1: Extra with layers up to Woodside Louisiana LNG Phase 2 | H1: Extra with layers up to Lake Charles LNG (SUSPENDED) | I1: Extra with layers up to Delfin FLNG vessels 2-3 | J1: Marginal breakeven - extra supply alone | K1: Marginal breakeven - STEO growth + extra | L1: Marginal breakeven - STEO growth + layers up to Cameron LNG Train 4 | M1: Marginal breakeven - STEO growth + layers up to Woodside Louisiana LNG Phase 2 | N1: Marginal breakeven - STEO growth + layers up to Lake Charles LNG (SUSPENDED) | O1: Marginal breakeven - STEO growth + layers up to Delfin FLNG vessels 2-3
A2: Base | B2: Dec 2026 | C2: 1 | D2: 1.2924834 | E2: 0 | F2: 0 | G2: 0 | H2: 0 | I2: 0 | K2: 2.3429808 | L2: 2.3429808 | M2: 2.3429808 | N2: 2.3429808 | O2: 2.3429808
A3: Base | B3: Dec 2028 | C3: 3 | D3: 3.7806313 | E3: 1.0522888 | F3: 1.0522888 | G3: 1.0522888 | H3: 1.0522888 | I3: 1.0522888 | J3: 2.3429808 | K3: 2.3429808 | L3: 2.3429808 | M3: 2.3429808 | N3: 2.3429808 | O3: 2.3429808
A4: Base | B4: Dec 2030 | C4: 5 | D4: 4.9480987 | E4: 4.6746252 | F4: 4.6746252 | G4: 4.6746252 | H4: 4.6746252 | I4: 4.6746252 | J4: 2.3429808 | K4: 2.8016184 | L4: 2.8016184 | M4: 2.8016184 | N4: 2.8016184 | O4: 2.8016184
A5: Base | B5: Dec 2033 | C5: 8 | D5: 5.3067946 | E5: 6.4544726 | F5: 7.5217161 | G5: 9.1383955 | H5: 11.554628 | I5: 12.725632 | J5: 2.3429808 | K5: 3.365233 | L5: 3.365233 | M5: 3.365233 | N5: 4.2289541 | O5: 4.2289541
A6: LNG and takeaway delayed 6 months | B6: Dec 2026 | C6: 1 | D6: 1.2924834 | E6: 0 | F6: 0 | G6: 0 | H6: 0 | I6: 0 | K6: 2.3429808 | L6: 2.3429808 | M6: 2.3429808 | N6: 2.3429808 | O6: 2.3429808
A7: LNG and takeaway delayed 6 months | B7: Dec 2028 | C7: 3 | D7: 3.7806313 | E7: 0 | F7: 0 | G7: 0 | H7: 0 | I7: 0 | K7: 2.3429808 | L7: 2.3429808 | M7: 2.3429808 | N7: 2.3429808 | O7: 2.3429808
A8: LNG and takeaway delayed 6 months | B8: Dec 2030 | C8: 5 | D8: 4.9480987 | E8: 1.5674701 | F8: 1.5674701 | G8: 1.5674701 | H8: 1.5674701 | I8: 1.5674701 | J8: 2.3429808 | K8: 2.3429808 | L8: 2.3429808 | M8: 2.3429808 | N8: 2.3429808 | O8: 2.3429808
A9: LNG and takeaway delayed 6 months | B9: Dec 2033 | C9: 8 | D9: 5.3067946 | E9: 6.4544726 | F9: 7.5217161 | G9: 9.1383955 | H9: 11.554628 | I9: 12.725632 | J9: 2.3429808 | K9: 3.365233 | L9: 3.365233 | M9: 3.365233 | N9: 4.2289541 | O9: 4.2289541

Sheet HH monthly values
A1: date | B1: Henry Hub monthly average
A2: 44197 | B2: 2.7126316
A3: 44228 | B3: 5.3536842
A4: 44256 | B4: 2.6182609
A5: 44287 | B5: 2.6628571
A6: 44317 | B6: 2.9125
A7: 44348 | B7: 3.2581818
A8: 44378 | B8: 3.8404762
A9: 44409 | B9: 4.0740909
A10: 44440 | B10: 5.1614286
A11: 44470 | B11: 5.5138095
A12: 44501 | B12: 5.0505
A13: 44531 | B13: 3.7577273
... A70: 46266 | B70: 2.9465

Sheet Sensitivity values
A1: Share of BEG legacy inventory left | B1: Western Haynesville productivity vs Tier 1 | C1: Base Dec 2030: STEO + extra | D1: Base Dec 2030: STEO + extra with all layers | E1: Base Dec 2033: STEO + extra | F1: Base Dec 2033: STEO + extra with all layers | G1: Delayed Dec 2033: STEO + extra | H1: Delayed Dec 2033: STEO + extra with all layers
A2: 1 | B2: 0.8 | C2: 2.8016184 | D2: 2.8016184 | E2: 3.365233 | F2: 4.2289541 | G2: 3.365233 | H2: 4.2289541
A3: 1 | B3: 1 | C3: 2.8016184 | D3: 2.8016184 | E3: 3.365233 | F3: 4.2289541 | G3: 3.365233 | H3: 4.2289541
A4: 1 | B4: 1.17 | C4: 2.8016184 | D4: 2.8016184 | E4: 3.365233 | F4: 3.7744966 | G4: 3.365233 | H4: 3.7744966
A5: 0.5 | B5: 0.8 | C5: 3.365233 | D5: 3.365233 | E5: 5.0623263 | F5: 5.0623263 | G5: 5.0623263 | H5: 5.0623263
A6: 0.5 | B6: 1 | C6: 3.365233 | D6: 3.365233 | E6: 4.247861 | F6: 4.247861 | G6: 4.247861 | H6: 4.247861
A7: 0.5 | B7: 1.17 | C7: 3.365233 | D7: 3.365233 | E7: 3.7744966 | F7: 3.7744966 | G7: 3.7744966 | H7: 3.7744966
A8: 0.25 | B8: 0.8 | C8: 5.0623263 | D8: 5.0623263 | E8: 5.0623263 | F8: 5.0623263 | G8: 5.0623263 | H8: 5.0623263
A9: 0.25 | B9: 1 | C9: 4.247861 | D9: 4.247861 | E9: 4.247861 | F9: 4.247861 | G9: 4.247861 | H9: 4.247861
A10: 0.25 | B10: 1.17 | C10: 3.7744966 | D10: 3.7744966 | E10: 3.7744966 | F10: 3.7744966 | G10: 3.7744966 | H10: 3.7744966
